Workbook

Sheet 0_Guide
B2: One Matrix - Four Steps (LLM-ready, no background assumed)
B3: A single progressive-disclosure matrix for screening, coding, deep-read analysis and reporting.
B5: CONTEXT PRIMER (read this before coding any paper)
B6: What is this review about | C6: This is a systematic literature review about DIGITAL TWINS used in the built-environment industry, specifically to improve SAFETY and QUALITY of designs. You are screening and coding academic papers.
B7: AECO | C7: AECO = Architecture, Engineering, Construction and Operations. It means the built-environment / construction industry (buildings, bridges, infrastructure, civil engineering). NOT manufacturing, automotive, aerospace, power/electrical equipment, healthcare, or agriculture.
B8: Digital Twin (DT) | C8: A Digital Twin is a live virtual replica of a physical asset that is connected to it by data. It is MORE than a static 3D/BIM model. If a paper only says the words 'digital twin' in passing but does not actually build or study one, treat DT as a buzzword (answer 'No').
B9: Design for Safety (DfS) | C9: Design for Safety = designing to prevent construction/operation safety incidents (e.g. fall from height, hazards, accident prevention).
B10: Safety (scope) | C10: The review scope is Design for Safety and construction/operational safety. Quality-only studies are out of scope.
B11: Prevention through Design (PtD) | C11: Prevention through Design = the principle of eliminating risks at the design stage before construction begins. Closely related to Design for Safety.
B12: BIM | C12: BIM = Building Information Modelling. A static, design-stage digital model. A BIM model alone is NOT a Digital Twin (no live data link).
B13: bidirectional | C13: 'bidirectional' means data flows BOTH ways: physical->virtual AND virtual->physical (the twin can act back on the real asset). One-way data flow is only a 'digital shadow'.
B14: Answer format | C14: Every Stage-1 and Stage-2 question is answered strictly as 'Yes' or 'No'. If genuinely unsure from the abstract, answer 'No' (conservative) and add a note. Do not invent information not present in the text.
B15: One reason only | C15: When a paper is excluded, the matrix auto-picks ONE standardized reason by priority. You do not write the reason yourself.
B17: THE FOUR STEPS
B18: Step 1 (all 450 papers) | C18: An LLM or reviewer fills the AMBER Stage-1 columns (G-K) for EVERY paper, from the TITLE and ABSTRACT only. Column L auto-decides Include/Exclude; column M auto-writes the single exclusion reason.
B19: Step 2 (the matrix) | C19: This workbook IS the summary matrix. There is nothing separate to generate.
B20: Retrieval + PDF gateway | C20: For Stage-1 includes, first mark column N 'PDF full text on hand?'. This is the gateway: only papers with the PDF on hand can be deep-read. You can revisit later - when a PDF is found, change N from 'No' to 'Yes' and the paper becomes ready for Stage-2/3.
B21: Step 3 (deep read) | C21: For papers whose PDF is on hand, fill the RED Stage-2 columns (P-R) and then the GREEN synthesis 'angle' columns (U-AG). These are the evidence for your findings section.
B22: Step 4 (report) | C22: Open 'Step1_Report' (screening + PRISMA chain + exclusion reasons) and 'Step3_Report' (capability-tier / phase / method / modality / validation / self-improvement tables). Both auto-tally from the same rows.
B24: COLOUR KEY
B25: Bands | C25: AMBER = Stage-1 input (from abstract) · BLUE = PDF gateway · RED = Stage-2 input (from full text) · GREEN = Stage-3 deep-read input · BLUE-GREY = auto formula, do not edit.
B26: Golden rule | C26: Never delete a paper. A paper excluded at any stage stays in the matrix with its reason recorded. This is what makes the PRISMA flow reproducible.
A27: Update 2026-09-30 | B27: Matrix rebuilt from SLR summary matrix step 1.md (956 records, 244 Stage-1 includes) and step 3.md (214 full-text coded: 200 included, 14 excluded; 30 includes awaiting full text). Differences against the previous 429-record matrix are listed in 3_Change_Log. 21 Methodology labels "Perception / Computer Vision" were normalised to "Computer Vision / CNN / object-detection".
A28: Update 2026-10-04 | B28: Stage-2/3 coding replaced with SLR summary matrix step 3.md (DfS-only scope): 244 Stage-1 includes; 240 full-text coded (222 included, 18 excluded); 4 awaiting full text. Stage-1 title/abstract screening applied the earlier broader criterion (Design for Safety, Design for Quality, Prevention through Design); quality-only papers carried through were removed at Stage 2 (Q = No). 21 methodology labels "Perception / Computer Vision" normalised to "Computer Vision / CNN / object-detection". Changes vs v260930 in 3_Change_Log.

Sheet 1_CodeLists
A1: YN | B1: Src | C1: Bin | D1: Tier | E1: DfX | F1: Self | G1: Method | H1: Modality | I1: Valid | J1: Cluster | K1: Fusion | L1: Conf
A2: Yes | B2: Scopus | C2: 0 | D2: Tier 1 - Digital Model (static, no live data) | E2: Design for Safety (DfS) | F2: None | G2: Computer Vision / CNN / object-detection | H2: Single (one data type) | I2: Conceptual (no test) | J2: BIM-to-Digital-Twin architecture | K2: Single | L2: High
A3: No | B3: Web of Science | C3: 1 | D3: Tier 2 - Digital Shadow (one-way physical to virtual) | E3: Other | F3: Mentioned only | G3: Graph Neural Network (GNN) | H3: Multi (two or more data types) | I3: Simulation | J3: Semantic interoperability | K3: Co-present | L3: Medium
B4: Lens.org | D4: Tier 3 - Digital Twin (bidirectional, two-way) | F4: Implemented | G4: LSTM / RNN (recurrent networks) | I4: Lab / scale-model experiment | J4: Perception / Computer Vision | K4: Aligned | L4: Low
B5: Backward-snowball | D5: Tier 4 - Cognitive / Self-improving | F5: Convergence-characterised | G5: Transformer / Large Language Model (LLM) | I5: Single case study | J5: Design for Safety | K5: Fused
B6: Forward-snowball | D6: Unclear | G6: Reinforcement Learning (RL) | I6: Cross-project (multiple real projects) | J6: Predictive analytics / decision support | K6: Unclear
G7: Bayesian / probabilistic | J7: Lifecycle / governance
G8: Agent-based model (ABM) | J8: Other
G9: Finite Element Method / physics-based
G10: Ontology / semantic
G11: Statistical / change-point
G12: Digital Twin platform (no machine learning)
G13: Other / Mixed

Sheet Matrix
P1: a | Q1: b | R1: c | T1: d - 2nd duplicate (none in merged 956 corpus)
G2: a | H2: b | I2: c | K2: e | L2: =COUNTIF(L4:L960,"Exclude") -> 712 | N2: =COUNTIF(N4:N960,"No") -> 4 | O2: =COUNTIF(O4:O960,"No") -> 4 | P2: =COUNTIF(P4:P960,"No") -> 14 | Q2: =COUNTIF(Q4:Q960,"No") -> 6 | R2: =COUNTIF(R4:R960,"No") -> 13 | S2: =COUNTIF(S4:S960,"Exclude") -> 18 | T2: 0
A3: =COUNTA(A5:A960) -> 956 | G3: =COUNTIF(G4:G960,"No") -> 415 | H3: =COUNTIF(H4:H960,"No") -> 268 | I3: =COUNTIF(I4:I960,"No") -> 166 | J3: =COUNTIF(J4:J960,"No") -> 1 | K3: =COUNTIF(K4:K960,"No") -> 20 | L3: =COUNTIF(L4:L960,"Include") -> 244 | N3: =COUNTIF(N4:N960,"Yes") -> 240 | O3: =COUNTIF(O4:O960,"Yes") -> 240 | P3: =COUNTIF(P4:P960,"Yes") -> 226 | Q3: =COUNTIF(Q4:Q960,"Yes") -> 234 | R3: =COUNTIF(R4:R960,"Yes") -> 227 | S3: =COUNTIF(S4:S960,"Include")-T2 -> 222
A4: ID | B4: Authors (year) | C4: Year | D4: Journal | E4: Title | F4: Source database | G4: Stage1: Domain is AECO (built environment)? | H4: Stage1: Digital Twin is core (not just a buzzword)? | I4: Stage1: About Design for Safety / safety / Prevention through Design? | J4: Stage1: Publication type OK (journal/conference article, not editorial/erratum)? | K4: Stage1: Written in English (full text)? | L4: STAGE-1 decision | M4: Stage-1 exclusion reason (auto) | N4: GATEWAY: PDF full text on hand? (change to Yes when found) | O4: Full text retrieved for PRISMA? | P4: Stage2: Digital Twin is the actual subject (full text)? | Q4: Stage2: Design for Safety confirmed in full text? | R4: Stage2: Methodology is clear enough to code? | S4: STAGE-2 decision | T4: Stage-2 exclusion reason (auto) | U4: Deep-read: Digital Twin capability tier | V4: Phase: Design (1/0) | W4: Phase: Construction (1/0) | X4: Phase: Operation (1/0) | Y4: Cross-phase? (auto) | Z4: Deep-read: Design-for-X target (DfS scope) | AA4: Deep-read: Self-improvement / convergence | AB4: Deep-read: Methodology | AC4: Deep-read: Data modality | AD4: Deep-read: Validation level | AE4: Deep-read: Quality appraisal score (0 to 5) | AF4: Deep-read: Thematic cluster | AG4: Deep-read: Key evidence / notes | AH4: Deep-read: Strength / research gap filled | AI4: Deep-read: Deficiencies & future work | AJ4: Deep-read: Fusion depth (AC1) | AK4: Deep-read: Fusion evidence (AC2) | AL4: Deep-read: Fusion confidence (AC3) | AM4: Fusion coding flag (review) | AN4: Full-text verification (date, source, outcome) | AO4: DOI
A5: 1 | B5: Ullah, F et al. (2026) | C5: 2026 | E5: A scoping review of green Internet of Things in construction and smart cities: current applications, adoption strategies and future directions | F5: Scopus | G5: Yes | H5: No | I5: No | J5: Yes | K5: Yes | L5: =IF(COUNTBLANK(G5:K5)=5,"",IF(COUNTIF(G5:K5,"No")>0,"EXCLUDE","INCLUDE")) -> EXCLUDE | M5: =IF(L5<>"EXCLUDE","",IF(G5="No","Wrong domain (non-AECO)",IF(H5="No","Digital Twin not core / buzzword",IF(I5="No","No Design for Safety / PtD focus",IF(J5="No","Wrong publication type",IF(K5="No","Non-English","")))))) -> Digital Twin not core / buzzword | S5: =IF(N5<>"Yes","",IF(COUNTBLANK(P5:R5)=3,"",IF(COUNTIF(P5:R5,"No")>0,"EXCLUDE","INCLUDE"))) | T5: =IF(S5<>"EXCLUDE","",IF(P5="No","Digital Twin mentioned only, not the subject",IF(Q5="No","No Design for Safety focus in full text",IF(R5="No","Methodology not codable","")))) | Y5: =IF(SUM(V5:X5)=0,"",IF(SUM(V5:X5)>=2,"Multi","Single")) | AN5: Step-1 note: G-IoT scoping review; DT only future trend, no DfS/DfQ core | AO5: 10.1108/SASBE-11-2023-0349
A6: 2 | B6: Pavón, R.M et al. (2026) | C6: 2026 | E6: Digital Twin development and implementation for the management of irrigation networks | F6: Scopus | G6: No | H6: Yes | I6: No | J6: Yes | K6: Yes | L6: =IF(COUNTBLANK(G6:K6)=5,"",IF(COUNTIF(G6:K6,"No")>0,"EXCLUDE","INCLUDE")) -> EXCLUDE | M6: =IF(L6<>"EXCLUDE","",IF(G6="No","Wrong domain (non-AECO)",IF(H6="No","Digital Twin not core / buzzword",IF(I6="No","No Design for Safety / PtD focus",IF(J6="No","Wrong publication type",IF(K6="No","Non-English","")))))) -> Wrong domain (non-AECO) | S6: =IF(N6<>"Yes","",IF(COUNTBLANK(P6:R6)=3,"",IF(COUNTIF(P6:R6,"No")>0,"EXCLUDE","INCLUDE"))) | T6: =IF(S6<>"EXCLUDE","",IF(P6="No","Digital Twin mentioned only, not the subject",IF(Q6="No","No Design for Safety focus in full text",IF(R6="No","Methodology not codable","")))) | Y6: =IF(SUM(V6:X6)=0,"",IF(SUM(V6:X6)>=2,"Multi","Single")) | AN6: Step-1 note: Irrigation networks; agriculture/water domain, no safety/quality angle | AO6: 10.1016/j.eswa.2025.129330
A7: 3 | B7: Zhu, H et al. (2025) | C7: 2025 | E7: Research on Multi-Sensor Data Fusion Based Real-Scene 3D Reconstruction and Digital Twin Visualization Methodology for Coal Mine Tunnels | F7: Scopus | G7: No | H7: Yes | I7: Yes | J7: Yes | K7: Yes | L7: =IF(COUNTBLANK(G7:K7)=5,"",IF(COUNTIF(G7:K7,"No")>0,"EXCLUDE","INCLUDE")) -> EXCLUDE | M7: =IF(L7<>"EXCLUDE","",IF(G7="No","Wrong domain (non-AECO)",IF(H7="No","Digital Twin not core / buzzword",IF(I7="No","No Design for Safety / PtD focus",IF(J7="No","Wrong publication type",IF(K7="No","Non-English","")))))) -> Wrong domain (non-AECO) | S7: =IF(N7<>"Yes","",IF(COUNTBLANK(P7:R7)=3,"",IF(COUNTIF(P7:R7,"No")>0,"EXCLUDE","INCLUDE"))) | T7: =IF(S7<>"EXCLUDE","",IF(P7="No","Digital Twin mentioned only, not the subject",IF(Q7="No","No Design for Safety focus in full text",IF(R7="No","Methodology not codable","")))) | Y7: =IF(SUM(V7:X7)=0,"",IF(SUM(V7:X7)>=2,"Multi","Single")) | AN7: Step-1 note: Coal mine tunnels; mining domain, not AECO | AO7: 10.3390/s25196153
A8: 4 | B8: Shen, Z et al. (2026) | C8: 2026 | E8: Hazard-responsive digital twin for weather-driven urban resilience and affordability | F8: Scopus | G8: Yes | H8: Yes | I8: No | J8: Yes | K8: Yes | L8: =IF(COUNTBLANK(G8:K8)=5,"",IF(COUNTIF(G8:K8,"No")>0,"EXCLUDE","INCLUDE")) -> EXCLUDE | M8: =IF(L8<>"EXCLUDE","",IF(G8="No","Wrong domain (non-AECO)",IF(H8="No","Digital Twin not core / buzzword",IF(I8="No","No Design for Safety / PtD focus",IF(J8="No","Wrong publication type",IF(K8="No","Non-English","")))))) -> No Design for Safety / PtD focus | S8: =IF(N8<>"Yes","",IF(COUNTBLANK(P8:R8)=3,"",IF(COUNTIF(P8:R8,"No")>0,"EXCLUDE","INCLUDE"))) | T8: =IF(S8<>"EXCLUDE","",IF(P8="No","Digital Twin mentioned only, not the subject",IF(Q8="No","No Design for Safety focus in full text",IF(R8="No","Methodology not codable","")))) | Y8: =IF(SUM(V8:X8)=0,"",IF(SUM(V8:X8)>=2,"Multi","Single")) | AN8: Step-1 note: Urban resilience/affordability DT; no DfS/DfQ focus | AO8: 10.1016/j.scs.2026.107413
A9: 5 | B9: Vallée, A (2026) | C9: 2026 | E9: From prediction to intervention: causal digital twins for personalized clinical decision support | F9: Scopus | G9: No | H9: Yes | I9: No | J9: Yes | K9: Yes | L9: =IF(COUNTBLANK(G9:K9)=5,"",IF(COUNTIF(G9:K9,"No")>0,"EXCLUDE","INCLUDE")) -> EXCLUDE | M9: =IF(L9<>"EXCLUDE","",IF(G9="No","Wrong domain (non-AECO)",IF(H9="No","Digital Twin not core / buzzword",IF(I9="No","No Design for Safety / PtD focus",IF(J9="No","Wrong publication type",IF(K9="No","Non-English","")))))) -> Wrong domain (non-AECO) | S9: =IF(N9<>"Yes","",IF(COUNTBLANK(P9:R9)=3,"",IF(COUNTIF(P9:R9,"No")>0,"EXCLUDE","INCLUDE"))) | T9: =IF(S9<>"EXCLUDE","",IF(P9="No","Digital Twin mentioned only, not the subject",IF(Q9="No","No Design for Safety focus in full text",IF(R9="No","Methodology not codable","")))) | Y9: =IF(SUM(V9:X9)=0,"",IF(SUM(V9:X9)>=2,"Multi","Single")) | AN9: Step-1 note: Clinical causal DT; healthcare domain | AO9: 10.1186/s12967-026-07895-8
A10: 6 | B10: Redondo, P et al. (2026) | C10: 2026 | E10: Residual dynamic spatio-temporal graph attention network for enhanced urban traffic origin/destination demand calibration | F10: Scopus | G10: No | H10: Yes | I10: No | J10: Yes | K10: Yes | L10: =IF(COUNTBLANK(G10:K10)=5,"",IF(COUNTIF(G10:K10,"No")>0,"EXCLUDE","INCLUDE")) -> EXCLUDE | M10: =IF(L10<>"EXCLUDE","",IF(G10="No","Wrong domain (non-AECO)",IF(H10="No","Digital Twin not core / buzzword",IF(I10="No","No Design for Safety / PtD focus",IF(J10="No","Wrong publication type",IF(K10="No","Non-English","")))))) -> Wrong domain (non-AECO) | S10: =IF(N10<>"Yes","",IF(COUNTBLANK(P10:R10)=3,"",IF(COUNTIF(P10:R10,"No")>0,"EXCLUDE","INCLUDE"))) | T10: =IF(S10<>"EXCLUDE","",IF(P10="No","Digital Twin mentioned only, not the subject",IF(Q10="No","No Design for Safety focus in full text",IF(R10="No","Methodology not codable","")))) | Y10: =IF(SUM(V10:X10)=0,"",IF(SUM(V10:X10)>=2,"Multi","Single")) | AN10: Step-1 note: Traffic OD calibration; SUMO as DT, not built asset | AO10: 10.1108/EC-09-2024-0900
A11: 7 | B11: Guo, X et al. (2026) | C11: 2026 | E11: Digital twin-enabled cooperative autonomous truck platooning framework for modeling, cost estimation, and decision-making in transportation systems | F11: Scopus | G11: No | H11: Yes | I11: No | J11: Yes | K11: Yes | L11: =IF(COUNTBLANK(G11:K11)=5,"",IF(COUNTIF(G11:K11,"No")>0,"EXCLUDE","INCLUDE")) -> EXCLUDE | M11: =IF(L11<>"EXCLUDE","",IF(G11="No","Wrong domain (non-AECO)",IF(H11="No","Digital Twin not core / buzzword",IF(I11="No","No Design for Safety / PtD focus",IF(J11="No","Wrong publication type",IF(K11="No","Non-English","")))))) -> Wrong domain (non-AECO) | S11: =IF(N11<>"Yes","",IF(COUNTBLANK(P11:R11)=3,"",IF(COUNTIF(P11:R11,"No")>0,"EXCLUDE","INCLUDE"))) | T11: =IF(S11<>"EXCLUDE","",IF(P11="No","Digital Twin mentioned only, not the subject",IF(Q11="No","No Design for Safety focus in full text",IF(R11="No","Methodology not codable","")))) | Y11: =IF(SUM(V11:X11)=0,"",IF(SUM(V11:X11)>=2,"Multi","Single")) | AN11: Step-1 note: Truck platooning logistics; not AECO | AO11: 10.1016/j.tre.2025.104596
A12: 8 | B12: Hong, K et al. (2025) | C12: 2025 | E12: Digital construction site layout planning and real-time trajectory analysis for proactive safety monitoring and control of struck-by hazards | F12: Scopus | G12: Yes | H12: Yes | I12: Yes | J12: Yes | K12: Yes | L12: =IF(COUNTBLANK(G12:K12)=5,"",IF(COUNTIF(G12:K12,"No")>0,"EXCLUDE","INCLUDE")) -> INCLUDE | M12: =IF(L12<>"EXCLUDE","",IF(G12="No","Wrong domain (non-AECO)",IF(H12="No","Digital Twin not core / buzzword",IF(I12="No","No Design for Safety / PtD focus",IF(J12="No","Wrong publication type",IF(K12="No","Non-English","")))))) | N12: Yes | O12: Yes | P12: Yes | Q12: Yes | R12: Yes | S12: =IF(N12<>"Yes","",IF(COUNTBLANK(P12:R12)=3,"",IF(COUNTIF(P12:R12,"No")>0,"EXCLUDE","INCLUDE"))) -> INCLUDE | T12: =IF(S12<>"EXCLUDE","",IF(P12="No","Digital Twin mentioned only, not the subject",IF(Q12="No","No Design for Safety focus in full text",IF(R12="No","Methodology not codable","")))) | U12: Tier 2 - Digital Shadow (one-way physical to virtual) | V12: 0 | W12: 1 | X12: 0 | Y12: =IF(SUM(V12:X12)=0,"",IF(SUM(V12:X12)>=2,"Multi","Single")) -> Single | Z12: Design for Safety (DfS) | AA12: None | AB12: Digital Twin platform (no machine learning) | AC12: Single (one data type) | AD12: Single case study | AE12: 4 | AF12: Design for Safety | AG12: Digital construction site layout planning and real-time trajectory analysis for proactive safety monitoring and control of struck-by hazards (DTCS Right-time Analysis and Mitigation module; DTU/TUM): RTK-GNSS + LoRa live location tracking of pedestrian workers and heavy equipment streamed to DTCS; semi-static and dynamic hazard zones (1-m boundary + operator blind-space geometry); real-time incident detection of unauthorized entry and too-close proximity; density maps / histogram heatmaps identify hazardous activities; safety-plan revision recommendations (separating worker/equipment areas, temporary pedestrian walkways); field experiments in Munich subway rail maintenance staging area showed significant reduction in spatial conflicts and improved zone connectivity, with newly detected hazards (rail traffic, delivery trucks) triggering iterative plan updates. One-way monitoring to analysis to mitigation recommendations/alerts for safety personnel; no actuation, no learning loop. [Full-text source: 04c-port] | AH12: Extends the Digital Twin for Construction Safety concept with a Right-time Analysis and Mitigation module tested at a Munich railway maintenance staging area: safeBIM rule checking plus RTK-GNSS over LoRa tracking at 1.0 cm median and 2.3 cm 95th percentile precision, detecting 99 unauthorized entries, mapping telehandler blind spots (right side obstructed to 1.9 m) and computing safety-weighted walkway routes that informed a revised safeBIM plan. | AI12: Experiments lasted a limited period in a controlled staging area, RTK-GNSS suffers signal loss and interference, and operator awareness of workers could not be recorded, so head-pose or eye-tracking data is proposed; future work includes longer data collection, other equipment types, drone-based condition capture, big data analytics and standards for safe distances. | AJ12: Single | AK12: Only RTK-GNSS over LoRa position tracking (1.0 cm median, 2.3 cm 95th percentile) drives the right-time analysis; no second measured data type exists. | AL12: High | AN12: Step-1 note: DTCS struck-by hazard monitoring; PtD planning | Coded from Step-3 deep-read markdown (DfS-only scope), imported 2026-10-04 | AO12: 10.1016/j.autcon.2025.106353
A13: 9 | B13: Oliinyk, V et al. (2025) | C13: 2025 | E13: Optimising the construction process through digitalisation: Case studies of projects under unstable resource supply | F13: Scopus | G13: Yes | H13: No | I13: No | J13: Yes | K13: Yes | L13: =IF(COUNTBLANK(G13:K13)=5,"",IF(COUNTIF(G13:K13,"No")>0,"EXCLUDE","INCLUDE")) -> EXCLUDE | M13: =IF(L13<>"EXCLUDE","",IF(G13="No","Wrong domain (non-AECO)",IF(H13="No","Digital Twin not core / buzzword",IF(I13="No","No Design for Safety / PtD focus",IF(J13="No","Wrong publication type",IF(K13="No","Non-English","")))))) -> Digital Twin not core / buzzword | S13: =IF(N13<>"Yes","",IF(COUNTBLANK(P13:R13)=3,"",IF(COUNTIF(P13:R13,"No")>0,"EXCLUDE","INCLUDE"))) | T13: =IF(S13<>"EXCLUDE","",IF(P13="No","Digital Twin mentioned only, not the subject",IF(Q13="No","No Design for Safety focus in full text",IF(R13="No","Methodology not codable","")))) | Y13: =IF(SUM(V13:X13)=0,"",IF(SUM(V13:X13)>=2,"Multi","Single")) | AN13: Step-1 note: Digitalisation overview; DT one of many technologies | AO13: 10.56318/as/1.2025.92
A14: 10 | B14: Zhao, B et al. (2026) | C14: 2026 | E14: From instance segmentation to physical quantification: High-resolution UAV-based dataset for façade defect assessment | F14: Scopus | G14: Yes | H14: No | I14: Yes | J14: Yes | K14: Yes | L14: =IF(COUNTBLANK(G14:K14)=5,"",IF(COUNTIF(G14:K14,"No")>0,"EXCLUDE","INCLUDE")) -> EXCLUDE | M14: =IF(L14<>"EXCLUDE","",IF(G14="No","Wrong domain (non-AECO)",IF(H14="No","Digital Twin not core / buzzword",IF(I14="No","No Design for Safety / PtD focus",IF(J14="No","Wrong publication type",IF(K14="No","Non-English","")))))) -> Digital Twin not core / buzzword | S14: =IF(N14<>"Yes","",IF(COUNTBLANK(P14:R14)=3,"",IF(COUNTIF(P14:R14,"No")>0,"EXCLUDE","INCLUDE"))) | T14: =IF(S14<>"EXCLUDE","",IF(P14="No","Digital Twin mentioned only, not the subject",IF(Q14="No","No Design for Safety focus in full text",IF(R14="No","Methodology not codable","")))) | Y14: =IF(SUM(V14:X14)=0,"",IF(SUM(V14:X14)>=2,"Multi","Single")) | AN14: Step-1 note: Defect dataset+segmentation; DT only deployment target | AO14: 10.1016/j.autcon.2026.106980
A15: 11 | B15: Kaewunruen, S et al. (2025) | C15: 2025 | E15: Digital twin-driven strategic demolition plan for circular asset management of bridge infrastructures | F15: Scopus | G15: Yes | H15: No | I15: No | J15: Yes | K15: Yes | L15: =IF(COUNTBLANK(G15:K15)=5,"",IF(COUNTIF(G15:K15,"No")>0,"EXCLUDE","INCLUDE")) -> EXCLUDE | M15: =IF(L15<>"EXCLUDE","",IF(G15="No","Wrong domain (non-AECO)",IF(H15="No","Digital Twin not core / buzzword",IF(I15="No","No Design for Safety / PtD focus",IF(J15="No","Wrong publication type",IF(K15="No","Non-English","")))))) -> Digital Twin not core / buzzword | S15: =IF(N15<>"Yes","",IF(COUNTBLANK(P15:R15)=3,"",IF(COUNTIF(P15:R15,"No")>0,"EXCLUDE","INCLUDE"))) | T15: =IF(S15<>"EXCLUDE","",IF(P15="No","Digital Twin mentioned only, not the subject",IF(Q15="No","No Design for Safety focus in full text",IF(R15="No","Methodology not codable","")))) | Y15: =IF(SUM(V15:X15)=0,"",IF(SUM(V15:X15)>=2,"Multi","Single")) | AN15: Step-1 note: BIM 6D circular demolition; no live DT, no DfS/DfQ | AO15: 10.1038/s41598-025-94117-8
A16: 12 | B16: Al-Sadoon, N et al. (2026) | C16: 2026 | E16: Enhancing resilience through environmental data integration in early construction planning: a cloud-based framework | F16: Scopus | G16: Yes | H16: No | I16: No | J16: Yes | K16: Yes | L16: =IF(COUNTBLANK(G16:K16)=5,"",IF(COUNTIF(G16:K16,"No")>0,"EXCLUDE","INCLUDE")) -> EXCLUDE | M16: =IF(L16<>"EXCLUDE","",IF(G16="No","Wrong domain (non-AECO)",IF(H16="No","Digital Twin not core / buzzword",IF(I16="No","No Design for Safety / PtD focus",IF(J16="No","Wrong publication type",IF(K16="No","Non-English","")))))) -> Digital Twin not core / buzzword | S16: =IF(N16<>"Yes","",IF(COUNTBLANK(P16:R16)=3,"",IF(COUNTIF(P16:R16,"No")>0,"EXCLUDE","INCLUDE"))) | T16: =IF(S16<>"EXCLUDE","",IF(P16="No","Digital Twin mentioned only, not the subject",IF(Q16="No","No Design for Safety focus in full text",IF(R16="No","Methodology not codable","")))) | Y16: =IF(SUM(V16:X16)=0,"",IF(SUM(V16:X16)>=2,"Multi","Single")) | AN16: Step-1 note: BIM-ICDD semantic linking; no DT | AO16: 10.3389/fbuil.2026.1748837
A17: 13 | B17: Jung, B et al. (2025) | C17: 2025 | E17: Transient-Aware Multi-Objective Optimization of Water Distribution Systems for Cost and Fire Flow Reliability | F17: Scopus | G17: No | H17: No | I17: Yes | J17: Yes | K17: Yes | L17: =IF(COUNTBLANK(G17:K17)=5,"",IF(COUNTIF(G17:K17,"No")>0,"EXCLUDE","INCLUDE")) -> EXCLUDE | M17: =IF(L17<>"EXCLUDE","",IF(G17="No","Wrong domain (non-AECO)",IF(H17="No","Digital Twin not core / buzzword",IF(I17="No","No Design for Safety / PtD focus",IF(J17="No","Wrong publication type",IF(K17="No","Non-English","")))))) -> Wrong domain (non-AECO) | S17: =IF(N17<>"Yes","",IF(COUNTBLANK(P17:R17)=3,"",IF(COUNTIF(P17:R17,"No")>0,"EXCLUDE","INCLUDE"))) | T17: =IF(S17<>"EXCLUDE","",IF(P17="No","Digital Twin mentioned only, not the subject",IF(Q17="No","No Design for Safety focus in full text",IF(R17="No","Methodology not codable","")))) | Y17: =IF(SUM(V17:X17)=0,"",IF(SUM(V17:X17)>=2,"Multi","Single")) | AN17: Step-1 note: Water distribution optimization; no DT, not AECO | AO17: 10.3390/su17188274
A18: 14 | B18: Sigmund, Z et al. (2026) | C18: 2026 | E18: Reducing Latency in Digital Twins: A Framework for Near-Real-Time Progress and Quality Reporting | F18: Scopus | G18: Yes | H18: Yes | I18: Yes | J18: Yes | K18: Yes | L18: =IF(COUNTBLANK(G18:K18)=5,"",IF(COUNTIF(G18:K18,"No")>0,"EXCLUDE","INCLUDE")) -> INCLUDE | M18: =IF(L18<>"EXCLUDE","",IF(G18="No","Wrong domain (non-AECO)",IF(H18="No","Digital Twin not core / buzzword",IF(I18="No","No Design for Safety / PtD focus",IF(J18="No","Wrong publication type",IF(K18="No","Non-English","")))))) | N18: Yes | O18: Yes | P18: Yes | Q18: Yes | R18: Yes | S18: =IF(N18<>"Yes","",IF(COUNTBLANK(P18:R18)=3,"",IF(COUNTIF(P18:R18,"No")>0,"EXCLUDE","INCLUDE"))) -> INCLUDE | T18: =IF(S18<>"EXCLUDE","",IF(P18="No","Digital Twin mentioned only, not the subject",IF(Q18="No","No Design for Safety focus in full text",IF(R18="No","Methodology not codable","")))) | U18: Tier 2 - Digital Shadow (one-way physical to virtual) | V18: 0 | W18: 1 | X18: 0 | Y18: =IF(SUM(V18:X18)=0,"",IF(SUM(V18:X18)>=2,"Multi","Single")) -> Single | Z18: Design for Safety (DfS) | AA18: None | AB18: Computer Vision / CNN / object-detection | AC18: Multi (two or more data types) | AD18: Conceptual (no test) | AE18: 2 | AF18: Perception / Computer Vision | AG18: Technical note (Buildings 2026, U Zagreb): proposes a tiered edge-cloud processing framework for near-real-time automated progress monitoring and quality reporting, synthesising NORMENG field metrics (terrestrial LiDAR, UAS photogrammetry, 360-degree vision); shifts to neural rendering to bypass photogrammetric latency; lightweight edge analysis for immediate safety/progress alarms plus asynchronous high-fidelity DT updates as single source of truth. Framework only - no implementation or empirical validation (informs AutoGreenTraC). One-way sensing->analysis->reporting; no actuation, no learning loop. [Full-text source: browser-oa] | AH18: Identifies data-acquisition latency and photogrammetric compute as the two bottlenecks and contributes a tiered edge-cloud hierarchy (millisecond safety alarms to asynchronous high-fidelity DT updates) with neural rendering as the latency bypass, grounded in NORMENG field metrics. | AI18: No implementation or empirical validation; latency targets, neural-rendering pipeline details and DT update scheduling remain future work in AutoGreenTraC. | AJ18: Unclear | AK18: LiDAR, SfM-MVS and 360-degree streams are discussed within a tiered hierarchy but no fusion mechanism is implemented or tested (framework only). | AL18: Low | AM18: REVIEW: fusion Unclear / Low confidence | AN18: Step-1 note: DT framework for near-real-time progress/quality reporting | Methodology label normalised (source: "Perception / Computer Vision") | Coded from Step-3 deep-read markdown (DfS-only scope), imported 2026-10-04 | AO18: 10.3390/buildings16071448
A19: 15 | B19: Cao, J et al. (2026) | C19: 2026 | E19: In-Depth Discussion on the Construction of Security Collaborative Management and Control System Based on Digital Twins and Intelligent Sensing in the United Nations Clean Coal Project | F19: Scopus | G19: No | H19: Yes | I19: Yes | J19: Yes | K19: Yes | L19: =IF(COUNTBLANK(G19:K19)=5,"",IF(COUNTIF(G19:K19,"No")>0,"EXCLUDE","INCLUDE")) -> EXCLUDE | M19: =IF(L19<>"EXCLUDE","",IF(G19="No","Wrong domain (non-AECO)",IF(H19="No","Digital Twin not core / buzzword",IF(I19="No","No Design for Safety / PtD focus",IF(J19="No","Wrong publication type",IF(K19="No","Non-English","")))))) -> Wrong domain (non-AECO) | S19: =IF(N19<>"Yes","",IF(COUNTBLANK(P19:R19)=3,"",IF(COUNTIF(P19:R19,"No")>0,"EXCLUDE","INCLUDE"))) | T19: =IF(S19<>"EXCLUDE","",IF(P19="No","Digital Twin mentioned only, not the subject",IF(Q19="No","No Design for Safety focus in full text",IF(R19="No","Methodology not codable","")))) | Y19: =IF(SUM(V19:X19)=0,"",IF(SUM(V19:X19)>=2,"Multi","Single")) | AN19: Step-1 note: Clean coal industrial project; not AECO built asset | AO19: 10.7716/aem.v15i3.3430
A20: 16 | B20: Kanyilmaz, A et al. (2026) | C20: 2026 | E20: AI-driven assessment of steel structures | F20: Scopus | G20: Yes | H20: No | I20: Yes | J20: Yes | K20: Yes | L20: =IF(COUNTBLANK(G20:K20)=5,"",IF(COUNTIF(G20:K20,"No")>0,"EXCLUDE","INCLUDE")) -> EXCLUDE | M20: =IF(L20<>"EXCLUDE","",IF(G20="No","Wrong domain (non-AECO)",IF(H20="No","Digital Twin not core / buzzword",IF(I20="No","No Design for Safety / PtD focus",IF(J20="No","Wrong publication type",IF(K20="No","Non-English","")))))) -> Digital Twin not core / buzzword | S20: =IF(N20<>"Yes","",IF(COUNTBLANK(P20:R20)=3,"",IF(COUNTIF(P20:R20,"No")>0,"EXCLUDE","INCLUDE"))) | T20: =IF(S20<>"EXCLUDE","",IF(P20="No","Digital Twin mentioned only, not the subject",IF(Q20="No","No Design for Safety focus in full text",IF(R20="No","Methodology not codable","")))) | Y20: =IF(SUM(V20:X20)=0,"",IF(SUM(V20:X20)>=2,"Multi","Single")) | AN20: Step-1 note: AI assessment case-study review; DT one of several methods | AO20: 10.1002/stab.70174
A21: 17 | B21: Casini, M (2026) | C21: 2026 | E21: From WebGIS to a Digital Twin for Sustainable Water Governance and Climate-Resilient River Basin District Planning: The AUBAC Case in Central Italy | F21: Scopus | G21: No | H21: Yes | I21: No | J21: Yes | K21: Yes | L21: =IF(COUNTBLANK(G21:K21)=5,"",IF(COUNTIF(G21:K21,"No")>0,"EXCLUDE","INCLUDE")) -> EXCLUDE | M21: =IF(L21<>"EXCLUDE","",IF(G21="No","Wrong domain (non-AECO)",IF(H21="No","Digital Twin not core / buzzword",IF(I21="No","No Design for Safety / PtD focus",IF(J21="No","Wrong publication type",IF(K21="No","Non-English","")))))) -> Wrong domain (non-AECO) | S21: =IF(N21<>"Yes","",IF(COUNTBLANK(P21:R21)=3,"",IF(COUNTIF(P21:R21,"No")>0,"EXCLUDE","INCLUDE"))) | T21: =IF(S21<>"EXCLUDE","",IF(P21="No","Digital Twin mentioned only, not the subject",IF(Q21="No","No Design for Safety focus in full text",IF(R21="No","Methodology not codable","")))) | Y21: =IF(SUM(V21:X21)=0,"",IF(SUM(V21:X21)>=2,"Multi","Single")) | AN21: Step-1 note: River-basin water governance; not built asset | AO21: 10.3390/su18052168
A22: 18 | B22: Gao, K et al. (2026) | C22: 2026 | E22: Resilient ventilation network construction in complex underground mining environments: A holistic strategy from resilience perception to resilience enhancement | F22: Scopus | G22: No | H22: Yes | I22: Yes | J22: Yes | K22: Yes | L22: =IF(COUNTBLANK(G22:K22)=5,"",IF(COUNTIF(G22:K22,"No")>0,"EXCLUDE","INCLUDE")) -> EXCLUDE | M22: =IF(L22<>"EXCLUDE","",IF(G22="No","Wrong domain (non-AECO)",IF(H22="No","Digital Twin not core / buzzword",IF(I22="No","No Design for Safety / PtD focus",IF(J22="No","Wrong publication type",IF(K22="No","Non-English","")))))) -> Wrong domain (non-AECO) | S22: =IF(N22<>"Yes","",IF(COUNTBLANK(P22:R22)=3,"",IF(COUNTIF(P22:R22,"No")>0,"EXCLUDE","INCLUDE"))) | T22: =IF(S22<>"EXCLUDE","",IF(P22="No","Digital Twin mentioned only, not the subject",IF(Q22="No","No Design for Safety focus in full text",IF(R22="No","Methodology not codable","")))) | Y22: =IF(SUM(V22:X22)=0,"",IF(SUM(V22:X22)>=2,"Multi","Single")) | AN22: Step-1 note: Mine ventilation resilience; mining domain | AO22: 10.1016/j.ress.2026.112634
A23: 19 | B23: Wang, G et al. (2025) | C23: 2025 | E23: Research on modeling and application of digital twin system for mine auxiliary transportation | F23: Scopus | G23: No | H23: Yes | I23: Yes | J23: Yes | K23: Yes | L23: =IF(COUNTBLANK(G23:K23)=5,"",IF(COUNTIF(G23:K23,"No")>0,"EXCLUDE","INCLUDE")) -> EXCLUDE | M23: =IF(L23<>"EXCLUDE","",IF(G23="No","Wrong domain (non-AECO)",IF(H23="No","Digital Twin not core / buzzword",IF(I23="No","No Design for Safety / PtD focus",IF(J23="No","Wrong publication type",IF(K23="No","Non-English","")))))) -> Wrong domain (non-AECO) | S23: =IF(N23<>"Yes","",IF(COUNTBLANK(P23:R23)=3,"",IF(COUNTIF(P23:R23,"No")>0,"EXCLUDE","INCLUDE"))) | T23: =IF(S23<>"EXCLUDE","",IF(P23="No","Digital Twin mentioned only, not the subject",IF(Q23="No","No Design for Safety focus in full text",IF(R23="No","Methodology not codable","")))) | Y23: =IF(SUM(V23:X23)=0,"",IF(SUM(V23:X23)>=2,"Multi","Single")) | AN23: Step-1 note: Mine auxiliary transport DT; mining domain | AO23: 10.1142/S1793962325500618
A24: 20 | B24: Zheng, H et al. (2026) | C24: 2026 | E24: Photorealistic Fire Scene Video Generation via Multimodal Large Language Model and Pre-Trained Video Diffusion Model | F24: Scopus | G24: No | H24: No | I24: No | J24: Yes | K24: Yes | L24: =IF(COUNTBLANK(G24:K24)=5,"",IF(COUNTIF(G24:K24,"No")>0,"EXCLUDE","INCLUDE")) -> EXCLUDE | M24: =IF(L24<>"EXCLUDE","",IF(G24="No","Wrong domain (non-AECO)",IF(H24="No","Digital Twin not core / buzzword",IF(I24="No","No Design for Safety / PtD focus",IF(J24="No","Wrong publication type",IF(K24="No","Non-English","")))))) -> Wrong domain (non-AECO) | S24: =IF(N24<>"Yes","",IF(COUNTBLANK(P24:R24)=3,"",IF(COUNTIF(P24:R24,"No")>0,"EXCLUDE","INCLUDE"))) | T24: =IF(S24<>"EXCLUDE","",IF(P24="No","Digital Twin mentioned only, not the subject",IF(Q24="No","No Design for Safety focus in full text",IF(R24="No","Methodology not codable","")))) | Y24: =IF(SUM(V24:X24)=0,"",IF(SUM(V24:X24)>=2,"Multi","Single")) | AN24: Step-1 note: Text-to-video fire generation; DT only future use | AO24: 10.26599/CVM.2025.9450511
A25: 21 | B25: Mahomed, A.S et al. (2025) | C25: 2025 | E25: Unleashing the Potential of 5G for Smart Cities: A Focus on Real-Time Digital Twin Integration | F25: Scopus | G25: Yes | H25: No | I25: No | J25: Yes | K25: Yes | L25: =IF(COUNTBLANK(G25:K25)=5,"",IF(COUNTIF(G25:K25,"No")>0,"EXCLUDE","INCLUDE")) -> EXCLUDE | M25: =IF(L25<>"EXCLUDE","",IF(G25="No","Wrong domain (non-AECO)",IF(H25="No","Digital Twin not core / buzzword",IF(I25="No","No Design for Safety / PtD focus",IF(J25="No","Wrong publication type",IF(K25="No","Non-English","")))))) -> Digital Twin not core / buzzword | S25: =IF(N25<>"Yes","",IF(COUNTBLANK(P25:R25)=3,"",IF(COUNTIF(P25:R25,"No")>0,"EXCLUDE","INCLUDE"))) | T25: =IF(S25<>"EXCLUDE","",IF(P25="No","Digital Twin mentioned only, not the subject",IF(Q25="No","No Design for Safety focus in full text",IF(R25="No","Methodology not codable","")))) | Y25: =IF(SUM(V25:X25)=0,"",IF(SUM(V25:X25)>=2,"Multi","Single")) | AN25: Step-1 note: 5G smart-city review; DT beneficiary, safety peripheral | AO25: 10.3390/smartcities8020070
A26: 22 | B26: Seng, N.H et al. (2025) | C26: 2025 | E26: Mapping the Evolution of 4D BIM in Construction Digitalisation: A Scientometric Analysis and Review | F26: Scopus | G26: Yes | H26: No | I26: No | J26: Yes | K26: Yes | L26: =IF(COUNTBLANK(G26:K26)=5,"",IF(COUNTIF(G26:K26,"No")>0,"EXCLUDE","INCLUDE")) -> EXCLUDE | M26: =IF(L26<>"EXCLUDE","",IF(G26="No","Wrong domain (non-AECO)",IF(H26="No","Digital Twin not core / buzzword",IF(I26="No","No Design for Safety / PtD focus",IF(J26="No","Wrong publication type",IF(K26="No","Non-English","")))))) -> Digital Twin not core / buzzword | S26: =IF(N26<>"Yes","",IF(COUNTBLANK(P26:R26)=3,"",IF(COUNTIF(P26:R26,"No")>0,"EXCLUDE","INCLUDE"))) | T26: =IF(S26<>"EXCLUDE","",IF(P26="No","Digital Twin mentioned only, not the subject",IF(Q26="No","No Design for Safety focus in full text",IF(R26="No","Methodology not codable","")))) | Y26: =IF(SUM(V26:X26)=0,"",IF(SUM(V26:X26)>=2,"Multi","Single")) | AN26: Step-1 note: 4D BIM scientometric; no DT core | AO26: 10.17576/jkukm-2025-37(6)-11
A27: 23 | B27: Cui, X (2026) | C27: 2026 | E27: Artificial intelligence assisted structural realignment of high-rise buildings through lifting, grouting and reinforcement | F27: Scopus | G27: Yes | H27: No | I27: Yes | J27: Yes | K27: Yes | L27: =IF(COUNTBLANK(G27:K27)=5,"",IF(COUNTIF(G27:K27,"No")>0,"EXCLUDE","INCLUDE")) -> EXCLUDE | M27: =IF(L27<>"EXCLUDE","",IF(G27="No","Wrong domain (non-AECO)",IF(H27="No","Digital Twin not core / buzzword",IF(I27="No","No Design for Safety / PtD focus",IF(J27="No","Wrong publication type",IF(K27="No","Non-English","")))))) -> Digital Twin not core / buzzword | S27: =IF(N27<>"Yes","",IF(COUNTBLANK(P27:R27)=3,"",IF(COUNTIF(P27:R27,"No")>0,"EXCLUDE","INCLUDE"))) | T27: =IF(S27<>"EXCLUDE","",IF(P27="No","Digital Twin mentioned only, not the subject",IF(Q27="No","No Design for Safety focus in full text",IF(R27="No","Methodology not codable","")))) | Y27: =IF(SUM(V27:X27)=0,"",IF(SUM(V27:X27)>=2,"Multi","Single")) | AN27: Step-1 note: AI rectification scoping review; DT one element | AO27: 10.1038/s41598-026-48789-5
A28: 24 | B28: Ammairih, A (2025) | C28: 2025 | E28: A methodological approach to hybrid AI systems for real-time infrastructure monitoring in civil engineering | F28: Scopus | G28: Yes | H28: No | I28: Yes | J28: Yes | K28: Yes | L28: =IF(COUNTBLANK(G28:K28)=5,"",IF(COUNTIF(G28:K28,"No")>0,"EXCLUDE","INCLUDE")) -> EXCLUDE | M28: =IF(L28<>"EXCLUDE","",IF(G28="No","Wrong domain (non-AECO)",IF(H28="No","Digital Twin not core / buzzword",IF(I28="No","No Design for Safety / PtD focus",IF(J28="No","Wrong publication type",IF(K28="No","Non-English","")))))) -> Digital Twin not core / buzzword | S28: =IF(N28<>"Yes","",IF(COUNTBLANK(P28:R28)=3,"",IF(COUNTIF(P28:R28,"No")>0,"EXCLUDE","INCLUDE"))) | T28: =IF(S28<>"EXCLUDE","",IF(P28="No","Digital Twin mentioned only, not the subject",IF(Q28="No","No Design for Safety focus in full text",IF(R28="No","Methodology not codable","")))) | Y28: =IF(SUM(V28:X28)=0,"",IF(SUM(V28:X28)>=2,"Multi","Single")) | AN28: Step-1 note: Hybrid AI SHM framework; no DT built | AO28: 10.1007/s42107-025-01409-5
A29: 25 | B29: Zhou, X et al. (2025) | C29: 2025 | E29: Scheme and algorithm designs for optical fiber sensors based configuration inversion of umbilical cables in deep-water | F29: Scopus | G29: No | H29: No | I29: Yes | J29: Yes | K29: Yes | L29: =IF(COUNTBLANK(G29:K29)=5,"",IF(COUNTIF(G29:K29,"No")>0,"EXCLUDE","INCLUDE")) -> EXCLUDE | M29: =IF(L29<>"EXCLUDE","",IF(G29="No","Wrong domain (non-AECO)",IF(H29="No","Digital Twin not core / buzzword",IF(I29="No","No Design for Safety / PtD focus",IF(J29="No","Wrong publication type",IF(K29="No","Non-English","")))))) -> Wrong domain (non-AECO) | S29: =IF(N29<>"Yes","",IF(COUNTBLANK(P29:R29)=3,"",IF(COUNTIF(P29:R29,"No")>0,"EXCLUDE","INCLUDE"))) | T29: =IF(S29<>"EXCLUDE","",IF(P29="No","Digital Twin mentioned only, not the subject",IF(Q29="No","No Design for Safety focus in full text",IF(R29="No","Methodology not codable","")))) | Y29: =IF(SUM(V29:X29)=0,"",IF(SUM(V29:X29)>=2,"Multi","Single")) | AN29: Step-1 note: Deep-water umbilical cables; marine, not AECO | AO29: 10.1016/j.oceaneng.2025.121363
A30: 26 | B30: Han, F et al. (2026) | C30: 2026 | E30: Construction Path of Shanghai Oriental Hub Municipal Pipeline Full Cycle Digital Twin Platform | F30: Scopus | G30: Yes | H30: Yes | I30: Yes | J30: Yes | K30: Yes | L30: =IF(COUNTBLANK(G30:K30)=5,"",IF(COUNTIF(G30:K30,"No")>0,"EXCLUDE","INCLUDE")) -> INCLUDE | M30: =IF(L30<>"EXCLUDE","",IF(G30="No","Wrong domain (non-AECO)",IF(H30="No","Digital Twin not core / buzzword",IF(I30="No","No Design for Safety / PtD focus",IF(J30="No","Wrong publication type",IF(K30="No","Non-English","")))))) | N30: Yes | O30: Yes | P30: Yes | Q30: Yes | R30: Yes | S30: =IF(N30<>"Yes","",IF(COUNTBLANK(P30:R30)=3,"",IF(COUNTIF(P30:R30,"No")>0,"EXCLUDE","INCLUDE"))) -> INCLUDE | T30: =IF(S30<>"EXCLUDE","",IF(P30="No","Digital Twin mentioned only, not the subject",IF(Q30="No","No Design for Safety focus in full text",IF(R30="No","Methodology not codable","")))) | U30: Tier 2 - Digital Shadow (one-way physical to virtual) | V30: 1 | W30: 1 | X30: 1 | Y30: =IF(SUM(V30:X30)=0,"",IF(SUM(V30:X30)>=2,"Multi","Single")) -> Multi | Z30: Design for Safety (DfS) | AA30: None | AB30: Other / Mixed | AC30: Multi (two or more data types) | AD30: Single case study | AE30: 4 | AF30: Lifecycle / governance | AG30: Full-cycle municipal pipeline DT platform (Shanghai Oriental Hub): BIM0–BIM6 full-phase connection + lightweight BIM-GIS, 28 IoT sensing nodes (water pressure, gas leakage, surface temp, <1 s delay) with 5-month pilot; addresses planning collision risks, construction rework, and delayed leakage detection; AI risk model predicted a valve aging risk 7 days in advance (verified on-site); 36.4% O&M cost reduction. One-way IoT→platform monitoring/decision support, no actuation and no self-improvement loop. [Full-text source: 04c-port] | AH30: Fills the gap between macro city-level twin frameworks and single-phase pipeline platforms with a full-cycle BIM0 to BIM6 plus lightweight BIM-GIS architecture for the Shanghai Oriental Hub; a 5-month pilot deployed 28 IoT nodes (pressure, gas leakage, surface temperature) with under 1 s delay, raising planning collision detection from 68 to 97 percent and predicting one valve aging risk 7 days in advance. | AI30: The pilot covers only water supply and gas pipelines, lacking power and communication monitoring modules, and its data is not yet connected to Pudong Airport systems for cross-node emergency linkage; multi-type pipeline adaptability and cross-departmental data interface standards are stated as future work. | AJ30: Aligned | AK30: Twenty-eight IoT sensing nodes (water pressure, gas leakage, surface temperature) are mapped into a lightweight BIM-GIS platform, and the AI risk model predicts per-asset (valve aging) rather than fusing streams. | AL30: Medium | AN30: Step-1 note: Full-cycle municipal pipeline DT; safe operation focus | Coded from Step-3 deep-read markdown (DfS-only scope), imported 2026-10-04 | AO30: 10.1155/adce/8916300
A31: 27 | B31: Carlini, B et al. (2025) | C31: 2025 | E31: Enhancing climate resilience in urban areas through satellite data: A case study of flood mapping during a rainfall event in Tuscany, Italy | F31: Scopus | G31: Yes | H31: No | I31: Yes | J31: Yes | K31: Yes | L31: =IF(COUNTBLANK(G31:K31)=5,"",IF(COUNTIF(G31:K31,"No")>0,"EXCLUDE","INCLUDE")) -> EXCLUDE | M31: =IF(L31<>"EXCLUDE","",IF(G31="No","Wrong domain (non-AECO)",IF(H31="No","Digital Twin not core / buzzword",IF(I31="No","No Design for Safety / PtD focus",IF(J31="No","Wrong publication type",IF(K31="No","Non-English","")))))) -> Digital Twin not core / buzzword | S31: =IF(N31<>"Yes","",IF(COUNTBLANK(P31:R31)=3,"",IF(COUNTIF(P31:R31,"No")>0,"EXCLUDE","INCLUDE"))) | T31: =IF(S31<>"EXCLUDE","",IF(P31="No","Digital Twin mentioned only, not the subject",IF(Q31="No","No Design for Safety focus in full text",IF(R31="No","Methodology not codable","")))) | Y31: =IF(SUM(V31:X31)=0,"",IF(SUM(V31:X31)>=2,"Multi","Single")) | AN31: Step-1 note: SAR flood mapping; GIS DT only supporting tool | AO31: 10.1016/j.heliyon.2025.e44108
A32: 28 | B32: Jian, R et al. (2026) | C32: 2026 | E32: BIM-GIS Integration for Collaborative Management in Complex Highway Engineering Projects | F32: Scopus | G32: Yes | H32: No | I32: Yes | J32: Yes | K32: Yes | L32: =IF(COUNTBLANK(G32:K32)=5,"",IF(COUNTIF(G32:K32,"No")>0,"EXCLUDE","INCLUDE")) -> EXCLUDE | M32: =IF(L32<>"EXCLUDE","",IF(G32="No","Wrong domain (non-AECO)",IF(H32="No","Digital Twin not core / buzzword",IF(I32="No","No Design for Safety / PtD focus",IF(J32="No","Wrong publication type",IF(K32="No","Non-English","")))))) -> Digital Twin not core / buzzword | S32: =IF(N32<>"Yes","",IF(COUNTBLANK(P32:R32)=3,"",IF(COUNTIF(P32:R32,"No")>0,"EXCLUDE","INCLUDE"))) | T32: =IF(S32<>"EXCLUDE","",IF(P32="No","Digital Twin mentioned only, not the subject",IF(Q32="No","No Design for Safety focus in full text",IF(R32="No","Methodology not codable","")))) | Y32: =IF(SUM(V32:X32)=0,"",IF(SUM(V32:X32)>=2,"Multi","Single")) | AN32: Step-1 note: BIM-GIS highway loop; DT integration future only | AO32: 10.4018/IJAEIS.414579
A33: 29 | B33: Choi, W.G et al. (2026) | C33: 2026 | E33: MirrorLake: A Digital Twin Platform for Real-Time Synchronization with the Real World | F33: Scopus | G33: No | H33: Yes | I33: No | J33: Yes | K33: Yes | L33: =IF(COUNTBLANK(G33:K33)=5,"",IF(COUNTIF(G33:K33,"No")>0,"EXCLUDE","INCLUDE")) -> EXCLUDE | M33: =IF(L33<>"EXCLUDE","",IF(G33="No","Wrong domain (non-AECO)",IF(H33="No","Digital Twin not core / buzzword",IF(I33="No","No Design for Safety / PtD focus",IF(J33="No","Wrong publication type",IF(K33="No","Non-English","")))))) -> Wrong domain (non-AECO) | S33: =IF(N33<>"Yes","",IF(COUNTBLANK(P33:R33)=3,"",IF(COUNTIF(P33:R33,"No")>0,"EXCLUDE","INCLUDE"))) | T33: =IF(S33<>"EXCLUDE","",IF(P33="No","Digital Twin mentioned only, not the subject",IF(Q33="No","No Design for Safety focus in full text",IF(R33="No","Methodology not codable","")))) | Y33: =IF(SUM(V33:X33)=0,"",IF(SUM(V33:X33)>=2,"Multi","Single")) | AN33: Step-1 note: Generic DT platform; AECO application unspecified | AO33: 10.1109/ACCESS.2026.3680878
A34: 30 | B34: Liu, W et al. (2026) | C34: 2026 | E34: Digital twin-enabled safety management: A bibliometric and knowledge mapping analysis with core challenge insights | F34: Scopus | G34: No | H34: Yes | I34: Yes | J34: Yes | K34: Yes | L34: =IF(COUNTBLANK(G34:K34)=5,"",IF(COUNTIF(G34:K34,"No")>0,"EXCLUDE","INCLUDE")) -> EXCLUDE | M34: =IF(L34<>"EXCLUDE","",IF(G34="No","Wrong domain (non-AECO)",IF(H34="No","Digital Twin not core / buzzword",IF(I34="No","No Design for Safety / PtD focus",IF(J34="No","Wrong publication type",IF(K34="No","Non-English","")))))) -> Wrong domain (non-AECO) | S34: =IF(N34<>"Yes","",IF(COUNTBLANK(P34:R34)=3,"",IF(COUNTIF(P34:R34,"No")>0,"EXCLUDE","INCLUDE"))) | T34: =IF(S34<>"EXCLUDE","",IF(P34="No","Digital Twin mentioned only, not the subject",IF(Q34="No","No Design for Safety focus in full text",IF(R34="No","Methodology not codable","")))) | Y34: =IF(SUM(V34:X34)=0,"",IF(SUM(V34:X34)>=2,"Multi","Single")) | AN34: Step-1 note: Process-industry DT-safety bibliometric; not AECO | AO34: 10.1016/j.jlp.2026.106105
A35: 31 | B35: Manocha, A et al. (2025) | C35: 2025 | E35: Enhancing sensor data reliability in structural health monitoring systems using digital twin technology | F35: Scopus | G35: Yes | H35: Yes | I35: Yes | J35: Yes | K35: Yes | L35: =IF(COUNTBLANK(G35:K35)=5,"",IF(COUNTIF(G35:K35,"No")>0,"EXCLUDE","INCLUDE")) -> INCLUDE | M35: =IF(L35<>"EXCLUDE","",IF(G35="No","Wrong domain (non-AECO)",IF(H35="No","Digital Twin not core / buzzword",IF(I35="No","No Design for Safety / PtD focus",IF(J35="No","Wrong publication type",IF(K35="No","Non-English","")))))) | N35: Yes | O35: Yes | P35: Yes | Q35: Yes | R35: Yes | S35: =IF(N35<>"Yes","",IF(COUNTBLANK(P35:R35)=3,"",IF(COUNTIF(P35:R35,"No")>0,"EXCLUDE","INCLUDE"))) -> INCLUDE | T35: =IF(S35<>"EXCLUDE","",IF(P35="No","Digital Twin mentioned only, not the subject",IF(Q35="No","No Design for Safety focus in full text",IF(R35="No","Methodology not codable","")))) | U35: Tier 2 - Digital Shadow (one-way physical to virtual) | V35: 0 | W35: 0 | X35: 1 | Y35: =IF(SUM(V35:X35)=0,"",IF(SUM(V35:X35)>=2,"Multi","Single")) -> Single | Z35: Design for Safety (DfS) | AA35: Implemented | AB35: Bayesian / probabilistic | AC35: Multi (two or more data types) | AD35: Single case study | AE35: 4 | AF35: Predictive analytics / decision support | AG35: cDTSHD structural-health DT framework links building smart sensors, cloud platform, virtual model and weighted Naive Bayes value-of-structural-health analysis to identify anomalies and building-health risk from irregular sensor data. Case-study validation tests the DT/cloud platform for real-time SHM; no actuation. [Full-text source: browser-oa] | AH35: Adds a sensor-data reliability layer to DT-enabled SHM, using weighted Naive Bayes and value-of-structural-health analysis to reduce misleading decisions from degraded sensors. | AI35: The demonstration is mainly one case/numerical SHM setup; broader building types, sensor suites, long-term drift and quantified false-alarm behaviour need validation. | AJ35: Fused | AK35: Building smart-sensor streams, cloud SHM data and virtual structural-health state are fused through weighted Naive Bayes and value-of-structural-health change analysis. | AL35: High | AN35: Step-1 note: DT + W-BBN for SHM sensor-data reliability incl. buildings | Coded from Step-3 deep-read markdown (DfS-only scope), imported 2026-10-04 | AO35: 10.1002/suco.202400969
A36: 32 | B36: Marangwanda, G.T et al. (2026) | C36: 2026 | E36: Development of a Boiler Monitoring System for Predictive Maintenance of Boiler Tube Failures | F36: Scopus | G36: No | H36: Yes | I36: Yes | J36: Yes | K36: Yes | L36: =IF(COUNTBLANK(G36:K36)=5,"",IF(COUNTIF(G36:K36,"No")>0,"EXCLUDE","INCLUDE")) -> EXCLUDE | M36: =IF(L36<>"EXCLUDE","",IF(G36="No","Wrong domain (non-AECO)",IF(H36="No","Digital Twin not core / buzzword",IF(I36="No","No Design for Safety / PtD focus",IF(J36="No","Wrong publication type",IF(K36="No","Non-English","")))))) -> Wrong domain (non-AECO) | S36: =IF(N36<>"Yes","",IF(COUNTBLANK(P36:R36)=3,"",IF(COUNTIF(P36:R36,"No")>0,"EXCLUDE","INCLUDE"))) | T36: =IF(S36<>"EXCLUDE","",IF(P36="No","Digital Twin mentioned only, not the subject",IF(Q36="No","No Design for Safety focus in full text",IF(R36="No","Methodology not codable","")))) | Y36: =IF(SUM(V36:X36)=0,"",IF(SUM(V36:X36)>=2,"Multi","Single")) | AN36: Step-1 note: Power-plant boiler monitoring; not AECO | AO36: 10.1115/1.4071543
A37: 33 | B37: Luning, X et al. (2025) | C37: 2025 | E37: Inversion model of stress state reconstruction for geological hazard pipelines based on digital twin | F37: Scopus | G37: No | H37: Yes | I37: Yes | J37: Yes | K37: Yes | L37: =IF(COUNTBLANK(G37:K37)=5,"",IF(COUNTIF(G37:K37,"No")>0,"EXCLUDE","INCLUDE")) -> EXCLUDE | M37: =IF(L37<>"EXCLUDE","",IF(G37="No","Wrong domain (non-AECO)",IF(H37="No","Digital Twin not core / buzzword",IF(I37="No","No Design for Safety / PtD focus",IF(J37="No","Wrong publication type",IF(K37="No","Non-English","")))))) -> Wrong domain (non-AECO) | S37: =IF(N37<>"Yes","",IF(COUNTBLANK(P37:R37)=3,"",IF(COUNTIF(P37:R37,"No")>0,"EXCLUDE","INCLUDE"))) | T37: =IF(S37<>"EXCLUDE","",IF(P37="No","Digital Twin mentioned only, not the subject",IF(Q37="No","No Design for Safety focus in full text",IF(R37="No","Methodology not codable","")))) | Y37: =IF(SUM(V37:X37)=0,"",IF(SUM(V37:X37)>=2,"Multi","Single")) | AN37: Step-1 note: Energy pipeline geohazard DT; not AECO | AO37: 10.1007/s42452-025-07435-x
A38: 34 | B38: Čaleta, D (2025) | C38: 2025 | E38: International Dimension of Critical Infrastructure Resilience: Challenges of the Mediterranean Security Environment | F38: Scopus | G38: Yes | H38: No | I38: No | J38: Yes | K38: Yes | L38: =IF(COUNTBLANK(G38:K38)=5,"",IF(COUNTIF(G38:K38,"No")>0,"EXCLUDE","INCLUDE")) -> EXCLUDE | M38: =IF(L38<>"EXCLUDE","",IF(G38="No","Wrong domain (non-AECO)",IF(H38="No","Digital Twin not core / buzzword",IF(I38="No","No Design for Safety / PtD focus",IF(J38="No","Wrong publication type",IF(K38="No","Non-English","")))))) -> Digital Twin not core / buzzword | S38: =IF(N38<>"Yes","",IF(COUNTBLANK(P38:R38)=3,"",IF(COUNTIF(P38:R38,"No")>0,"EXCLUDE","INCLUDE"))) | T38: =IF(S38<>"EXCLUDE","",IF(P38="No","Digital Twin mentioned only, not the subject",IF(Q38="No","No Design for Safety focus in full text",IF(R38="No","Methodology not codable","")))) | Y38: =IF(SUM(V38:X38)=0,"",IF(SUM(V38:X38)>=2,"Multi","Single")) | AN38: Step-1 note: CI resilience policy paper; no DT | AO38: 10.70908/2232-6022/18.177-205
A39: 35 | B39: Matsuk, Z et al. (2026) | C39: 2026 | E39: SYMMETRIC APPROACH TO INDUSTRIAL SAFETY RISK ASSESSMENT BASED ON MUTUAL PROBABILITY CORRESPONDENCE | F39: Scopus | G39: No | H39: No | I39: Yes | J39: Yes | K39: Yes | L39: =IF(COUNTBLANK(G39:K39)=5,"",IF(COUNTIF(G39:K39,"No")>0,"EXCLUDE","INCLUDE")) -> EXCLUDE | M39: =IF(L39<>"EXCLUDE","",IF(G39="No","Wrong domain (non-AECO)",IF(H39="No","Digital Twin not core / buzzword",IF(I39="No","No Design for Safety / PtD focus",IF(J39="No","Wrong publication type",IF(K39="No","Non-English","")))))) -> Wrong domain (non-AECO) | S39: =IF(N39<>"Yes","",IF(COUNTBLANK(P39:R39)=3,"",IF(COUNTIF(P39:R39,"No")>0,"EXCLUDE","INCLUDE"))) | T39: =IF(S39<>"EXCLUDE","",IF(P39="No","Digital Twin mentioned only, not the subject",IF(Q39="No","No Design for Safety focus in full text",IF(R39="No","Methodology not codable","")))) | Y39: =IF(SUM(V39:X39)=0,"",IF(SUM(V39:X39)>=2,"Multi","Single")) | AN39: Step-1 note: Industrial safety Bayesian network; not AECO | AO39: 10.15587/2706-5448.2026.353068
A40: 36 | B40: Kim, J et al. (2026) | C40: 2026 | E40: Active gravity-aligned reference Axis for high-precision verticality assessment in construction | F40: Scopus | G40: Yes | H40: No | I40: Yes | J40: Yes | K40: Yes | L40: =IF(COUNTBLANK(G40:K40)=5,"",IF(COUNTIF(G40:K40,"No")>0,"EXCLUDE","INCLUDE")) -> EXCLUDE | M40: =IF(L40<>"EXCLUDE","",IF(G40="No","Wrong domain (non-AECO)",IF(H40="No","Digital Twin not core / buzzword",IF(I40="No","No Design for Safety / PtD focus",IF(J40="No","Wrong publication type",IF(K40="No","Non-English","")))))) -> Digital Twin not core / buzzword | S40: =IF(N40<>"Yes","",IF(COUNTBLANK(P40:R40)=3,"",IF(COUNTIF(P40:R40,"No")>0,"EXCLUDE","INCLUDE"))) | T40: =IF(S40<>"EXCLUDE","",IF(P40="No","Digital Twin mentioned only, not the subject",IF(Q40="No","No Design for Safety focus in full text",IF(R40="No","Methodology not codable","")))) | Y40: =IF(SUM(V40:X40)=0,"",IF(SUM(V40:X40)>=2,"Multi","Single")) | AN40: Step-1 note: Verticality sensing device; no DT | AO40: 10.1016/j.autcon.2026.107025
A41: 37 | B41: Chen, Y et al. (2025) | C41: 2025 | E41: Automated dimension estimation of bridge components using semantic segmentation and geometric fitting of point cloud data | F41: Scopus | G41: Yes | H41: No | I41: Yes | J41: Yes | K41: Yes | L41: =IF(COUNTBLANK(G41:K41)=5,"",IF(COUNTIF(G41:K41,"No")>0,"EXCLUDE","INCLUDE")) -> EXCLUDE | M41: =IF(L41<>"EXCLUDE","",IF(G41="No","Wrong domain (non-AECO)",IF(H41="No","Digital Twin not core / buzzword",IF(I41="No","No Design for Safety / PtD focus",IF(J41="No","Wrong publication type",IF(K41="No","Non-English","")))))) -> Digital Twin not core / buzzword | S41: =IF(N41<>"Yes","",IF(COUNTBLANK(P41:R41)=3,"",IF(COUNTIF(P41:R41,"No")>0,"EXCLUDE","INCLUDE"))) | T41: =IF(S41<>"EXCLUDE","",IF(P41="No","Digital Twin mentioned only, not the subject",IF(Q41="No","No Design for Safety focus in full text",IF(R41="No","Methodology not codable","")))) | Y41: =IF(SUM(V41:X41)=0,"",IF(SUM(V41:X41)>=2,"Multi","Single")) | AN41: Step-1 note: Point-cloud dimension estimation; DT peripheral | AO41: 10.1016/j.engstruct.2025.120837
A42: 38 | B42: Liu, D et al. (2026) | C42: 2026 | E42: Advances in simulation technology for welding of non-metallic pipes: a systematic review and future perspectives | F42: Scopus | G42: No | H42: No | I42: Yes | J42: Yes | K42: Yes | L42: =IF(COUNTBLANK(G42:K42)=5,"",IF(COUNTIF(G42:K42,"No")>0,"EXCLUDE","INCLUDE")) -> EXCLUDE | M42: =IF(L42<>"EXCLUDE","",IF(G42="No","Wrong domain (non-AECO)",IF(H42="No","Digital Twin not core / buzzword",IF(I42="No","No Design for Safety / PtD focus",IF(J42="No","Wrong publication type",IF(K42="No","Non-English","")))))) -> Wrong domain (non-AECO) | S42: =IF(N42<>"Yes","",IF(COUNTBLANK(P42:R42)=3,"",IF(COUNTIF(P42:R42,"No")>0,"EXCLUDE","INCLUDE"))) | T42: =IF(S42<>"EXCLUDE","",IF(P42="No","Digital Twin mentioned only, not the subject",IF(Q42="No","No Design for Safety focus in full text",IF(R42="No","Methodology not codable","")))) | Y42: =IF(SUM(V42:X42)=0,"",IF(SUM(V42:X42)>=2,"Multi","Single")) | AN42: Step-1 note: Pipe welding simulation review; industrial | AO42: 10.1007/s00170-026-19002-8
A43: 39 | B43: Sassi, M.S.H et al. (2026) | C43: 2026 | E43: A cognitive digital twin architecture for intelligent gas distribution systems | F43: Scopus | G43: No | H43: Yes | I43: Yes | J43: Yes | K43: Yes | L43: =IF(COUNTBLANK(G43:K43)=5,"",IF(COUNTIF(G43:K43,"No")>0,"EXCLUDE","INCLUDE")) -> EXCLUDE | M43: =IF(L43<>"EXCLUDE","",IF(G43="No","Wrong domain (non-AECO)",IF(H43="No","Digital Twin not core / buzzword",IF(I43="No","No Design for Safety / PtD focus",IF(J43="No","Wrong publication type",IF(K43="No","Non-English","")))))) -> Wrong domain (non-AECO) | S43: =IF(N43<>"Yes","",IF(COUNTBLANK(P43:R43)=3,"",IF(COUNTIF(P43:R43,"No")>0,"EXCLUDE","INCLUDE"))) | T43: =IF(S43<>"EXCLUDE","",IF(P43="No","Digital Twin mentioned only, not the subject",IF(Q43="No","No Design for Safety focus in full text",IF(R43="No","Methodology not codable","")))) | Y43: =IF(SUM(V43:X43)=0,"",IF(SUM(V43:X43)>=2,"Multi","Single")) | AN43: Step-1 note: Gas utility cognitive DT; not built asset | AO43: 10.1016/j.sasc.2026.200532
A44: 40 | B44: Prokhorova, V.V et al. (2026) | C44: 2026 | E44: METHODOLOGY FOR ASSESSING THE CONDITION OF POWER PLANT UNITS USING DIGITAL TWIN MODELS; [Методика оцінки стану енергоблоків електростанцій із використанням моделей цифрових двійників] | F44: Scopus | G44: No | H44: Yes | I44: Yes | J44: Yes | K44: Yes | L44: =IF(COUNTBLANK(G44:K44)=5,"",IF(COUNTIF(G44:K44,"No")>0,"EXCLUDE","INCLUDE")) -> EXCLUDE | M44: =IF(L44<>"EXCLUDE","",IF(G44="No","Wrong domain (non-AECO)",IF(H44="No","Digital Twin not core / buzzword",IF(I44="No","No Design for Safety / PtD focus",IF(J44="No","Wrong publication type",IF(K44="No","Non-English","")))))) -> Wrong domain (non-AECO) | S44: =IF(N44<>"Yes","",IF(COUNTBLANK(P44:R44)=3,"",IF(COUNTIF(P44:R44,"No")>0,"EXCLUDE","INCLUDE"))) | T44: =IF(S44<>"EXCLUDE","",IF(P44="No","Digital Twin mentioned only, not the subject",IF(Q44="No","No Design for Safety focus in full text",IF(R44="No","Methodology not codable","")))) | Y44: =IF(SUM(V44:X44)=0,"",IF(SUM(V44:X44)>=2,"Multi","Single")) | AN44: Step-1 note: Nuclear power plant DT; not AECO | AO44: 10.33271/nvngu/2026-2/084
A45: 41 | B45: Heidari, M.R et al. (2026) | C45: 2026 | E45: Enhancing safety in construction: A framework predicting neuro-cognitive tipping points from environmental stressors | F45: Scopus | G45: Yes | H45: No | I45: Yes | J45: Yes | K45: Yes | L45: =IF(COUNTBLANK(G45:K45)=5,"",IF(COUNTIF(G45:K45,"No")>0,"EXCLUDE","INCLUDE")) -> EXCLUDE | M45: =IF(L45<>"EXCLUDE","",IF(G45="No","Wrong domain (non-AECO)",IF(H45="No","Digital Twin not core / buzzword",IF(I45="No","No Design for Safety / PtD focus",IF(J45="No","Wrong publication type",IF(K45="No","Non-English","")))))) -> Digital Twin not core / buzzword | S45: =IF(N45<>"Yes","",IF(COUNTBLANK(P45:R45)=3,"",IF(COUNTIF(P45:R45,"No")>0,"EXCLUDE","INCLUDE"))) | T45: =IF(S45<>"EXCLUDE","",IF(P45="No","Digital Twin mentioned only, not the subject",IF(Q45="No","No Design for Safety focus in full text",IF(R45="No","Methodology not codable","")))) | Y45: =IF(SUM(V45:X45)=0,"",IF(SUM(V45:X45)>=2,"Multi","Single")) | AN45: Step-1 note: Neuro-cognitive safety framework; no DT | AO45: 10.1016/j.ssci.2026.107369
A46: 42 | B46: Wang, S et al. (2026) | C46: 2026 | E46: Probabilistic Characteristics Study of Tensile Properties of Bamboo Inter-Node Material Based on Random Field Theory | F46: Scopus | G46: Yes | H46: No | I46: No | J46: Yes | K46: Yes | L46: =IF(COUNTBLANK(G46:K46)=5,"",IF(COUNTIF(G46:K46,"No")>0,"EXCLUDE","INCLUDE")) -> EXCLUDE | M46: =IF(L46<>"EXCLUDE","",IF(G46="No","Wrong domain (non-AECO)",IF(H46="No","Digital Twin not core / buzzword",IF(I46="No","No Design for Safety / PtD focus",IF(J46="No","Wrong publication type",IF(K46="No","Non-English","")))))) -> Digital Twin not core / buzzword | S46: =IF(N46<>"Yes","",IF(COUNTBLANK(P46:R46)=3,"",IF(COUNTIF(P46:R46,"No")>0,"EXCLUDE","INCLUDE"))) | T46: =IF(S46<>"EXCLUDE","",IF(P46="No","Digital Twin mentioned only, not the subject",IF(Q46="No","No Design for Safety focus in full text",IF(R46="No","Methodology not codable","")))) | Y46: =IF(SUM(V46:X46)=0,"",IF(SUM(V46:X46)>=2,"Multi","Single")) | AN46: Step-1 note: Bamboo random-field modelling; no DT | AO46: 10.3390/buildings16142826
A47: 43 | B47: Kiran, M et al. (2026) | C47: 2026 | E47: A digital twin framework for predicting and simulating type 2 diabetes onset using retrospective lifestyle data | F47: Scopus | G47: No | H47: Yes | I47: No | J47: Yes | K47: Yes | L47: =IF(COUNTBLANK(G47:K47)=5,"",IF(COUNTIF(G47:K47,"No")>0,"EXCLUDE","INCLUDE")) -> EXCLUDE | M47: =IF(L47<>"EXCLUDE","",IF(G47="No","Wrong domain (non-AECO)",IF(H47="No","Digital Twin not core / buzzword",IF(I47="No","No Design for Safety / PtD focus",IF(J47="No","Wrong publication type",IF(K47="No","Non-English","")))))) -> Wrong domain (non-AECO) | S47: =IF(N47<>"Yes","",IF(COUNTBLANK(P47:R47)=3,"",IF(COUNTIF(P47:R47,"No")>0,"EXCLUDE","INCLUDE"))) | T47: =IF(S47<>"EXCLUDE","",IF(P47="No","Digital Twin mentioned only, not the subject",IF(Q47="No","No Design for Safety focus in full text",IF(R47="No","Methodology not codable","")))) | Y47: =IF(SUM(V47:X47)=0,"",IF(SUM(V47:X47)>=2,"Multi","Single")) | AN47: Step-1 note: Diabetes prediction DT; healthcare | AO47: 10.3389/fdgth.2026.1710829
A48: 44 | B48: Kalkanlı, D et al. (2026) | C48: 2026 | E48: Human-Centric Digital Twins for Spatial Sustainability: A Procedural VR Framework for Calibrating Agent-Based Evacuation Models in Diverse Urban Morphologies | F48: Scopus | G48: Yes | H48: Yes | I48: Yes | J48: Yes | K48: Yes | L48: =IF(COUNTBLANK(G48:K48)=5,"",IF(COUNTIF(G48:K48,"No")>0,"EXCLUDE","INCLUDE")) -> INCLUDE | M48: =IF(L48<>"EXCLUDE","",IF(G48="No","Wrong domain (non-AECO)",IF(H48="No","Digital Twin not core / buzzword",IF(I48="No","No Design for Safety / PtD focus",IF(J48="No","Wrong publication type",IF(K48="No","Non-English","")))))) | N48: Yes | O48: Yes | P48: Yes | Q48: Yes | R48: Yes | S48: =IF(N48<>"Yes","",IF(COUNTBLANK(P48:R48)=3,"",IF(COUNTIF(P48:R48,"No")>0,"EXCLUDE","INCLUDE"))) -> INCLUDE | T48: =IF(S48<>"EXCLUDE","",IF(P48="No","Digital Twin mentioned only, not the subject",IF(Q48="No","No Design for Safety focus in full text",IF(R48="No","Methodology not codable","")))) | U48: Tier 1 - Digital Model (static, no live data) | V48: 1 | W48: 0 | X48: 1 | Y48: =IF(SUM(V48:X48)=0,"",IF(SUM(V48:X48)>=2,"Multi","Single")) -> Multi | Z48: Design for Safety (DfS) | AA48: None | AB48: Agent-based model (ABM) | AC48: Multi (two or more data types) | AD48: Simulation | AE48: 4 | AF48: Design for Safety | AG48: Human-centric digital twin framework (ITU/ITC, Sustainability 2026): procedural generation creates orthogonal vs organic urban morphologies; immersive VR acts as a behavioural wind tunnel to calibrate agent-based evacuation models; validated with 37 participants under day/night visibility; night evacuation in organic layouts showed greater variability and longer times, confirming spatial configuration dictates resilience. Static procedural models + VR experiments (no live data link); no actuation, no learning loop. [Full-text source: browser-oa] | AH48: Fills the behavioral data-scarcity gap in evacuation ABMs: procedural VR with 37 participants quantifies locomotion differences between orthogonal and organic morphologies, showing night-time divergence and confirming configuration-driven resilience in data-scarce settings. | AI48: VR experiments are controlled simulations rather than real evacuations; 37-participant sample and two archetypes limit generalisation, and the calibrated ABM is not validated against field evacuation data. | AJ48: Fused | AK48: VR-derived behavioural parameters and procedural geometry are fused into the calibrated ABM agents for evacuation simulation. | AL48: Medium | AN48: Step-1 note: Human-centric DT + VR evacuation calibration; life safety | Coded from Step-3 deep-read markdown (DfS-only scope), imported 2026-10-04 | AO48: 10.3390/su18031482
A49: 45 | B49: Liu, C et al. (2025) | C49: 2025 | E49: Vision language model-enhanced embodied intelligence for digital twin-assisted human-robot collaborative assembly | F49: Scopus | G49: No | H49: Yes | I49: Yes | J49: Yes | K49: Yes | L49: =IF(COUNTBLANK(G49:K49)=5,"",IF(COUNTIF(G49:K49,"No")>0,"EXCLUDE","INCLUDE")) -> EXCLUDE | M49: =IF(L49<>"EXCLUDE","",IF(G49="No","Wrong domain (non-AECO)",IF(H49="No","Digital Twin not core / buzzword",IF(I49="No","No Design for Safety / PtD focus",IF(J49="No","Wrong publication type",IF(K49="No","Non-English","")))))) -> Wrong domain (non-AECO) | S49: =IF(N49<>"Yes","",IF(COUNTBLANK(P49:R49)=3,"",IF(COUNTIF(P49:R49,"No")>0,"EXCLUDE","INCLUDE"))) | T49: =IF(S49<>"EXCLUDE","",IF(P49="No","Digital Twin mentioned only, not the subject",IF(Q49="No","No Design for Safety focus in full text",IF(R49="No","Methodology not codable","")))) | Y49: =IF(SUM(V49:X49)=0,"",IF(SUM(V49:X49)>=2,"Multi","Single")) | AN49: Step-1 note: Manufacturing HRC assembly; not AECO | AO49: 10.1016/j.jii.2025.100943
A50: 46 | B50: Cervantes E., MEng. et al. (2026) | C50: 2026 | E50: Climate Change Impacts on Reinforced Concrete Structures: A Bibliometric Analysis | F50: Scopus | G50: Yes | H50: No | I50: No | J50: Yes | K50: Yes | L50: =IF(COUNTBLANK(G50:K50)=5,"",IF(COUNTIF(G50:K50,"No")>0,"EXCLUDE","INCLUDE")) -> EXCLUDE | M50: =IF(L50<>"EXCLUDE","",IF(G50="No","Wrong domain (non-AECO)",IF(H50="No","Digital Twin not core / buzzword",IF(I50="No","No Design for Safety / PtD focus",IF(J50="No","Wrong publication type",IF(K50="No","Non-English","")))))) -> Digital Twin not core / buzzword | S50: =IF(N50<>"Yes","",IF(COUNTBLANK(P50:R50)=3,"",IF(COUNTIF(P50:R50,"No")>0,"EXCLUDE","INCLUDE"))) | T50: =IF(S50<>"EXCLUDE","",IF(P50="No","Digital Twin mentioned only, not the subject",IF(Q50="No","No Design for Safety focus in full text",IF(R50="No","Methodology not codable","")))) | Y50: =IF(SUM(V50:X50)=0,"",IF(SUM(V50:X50)>=2,"Multi","Single")) | AN50: Step-1 note: Climate/RC bibliometric; no DT core | AO50: 10.1080/10168664.2026.2649216
A51: 47 | B51: Huang, H et al. (2025) | C51: 2025 | E51: Parametric modeling and safety simulation of pit excavation affecting adjacent tunnels based on BIM-FEM framework | F51: Scopus | G51: Yes | H51: No | I51: Yes | J51: Yes | K51: Yes | L51: =IF(COUNTBLANK(G51:K51)=5,"",IF(COUNTIF(G51:K51,"No")>0,"EXCLUDE","INCLUDE")) -> EXCLUDE | M51: =IF(L51<>"EXCLUDE","",IF(G51="No","Wrong domain (non-AECO)",IF(H51="No","Digital Twin not core / buzzword",IF(I51="No","No Design for Safety / PtD focus",IF(J51="No","Wrong publication type",IF(K51="No","Non-English","")))))) -> Digital Twin not core / buzzword | S51: =IF(N51<>"Yes","",IF(COUNTBLANK(P51:R51)=3,"",IF(COUNTIF(P51:R51,"No")>0,"EXCLUDE","INCLUDE"))) | T51: =IF(S51<>"EXCLUDE","",IF(P51="No","Digital Twin mentioned only, not the subject",IF(Q51="No","No Design for Safety focus in full text",IF(R51="No","Methodology not codable","")))) | Y51: =IF(SUM(V51:X51)=0,"",IF(SUM(V51:X51)>=2,"Multi","Single")) | AN51: Step-1 note: BIM-FEM pit excavation framework; no DT | AO51: 10.1016/j.tust.2025.106800
A52: 48 | B52: Catalán, V et al. (2025) | C52: 2025 | E52: Virtual Reality and Digital Twins for Catastrophic Failure Prevention in Industry 4.0 | F52: Scopus | G52: No | H52: Yes | I52: Yes | J52: Yes | K52: Yes | L52: =IF(COUNTBLANK(G52:K52)=5,"",IF(COUNTIF(G52:K52,"No")>0,"EXCLUDE","INCLUDE")) -> EXCLUDE | M52: =IF(L52<>"EXCLUDE","",IF(G52="No","Wrong domain (non-AECO)",IF(H52="No","Digital Twin not core / buzzword",IF(I52="No","No Design for Safety / PtD focus",IF(J52="No","Wrong publication type",IF(K52="No","Non-English","")))))) -> Wrong domain (non-AECO) | S52: =IF(N52<>"Yes","",IF(COUNTBLANK(P52:R52)=3,"",IF(COUNTIF(P52:R52,"No")>0,"EXCLUDE","INCLUDE"))) | T52: =IF(S52<>"EXCLUDE","",IF(P52="No","Digital Twin mentioned only, not the subject",IF(Q52="No","No Design for Safety focus in full text",IF(R52="No","Methodology not codable","")))) | Y52: =IF(SUM(V52:X52)=0,"",IF(SUM(V52:X52)>=2,"Multi","Single")) | AN52: Step-1 note: Industrial engine VR/DT; not AECO | AO52: 10.3390/app15137230
A53: 49 | B53: Wang, H et al. (2026) | C53: 2026 | E53: Digital twin modeling for multi-component thermo-mechanical state inference with shared sparse-observation-and-physics constraints in a unified latent space | F53: Scopus | G53: No | H53: Yes | I53: Yes | J53: Yes | K53: Yes | L53: =IF(COUNTBLANK(G53:K53)=5,"",IF(COUNTIF(G53:K53,"No")>0,"EXCLUDE","INCLUDE")) -> EXCLUDE | M53: =IF(L53<>"EXCLUDE","",IF(G53="No","Wrong domain (non-AECO)",IF(H53="No","Digital Twin not core / buzzword",IF(I53="No","No Design for Safety / PtD focus",IF(J53="No","Wrong publication type",IF(K53="No","Non-English","")))))) -> Wrong domain (non-AECO) | S53: =IF(N53<>"Yes","",IF(COUNTBLANK(P53:R53)=3,"",IF(COUNTIF(P53:R53,"No")>0,"EXCLUDE","INCLUDE"))) | T53: =IF(S53<>"EXCLUDE","",IF(P53="No","Digital Twin mentioned only, not the subject",IF(Q53="No","No Design for Safety focus in full text",IF(R53="No","Methodology not codable","")))) | Y53: =IF(SUM(V53:X53)=0,"",IF(SUM(V53:X53)>=2,"Multi","Single")) | AN53: Step-1 note: Turbine cylinder thermo-mechanical DT; energy equipment | AO53: 10.1016/j.applthermaleng.2026.132643
A54: 50 | B54: Maqsoom, A et al. (2026) | C54: 2026 | E54: BIM-Driven Safety: Automated Rule-Based Multihazard Detection and Legal Compliance in High-Rise Construction | F54: Scopus | G54: Yes | H54: No | I54: Yes | J54: Yes | K54: Yes | L54: =IF(COUNTBLANK(G54:K54)=5,"",IF(COUNTIF(G54:K54,"No")>0,"EXCLUDE","INCLUDE")) -> EXCLUDE | M54: =IF(L54<>"EXCLUDE","",IF(G54="No","Wrong domain (non-AECO)",IF(H54="No","Digital Twin not core / buzzword",IF(I54="No","No Design for Safety / PtD focus",IF(J54="No","Wrong publication type",IF(K54="No","Non-English","")))))) -> Digital Twin not core / buzzword | S54: =IF(N54<>"Yes","",IF(COUNTBLANK(P54:R54)=3,"",IF(COUNTIF(P54:R54,"No")>0,"EXCLUDE","INCLUDE"))) | T54: =IF(S54<>"EXCLUDE","",IF(P54="No","Digital Twin mentioned only, not the subject",IF(Q54="No","No Design for Safety focus in full text",IF(R54="No","Methodology not codable","")))) | Y54: =IF(SUM(V54:X54)=0,"",IF(SUM(V54:X54)>=2,"Multi","Single")) | AN54: Step-1 note: 8D BIM rule-checking; DT framing only | AO54: 10.1061/JLADAH.LADR-1409
A55: 51 | B55: Repetto, M et al. (2026) | C55: 2026 | E55: A Cybersecurity Digital Twin Architecture for Modelling Threats in Interconnected Systems | F55: Scopus | G55: No | H55: Yes | I55: No | J55: Yes | K55: Yes | L55: =IF(COUNTBLANK(G55:K55)=5,"",IF(COUNTIF(G55:K55,"No")>0,"EXCLUDE","INCLUDE")) -> EXCLUDE | M55: =IF(L55<>"EXCLUDE","",IF(G55="No","Wrong domain (non-AECO)",IF(H55="No","Digital Twin not core / buzzword",IF(I55="No","No Design for Safety / PtD focus",IF(J55="No","Wrong publication type",IF(K55="No","Non-English","")))))) -> Wrong domain (non-AECO) | S55: =IF(N55<>"Yes","",IF(COUNTBLANK(P55:R55)=3,"",IF(COUNTIF(P55:R55,"No")>0,"EXCLUDE","INCLUDE"))) | T55: =IF(S55<>"EXCLUDE","",IF(P55="No","Digital Twin mentioned only, not the subject",IF(Q55="No","No Design for Safety focus in full text",IF(R55="No","Methodology not codable","")))) | Y55: =IF(SUM(V55:X55)=0,"",IF(SUM(V55:X55)>=2,"Multi","Single")) | AN55: Step-1 note: OT/IT cybersecurity DT; not AECO | AO55: 10.60097/ACIG/221493
A56: 52 | B56: Shao, Z et al. (2026) | C56: 2026 | E56: An Aero-Thermodynamic Physics-Informed Neural Network for Small-Sample Performance Prediction of Variable-Speed Centrifugal Chillers | F56: Scopus | G56: Yes | H56: Yes | I56: No | J56: Yes | K56: Yes | L56: =IF(COUNTBLANK(G56:K56)=5,"",IF(COUNTIF(G56:K56,"No")>0,"EXCLUDE","INCLUDE")) -> EXCLUDE | M56: =IF(L56<>"EXCLUDE","",IF(G56="No","Wrong domain (non-AECO)",IF(H56="No","Digital Twin not core / buzzword",IF(I56="No","No Design for Safety / PtD focus",IF(J56="No","Wrong publication type",IF(K56="No","Non-English","")))))) -> No Design for Safety / PtD focus | S56: =IF(N56<>"Yes","",IF(COUNTBLANK(P56:R56)=3,"",IF(COUNTIF(P56:R56,"No")>0,"EXCLUDE","INCLUDE"))) | T56: =IF(S56<>"EXCLUDE","",IF(P56="No","Digital Twin mentioned only, not the subject",IF(Q56="No","No Design for Safety focus in full text",IF(R56="No","Methodology not codable","")))) | Y56: =IF(SUM(V56:X56)=0,"",IF(SUM(V56:X56)>=2,"Multi","Single")) | AN56: Step-1 note: HVAC chiller DT; energy only, no safety/quality | AO56: 10.3390/en19061563
A57: 53 | B57: Zhu, H et al. (2026) | C57: 2026 | E57: Digital twin-enhanced multi-agent reinforcement learning for distributed control of collaborative robotic arms in angle steel tower dismantling | F57: Scopus | G57: No | H57: Yes | I57: Yes | J57: Yes | K57: Yes | L57: =IF(COUNTBLANK(G57:K57)=5,"",IF(COUNTIF(G57:K57,"No")>0,"EXCLUDE","INCLUDE")) -> EXCLUDE | M57: =IF(L57<>"EXCLUDE","",IF(G57="No","Wrong domain (non-AECO)",IF(H57="No","Digital Twin not core / buzzword",IF(I57="No","No Design for Safety / PtD focus",IF(J57="No","Wrong publication type",IF(K57="No","Non-English","")))))) -> Wrong domain (non-AECO) | S57: =IF(N57<>"Yes","",IF(COUNTBLANK(P57:R57)=3,"",IF(COUNTIF(P57:R57,"No")>0,"EXCLUDE","INCLUDE"))) | T57: =IF(S57<>"EXCLUDE","",IF(P57="No","Digital Twin mentioned only, not the subject",IF(Q57="No","No Design for Safety focus in full text",IF(R57="No","Methodology not codable","")))) | Y57: =IF(SUM(V57:X57)=0,"",IF(SUM(V57:X57)>=2,"Multi","Single")) | AN57: Step-1 note: Transmission tower dismantling; power, not AECO | AO57: 10.1088/2631-8695/ae3b9e
A58: 54 | B58: Deng, J et al. (2026) | C58: 2026 | E58: A Digital Twin of Life-Cycle Bearing Based on a Defect-Guided Conditional Diffusion Model for Predicting Remaining Life under Limited Degradation Data | F58: Scopus | G58: No | H58: Yes | I58: Yes | J58: Yes | K58: Yes | L58: =IF(COUNTBLANK(G58:K58)=5,"",IF(COUNTIF(G58:K58,"No")>0,"EXCLUDE","INCLUDE")) -> EXCLUDE | M58: =IF(L58<>"EXCLUDE","",IF(G58="No","Wrong domain (non-AECO)",IF(H58="No","Digital Twin not core / buzzword",IF(I58="No","No Design for Safety / PtD focus",IF(J58="No","Wrong publication type",IF(K58="No","Non-English","")))))) -> Wrong domain (non-AECO) | S58: =IF(N58<>"Yes","",IF(COUNTBLANK(P58:R58)=3,"",IF(COUNTIF(P58:R58,"No")>0,"EXCLUDE","INCLUDE"))) | T58: =IF(S58<>"EXCLUDE","",IF(P58="No","Digital Twin mentioned only, not the subject",IF(Q58="No","No Design for Safety focus in full text",IF(R58="No","Methodology not codable","")))) | Y58: =IF(SUM(V58:X58)=0,"",IF(SUM(V58:X58)>=2,"Multi","Single")) | AN58: Step-1 note: Bearing RUL diffusion DT; industrial machinery | AO58: 10.1061/AJRUA6.RUENG-1786
A59: 55 | B59: Moe, S.J.S et al. (2026) | C59: 2026 | E59: Optimizing Federated Learning based on Weighted Hyperparameter Aggregation in Energy-constrained Building Construction | F59: Scopus | G59: Yes | H59: Yes | I59: Yes | J59: Yes | K59: Yes | L59: =IF(COUNTBLANK(G59:K59)=5,"",IF(COUNTIF(G59:K59,"No")>0,"EXCLUDE","INCLUDE")) -> INCLUDE | M59: =IF(L59<>"EXCLUDE","",IF(G59="No","Wrong domain (non-AECO)",IF(H59="No","Digital Twin not core / buzzword",IF(I59="No","No Design for Safety / PtD focus",IF(J59="No","Wrong publication type",IF(K59="No","Non-English","")))))) | N59: Yes | O59: Yes | P59: Yes | Q59: Yes | R59: Yes | S59: =IF(N59<>"Yes","",IF(COUNTBLANK(P59:R59)=3,"",IF(COUNTIF(P59:R59,"No")>0,"EXCLUDE","INCLUDE"))) -> INCLUDE | T59: =IF(S59<>"EXCLUDE","",IF(P59="No","Digital Twin mentioned only, not the subject",IF(Q59="No","No Design for Safety focus in full text",IF(R59="No","Methodology not codable","")))) | U59: Tier 2 - Digital Shadow (one-way physical to virtual) | V59: 0 | W59: 1 | X59: 0 | Y59: =IF(SUM(V59:X59)=0,"",IF(SUM(V59:X59)>=2,"Multi","Single")) -> Single | Z59: Design for Safety (DfS) | AA59: Implemented | AB59: Other / Mixed | AC59: Multi (two or more data types) | AD59: Single case study | AE59: 4 | AF59: Predictive analytics / decision support | AG59: One-shot local Bayesian optimization + loss-weighted hyperparameter aggregation for federated learning (FL), integrated into a Digital Twin platform for device registration, orchestration, and telemetry (Jeju National U, Cluster Computing 2026): clients optimise hyperparameters locally on small data subsets, the server aggregates a single global set for collaborative training; training-method agnostic; evaluated on MNIST/EEGEyeState/Weather plus a private worker-safety dataset; 6.44% average end-to-end improvement, faster convergence, lower MAE vs simple averaging, reduced response time on Raspberry Pi AIoT clients; on-device inference supports near-real-time safety alerts to supervisors and wearables. One-way telemetry->prediction->alerts; FL retraining loop implemented but no convergence criterion and no physical actuation. [Full-text source: Endnote] | AH59: Fills the FL-HPO gap for energy-constrained construction edge nodes: one-shot local Bayesian optimisation removes iterative client-server tuning rounds, and loss-weighted aggregation of client-proposed hyperparameters yields a single global set that improves convergence, accuracy/MAE and Raspberry-Pi response time (+6.44% end-to-end) while keeping site-sensitive safety data on-device for privacy. | AI59: Evaluation spans three public datasets plus one private worker-safety dataset rather than a longitudinal on-site deployment; convergence of the aggregated hyperparameters is not theoretically characterised; communication/privacy of shared hyperparameters and scalability to large fleets are discussed but not empirically bounded. | AJ59: Fused | AK59: Client-proposed hyperparameters from heterogeneous local data are loss-weighted into one global FL configuration, and worker-safety telemetry is joined with the DT orchestration layer for training and inference. | AL59: Medium | AN59: Step-1 note: Federated-learning HPO inside DT platform; worker safety | Coded from Step-3 deep-read markdown (DfS-only scope), imported 2026-10-04 | AO59: 10.1007/s10586-025-05908-7
A60: 56 | B60: Jiang, Y et al. (2026) | C60: 2026 | E60: Enhancing Autonomous Vehicle Localization Through Cooperative LiDAR and Smart Infrastructure Integration | F60: Scopus | G60: No | H60: No | I60: Yes | J60: Yes | K60: Yes | L60: =IF(COUNTBLANK(G60:K60)=5,"",IF(COUNTIF(G60:K60,"No")>0,"EXCLUDE","INCLUDE")) -> EXCLUDE | M60: =IF(L60<>"EXCLUDE","",IF(G60="No","Wrong domain (non-AECO)",IF(H60="No","Digital Twin not core / buzzword",IF(I60="No","No Design for Safety / PtD focus",IF(J60="No","Wrong publication type",IF(K60="No","Non-English","")))))) -> Wrong domain (non-AECO) | S60: =IF(N60<>"Yes","",IF(COUNTBLANK(P60:R60)=3,"",IF(COUNTIF(P60:R60,"No")>0,"EXCLUDE","INCLUDE"))) | T60: =IF(S60<>"EXCLUDE","",IF(P60="No","Digital Twin mentioned only, not the subject",IF(Q60="No","No Design for Safety focus in full text",IF(R60="No","Methodology not codable","")))) | Y60: =IF(SUM(V60:X60)=0,"",IF(SUM(V60:X60)>=2,"Multi","Single")) | AN60: Step-1 note: AV localization; vehicles, not AECO | AO60: 10.1109/OJITS.2026.3664106
A61: 57 | B61: Mousavi, V et al. (2026) | C61: 2026 | E61: Deep reinforcement learning-based decision support system for optimal maintenance planning in bridge digital twins | F61: Scopus | G61: Yes | H61: Yes | I61: Yes | J61: Yes | K61: Yes | L61: =IF(COUNTBLANK(G61:K61)=5,"",IF(COUNTIF(G61:K61,"No")>0,"EXCLUDE","INCLUDE")) -> INCLUDE | M61: =IF(L61<>"EXCLUDE","",IF(G61="No","Wrong domain (non-AECO)",IF(H61="No","Digital Twin not core / buzzword",IF(I61="No","No Design for Safety / PtD focus",IF(J61="No","Wrong publication type",IF(K61="No","Non-English","")))))) | N61: Yes | O61: Yes | P61: Yes | Q61: Yes | R61: Yes | S61: =IF(N61<>"Yes","",IF(COUNTBLANK(P61:R61)=3,"",IF(COUNTIF(P61:R61,"No")>0,"EXCLUDE","INCLUDE"))) -> INCLUDE | T61: =IF(S61<>"EXCLUDE","",IF(P61="No","Digital Twin mentioned only, not the subject",IF(Q61="No","No Design for Safety focus in full text",IF(R61="No","Methodology not codable","")))) | U61: Tier 2 - Digital Shadow (one-way physical to virtual) | V61: 0 | W61: 0 | X61: 1 | Y61: =IF(SUM(V61:X61)=0,"",IF(SUM(V61:X61)>=2,"Multi","Single")) -> Single | Z61: Design for Safety (DfS) | AA61: Implemented | AB61: Reinforcement Learning (RL) | AC61: Multi (two or more data types) | AD61: Cross-project (multiple real projects) | AE61: 4 | AF61: Predictive analytics / decision support | AG61: RL-based decision support system for bridge maintenance inside digital-twin environments (Western Sydney U, EngAppAI 2026): multi-objective deep centralized multi-agent actor-critic (MO-DCMAC) models maintenance cost, structural failure risk and serviceability as a vector-valued reward with fixed linear utility; evaluated on three real bridge case studies vs established rule-based policies, achieving highest overall utility by penalizing high-frequency site visits and balancing intervention cost with risk mitigation. Maintenance-policy recommendations to asset managers (no automated actuation); RL training loop implemented but no convergence criterion. [Full-text source: browser-oa] | AH61: Brings multi-objective deep RL into bridge digital twins: vector-valued reward (cost, failure risk, serviceability) with linear utility outperforms rule-based policies across three real bridge case studies, yielding fewer but more impactful interventions. | AI61: Fixed linear utility function prevents adaptive preference trade-offs; RL convergence not characterised; policies are recommendations (no closed-loop actuation) and case studies are retrospective. | AJ61: Fused | AK61: Maintenance cost, structural failure risk and serviceability are fused in one vector-valued reward with linear scalarization for MO-DCMAC training in bridge DT environments. | AL61: High | AN61: Step-1 note: RL-DSS for bridge maintenance inside bridge DT | Coded from Step-3 deep-read markdown (DfS-only scope), imported 2026-10-04 | AO61: 10.1016/j.engappai.2026.115649
A62: 58 | B62: Jakobo, E.P et al. (2025) | C62: 2025 | E62: Investigating the Applicability of Industry 4.0 Technologies in Road Construction Projects: A Quantitative Research Design From Construction 4.0 Perspectives | F62: Scopus | G62: Yes | H62: No | I62: No | J62: Yes | K62: Yes | L62: =IF(COUNTBLANK(G62:K62)=5,"",IF(COUNTIF(G62:K62,"No")>0,"EXCLUDE","INCLUDE")) -> EXCLUDE | M62: =IF(L62<>"EXCLUDE","",IF(G62="No","Wrong domain (non-AECO)",IF(H62="No","Digital Twin not core / buzzword",IF(I62="No","No Design for Safety / PtD focus",IF(J62="No","Wrong publication type",IF(K62="No","Non-English","")))))) -> Digital Twin not core / buzzword | S62: =IF(N62<>"Yes","",IF(COUNTBLANK(P62:R62)=3,"",IF(COUNTIF(P62:R62,"No")>0,"EXCLUDE","INCLUDE"))) | T62: =IF(S62<>"EXCLUDE","",IF(P62="No","Digital Twin mentioned only, not the subject",IF(Q62="No","No Design for Safety focus in full text",IF(R62="No","Methodology not codable","")))) | Y62: =IF(SUM(V62:X62)=0,"",IF(SUM(V62:X62)>=2,"Multi","Single")) | AN62: Step-1 note: C4.0 adoption survey; DT one technology in list | AO62: 10.1002/eng2.70406
A63: 59 | B63: Balaska, V et al. (2026) | C63: 2026 | E63: UAV Object Detection and Positioning in a Mining Industrial Metaverse With Custom Geo-Referenced Data | F63: Scopus | G63: No | H63: Yes | I63: Yes | J63: Yes | K63: Yes | L63: =IF(COUNTBLANK(G63:K63)=5,"",IF(COUNTIF(G63:K63,"No")>0,"EXCLUDE","INCLUDE")) -> EXCLUDE | M63: =IF(L63<>"EXCLUDE","",IF(G63="No","Wrong domain (non-AECO)",IF(H63="No","Digital Twin not core / buzzword",IF(I63="No","No Design for Safety / PtD focus",IF(J63="No","Wrong publication type",IF(K63="No","Non-English","")))))) -> Wrong domain (non-AECO) | S63: =IF(N63<>"Yes","",IF(COUNTBLANK(P63:R63)=3,"",IF(COUNTIF(P63:R63,"No")>0,"EXCLUDE","INCLUDE"))) | T63: =IF(S63<>"EXCLUDE","",IF(P63="No","Digital Twin mentioned only, not the subject",IF(Q63="No","No Design for Safety focus in full text",IF(R63="No","Methodology not codable","")))) | Y63: =IF(SUM(V63:X63)=0,"",IF(SUM(V63:X63)>=2,"Multi","Single")) | AN63: Step-1 note: Mining metaverse UAV system; mining domain | AO63: 10.1049/cps2.70048
A64: 60 | B64: Li, T et al. (2025) | C64: 2025 | E64: A Multi-Sensor Fusion Approach Combined with RandLA-Net for Large-Scale Point Cloud Segmentation in Power Grid Scenario | F64: Scopus | G64: No | H64: Yes | I64: Yes | J64: Yes | K64: Yes | L64: =IF(COUNTBLANK(G64:K64)=5,"",IF(COUNTIF(G64:K64,"No")>0,"EXCLUDE","INCLUDE")) -> EXCLUDE | M64: =IF(L64<>"EXCLUDE","",IF(G64="No","Wrong domain (non-AECO)",IF(H64="No","Digital Twin not core / buzzword",IF(I64="No","No Design for Safety / PtD focus",IF(J64="No","Wrong publication type",IF(K64="No","Non-English","")))))) -> Wrong domain (non-AECO) | S64: =IF(N64<>"Yes","",IF(COUNTBLANK(P64:R64)=3,"",IF(COUNTIF(P64:R64,"No")>0,"EXCLUDE","INCLUDE"))) | T64: =IF(S64<>"EXCLUDE","",IF(P64="No","Digital Twin mentioned only, not the subject",IF(Q64="No","No Design for Safety focus in full text",IF(R64="No","Methodology not codable","")))) | Y64: =IF(SUM(V64:X64)=0,"",IF(SUM(V64:X64)>=2,"Multi","Single")) | AN64: Step-1 note: Power grid tower segmentation; not AECO | AO64: 10.3390/s25113350
A65: 61 | B65: Torres-Polo, M et al. (2026) | C65: 2026 | E65: Computational Economics of Circular Construction: Machine Learning and Digital Twins for Optimizing Demolition Waste Recovery and Business Value | F65: Scopus | G65: Yes | H65: No | I65: No | J65: Yes | K65: Yes | L65: =IF(COUNTBLANK(G65:K65)=5,"",IF(COUNTIF(G65:K65,"No")>0,"EXCLUDE","INCLUDE")) -> EXCLUDE | M65: =IF(L65<>"EXCLUDE","",IF(G65="No","Wrong domain (non-AECO)",IF(H65="No","Digital Twin not core / buzzword",IF(I65="No","No Design for Safety / PtD focus",IF(J65="No","Wrong publication type",IF(K65="No","Non-English","")))))) -> Digital Twin not core / buzzword | S65: =IF(N65<>"Yes","",IF(COUNTBLANK(P65:R65)=3,"",IF(COUNTIF(P65:R65,"No")>0,"EXCLUDE","INCLUDE"))) | T65: =IF(S65<>"EXCLUDE","",IF(P65="No","Digital Twin mentioned only, not the subject",IF(Q65="No","No Design for Safety focus in full text",IF(R65="No","Methodology not codable","")))) | Y65: =IF(SUM(V65:X65)=0,"",IF(SUM(V65:X65)>=2,"Multi","Single")) | AN65: Step-1 note: Circular CDW review; DT one enabler, no DfS/DfQ | AO65: 10.3390/computation14040076
A66: 62 | B66: Martini, T et al. (2025) | C66: 2025 | E66: Digital twin representation of socio-technical systems through a distributed co-simulation approach for crisis management | F66: Scopus | G66: Yes | H66: Yes | I66: Yes | J66: Yes | K66: Yes | L66: =IF(COUNTBLANK(G66:K66)=5,"",IF(COUNTIF(G66:K66,"No")>0,"EXCLUDE","INCLUDE")) -> INCLUDE | M66: =IF(L66<>"EXCLUDE","",IF(G66="No","Wrong domain (non-AECO)",IF(H66="No","Digital Twin not core / buzzword",IF(I66="No","No Design for Safety / PtD focus",IF(J66="No","Wrong publication type",IF(K66="No","Non-English","")))))) | N66: Yes | O66: Yes | P66: Yes | Q66: Yes | R66: Yes | S66: =IF(N66<>"Yes","",IF(COUNTBLANK(P66:R66)=3,"",IF(COUNTIF(P66:R66,"No")>0,"EXCLUDE","INCLUDE"))) -> INCLUDE | T66: =IF(S66<>"EXCLUDE","",IF(P66="No","Digital Twin mentioned only, not the subject",IF(Q66="No","No Design for Safety focus in full text",IF(R66="No","Methodology not codable","")))) | U66: Tier 1 - Digital Model (static, no live data) | V66: 0 | W66: 0 | X66: 1 | Y66: =IF(SUM(V66:X66)=0,"",IF(SUM(V66:X66)>=2,"Multi","Single")) -> Single | Z66: Design for Safety (DfS) | AA66: None | AB66: Other / Mixed | AC66: Multi (two or more data types) | AD66: Simulation | AE66: 3 | AF66: Predictive analytics / decision support | AG66: Digital urban twin for crisis management via modular distributed co-simulation (Fraunhofer SIRIOS): engineering-model simulation modules for water, electricity, gas, telecom, built environment and agent-based emergency response exchange events over a CloudEvents/FROST (SensorThings) event-stream architecture; mapping interdependencies and cascading failures among critical infrastructures; proof-of-concept on urban flooding/heavy-rainfall scenario predicting system states and structural impacts for authorities and training. Scenario-driven co-simulation; no live sensor loop demonstrated, no actuation, no learning loop. [Full-text source: Endnote] | AH66: Fills the gap between single-sector simulations and real crisis management: a modular event-stream co-simulation maps interdependencies and cascading effects across water, electricity, gas, telecom, built environment and emergency response in one urban digital twin, demonstrated on an urban flooding proof-of-concept for authorities and training. | AI66: Proof-of-concept covers only a flooding scenario; no live sensor ingestion or real-time operation demonstrated, validation against real crisis data is missing, and assumptions on initial conditions and monitoring availability limit accuracy for large-scale cascading failures. | AJ66: Fused | AK66: Sector simulation outputs (water/electricity/gas/telecom, buildings, emergency response) are exchanged as events in one co-simulation to compute cascading effects; modules remain loosely coupled simulators rather than a single fused model. | AL66: Medium | AN66: Step-1 note: Urban DT co-simulation for crisis management | Coded from Step-3 deep-read markdown (DfS-only scope), imported 2026-10-04 | AO66: 10.1007/s10669-025-10035-0
A67: 63 | B67: Candigliota, E et al. (2025) | C67: 2025 | E67: The Integration of a Multidomain Monitoring Platform with Structural Data: A Building Case Study | F67: Scopus | G67: Yes | H67: Yes | I67: Yes | J67: Yes | K67: Yes | L67: =IF(COUNTBLANK(G67:K67)=5,"",IF(COUNTIF(G67:K67,"No")>0,"EXCLUDE","INCLUDE")) -> INCLUDE | M67: =IF(L67<>"EXCLUDE","",IF(G67="No","Wrong domain (non-AECO)",IF(H67="No","Digital Twin not core / buzzword",IF(I67="No","No Design for Safety / PtD focus",IF(J67="No","Wrong publication type",IF(K67="No","Non-English","")))))) | N67: Yes | O67: Yes | P67: Yes | Q67: Yes | R67: Yes | S67: =IF(N67<>"Yes","",IF(COUNTBLANK(P67:R67)=3,"",IF(COUNTIF(P67:R67,"No")>0,"EXCLUDE","INCLUDE"))) -> INCLUDE | T67: =IF(S67<>"EXCLUDE","",IF(P67="No","Digital Twin mentioned only, not the subject",IF(Q67="No","No Design for Safety focus in full text",IF(R67="No","Methodology not codable","")))) | U67: Tier 2 - Digital Shadow (one-way physical to virtual) | V67: 0 | W67: 0 | X67: 1 | Y67: =IF(SUM(V67:X67)=0,"",IF(SUM(V67:X67)>=2,"Multi","Single")) -> Single | Z67: Design for Safety (DfS) | AA67: None | AB67: Digital Twin platform (no machine learning) | AC67: Multi (two or more data types) | AD67: Single case study | AE67: 3 | AF67: BIM-to-Digital-Twin architecture | AG67: Multidomain monitoring integration (ENEA, Sustainability 2025): affordable NDT procedure for post-earthquake damage assessment of RC buildings; NDT results and distributed sensor nodes inserted into the LIS platform to create the building digital twin for automated monitoring, management and preventive maintenance; QR-code interface simplifies operator workflow; case study on a 2016-earthquake-damaged building in Marche, Italy (MULTICLIMACT). One-way monitoring->twin->maintenance decisions; no actuation, no learning loop. [Full-text source: browser-oa] | AH67: Delivers an affordable, ready-to-use NDT-plus-LIS procedure that stores post-earthquake damage data in an interoperable building digital twin with distributed sensor nodes and a QR-code interface, supporting automated preventive maintenance. | AI67: Single building case; the DT stores and visualises data but performs no predictive analytics; long-term sensor reliability and multi-site scalability are not demonstrated. | AJ67: Fused | AK67: NDT results, distributed sensor-node data and BIM geometry are integrated in the LIS platform as one building twin. | AL67: Medium | AN67: Step-1 note: NDT + digital twin for building damage assessment | Coded from Step-3 deep-read markdown (DfS-only scope), imported 2026-10-04 | AO67: 10.3390/su17073076
A68: 64 | B68: Speiser, K et al. (2026) | C68: 2026 | E68: Agentic system for construction safety risk assessments using large language models and knowledge graphs | F68: Scopus | G68: Yes | H68: No | I68: Yes | J68: Yes | K68: Yes | L68: =IF(COUNTBLANK(G68:K68)=5,"",IF(COUNTIF(G68:K68,"No")>0,"EXCLUDE","INCLUDE")) -> EXCLUDE | M68: =IF(L68<>"EXCLUDE","",IF(G68="No","Wrong domain (non-AECO)",IF(H68="No","Digital Twin not core / buzzword",IF(I68="No","No Design for Safety / PtD focus",IF(J68="No","Wrong publication type",IF(K68="No","Non-English","")))))) -> Digital Twin not core / buzzword | S68: =IF(N68<>"Yes","",IF(COUNTBLANK(P68:R68)=3,"",IF(COUNTIF(P68:R68,"No")>0,"EXCLUDE","INCLUDE"))) | T68: =IF(S68<>"EXCLUDE","",IF(P68="No","Digital Twin mentioned only, not the subject",IF(Q68="No","No Design for Safety focus in full text",IF(R68="No","Methodology not codable","")))) | Y68: =IF(SUM(V68:X68)=0,"",IF(SUM(V68:X68)>=2,"Multi","Single")) | AN68: Step-1 note: LLM-agent safety risk assessment; no DT built | AO68: 10.1016/j.aei.2026.104681
A69: 65 | B69: Mandal, D et al. (2026) | C69: 2026 | E69: FlowsDT: A geospatial digital twin for navigating urban flood dynamics | F69: Scopus | G69: Yes | H69: Yes | I69: Yes | J69: Yes | K69: Yes | L69: =IF(COUNTBLANK(G69:K69)=5,"",IF(COUNTIF(G69:K69,"No")>0,"EXCLUDE","INCLUDE")) -> INCLUDE | M69: =IF(L69<>"EXCLUDE","",IF(G69="No","Wrong domain (non-AECO)",IF(H69="No","Digital Twin not core / buzzword",IF(I69="No","No Design for Safety / PtD focus",IF(J69="No","Wrong publication type",IF(K69="No","Non-English","")))))) | N69: Yes | O69: Yes | P69: Yes | Q69: Yes | R69: Yes | S69: =IF(N69<>"Yes","",IF(COUNTBLANK(P69:R69)=3,"",IF(COUNTIF(P69:R69,"No")>0,"EXCLUDE","INCLUDE"))) -> INCLUDE | T69: =IF(S69<>"EXCLUDE","",IF(P69="No","Digital Twin mentioned only, not the subject",IF(Q69="No","No Design for Safety focus in full text",IF(R69="No","Methodology not codable","")))) | U69: Tier 1 - Digital Model (static, no live data) | V69: 0 | W69: 0 | X69: 1 | Y69: =IF(SUM(V69:X69)=0,"",IF(SUM(V69:X69)>=2,"Multi","Single")) -> Single | Z69: Design for Safety (DfS) | AA69: None | AB69: Finite Element Method / physics-based | AC69: Multi (two or more data types) | AD69: Single case study | AE69: 4 | AF69: Predictive analytics / decision support | AG69: FlowsDT-Galveston geospatial digital twin (Texas A&M, Comput Environ Urban Syst 2026): 1D-2D coupled PCSWMM hydrodynamic models over LiDAR topography, land cover and storm-sewer geometry elevate the urban twin to LoD4 (underground network); validated with historical flood events and social sensing; simulates 2/10/25/50/100-yr scenarios - buildings inundated >1 ft +5.7%, roads +6.7%; supports proactive flood management and urban planning. Scenario-simulation twin; real-time sensor integration only described as potential; no actuation, no learning loop. [Full-text source: browser-oa] | AH69: Elevates urban flood digital twins to LoD4 by coupling 1D storm-sewer and 2D surface-flow models, validated against historical floods and social sensing across five return periods for street/basement-level risk mapping. | AI69: No real-time sensor integration yet (potential only); social-sensing validation is coarse; 4D immersive visualisation is described but an interactive stakeholder interface is not delivered. | AJ69: Fused | AK69: LiDAR topography, land cover and storm-sewer geometries are fused in the coupled 1D-2D hydrodynamic model. | AL69: High | AN69: Step-1 note: Geospatial urban flood DT; resilience/safety | Coded from Step-3 deep-read markdown (DfS-only scope), imported 2026-10-04 | AO69: 10.1016/j.compenvurbsys.2026.102414
A70: 66 | B70: Zhang, H et al. (2026) | C70: 2026 | E70: TwinOR: photorealistic digital twins of dynamic operating rooms for embodied AI research | F70: Scopus | G70: No | H70: Yes | I70: No | J70: Yes | K70: Yes | L70: =IF(COUNTBLANK(G70:K70)=5,"",IF(COUNTIF(G70:K70,"No")>0,"EXCLUDE","INCLUDE")) -> EXCLUDE | M70: =IF(L70<>"EXCLUDE","",IF(G70="No","Wrong domain (non-AECO)",IF(H70="No","Digital Twin not core / buzzword",IF(I70="No","No Design for Safety / PtD focus",IF(J70="No","Wrong publication type",IF(K70="No","Non-English","")))))) -> Wrong domain (non-AECO) | S70: =IF(N70<>"Yes","",IF(COUNTBLANK(P70:R70)=3,"",IF(COUNTIF(P70:R70,"No")>0,"EXCLUDE","INCLUDE"))) | T70: =IF(S70<>"EXCLUDE","",IF(P70="No","Digital Twin mentioned only, not the subject",IF(Q70="No","No Design for Safety focus in full text",IF(R70="No","Methodology not codable","")))) | Y70: =IF(SUM(V70:X70)=0,"",IF(SUM(V70:X70)>=2,"Multi","Single")) | AN70: Step-1 note: Operating-room DT; healthcare | AO70: 10.1007/s11548-026-03644-w
A71: 67 | B71: Delhibabu, R et al. (2026) | C71: 2026 | E71: Interconnected digital twins of subway stations for decision support systems | F71: Scopus | G71: Yes | H71: Yes | I71: Yes | J71: Yes | K71: Yes | L71: =IF(COUNTBLANK(G71:K71)=5,"",IF(COUNTIF(G71:K71,"No")>0,"EXCLUDE","INCLUDE")) -> INCLUDE | M71: =IF(L71<>"EXCLUDE","",IF(G71="No","Wrong domain (non-AECO)",IF(H71="No","Digital Twin not core / buzzword",IF(I71="No","No Design for Safety / PtD focus",IF(J71="No","Wrong publication type",IF(K71="No","Non-English","")))))) | N71: Yes | O71: Yes | P71: Yes | Q71: Yes | R71: Yes | S71: =IF(N71<>"Yes","",IF(COUNTBLANK(P71:R71)=3,"",IF(COUNTIF(P71:R71,"No")>0,"EXCLUDE","INCLUDE"))) -> INCLUDE | T71: =IF(S71<>"EXCLUDE","",IF(P71="No","Digital Twin mentioned only, not the subject",IF(Q71="No","No Design for Safety focus in full text",IF(R71="No","Methodology not codable","")))) | U71: Tier 2 - Digital Shadow (one-way physical to virtual) | V71: 0 | W71: 0 | X71: 1 | Y71: =IF(SUM(V71:X71)=0,"",IF(SUM(V71:X71)>=2,"Multi","Single")) -> Single | Z71: Design for Safety (DfS) | AA71: None | AB71: Computer Vision / CNN / object-detection | AC71: Multi (two or more data types) | AD71: Single case study | AE71: 4 | AF71: Predictive analytics / decision support | AG71: Interconnected digital twins of subway stations for decision support (VIT/FRC RAS): per-station DTs interconnected to interact during operational scenarios; cameras, microphones, sensors processed in fog computing; mobile app with intelligent assistant displays detected events and answers queries via voice; event detection for hazardous situations (fire/explosion); implementation improved personnel response time by 17.4% vs REPEAT platform. One-way monitoring to event detection to decision support for operators; no actuation and no learning loop. [Full-text source: 04c-port] | AH71: Fills the incident-response gap of subway station digital twins: interconnected per-station twins process camera, microphone and sensor data in a fog computing environment, a fine-tuned YOLOv8 detector (mAP 0.5 of 92.4 percent) spots events shown on a mobile app with a voice assistant, and personnel response times improved by 17.4 percent versus the REPEAT platform across 50 simulated trials. | AI71: Results come from simulated emergency scenarios, and continuous TCP/IP connectivity is assumed, so deep subterranean network degradation could break the fog-to-mobile pipeline; speech recognition reaches only a 14.2 percent word error rate under 85 dB noise, and the app runs only on Android and Linux; future plans include signaling and control integration to automatically stop trains and escalators. | AJ71: Co-present | AK71: Camera feeds drive YOLOv8 event detection while microphone and sensor streams support a separate voice-assistant pipeline in the same fog-computing platform, with no common representation stated. | AL71: Medium | AN71: Step-1 note: Interconnected subway station DTs; incident response | Methodology label normalised (source: "Perception / Computer Vision") | Coded from Step-3 deep-read markdown (DfS-only scope), imported 2026-10-04 | AO71: 10.1016/j.rineng.2026.110745
A72: 68 | B72: Khan, M.S (2025) | C72: 2025 | E72: Data-driven digital twin-based smart tunnel maintenance system | F72: Scopus | G72: Yes | H72: Yes | I72: Yes | J72: Yes | K72: Yes | L72: =IF(COUNTBLANK(G72:K72)=5,"",IF(COUNTIF(G72:K72,"No")>0,"EXCLUDE","INCLUDE")) -> INCLUDE | M72: =IF(L72<>"EXCLUDE","",IF(G72="No","Wrong domain (non-AECO)",IF(H72="No","Digital Twin not core / buzzword",IF(I72="No","No Design for Safety / PtD focus",IF(J72="No","Wrong publication type",IF(K72="No","Non-English","")))))) | N72: Yes | O72: Yes | P72: Yes | Q72: Yes | R72: Yes | S72: =IF(N72<>"Yes","",IF(COUNTBLANK(P72:R72)=3,"",IF(COUNTIF(P72:R72,"No")>0,"EXCLUDE","INCLUDE"))) -> INCLUDE | T72: =IF(S72<>"EXCLUDE","",IF(P72="No","Digital Twin mentioned only, not the subject",IF(Q72="No","No Design for Safety focus in full text",IF(R72="No","Methodology not codable","")))) | U72: Tier 2 - Digital Shadow (one-way physical to virtual) | V72: 0 | W72: 0 | X72: 1 | Y72: =IF(SUM(V72:X72)=0,"",IF(SUM(V72:X72)>=2,"Multi","Single")) -> Single | Z72: Design for Safety (DfS) | AA72: None | AB72: Other / Mixed | AC72: Multi (two or more data types) | AD72: Single case study | AE72: 3 | AF72: Predictive analytics / decision support | AG72: Data-driven digital-twin-based smart tunnel maintenance (Hanyang U, Intelligent Geoengineering 2025): six-layer framework integrates monitoring-system data, FM-system records and BIM models via a hierarchical tunnel data model/classification; tunnel case study generates maintenance plans and work orders from historical and current condition data with 3D visualisation; ML models predict twin state with sufficiently high accuracy for proactive FM planning and failure prevention. One-way monitoring->prediction->maintenance decisions; offline ML, no actuation, no learning loop. [Full-text source: browser-oa] | AH72: Integrates monitoring, FM and BIM layers in one six-layer tunnel DT with a hierarchical data model, generating predictive maintenance plans and work orders that were validated on a real tunnel. | AI72: ML model details and prediction accuracy metrics are only summarily reported; one tunnel case; no actuation or online model updating. | AJ72: Fused | AK72: Monitoring, FM and BIM data streams are fused through the hierarchical tunnel data model into one DT state. | AL72: Medium | AN72: Step-1 note: Data-driven tunnel maintenance DT; safety/resilience | Coded from Step-3 deep-read markdown (DfS-only scope), imported 2026-10-04 | AO72: 10.1016/j.ige.2025.09.002
A73: 69 | B73: Mehrishal, S et al. (2025) | C73: 2025 | E73: Tunnel Rapid AI Classification (TRaiC): An Open-Source Code for 360° Tunnel Face Mapping, Discontinuity Analysis, and RAG-LLM-Powered Geo-Engineering Reporting | F73: Scopus | G73: Yes | H73: Yes | I73: No | J73: Yes | K73: Yes | L73: =IF(COUNTBLANK(G73:K73)=5,"",IF(COUNTIF(G73:K73,"No")>0,"EXCLUDE","INCLUDE")) -> EXCLUDE | M73: =IF(L73<>"EXCLUDE","",IF(G73="No","Wrong domain (non-AECO)",IF(H73="No","Digital Twin not core / buzzword",IF(I73="No","No Design for Safety / PtD focus",IF(J73="No","Wrong publication type",IF(K73="No","Non-English","")))))) -> No Design for Safety / PtD focus | S73: =IF(N73<>"Yes","",IF(COUNTBLANK(P73:R73)=3,"",IF(COUNTIF(P73:R73,"No")>0,"EXCLUDE","INCLUDE"))) | T73: =IF(S73<>"EXCLUDE","",IF(P73="No","Digital Twin mentioned only, not the subject",IF(Q73="No","No Design for Safety focus in full text",IF(R73="No","Methodology not codable","")))) | Y73: =IF(SUM(V73:X73)=0,"",IF(SUM(V73:X73)>=2,"Multi","Single")) | AN73: Step-1 note: Tunnel face mapping tool; safety peripheral | AO73: 10.3390/rs17162891
A74: 70 | B74: Hijjawi, M et al. (2026) | C74: 2026 | E74: Digital Twin–Driven Reinforcement Learning for Proactive Cyber-Financial Threat Mitigation in Smart Healthcare Systems | F74: Scopus | G74: No | H74: Yes | I74: No | J74: Yes | K74: Yes | L74: =IF(COUNTBLANK(G74:K74)=5,"",IF(COUNTIF(G74:K74,"No")>0,"EXCLUDE","INCLUDE")) -> EXCLUDE | M74: =IF(L74<>"EXCLUDE","",IF(G74="No","Wrong domain (non-AECO)",IF(H74="No","Digital Twin not core / buzzword",IF(I74="No","No Design for Safety / PtD focus",IF(J74="No","Wrong publication type",IF(K74="No","Non-English","")))))) -> Wrong domain (non-AECO) | S74: =IF(N74<>"Yes","",IF(COUNTBLANK(P74:R74)=3,"",IF(COUNTIF(P74:R74,"No")>0,"EXCLUDE","INCLUDE"))) | T74: =IF(S74<>"EXCLUDE","",IF(P74="No","Digital Twin mentioned only, not the subject",IF(Q74="No","No Design for Safety focus in full text",IF(R74="No","Methodology not codable","")))) | Y74: =IF(SUM(V74:X74)=0,"",IF(SUM(V74:X74)>=2,"Multi","Single")) | AN74: Step-1 note: Healthcare cyber-financial DT; healthcare | AO74: 10.59543/jidmis.v3.1141
A75: 71 | B75: Deng, R et al. (2026) | C75: 2026 | E75: Safety risk perception of high-rise building construction process based on digital twin technology | F75: Scopus | G75: Yes | H75: Yes | I75: Yes | J75: Yes | K75: Yes | L75: =IF(COUNTBLANK(G75:K75)=5,"",IF(COUNTIF(G75:K75,"No")>0,"EXCLUDE","INCLUDE")) -> INCLUDE | M75: =IF(L75<>"EXCLUDE","",IF(G75="No","Wrong domain (non-AECO)",IF(H75="No","Digital Twin not core / buzzword",IF(I75="No","No Design for Safety / PtD focus",IF(J75="No","Wrong publication type",IF(K75="No","Non-English","")))))) | N75: Yes | O75: Yes | P75: Yes | Q75: Yes | R75: Yes | S75: =IF(N75<>"Yes","",IF(COUNTBLANK(P75:R75)=3,"",IF(COUNTIF(P75:R75,"No")>0,"EXCLUDE","INCLUDE"))) -> INCLUDE | T75: =IF(S75<>"EXCLUDE","",IF(P75="No","Digital Twin mentioned only, not the subject",IF(Q75="No","No Design for Safety focus in full text",IF(R75="No","Methodology not codable","")))) | U75: Tier 2 - Digital Shadow (one-way physical to virtual) | V75: 0 | W75: 1 | X75: 0 | Y75: =IF(SUM(V75:X75)=0,"",IF(SUM(V75:X75)>=2,"Multi","Single")) -> Single | Z75: Design for Safety (DfS) | AA75: None | AB75: Statistical / change-point | AC75: Multi (two or more data types) | AD75: Simulation | AE75: 3 | AF75: Predictive analytics / decision support | AG75: Safety risk perception method for high-rise construction based on DT (Chongqing Polytechnic, IJCIS 2026): improved grey relational analysis screens safety influence factors; local linear embedding reduces factor-data dimension; DT architecture establishes a bidirectional mapping between physical construction space and virtual information space, defining a construction risk index with coupling influence terms; multi-level early warning thresholds embeddable in the existing site monitoring platform; experiments (incl. immersive-VR scenario data with EEG/eye-tracking plus sensor data) give recall 96.57-99.06%, accuracy 96.76-97.89%, perception time 0.62-0.87 s. One-way monitoring->risk perception->early warning; no actuation and no learning loop. [Full-text source: Endnote] | AH75: Fills the recall/accuracy/latency gaps of previous safety-perception methods (dual-attention, BIM+GIS, multi-class AdaBoost): grey-relational screening plus LLE plus a coupling-risk DT index reaches 96.57-99.06% recall, 96.76-97.89% accuracy and 0.62-0.87 s perception time. | AI75: Experiments rely on simulated/VR scenario data and multi-source construction data rather than a full live high-rise deployment; grey-relational factor screening depends on expert weighting, and the mapping to an existing site monitoring platform is described as feasible but not demonstrated end-to-end on site. | AJ75: Fused | AK75: Grey-relational factor screening, LLE-reduced multi-source construction data and coupling influence terms are combined into a single construction risk index that drives hierarchical early warning. | AL75: Medium | AN75: Step-1 note: DT risk perception for high-rise construction safety | Coded from Step-3 deep-read markdown (DfS-only scope), imported 2026-10-04 | AO75: 10.1504/IJCIS.2026.155961
A76: 72 | B76: Du, W et al. (2025) | C76: 2025 | E76: Physics-based and data-driven long-term evolution of a landslide: From inversion to prediction | F76: Scopus | G76: Yes | H76: Yes | I76: Yes | J76: Yes | K76: Yes | L76: =IF(COUNTBLANK(G76:K76)=5,"",IF(COUNTIF(G76:K76,"No")>0,"EXCLUDE","INCLUDE")) -> INCLUDE | M76: =IF(L76<>"EXCLUDE","",IF(G76="No","Wrong domain (non-AECO)",IF(H76="No","Digital Twin not core / buzzword",IF(I76="No","No Design for Safety / PtD focus",IF(J76="No","Wrong publication type",IF(K76="No","Non-English","")))))) | N76: Yes | O76: Yes | P76: Yes | Q76: Yes | R76: Yes | S76: =IF(N76<>"Yes","",IF(COUNTBLANK(P76:R76)=3,"",IF(COUNTIF(P76:R76,"No")>0,"EXCLUDE","INCLUDE"))) -> INCLUDE | T76: =IF(S76<>"EXCLUDE","",IF(P76="No","Digital Twin mentioned only, not the subject",IF(Q76="No","No Design for Safety focus in full text",IF(R76="No","Methodology not codable","")))) | U76: Tier 2 - Digital Shadow (one-way physical to virtual) | V76: 0 | W76: 0 | X76: 1 | Y76: =IF(SUM(V76:X76)=0,"",IF(SUM(V76:X76)>=2,"Multi","Single")) -> Single | Z76: Design for Safety (DfS) | AA76: Implemented | AB76: Finite Element Method / physics-based | AC76: Multi (two or more data types) | AD76: Single case study | AE76: 4 | AF76: Predictive analytics / decision support | AG76: Taihe landslide twin combines GNSS/inclinometer monitoring, geological surveys and laboratory soil properties with a 1,162,841-particle GIMP-MPM model; state inversion and wet-dry strength degradation drive a 10-year failure forecast. No physical control loop. [Full-text source: browser-oa] | AH76: Combines monitored Taihe landslide state with MPM inversion and wet-dry degradation laws; forecasts east-side collapse beyond 260 m by year five and deposits beyond 460 m by year ten. | AI76: The ten-year forecast depends on an assumed annual wet-dry cycle and literature-derived degradation curves; coarse spatial/time discretization and uncertainty sensitivity remain open. | AJ76: Fused | AK76: GNSS/inclinometer and geological state observations constrain MPM inversion; lab/literature wet-dry strength evolution updates the twin state over successive long-term analysis steps. | AL76: High | AN76: Step-1 note: MPM geohazard twin; disaster prevention/mitigation | Coded from Step-3 deep-read markdown (DfS-only scope), imported 2026-10-04 | AO76: 10.1016/j.enggeo.2025.108252
A77: 73 | B77: Jiang, J et al. (2026) | C77: 2026 | E77: Application of the multimodal model for predicting rock mechanical parameters via MWD feature splicing and fusion | F77: Scopus | G77: Yes | H77: No | I77: Yes | J77: Yes | K77: Yes | L77: =IF(COUNTBLANK(G77:K77)=5,"",IF(COUNTIF(G77:K77,"No")>0,"EXCLUDE","INCLUDE")) -> EXCLUDE | M77: =IF(L77<>"EXCLUDE","",IF(G77="No","Wrong domain (non-AECO)",IF(H77="No","Digital Twin not core / buzzword",IF(I77="No","No Design for Safety / PtD focus",IF(J77="No","Wrong publication type",IF(K77="No","Non-English","")))))) -> Digital Twin not core / buzzword | S77: =IF(N77<>"Yes","",IF(COUNTBLANK(P77:R77)=3,"",IF(COUNTIF(P77:R77,"No")>0,"EXCLUDE","INCLUDE"))) | T77: =IF(S77<>"EXCLUDE","",IF(P77="No","Digital Twin mentioned only, not the subject",IF(Q77="No","No Design for Safety focus in full text",IF(R77="No","Methodology not codable","")))) | Y77: =IF(SUM(V77:X77)=0,"",IF(SUM(V77:X77)>=2,"Multi","Single")) | AN77: Step-1 note: MWD multimodal prediction; no DT | AO77: 10.1016/j.trgeo.2026.102063
A78: 74 | B78: Jahanbiglari, A et al. (2026) | C78: 2026 | E78: Human-AI trust for safer heavy-duty equipment management: Insights from socio-technical literature review and interviews | F78: Scopus | G78: Yes | H78: No | I78: Yes | J78: Yes | K78: Yes | L78: =IF(COUNTBLANK(G78:K78)=5,"",IF(COUNTIF(G78:K78,"No")>0,"EXCLUDE","INCLUDE")) -> EXCLUDE | M78: =IF(L78<>"EXCLUDE","",IF(G78="No","Wrong domain (non-AECO)",IF(H78="No","Digital Twin not core / buzzword",IF(I78="No","No Design for Safety / PtD focus",IF(J78="No","Wrong publication type",IF(K78="No","Non-English","")))))) -> Digital Twin not core / buzzword | S78: =IF(N78<>"Yes","",IF(COUNTBLANK(P78:R78)=3,"",IF(COUNTIF(P78:R78,"No")>0,"EXCLUDE","INCLUDE"))) | T78: =IF(S78<>"EXCLUDE","",IF(P78="No","Digital Twin mentioned only, not the subject",IF(Q78="No","No Design for Safety focus in full text",IF(R78="No","Methodology not codable","")))) | Y78: =IF(SUM(V78:X78)=0,"",IF(SUM(V78:X78)>=2,"Multi","Single")) | AN78: Step-1 note: Human-AI trust review; DT peripheral enabling tech | AO78: 10.1016/j.dibe.2026.100983
A79: 75 | B79: Mukherjee, R et al. (2026) | C79: 2026 | E79: Digital Twins Reimagined: Zero-Day LLM-Powered Moving Target Defense In-Depth for Real-Time CPS | F79: Scopus | G79: No | H79: Yes | I79: No | J79: Yes | K79: Yes | L79: =IF(COUNTBLANK(G79:K79)=5,"",IF(COUNTIF(G79:K79,"No")>0,"EXCLUDE","INCLUDE")) -> EXCLUDE | M79: =IF(L79<>"EXCLUDE","",IF(G79="No","Wrong domain (non-AECO)",IF(H79="No","Digital Twin not core / buzzword",IF(I79="No","No Design for Safety / PtD focus",IF(J79="No","Wrong publication type",IF(K79="No","Non-English","")))))) -> Wrong domain (non-AECO) | S79: =IF(N79<>"Yes","",IF(COUNTBLANK(P79:R79)=3,"",IF(COUNTIF(P79:R79,"No")>0,"EXCLUDE","INCLUDE"))) | T79: =IF(S79<>"EXCLUDE","",IF(P79="No","Digital Twin mentioned only, not the subject",IF(Q79="No","No Design for Safety focus in full text",IF(R79="No","Methodology not codable","")))) | Y79: =IF(SUM(V79:X79)=0,"",IF(SUM(V79:X79)>=2,"Multi","Single")) | AN79: Step-1 note: Generic CPS zero-day security; not AECO | AO79: 10.1109/JIOT.2026.3679937
A80: 76 | B80: Tzvetanov, K.T et al. (2025) | C80: 2025 | E80: Emergency preparedness planning for active shooter situations through higher-fidelity agent-based active shooter simulations: Framework for computational modeling of injury and blood loss | F80: Scopus | G80: No | H80: No | I80: Yes | J80: Yes | K80: Yes | L80: =IF(COUNTBLANK(G80:K80)=5,"",IF(COUNTIF(G80:K80,"No")>0,"EXCLUDE","INCLUDE")) -> EXCLUDE | M80: =IF(L80<>"EXCLUDE","",IF(G80="No","Wrong domain (non-AECO)",IF(H80="No","Digital Twin not core / buzzword",IF(I80="No","No Design for Safety / PtD focus",IF(J80="No","Wrong publication type",IF(K80="No","Non-English","")))))) -> Wrong domain (non-AECO) | S80: =IF(N80<>"Yes","",IF(COUNTBLANK(P80:R80)=3,"",IF(COUNTIF(P80:R80,"No")>0,"EXCLUDE","INCLUDE"))) | T80: =IF(S80<>"EXCLUDE","",IF(P80="No","Digital Twin mentioned only, not the subject",IF(Q80="No","No Design for Safety focus in full text",IF(R80="No","Methodology not codable","")))) | Y80: =IF(SUM(V80:X80)=0,"",IF(SUM(V80:X80)>=2,"Multi","Single")) | AN80: Step-1 note: Active-shooter ABM; no DT, not AECO asset | AO80: 10.5055/jem.0929
A81: 77 | B81: Xie, L et al. (2026) | C81: 2026 | E81: Real-time, crowdsourcing-enhanced forecasting of building functionality during urban floods | F81: Scopus | G81: Yes | H81: No | I81: Yes | J81: Yes | K81: Yes | L81: =IF(COUNTBLANK(G81:K81)=5,"",IF(COUNTIF(G81:K81,"No")>0,"EXCLUDE","INCLUDE")) -> EXCLUDE | M81: =IF(L81<>"EXCLUDE","",IF(G81="No","Wrong domain (non-AECO)",IF(H81="No","Digital Twin not core / buzzword",IF(I81="No","No Design for Safety / PtD focus",IF(J81="No","Wrong publication type",IF(K81="No","Non-English","")))))) -> Digital Twin not core / buzzword | S81: =IF(N81<>"Yes","",IF(COUNTBLANK(P81:R81)=3,"",IF(COUNTIF(P81:R81,"No")>0,"EXCLUDE","INCLUDE"))) | T81: =IF(S81<>"EXCLUDE","",IF(P81="No","Digital Twin mentioned only, not the subject",IF(Q81="No","No Design for Safety focus in full text",IF(R81="No","Methodology not codable","")))) | Y81: =IF(SUM(V81:X81)=0,"",IF(SUM(V81:X81)>=2,"Multi","Single")) | AN81: Step-1 note: Flood impact forecasting; no DT | AO81: 10.1016/j.cacaie.2026.100163
A82: 78 | B82: Shao, C et al. (2025) | C82: 2025 | E82: A visualization system for dam safety monitoring with application of digital twin platform | F82: Scopus | G82: Yes | H82: Yes | I82: Yes | J82: Yes | K82: Yes | L82: =IF(COUNTBLANK(G82:K82)=5,"",IF(COUNTIF(G82:K82,"No")>0,"EXCLUDE","INCLUDE")) -> INCLUDE | M82: =IF(L82<>"EXCLUDE","",IF(G82="No","Wrong domain (non-AECO)",IF(H82="No","Digital Twin not core / buzzword",IF(I82="No","No Design for Safety / PtD focus",IF(J82="No","Wrong publication type",IF(K82="No","Non-English","")))))) | N82: Yes | O82: Yes | P82: Yes | Q82: Yes | R82: Yes | S82: =IF(N82<>"Yes","",IF(COUNTBLANK(P82:R82)=3,"",IF(COUNTIF(P82:R82,"No")>0,"EXCLUDE","INCLUDE"))) -> INCLUDE | T82: =IF(S82<>"EXCLUDE","",IF(P82="No","Digital Twin mentioned only, not the subject",IF(Q82="No","No Design for Safety focus in full text",IF(R82="No","Methodology not codable","")))) | U82: Tier 2 - Digital Shadow (one-way physical to virtual) | V82: 0 | W82: 0 | X82: 1 | Y82: =IF(SUM(V82:X82)=0,"",IF(SUM(V82:X82)>=2,"Multi","Single")) -> Single | Z82: Design for Safety (DfS) | AA82: None | AB82: Other / Mixed | AC82: Multi (two or more data types) | AD82: Single case study | AE82: 3 | AF82: Design for Safety | AG82: The Jinping-I arch-dam platform connects sensor databases, preprocessing, FEM monitoring fields and safety-warning models; it demonstrates live monitoring-data visualization and simulated flood-discharge scenes on a real dam. The paper does not report automated actuation. [Full-text source: browser-oa] | AH82: Connects dam monitoring data, FEM fields and warning models in a real Jinping-I platform, with database preprocessing and real-time visualization for safety assessment. | AI82: The case demonstrates platform functions but supplies limited quantified warning-performance validation; extreme-event response and emergency-plan integration remain future work. | AJ82: Fused | AK82: Sensor databases feed FEM monitoring fields and safety models in the Jinping-I platform; the text describes integrated modules but does not quantify field-level fusion accuracy. | AL82: Medium | AN82: Step-1 note: Dam safety monitoring visualization DT platform | Coded from Step-3 deep-read markdown (DfS-only scope), imported 2026-10-04 | AO82: 10.1016/j.eswa.2025.126740
A83: 79 | B83: Akhavian, R et al. (2026) | C83: 2026 | E83: Semantic-Gravity Iterative Closest Point and AI-assisted navigation for Robot-Ready Construction Digital Twins | F83: Scopus | G83: Yes | H83: Yes | I83: Yes | J83: Yes | K83: Yes | L83: =IF(COUNTBLANK(G83:K83)=5,"",IF(COUNTIF(G83:K83,"No")>0,"EXCLUDE","INCLUDE")) -> INCLUDE | M83: =IF(L83<>"EXCLUDE","",IF(G83="No","Wrong domain (non-AECO)",IF(H83="No","Digital Twin not core / buzzword",IF(I83="No","No Design for Safety / PtD focus",IF(J83="No","Wrong publication type",IF(K83="No","Non-English","")))))) | N83: Yes | O83: Yes | P83: Yes | Q83: Yes | R83: Yes | S83: =IF(N83<>"Yes","",IF(COUNTBLANK(P83:R83)=3,"",IF(COUNTIF(P83:R83,"No")>0,"EXCLUDE","INCLUDE"))) -> INCLUDE | T83: =IF(S83<>"EXCLUDE","",IF(P83="No","Digital Twin mentioned only, not the subject",IF(Q83="No","No Design for Safety focus in full text",IF(R83="No","Methodology not codable","")))) | U83: Tier 2 - Digital Shadow (one-way physical to virtual) | V83: 0 | W83: 1 | X83: 0 | Y83: =IF(SUM(V83:X83)=0,"",IF(SUM(V83:X83)>=2,"Multi","Single")) -> Single | Z83: Design for Safety (DfS) | AA83: None | AB83: Other / Mixed | AC83: Multi (two or more data types) | AD83: Simulation | AE83: 4 | AF83: Perception / Computer Vision | AG83: BIM2RDT pipeline (SDSU/UCSD, AutCon 2026): transforms static BIM into robot-ready construction digital twins; Semantic-Gravity ICP uses LLM-guided semantic reasoning to assign BIM-family-specific upright priors for low-feature scan-to-BIM registration (RMSE reduced 60-97% in high-noise controlled experiments); YOLOE open-vocabulary detection conditions perception; HAV vibration sensing written into IFC-compatible twin (IfcEvent/IfcTask) feeds context-aware cost maps for safety-aware robot path planning. Sensing->twin->planning loop with IFC updates, but robot actuation not demonstrated (navigation constraints proposed); controlled experiments only; no learning loop. [Full-text source: browser-oa] | AH83: Semantic-Gravity ICP with LLM-inferred upright priors cuts registration RMSE by 60-97% in low-feature scenes, and the BIM2RDT loop writes sensor-detected safety activities (HAV) into IFC for context-aware robot planning. | AI83: Controlled experiments without real construction-site robots; LLM orchestration is narrow/bounded (no long-horizon autonomy); actuation not demonstrated; generalisation across site types untested. | AJ83: Fused | AK83: BIM geometry, UGV visual observations and IoT/HAV sensing are fused in the twin, with semantic activity layers written to IFC. | AL83: Medium | AN83: Step-1 note: BIM2RDT robot-ready DT; safety monitoring + path planning | Coded from Step-3 deep-read markdown (DfS-only scope), imported 2026-10-04 | AO83: 10.1016/j.autcon.2026.107134
A84: 80 | B84: Hasan, A et al. (2026) | C84: 2026 | E84: Agentic AI in Wind Energy Systems: Multi-Agent Architectures for Optimization and Resilience | F84: Scopus | G84: No | H84: Yes | I84: No | J84: Yes | K84: Yes | L84: =IF(COUNTBLANK(G84:K84)=5,"",IF(COUNTIF(G84:K84,"No")>0,"EXCLUDE","INCLUDE")) -> EXCLUDE | M84: =IF(L84<>"EXCLUDE","",IF(G84="No","Wrong domain (non-AECO)",IF(H84="No","Digital Twin not core / buzzword",IF(I84="No","No Design for Safety / PtD focus",IF(J84="No","Wrong publication type",IF(K84="No","Non-English","")))))) -> Wrong domain (non-AECO) | S84: =IF(N84<>"Yes","",IF(COUNTBLANK(P84:R84)=3,"",IF(COUNTIF(P84:R84,"No")>0,"EXCLUDE","INCLUDE"))) | T84: =IF(S84<>"EXCLUDE","",IF(P84="No","Digital Twin mentioned only, not the subject",IF(Q84="No","No Design for Safety focus in full text",IF(R84="No","Methodology not codable","")))) | Y84: =IF(SUM(V84:X84)=0,"",IF(SUM(V84:X84)>=2,"Multi","Single")) | AN84: Step-1 note: Wind energy agentic AI; not AECO | AO84: 10.1109/ACCESS.2026.3654529
A85: 81 | B85: Chang, X et al. (2026) | C85: 2026 | E85: Structural evaluation of cracked shield tunnels using computer-vision-based model updating techniques | F85: Scopus | G85: Yes | H85: No | I85: Yes | J85: Yes | K85: Yes | L85: =IF(COUNTBLANK(G85:K85)=5,"",IF(COUNTIF(G85:K85,"No")>0,"EXCLUDE","INCLUDE")) -> EXCLUDE | M85: =IF(L85<>"EXCLUDE","",IF(G85="No","Wrong domain (non-AECO)",IF(H85="No","Digital Twin not core / buzzword",IF(I85="No","No Design for Safety / PtD focus",IF(J85="No","Wrong publication type",IF(K85="No","Non-English","")))))) -> Digital Twin not core / buzzword | S85: =IF(N85<>"Yes","",IF(COUNTBLANK(P85:R85)=3,"",IF(COUNTIF(P85:R85,"No")>0,"EXCLUDE","INCLUDE"))) | T85: =IF(S85<>"EXCLUDE","",IF(P85="No","Digital Twin mentioned only, not the subject",IF(Q85="No","No Design for Safety focus in full text",IF(R85="No","Methodology not codable","")))) | Y85: =IF(SUM(V85:X85)=0,"",IF(SUM(V85:X85)>=2,"Multi","Single")) | AN85: Step-1 note: CV-based FE model updating; no DT | AO85: 10.1016/j.aei.2025.103818
A86: 82 | B86: Bahreini, F et al. (2025) | C86: 2025 | E86: Developing Computer Vision-Based Digital Twin for Vegetation Management near Power Distribution Networks | F86: Scopus | G86: No | H86: Yes | I86: Yes | J86: Yes | K86: Yes | L86: =IF(COUNTBLANK(G86:K86)=5,"",IF(COUNTIF(G86:K86,"No")>0,"EXCLUDE","INCLUDE")) -> EXCLUDE | M86: =IF(L86<>"EXCLUDE","",IF(G86="No","Wrong domain (non-AECO)",IF(H86="No","Digital Twin not core / buzzword",IF(I86="No","No Design for Safety / PtD focus",IF(J86="No","Wrong publication type",IF(K86="No","Non-English","")))))) -> Wrong domain (non-AECO) | S86: =IF(N86<>"Yes","",IF(COUNTBLANK(P86:R86)=3,"",IF(COUNTIF(P86:R86,"No")>0,"EXCLUDE","INCLUDE"))) | T86: =IF(S86<>"EXCLUDE","",IF(P86="No","Digital Twin mentioned only, not the subject",IF(Q86="No","No Design for Safety focus in full text",IF(R86="No","Methodology not codable","")))) | Y86: =IF(SUM(V86:X86)=0,"",IF(SUM(V86:X86)>=2,"Multi","Single")) | AN86: Step-1 note: Power distribution vegetation DT; not AECO | AO86: 10.3390/rs17213565
A87: 83 | B87: Zhang, Y et al. (2026) | C87: 2026 | E87: Digital twins for low-altitude transportation and logistics: A barrier-centric survey of UAV and eVTOL systems | F87: Scopus | G87: No | H87: Yes | I87: No | J87: Yes | K87: Yes | L87: =IF(COUNTBLANK(G87:K87)=5,"",IF(COUNTIF(G87:K87,"No")>0,"EXCLUDE","INCLUDE")) -> EXCLUDE | M87: =IF(L87<>"EXCLUDE","",IF(G87="No","Wrong domain (non-AECO)",IF(H87="No","Digital Twin not core / buzzword",IF(I87="No","No Design for Safety / PtD focus",IF(J87="No","Wrong publication type",IF(K87="No","Non-English","")))))) -> Wrong domain (non-AECO) | S87: =IF(N87<>"Yes","",IF(COUNTBLANK(P87:R87)=3,"",IF(COUNTIF(P87:R87,"No")>0,"EXCLUDE","INCLUDE"))) | T87: =IF(S87<>"EXCLUDE","",IF(P87="No","Digital Twin mentioned only, not the subject",IF(Q87="No","No Design for Safety focus in full text",IF(R87="No","Methodology not codable","")))) | Y87: =IF(SUM(V87:X87)=0,"",IF(SUM(V87:X87)>=2,"Multi","Single")) | AN87: Step-1 note: UAV/eVTOL logistics survey; not AECO | AO87: 10.1016/j.tre.2026.105116
A88: 84 | B88: Gusev, A.L et al. (2026) | C88: 2026 | E88: Maglev-enhanced vertical-axis wind turbines for hydrogen production and storage systems | F88: Scopus | G88: No | H88: No | I88: No | J88: Yes | K88: Yes | L88: =IF(COUNTBLANK(G88:K88)=5,"",IF(COUNTIF(G88:K88,"No")>0,"EXCLUDE","INCLUDE")) -> EXCLUDE | M88: =IF(L88<>"EXCLUDE","",IF(G88="No","Wrong domain (non-AECO)",IF(H88="No","Digital Twin not core / buzzword",IF(I88="No","No Design for Safety / PtD focus",IF(J88="No","Wrong publication type",IF(K88="No","Non-English","")))))) -> Wrong domain (non-AECO) | S88: =IF(N88<>"Yes","",IF(COUNTBLANK(P88:R88)=3,"",IF(COUNTIF(P88:R88,"No")>0,"EXCLUDE","INCLUDE"))) | T88: =IF(S88<>"EXCLUDE","",IF(P88="No","Digital Twin mentioned only, not the subject",IF(Q88="No","No Design for Safety focus in full text",IF(R88="No","Methodology not codable","")))) | Y88: =IF(SUM(V88:X88)=0,"",IF(SUM(V88:X88)>=2,"Multi","Single")) | AN88: Step-1 note: Maglev wind turbines/hydrogen; energy, not AECO | AO88: 10.1016/j.ijhydene.2026.156914
A89: 85 | B89: Kumar, A et al. (2026) | C89: 2026 | E89: Explainable artificial intelligence based simulation-to-real domain adaptation for robust rotor condition monitoring | F89: Scopus | G89: No | H89: Yes | I89: Yes | J89: Yes | K89: Yes | L89: =IF(COUNTBLANK(G89:K89)=5,"",IF(COUNTIF(G89:K89,"No")>0,"EXCLUDE","INCLUDE")) -> EXCLUDE | M89: =IF(L89<>"EXCLUDE","",IF(G89="No","Wrong domain (non-AECO)",IF(H89="No","Digital Twin not core / buzzword",IF(I89="No","No Design for Safety / PtD focus",IF(J89="No","Wrong publication type",IF(K89="No","Non-English","")))))) -> Wrong domain (non-AECO) | S89: =IF(N89<>"Yes","",IF(COUNTBLANK(P89:R89)=3,"",IF(COUNTIF(P89:R89,"No")>0,"EXCLUDE","INCLUDE"))) | T89: =IF(S89<>"EXCLUDE","",IF(P89="No","Digital Twin mentioned only, not the subject",IF(Q89="No","No Design for Safety focus in full text",IF(R89="No","Methodology not codable","")))) | Y89: =IF(SUM(V89:X89)=0,"",IF(SUM(V89:X89)>=2,"Multi","Single")) | AN89: Step-1 note: Rotor condition monitoring; industrial machinery | AO89: 10.1016/j.aei.2026.104652
A90: 86 | B90: Tu, W et al. (2026) | C90: 2026 | E90: Serviceability assessment and structural response forecasting of near-coast utility tunnels under soft-soil conditions | F90: Scopus | G90: Yes | H90: No | I90: Yes | J90: Yes | K90: Yes | L90: =IF(COUNTBLANK(G90:K90)=5,"",IF(COUNTIF(G90:K90,"No")>0,"EXCLUDE","INCLUDE")) -> EXCLUDE | M90: =IF(L90<>"EXCLUDE","",IF(G90="No","Wrong domain (non-AECO)",IF(H90="No","Digital Twin not core / buzzword",IF(I90="No","No Design for Safety / PtD focus",IF(J90="No","Wrong publication type",IF(K90="No","Non-English","")))))) -> Digital Twin not core / buzzword | S90: =IF(N90<>"Yes","",IF(COUNTBLANK(P90:R90)=3,"",IF(COUNTIF(P90:R90,"No")>0,"EXCLUDE","INCLUDE"))) | T90: =IF(S90<>"EXCLUDE","",IF(P90="No","Digital Twin mentioned only, not the subject",IF(Q90="No","No Design for Safety focus in full text",IF(R90="No","Methodology not codable","")))) | Y90: =IF(SUM(V90:X90)=0,"",IF(SUM(V90:X90)>=2,"Multi","Single")) | AN90: Step-1 note: Utility tunnel monitoring framework; no DT | AO90: 10.1016/j.istruc.2026.112340
A91: 87 | B91: Yan, H et al. (2026) | C91: 2026 | E91: Digital twin-enabled 3D near-misses prediction method based on trajectories and postures for proactive construction safety management | F91: Scopus | G91: Yes | H91: Yes | I91: Yes | J91: Yes | K91: Yes | L91: =IF(COUNTBLANK(G91:K91)=5,"",IF(COUNTIF(G91:K91,"No")>0,"EXCLUDE","INCLUDE")) -> INCLUDE | M91: =IF(L91<>"EXCLUDE","",IF(G91="No","Wrong domain (non-AECO)",IF(H91="No","Digital Twin not core / buzzword",IF(I91="No","No Design for Safety / PtD focus",IF(J91="No","Wrong publication type",IF(K91="No","Non-English","")))))) | N91: Yes | O91: Yes | P91: Yes | Q91: Yes | R91: Yes | S91: =IF(N91<>"Yes","",IF(COUNTBLANK(P91:R91)=3,"",IF(COUNTIF(P91:R91,"No")>0,"EXCLUDE","INCLUDE"))) -> INCLUDE | T91: =IF(S91<>"EXCLUDE","",IF(P91="No","Digital Twin mentioned only, not the subject",IF(Q91="No","No Design for Safety focus in full text",IF(R91="No","Methodology not codable","")))) | U91: Tier 2 - Digital Shadow (one-way physical to virtual) | V91: 0 | W91: 1 | X91: 0 | Y91: =IF(SUM(V91:X91)=0,"",IF(SUM(V91:X91)>=2,"Multi","Single")) -> Single | Z91: Design for Safety (DfS) | AA91: None | AB91: Transformer / Large Language Model (LLM) | AC91: Multi (two or more data types) | AD91: Single case study | AE91: 4 | AF91: Predictive analytics / decision support | AG91: Computer-vision-based digital twin framework for proactive near-miss prediction (Harbin IT): integrates real-time worker trajectories, postures and interactions into a dynamic 3D construction-site model; non-autoregressive transformer predicts future movement sequences (human motion model trained on Human3.6M dataset, inverse kinematics for joint angles) + collision detection identifies potential near-misses with early warnings; field-validated in three high-risk zones (forklift paths, floor openings, material lifting). One-way perception to prediction to early warning for safety managers; no actuation and no self-improvement loop (model is offline-trained). [Full-text source: 04c-port] | AH91: Extends near-miss management from 2D detection to in-process 3D prediction: YOLOv5, SGBM, DeepSORT and MediaPipe keypoints feed a non-autoregressive transformer that forecasts worker trajectories (ADE 0.134) and postures (ADE 0.501), reconstructed by an LBFGS inverse-kinematics solver in Unreal Engine, predicting near-misses with 93.32% precision and 96.08% recall across forklift, floor-opening, and material-lifting zones. | AI91: The motion prediction model is trained on the Human3.6M laboratory dataset, creating a generalization gap to real construction postures; occlusions, lighting variability, and camera positioning limit reliability, and validation covered only three relatively simple high-risk zones. Future work adds more sensor types, lightweight edge-distributed architectures, domain-adaptive learning, and broader site validation. | AJ91: Fused | AK91: Worker trajectories (YOLOv5/SGBM/DeepSORT/MediaPipe) and BIM scene geometry jointly feed a non-autoregressive transformer plus inverse-kinematics reconstruction for 3D near-miss prediction. | AL91: High | AN91: Step-1 note: DT 3D near-miss prediction; proactive safety | Coded from Step-3 deep-read markdown (DfS-only scope), imported 2026-10-04 | AO91: 10.1108/ECAM-05-2025-0732
A92: 88 | B92: Sun, H et al. (2025) | C92: 2025 | E92: Digital twin of advanced geological conditions in rock tunnel construction | F92: Scopus | G92: Yes | H92: Yes | I92: Yes | J92: Yes | K92: Yes | L92: =IF(COUNTBLANK(G92:K92)=5,"",IF(COUNTIF(G92:K92,"No")>0,"EXCLUDE","INCLUDE")) -> INCLUDE | M92: =IF(L92<>"EXCLUDE","",IF(G92="No","Wrong domain (non-AECO)",IF(H92="No","Digital Twin not core / buzzword",IF(I92="No","No Design for Safety / PtD focus",IF(J92="No","Wrong publication type",IF(K92="No","Non-English","")))))) | N92: Yes | O92: Yes | P92: Yes | Q92: Yes | R92: Yes | S92: =IF(N92<>"Yes","",IF(COUNTBLANK(P92:R92)=3,"",IF(COUNTIF(P92:R92,"No")>0,"EXCLUDE","INCLUDE"))) -> INCLUDE | T92: =IF(S92<>"EXCLUDE","",IF(P92="No","Digital Twin mentioned only, not the subject",IF(Q92="No","No Design for Safety focus in full text",IF(R92="No","Methodology not codable","")))) | U92: Tier 3 - Digital Twin (bidirectional, two-way) | V92: 0 | W92: 1 | X92: 0 | Y92: =IF(SUM(V92:X92)=0,"",IF(SUM(V92:X92)>=2,"Multi","Single")) -> Single | Z92: Design for Safety (DfS) | AA92: None | AB92: Other / Mixed | AC92: Multi (two or more data types) | AD92: Single case study | AE92: 4 | AF92: Predictive analytics / decision support | AG92: Digital twin for advanced geological conditions in rock tunnel construction (Tongji U): multi-source geological data (water content, lithology, integrity) → multi-dimensional virtual models (geometric, attribute, behavior); fuzzy cloud probability model quantifies uncertainty for intelligent rock classification (92.95% accuracy); iS3 platform implements closed-loop data-model-decision; validated on five rock tunnel projects. Closed-loop data→model→decision→feedback → Tier 3; no learning loop (fuzzy cloud is probabilistic, not learning). [Full-text source: 04c-port] | AH92: Closes the data-model-decision loop for geological uncertainty ahead of tunnel faces: TEM, GPR and borehole data become point-cloud models of water content, lithology and integrity via KNN interpolation, and a fuzzy cloud probability model quantifies uncertainty to classify surrounding rock per meter within a 30 m range, achieving 92.95 percent accuracy across 539 exposed-rock records of five tunnels on the Tongji iS3 platform. | AI92: Decision factors cover only water content, lithology and integrity; GPR captures a single cross-section so longitudinal integrity variation is missing, databases are unevenly sized, and per-cycle computation of 10-60 s grows to 2-5 minutes for concurrent tunnels; the authors propose GPU and KD-tree acceleration plus extension to soft-soil and underwater tunnels. | AJ92: Fused | AK92: TEM, GPR and borehole data are converted into point-cloud models of water content, lithology and integrity and jointly classified by a fuzzy cloud probability model into surrounding-rock classes. | AL92: High | AN92: Step-1 note: Geological DT for rock tunnel; risk management | Coded from Step-3 deep-read markdown (DfS-only scope), imported 2026-10-04 | AO92: 10.1016/j.autcon.2025.106407
A93: 89 | B93: Chan, F.K.S et al. (2026) | C93: 2026 | E93: Smart Technological Urban Flood Management Strategies Are “Must-Do” Approaches: The Case of Chinese Coastal Megacity, Ningbo, East Coast of China | F93: Scopus | G93: Yes | H93: Yes | I93: Yes | J93: Yes | K93: Yes | L93: =IF(COUNTBLANK(G93:K93)=5,"",IF(COUNTIF(G93:K93,"No")>0,"EXCLUDE","INCLUDE")) -> INCLUDE | M93: =IF(L93<>"EXCLUDE","",IF(G93="No","Wrong domain (non-AECO)",IF(H93="No","Digital Twin not core / buzzword",IF(I93="No","No Design for Safety / PtD focus",IF(J93="No","Wrong publication type",IF(K93="No","Non-English","")))))) | N93: Yes | O93: Yes | P93: Yes | Q93: Yes | R93: Yes | S93: =IF(N93<>"Yes","",IF(COUNTBLANK(P93:R93)=3,"",IF(COUNTIF(P93:R93,"No")>0,"EXCLUDE","INCLUDE"))) -> INCLUDE | T93: =IF(S93<>"EXCLUDE","",IF(P93="No","Digital Twin mentioned only, not the subject",IF(Q93="No","No Design for Safety focus in full text",IF(R93="No","Methodology not codable","")))) | U93: Tier 2 - Digital Shadow (one-way physical to virtual) | V93: 0 | W93: 0 | X93: 1 | Y93: =IF(SUM(V93:X93)=0,"",IF(SUM(V93:X93)>=2,"Multi","Single")) -> Single | Z93: Design for Safety (DfS) | AA93: None | AB93: Digital Twin platform (no machine learning) | AC93: Multi (two or more data types) | AD93: Single case study | AE93: 3 | AF93: Lifecycle / governance | AG93: Ningbo smart flood management case study (UNNC/Leeds, Water 2026): assesses the city Water Bureau deployed digital twin with 3D flood mapping and real-time monitoring during typhoons In-Fa (2021) and Muifa (2022), demonstrating effective safeguarding of public safety; priorities identified: computing capacity, cross-departmental coordination, open data sharing and AI integration. Governance-level evaluation of a deployed one-way monitoring/decision-support platform; no actuation, no learning loop (AI not yet integrated). [Full-text source: browser-oa] | AH93: Provides real-event evidence (typhoons In-Fa and Muifa) that a city-scale DT with 3D flood mapping and real-time monitoring safeguards public safety, with concrete governance recommendations for scaling. | AI93: Second-hand evaluation of a government platform (no technical details of the twin architecture or fusion); no quantitative flood metrics; AI integration is only recommended. | AJ93: Unclear | AK93: The deployed Ningbo platform integrates 3D flood mapping with real-time monitoring, but fusion architecture is not described in this governance-focused study. | AL93: Low | AM93: REVIEW: fusion Unclear / Low confidence | AN93: Step-1 note: Ningbo smart flood DT; public safety | Coded from Step-3 deep-read markdown (DfS-only scope), imported 2026-10-04 | AO93: 10.3390/w18030427
A94: 90 | B94: Allalou, R et al. (2026) | C94: 2026 | E94: BIM-GIS integrated hydrodynamic modeling for road flood risk assessment: A case study in Algeria’s Chiffa Wadi | F94: Scopus | G94: Yes | H94: No | I94: Yes | J94: Yes | K94: Yes | L94: =IF(COUNTBLANK(G94:K94)=5,"",IF(COUNTIF(G94:K94,"No")>0,"EXCLUDE","INCLUDE")) -> EXCLUDE | M94: =IF(L94<>"EXCLUDE","",IF(G94="No","Wrong domain (non-AECO)",IF(H94="No","Digital Twin not core / buzzword",IF(I94="No","No Design for Safety / PtD focus",IF(J94="No","Wrong publication type",IF(K94="No","Non-English","")))))) -> Digital Twin not core / buzzword | S94: =IF(N94<>"Yes","",IF(COUNTBLANK(P94:R94)=3,"",IF(COUNTIF(P94:R94,"No")>0,"EXCLUDE","INCLUDE"))) | T94: =IF(S94<>"EXCLUDE","",IF(P94="No","Digital Twin mentioned only, not the subject",IF(Q94="No","No Design for Safety focus in full text",IF(R94="No","Methodology not codable","")))) | Y94: =IF(SUM(V94:X94)=0,"",IF(SUM(V94:X94)>=2,"Multi","Single")) | AN94: Step-1 note: BIM-GIS-HDM flood framework; DT future only | AO94: 10.1016/j.ress.2025.111906
A95: 91 | B95: Sun, J et al. (2026) | C95: 2026 | E95: An Enhanced Digital Twin-Driven Fault Diagnosis Approach Based on Deep Multimodal Information Fusion for Marine Machinery | F95: Scopus | G95: No | H95: Yes | I95: Yes | J95: Yes | K95: Yes | L95: =IF(COUNTBLANK(G95:K95)=5,"",IF(COUNTIF(G95:K95,"No")>0,"EXCLUDE","INCLUDE")) -> EXCLUDE | M95: =IF(L95<>"EXCLUDE","",IF(G95="No","Wrong domain (non-AECO)",IF(H95="No","Digital Twin not core / buzzword",IF(I95="No","No Design for Safety / PtD focus",IF(J95="No","Wrong publication type",IF(K95="No","Non-English","")))))) -> Wrong domain (non-AECO) | S95: =IF(N95<>"Yes","",IF(COUNTBLANK(P95:R95)=3,"",IF(COUNTIF(P95:R95,"No")>0,"EXCLUDE","INCLUDE"))) | T95: =IF(S95<>"EXCLUDE","",IF(P95="No","Digital Twin mentioned only, not the subject",IF(Q95="No","No Design for Safety focus in full text",IF(R95="No","Methodology not codable","")))) | Y95: =IF(SUM(V95:X95)=0,"",IF(SUM(V95:X95)>=2,"Multi","Single")) | AN95: Step-1 note: Marine machinery fault DT; offshore, not AECO | AO95: 10.1109/JSEN.2025.3644934
A96: 92 | B96: Nguyen, T.H et al. (2026) | C96: 2026 | E96: Towards Digital Twin in Flood Forecasting with Data Assimilation Satellite Earth Observations—A Proof-of-Concept | F96: Scopus | G96: No | H96: Yes | I96: Yes | J96: Yes | K96: Yes | L96: =IF(COUNTBLANK(G96:K96)=5,"",IF(COUNTIF(G96:K96,"No")>0,"EXCLUDE","INCLUDE")) -> EXCLUDE | M96: =IF(L96<>"EXCLUDE","",IF(G96="No","Wrong domain (non-AECO)",IF(H96="No","Digital Twin not core / buzzword",IF(I96="No","No Design for Safety / PtD focus",IF(J96="No","Wrong publication type",IF(K96="No","Non-English","")))))) -> Wrong domain (non-AECO) | S96: =IF(N96<>"Yes","",IF(COUNTBLANK(P96:R96)=3,"",IF(COUNTIF(P96:R96,"No")>0,"EXCLUDE","INCLUDE"))) | T96: =IF(S96<>"EXCLUDE","",IF(P96="No","Digital Twin mentioned only, not the subject",IF(Q96="No","No Design for Safety focus in full text",IF(R96="No","Methodology not codable","")))) | Y96: =IF(SUM(V96:X96)=0,"",IF(SUM(V96:X96)>=2,"Multi","Single")) | AN96: Step-1 note: River flood forecasting DT; hydrology domain | AO96: 10.3390/rs18050685
A97: 93 | B97: Teng, H et al. (2026) | C97: 2026 | E97: Dual-Dimensional Collaborative Analysis for the Optimization of Slope Monitoring Points | F97: Scopus | G97: Yes | H97: Yes | I97: Yes | J97: Yes | K97: Yes | L97: =IF(COUNTBLANK(G97:K97)=5,"",IF(COUNTIF(G97:K97,"No")>0,"EXCLUDE","INCLUDE")) -> INCLUDE | M97: =IF(L97<>"EXCLUDE","",IF(G97="No","Wrong domain (non-AECO)",IF(H97="No","Digital Twin not core / buzzword",IF(I97="No","No Design for Safety / PtD focus",IF(J97="No","Wrong publication type",IF(K97="No","Non-English","")))))) | N97: No | O97: No | S97: =IF(N97<>"Yes","",IF(COUNTBLANK(P97:R97)=3,"",IF(COUNTIF(P97:R97,"No")>0,"EXCLUDE","INCLUDE"))) | T97: =IF(S97<>"EXCLUDE","",IF(P97="No","Digital Twin mentioned only, not the subject",IF(Q97="No","No Design for Safety focus in full text",IF(R97="No","Methodology not codable","")))) | Y97: =IF(SUM(V97:X97)=0,"",IF(SUM(V97:X97)>=2,"Multi","Single")) | AN97: Step-1 note: FLAC3D-as-twin slope monitoring optimization; landslide safety | Full text not coded: Endnote candidate(s) found but identity not verified | AO97: 10.1061/IJGNAI.GMENG-13767
A98: 94 | B98: Domina, O et al. (2025) | C98: 2025 | E98: THE IMPACT OF ARTIFICIAL INTELLIGENCE ON THE FORMATION OF A TEACHER’S DIGITAL TWIN IN THE METAVERSE | F98: Scopus | G98: No | H98: No | I98: No | J98: Yes | K98: Yes | L98: =IF(COUNTBLANK(G98:K98)=5,"",IF(COUNTIF(G98:K98,"No")>0,"EXCLUDE","INCLUDE")) -> EXCLUDE | M98: =IF(L98<>"EXCLUDE","",IF(G98="No","Wrong domain (non-AECO)",IF(H98="No","Digital Twin not core / buzzword",IF(I98="No","No Design for Safety / PtD focus",IF(J98="No","Wrong publication type",IF(K98="No","Non-English","")))))) -> Wrong domain (non-AECO) | S98: =IF(N98<>"Yes","",IF(COUNTBLANK(P98:R98)=3,"",IF(COUNTIF(P98:R98,"No")>0,"EXCLUDE","INCLUDE"))) | T98: =IF(S98<>"EXCLUDE","",IF(P98="No","Digital Twin mentioned only, not the subject",IF(Q98="No","No Design for Safety focus in full text",IF(R98="No","Methodology not codable","")))) | Y98: =IF(SUM(V98:X98)=0,"",IF(SUM(V98:X98)>=2,"Multi","Single")) | AN98: Step-1 note: Teacher digital twin in metaverse; education | AO98: 10.15330/jpnu.12.3.169-185
A99: 95 | B99: Guo, C et al. (2026) | C99: 2026 | E99: Deep Reinforcement Learning-Based Intelligent Battery Charging Strategy | F99: Scopus | G99: No | H99: Yes | I99: No | J99: Yes | K99: Yes | L99: =IF(COUNTBLANK(G99:K99)=5,"",IF(COUNTIF(G99:K99,"No")>0,"EXCLUDE","INCLUDE")) -> EXCLUDE | M99: =IF(L99<>"EXCLUDE","",IF(G99="No","Wrong domain (non-AECO)",IF(H99="No","Digital Twin not core / buzzword",IF(I99="No","No Design for Safety / PtD focus",IF(J99="No","Wrong publication type",IF(K99="No","Non-English","")))))) -> Wrong domain (non-AECO) | S99: =IF(N99<>"Yes","",IF(COUNTBLANK(P99:R99)=3,"",IF(COUNTIF(P99:R99,"No")>0,"EXCLUDE","INCLUDE"))) | T99: =IF(S99<>"EXCLUDE","",IF(P99="No","Digital Twin mentioned only, not the subject",IF(Q99="No","No Design for Safety focus in full text",IF(R99="No","Methodology not codable","")))) | Y99: =IF(SUM(V99:X99)=0,"",IF(SUM(V99:X99)>=2,"Multi","Single")) | AN99: Step-1 note: Battery charging DRL; not AECO | AO99: 10.1002/ente.70567
A100: 96 | B100: Arin, I.A et al. (2025) | C100: 2025 | E100: An Integrated Digital Twin Architecture for Proposing Field Service Management Model in Fiber Optic Network Infrastructure: A Design Science Approach | F100: Scopus | G100: No | H100: Yes | I100: No | J100: Yes | K100: Yes | L100: =IF(COUNTBLANK(G100:K100)=5,"",IF(COUNTIF(G100:K100,"No")>0,"EXCLUDE","INCLUDE")) -> EXCLUDE | M100: =IF(L100<>"EXCLUDE","",IF(G100="No","Wrong domain (non-AECO)",IF(H100="No","Digital Twin not core / buzzword",IF(I100="No","No Design for Safety / PtD focus",IF(J100="No","Wrong publication type",IF(K100="No","Non-English","")))))) -> Wrong domain (non-AECO) | S100: =IF(N100<>"Yes","",IF(COUNTBLANK(P100:R100)=3,"",IF(COUNTIF(P100:R100,"No")>0,"EXCLUDE","INCLUDE"))) | T100: =IF(S100<>"EXCLUDE","",IF(P100="No","Digital Twin mentioned only, not the subject",IF(Q100="No","No Design for Safety focus in full text",IF(R100="No","Methodology not codable","")))) | Y100: =IF(SUM(V100:X100)=0,"",IF(SUM(V100:X100)>=2,"Multi","Single")) | AN100: Step-1 note: Telecom fiber FSM DT; not AECO | AO100: 10.18280/isi.300511
...

Sheet Step1_Report
A1: STEP 1 & PRISMA - screening outcomes (auto)
A3: PRISMA stage | B3: n
A4: Records identified (in matrix) | B4: =COUNTA(Matrix!$A$5:$A$960) -> 956
A5: Records screened (Stage-1 decided) | B5: =COUNTIF(Matrix!$L$5:$L$960,"INCLUDE")+COUNTIF(Matrix!$L$5:$L$960,"EXCLUDE") -> 956
A6: Excluded at Stage-1 (title/abstract) | B6: =COUNTIF(Matrix!$L$5:$L$960,"EXCLUDE") -> 712
A7: Stage-1 INCLUDE -> sought for retrieval | B7: =COUNTIF(Matrix!$L$5:$L$960,"INCLUDE") -> 244
A8: PDF full text on hand (gateway = Yes) | B8: =COUNTIFS(Matrix!$L$5:$L$960,"INCLUDE",Matrix!$N$5:$N$960,"Yes") -> 240
A9: PDF not yet on hand (revisit later) | B9: =COUNTIFS(Matrix!$L$5:$L$960,"INCLUDE",Matrix!$N$5:$N$960,"No") -> 4
A10: Reports assessed for eligibility (full text) | B10: =COUNTIFS(Matrix!$N$5:$N$960,"Yes",Matrix!$S$5:$S$960,"INCLUDE")+COUNTIFS(Matrix!$N$5:$N$960,"Yes",Matrix!$S$5:$S$960,"EXCLUDE") -> 240
A11: Excluded at Stage-2 (full text, with reasons) | B11: =COUNTIF(Matrix!$S$5:$S$960,"EXCLUDE") -> 18
A12: STUDIES INCLUDED IN SYNTHESIS | B12: =COUNTIF(Matrix!$S$5:$S$960,"INCLUDE") -> 222
A14: Stage-1 exclusion reasons
A15: Reason | B15: n
A16: Wrong domain (non-AECO) | B16: =COUNTIF(Matrix!$M$5:$M$960,"Wrong domain (non-AECO)") -> 415
A17: Digital Twin not core / buzzword | B17: =COUNTIF(Matrix!$M$5:$M$960,"Digital Twin not core / buzzword") -> 229
A18: No Design for Safety / PtD focus | B18: =COUNTIF(Matrix!$M$5:$M$960,"No Design for Safety / PtD focus") -> 63
A19: Wrong publication type | B19: =COUNTIF(Matrix!$M$5:$M$960,"Wrong publication type") -> 1
A20: Non-English | B20: =COUNTIF(Matrix!$M$5:$M$960,"Non-English") -> 4
A21: Total Stage-1 exclusions | B21: =SUM(B16:B20) -> 712
A23: Stage-2 (full-text) exclusion reasons
A24: Reason | B24: n
A25: Digital Twin mentioned only, not the subject | B25: =COUNTIF(Matrix!$T$5:$T$960,"Digital Twin mentioned only, not the subject") -> 14
A26: No Design for Safety focus in full text | B26: =COUNTIF(Matrix!$T$5:$T$960,"No Design for Safety focus in full text") -> 4
A27: Methodology not codable | B27: =COUNTIF(Matrix!$T$5:$T$960,"Methodology not codable") -> 0
A28: Total Stage-2 exclusions | B28: =SUM(B25:B27) -> 18

Sheet PRISMA_Shapes
E14: 112
E15: 99
E16: 30
E17: 21
A58: LIVE DATA FEED — the text of every shape above is generated from these formula cells
A59: Key | B59: Text used in shape (live formula)
A60: Identified | B60: ="Records identified from databases"&CHAR(10)&"(Scopus · Web of Science)"&CHAR(10)&"n = "&TEXT(Step1_Report!$B$4,"0") -> Records identified from databases (Scopus · Web of Science) n = 956
A61: Screened | B61: ="Records screened at Stage 1"&CHAR(10)&"(title & abstract)"&CHAR(10)&"n = "&TEXT(Step1_Report!$B$5,"0") -> Records screened at Stage 1 (title & abstract) n = 956
A62: Excluded1 | B62: ="Records excluded at Stage 1 n = "&TEXT(Step1_Report!$B$6,"0")&CHAR(10)&"• "&Step1_Report!$A$17&": "&TEXT(Step1_Report!$B$17,"0")&CHAR(10)&"• "&Step1_Report!$A$16&": "&TEXT(Step1_Report!$B$16,"0")&CHAR(10)&"• "&Step1_Report!$A$20&": "&TEXT(Step1_Report!$B$20,"0")&CHAR(10)&"• "&Step1_Report!$A$18&": "&TEXT(Step1_Report!$B$18,"0")&CHAR(10)&"• "&Step1_Report!$A$19&": "&TEXT(Step1_Report!$B$19,"0") -> Records excluded at Stage 1 n = 712 • Digital Twin not core / buzzword: 229 • Wrong domain (non-AECO): 415 • Non-English: 4 • No Design for Safety / PtD focus: 63 • Wrong publication type: 1
A63: Sought | B63: ="Reports sought for retrieval"&CHAR(10)&"n = "&TEXT(Step1_Report!$B$7,"0") -> Reports sought for retrieval n = 244
A64: NotRetrieved | B64: ="Reports not retrieved"&CHAR(10)&"(full-text PDF not on hand)"&CHAR(10)&"n = "&TEXT(Step1_Report!$B$7-Step1_Report!$B$10,"0") -> Reports not retrieved (full-text PDF not on hand) n = 4
A65: Assessed | B65: ="Reports assessed for eligibility"&CHAR(10)&"(Stage 2 — full text)"&CHAR(10)&"n = "&TEXT(Step1_Report!$B$10,"0") -> Reports assessed for eligibility (Stage 2 — full text) n = 240
A66: Excluded2 | B66: ="Reports excluded at Stage 2 n = "&TEXT(Step1_Report!$B$11,"0")&CHAR(10)&"• "&Step1_Report!$A$25&": "&TEXT(Step1_Report!$B$25,"0")&CHAR(10)&"• "&Step1_Report!$A$26&": "&TEXT(Step1_Report!$B$26,"0")&CHAR(10)&"• "&Step1_Report!$A$27&": "&TEXT(Step1_Report!$B$27,"0") -> Reports excluded at Stage 2 n = 18 • Digital Twin mentioned only, not the subject: 14 • No Design for Safety focus in full text: 4 • Methodology not codable: 0
A67: Included | B67: ="STUDIES INCLUDED IN SYNTHESIS"&CHAR(10)&"n = "&TEXT(Step1_Report!$B$12,"0") -> STUDIES INCLUDED IN SYNTHESIS n = 222
A68: PanelHeader | B68: ="Characteristics of the "&TEXT(Step3_Report!$B$2,"0")&" included studies" -> Characteristics of the 222 included studies
A69: PanelTier | B69: ="Digital Twin capability tier (Gap 1)"&CHAR(10)&"• Tier 1 – Digital Model: "&TEXT(Step3_Report!$B$6,"0")&" ("&TEXT(Step3_Report!$C$6,"0.0%")&")"&CHAR(10)&"• Tier 2 – Digital Shadow: "&TEXT(Step3_Report!$B$7,"0")&" ("&TEXT(Step3_Report!$C$7,"0.0%")&")"&CHAR(10)&"• Tier 3 – Digital Twin: "&TEXT(Step3_Report!$B$8,"0")&" ("&TEXT(Step3_Report!$C$8,"0.0%")&")"&CHAR(10)&"• Tier 4 – Cognitive: "&TEXT(Step3_Report!$B$9,"0")&" ("&TEXT(Step3_Report!$C$9,"0.0%")&")"&CHAR(10)&"• Unclear: "&TEXT(Step3_Report!$B$10,"0")&" ("&TEXT(Step3_Report!$C$10,"0.0%")&")" -> Digital Twin capability tier (Gap 1) • Tier 1 – Digital Model: 52 (23.4%) • Tier 2 – Digital Shadow: 137 (61.7%) • Tier 3 – Digital Twin: 29 (13.1%) • Tier 4 – Cognitive: 0 (0.0%) • Unclear: 4 (1.8%)
A70: PanelSelf | B70: =Step3_Report!$A$13&CHAR(10)&"• None: "&TEXT(Step3_Report!$B$15,"0")&" ("&TEXT(Step3_Report!$C$15,"0.0%")&")"&CHAR(10)&"• Mentioned only: "&TEXT(Step3_Report!$B$16,"0")&" ("&TEXT(Step3_Report!$C$16,"0.0%")&")"&CHAR(10)&"• Implemented: "&TEXT(Step3_Report!$B$17,"0")&" ("&TEXT(Step3_Report!$C$17,"0.0%")&")"&CHAR(10)&"• Convergence-characterised: "&TEXT(Step3_Report!$B$18,"0")&" ("&TEXT(Step3_Report!$C$18,"0.0%")&")" -> Self-improvement / convergence (Gap 4 - core gap) • None: 185 (83.3%) • Mentioned only: 6 (2.7%) • Implemented: 31 (14.0%) • Convergence-characterised: 0 (0.0%)
A71: PanelValid | B71: =Step3_Report!$A$35&CHAR(10)&"• "&Step3_Report!$A$37&": "&TEXT(Step3_Report!$B$37,"0")&" ("&TEXT(Step3_Report!$C$37,"0.0%")&")"&CHAR(10)&"• "&Step3_Report!$A$38&": "&TEXT(Step3_Report!$B$38,"0")&" ("&TEXT(Step3_Report!$C$38,"0.0%")&")"&CHAR(10)&"• "&Step3_Report!$A$39&": "&TEXT(Step3_Report!$B$39,"0")&" ("&TEXT(Step3_Report!$C$39,"0.0%")&")"&CHAR(10)&"• "&Step3_Report!$A$40&": "&TEXT(Step3_Report!$B$40,"0")&" ("&TEXT(Step3_Report!$C$40,"0.0%")&")"&CHAR(10)&"• "&Step3_Report!$A$41&": "&TEXT(Step3_Report!$B$41,"0")&" ("&TEXT(Step3_Report!$C$41,"0.0%")&")" -> Validation level (Gap 5) • Conceptual (no test): 16 (7.2%) • Simulation: 44 (19.8%) • Lab / scale-model experiment: 0 (0.0%) • Single case study: 151 (68.0%) • Cross-project (multiple real projects): 11 (5.0%)
A72: PanelPhase | B72: ="Lifecycle phase coverage (Gap 3)"&CHAR(10)&"• Design (any): "&TEXT(Step3_Report!$B$62,"0")&CHAR(10)&"• Construction (any): "&TEXT(Step3_Report!$B$63,"0")&CHAR(10)&"• Operation (any): "&TEXT(Step3_Report!$B$64,"0")&CHAR(10)&"• Single-phase: "&TEXT(Step3_Report!$B$65,"0")&CHAR(10)&"• Multi-phase (cross-phase): "&TEXT(Step3_Report!$B$66,"0") -> Lifecycle phase coverage (Gap 3) • Design (any): 10 • Construction (any): 97 • Operation (any): 122 • Single-phase: 216 • Multi-phase (cross-phase): 6
A73: Title | B73: ="PRISMA 2020 flow diagram — Digital Twins for Design for Safety in AECO" -> PRISMA 2020 flow diagram — Digital Twins for Design for Safety in AECO
A74: Footnote | B74: Shapes version. Rebuilt 2026-10-04 from Step-1 (956 records) and Step-3 DfS-only markdown. "Not retrieved" = Stage-1 includes whose full text is not yet coded. The hand-drawn PRISMA diagram shapes must be refreshed to these numbers.
A75: PanelModality | B75: =Step3_Report!$A$29&CHAR(10)&"• Single (one data type): "&TEXT(Step3_Report!$B$31,"0")&" ("&TEXT(Step3_Report!$C$31,"0.0%")&")"&CHAR(10)&"• Multi (two or more data types): "&TEXT(Step3_Report!$B$32,"0")&" ("&TEXT(Step3_Report!$C$32,"0.0%")&")" -> Data modality (Gap 2) • Single (one data type): 19 (8.6%) • Multi (two or more data types): 203 (91.4%)
A76: PanelFusion | B76: =Step3_Report!$A$88&CHAR(10)&"• Single: "&TEXT(Step3_Report!$B$90,"0")&" ("&TEXT(Step3_Report!$C$90,"0.0%")&")"&CHAR(10)&"• Co-present: "&TEXT(Step3_Report!$B$91,"0")&" ("&TEXT(Step3_Report!$C$91,"0.0%")&")"&CHAR(10)&"• Aligned: "&TEXT(Step3_Report!$B$92,"0")&" ("&TEXT(Step3_Report!$C$92,"0.0%")&")"&CHAR(10)&"• Fused: "&TEXT(Step3_Report!$B$93,"0")&" ("&TEXT(Step3_Report!$C$93,"0.0%")&")"&CHAR(10)&"• Unclear: "&TEXT(Step3_Report!$B$94,"0")&" ("&TEXT(Step3_Report!$C$94,"0.0%")&")" -> Fusion depth (Gap 2b - how deeply are the data types actually integrated?) • Single: 20 (9.0%) • Co-present: 2 (0.9%) • Aligned: 34 (15.3%) • Fused: 152 (68.5%) • Unclear: 14 (6.3%)
A77: FusionHeadline | B77: =Step3_Report!$A$113 -> Even among the 152 Fused studies, 121 (79.6%) implement no self-improvement and 0 characterise convergence - deep data integration does NOT translate into adaptive capability.
A79: CUSTOM SHAPE FEED — matches the hand-styled wording of the diagram shapes (live formulas)
A80: Shape name | B80: Text pushed into shape (live formula)
A81: PR_Screened | B81: ="1st screening by title & abstract"&CHAR(10)&"n = "&TEXT(Step1_Report!$B$5,"0") -> 1st screening by title & abstract n = 956
A82: PR_Sought | B82: ="Reports sought for retrieval"&CHAR(10)&"n = "&TEXT(Step1_Report!$B$7,"0") -> Reports sought for retrieval n = 244
A83: PR_Assessed | B83: ="Reports assessed for eligibility"&CHAR(10)&"n = "&TEXT(Step1_Report!$B$10,"0") -> Reports assessed for eligibility n = 240
A84: PR_Included | B84: ="Studies Included In Synthesis (n = "&TEXT(Step1_Report!$B$12,"0")&")" -> Studies Included In Synthesis (n = 222)
A85: PR_Excluded1 | B85: ="Records excluded in 1st screening (n = "&TEXT(Step1_Report!$B$6,"0")&")"&CHAR(10)&"1. Digital Twin not core / buzzword: a = "&TEXT(Step1_Report!$B$17,"0")&CHAR(10)&"2. Wrong domain (non-AECO): b = "&TEXT(Step1_Report!$B$16,"0")&CHAR(10)&"3. Non-English: c = "&TEXT(Step1_Report!$B$20,"0")&CHAR(10)&"4. No DfS/DfQ: d = "&TEXT(Step1_Report!$B$18,"0") -> Records excluded in 1st screening (n = 712) 1. Digital Twin not core / buzzword: a = 229 2. Wrong domain (non-AECO): b = 415 3. Non-English: c = 4 4. No DfS/DfQ: d = 63
A86: PR_NotRetrieved | B86: ="2nd screening (n = "&TEXT(Step1_Report!$B$7-Step1_Report!$B$10,"0")&")"&CHAR(10)&"1. full-text PDF not retrieved: a = "&TEXT(Step1_Report!$B$9-2,"0")&CHAR(10)&"2. 2nd deduplication: b = 2" -> 2nd screening (n = 4) 1. full-text PDF not retrieved: a = 2 2. 2nd deduplication: b = 2
A87: PR_Excluded2 | B87: ="Reports excluded at 2nd screening (n = "&TEXT(Step1_Report!$B$11,"0")&")"&CHAR(10)&"1. Digital Twin not core / buzzword: a = "&TEXT(Step1_Report!$B$25,"0")&CHAR(10)&"2. No DfS focus: b = "&TEXT(Step1_Report!$B$26,"0") -> Reports excluded at 2nd screening (n = 18) 1. Digital Twin not core / buzzword: a = 14 2. No DfS focus: b = 4
A88: PR_PanelTier | B88: =$B$69 -> Digital Twin capability tier (Gap 1) • Tier 1 – Digital Model: 52 (23.4%) • Tier 2 – Digital Shadow: 137 (61.7%) • Tier 3 – Digital Twin: 29 (13.1%) • Tier 4 – Cognitive: 0 (0.0%) • Unclear: 4 (1.8%)
A89: PR_PanelSelf | B89: =$B$70 -> Self-improvement / convergence (Gap 4 - core gap) • None: 185 (83.3%) • Mentioned only: 6 (2.7%) • Implemented: 31 (14.0%) • Convergence-characterised: 0 (0.0%)
A90: PR_PanelValid | B90: =$B$71 -> Validation level (Gap 5) • Conceptual (no test): 16 (7.2%) • Simulation: 44 (19.8%) • Lab / scale-model experiment: 0 (0.0%) • Single case study: 151 (68.0%) • Cross-project (multiple real projects): 11 (5.0%)
A91: PR_PanelPhase | B91: =$B$72 -> Lifecycle phase coverage (Gap 3) • Design (any): 10 • Construction (any): 97 • Operation (any): 122 • Single-phase: 216 • Multi-phase (cross-phase): 6
A92: PR_PanelModality | B92: =$B$75 -> Data modality (Gap 2) • Single (one data type): 19 (8.6%) • Multi (two or more data types): 203 (91.4%)
A93: PR_PanelFusion | B93: =$B$76 -> Fusion depth (Gap 2b - how deeply are the data types actually integrated?) • Single: 20 (9.0%) • Co-present: 2 (0.9%) • Aligned: 34 (15.3%) • Fused: 152 (68.5%) • Unclear: 14 (6.3%)
A94: PR_FusionHeadline | B94: =$B$77 -> Even among the 152 Fused studies, 121 (79.6%) implement no self-improvement and 0 characterise convergence - deep data integration does NOT translate into adaptive capability.
A95: PR_Title | B95: =$B$73 -> PRISMA 2020 flow diagram — Digital Twins for Design for Safety in AECO

Sheet Step3_Report
A1: STEP 3 - deep-read synthesis tables (auto = findings section)
A2: Total included studies | B2: =COUNTIF(Matrix!$S$5:$S$960,"INCLUDE") -> 222
A4: Digital Twin capability tier (Gap 1)
A5: Tier Level | B5: n | C5: % of incl.
A6: Tier 1 - Digital Model (static, no live data) | B6: =COUNTIFS(Matrix!$S$5:$S$960,"INCLUDE",Matrix!$U$5:$U$960,"Tier 1 - Digital Model (static, no live data)") -> 52 | C6: =IF($B$2=0,"-",B6/$B$2) -> 0.23423423
A7: Tier 2 - Digital Shadow (one-way physical to virtual) | B7: =COUNTIFS(Matrix!$S$5:$S$960,"INCLUDE",Matrix!$U$5:$U$960,"Tier 2 - Digital Shadow (one-way physical to virtual)") -> 137 | C7: =IF($B$2=0,"-",B7/$B$2) -> 0.61711712
A8: Tier 3 - Digital Twin (bidirectional, two-way) | B8: =COUNTIFS(Matrix!$S$5:$S$960,"INCLUDE",Matrix!$U$5:$U$960,"Tier 3 - Digital Twin (bidirectional, two-way)") -> 29 | C8: =IF($B$2=0,"-",B8/$B$2) -> 0.13063063
A9: Tier 4 - Cognitive / Self-improving | B9: =COUNTIFS(Matrix!$S$5:$S$960,"INCLUDE",Matrix!$U$5:$U$960,"Tier 4 - Cognitive / Self-improving") -> 0 | C9: =IF($B$2=0,"-",B9/$B$2) -> 0
A10: Unclear | B10: =COUNTIFS(Matrix!$S$5:$S$960,"INCLUDE",Matrix!$U$5:$U$960,"Unclear") -> 4 | C10: =IF($B$2=0,"-",B10/$B$2) -> 0.018018018
B11: =SUM(B6:B10) -> 222
A13: Self-improvement / convergence (Gap 4 - core gap)
A14: Category | B14: n | C14: % of incl.
A15: None | B15: =COUNTIFS(Matrix!$S$5:$S$960,"INCLUDE",Matrix!$AA$5:$AA$960,"None") -> 185 | C15: =IF($B$2=0,"-",B15/$B$2) -> 0.83333333
A16: Mentioned only | B16: =COUNTIFS(Matrix!$S$5:$S$960,"INCLUDE",Matrix!$AA$5:$AA$960,"Mentioned only") -> 6 | C16: =IF($B$2=0,"-",B16/$B$2) -> 0.027027027
A17: Implemented | B17: =COUNTIFS(Matrix!$S$5:$S$960,"INCLUDE",Matrix!$AA$5:$AA$960,"Implemented") -> 31 | C17: =IF($B$2=0,"-",B17/$B$2) -> 0.13963964
A18: Convergence-characterised | B18: =COUNTIFS(Matrix!$S$5:$S$960,"INCLUDE",Matrix!$AA$5:$AA$960,"Convergence-characterised") -> 0 | C18: =IF($B$2=0,"-",B18/$B$2) -> 0
B19: =SUM(B15:B18) -> 222 | C19: =IF(B19=$B$2,"OK","MISMATCH") -> OK
A21: Design-for-X target (scope = Design for Safety)
A22: Category | B22: n | C22: % of incl.
A23: Design for Safety (DfS) | B23: =COUNTIFS(Matrix!$S$5:$S$960,"INCLUDE",Matrix!$Z$5:$Z$960,"Design for Safety (DfS)") -> 222 | C23: =IF($B$2=0,"-",B23/$B$2) -> 1
A24: Other | B24: =COUNTIFS(Matrix!$S$5:$S$960,"INCLUDE",Matrix!$Z$5:$Z$960,"Other") -> 0 | C24: =IF($B$2=0,"-",B24/$B$2) -> 0
B27: =SUM(B23:B26) -> 222 | C27: =IF(B27=$B$2,"OK","MISMATCH") -> OK
A29: Data modality (Gap 2)
A30: Category | B30: n | C30: % of incl.
A31: Single (one data type) | B31: =COUNTIFS(Matrix!$S$5:$S$960,"INCLUDE",Matrix!$AC$5:$AC$960,"Single (one data type)") -> 19 | C31: =IF($B$2=0,"-",B31/$B$2) -> 0.085585586
A32: Multi (two or more data types) | B32: =COUNTIFS(Matrix!$S$5:$S$960,"INCLUDE",Matrix!$AC$5:$AC$960,"Multi (two or more data types)") -> 203 | C32: =IF($B$2=0,"-",B32/$B$2) -> 0.91441441
B33: =SUM(B31:B32) -> 222 | C33: =IF(B33=$B$2,"OK","MISMATCH") -> OK
A35: Validation level (Gap 5)
A36: Category | B36: n | C36: % of incl.
A37: ='1_CodeLists'!$I$2 -> Conceptual (no test) | B37: =COUNTIFS(Matrix!$S$5:$S$960,"INCLUDE",Matrix!$AD$5:$AD$960,$A37) -> 16 | C37: =IF($B$2=0,"-",B37/$B$2) -> 0.072072072
A38: ='1_CodeLists'!$I$3 -> Simulation | B38: =COUNTIFS(Matrix!$S$5:$S$960,"INCLUDE",Matrix!$AD$5:$AD$960,$A38) -> 44 | C38: =IF($B$2=0,"-",B38/$B$2) -> 0.1981982
A39: ='1_CodeLists'!$I$4 -> Lab / scale-model experiment | B39: =COUNTIFS(Matrix!$S$5:$S$960,"INCLUDE",Matrix!$AD$5:$AD$960,$A39) -> 0 | C39: =IF($B$2=0,"-",B39/$B$2) -> 0
A40: ='1_CodeLists'!$I$5 -> Single case study | B40: =COUNTIFS(Matrix!$S$5:$S$960,"INCLUDE",Matrix!$AD$5:$AD$960,$A40) -> 151 | C40: =IF($B$2=0,"-",B40/$B$2) -> 0.68018018
A41: ='1_CodeLists'!$I$6 -> Cross-project (multiple real projects) | B41: =COUNTIFS(Matrix!$S$5:$S$960,"INCLUDE",Matrix!$AD$5:$AD$960,$A41) -> 11 | C41: =IF($B$2=0,"-",B41/$B$2) -> 0.04954955
A42: Total (must equal included) | B42: =SUM(B37:B41) -> 222 | C42: =IF(B42=$B$2,"OK","MISMATCH") -> OK
A44: Methodology (RQ2)
A45: Category | B45: n | C45: % of incl.
A46: Computer Vision / CNN / object-detection | B46: =COUNTIFS(Matrix!$S$5:$S$960,"INCLUDE",Matrix!$AB$5:$AB$960,"Computer Vision / CNN / object-detection") -> 25 | C46: =IF($B$2=0,"-",B46/$B$2) -> 0.11261261
A47: Graph Neural Network (GNN) | B47: =COUNTIFS(Matrix!$S$5:$S$960,"INCLUDE",Matrix!$AB$5:$AB$960,"Graph Neural Network (GNN)") -> 5 | C47: =IF($B$2=0,"-",B47/$B$2) -> 0.022522523
A48: LSTM / RNN (recurrent networks) | B48: =COUNTIFS(Matrix!$S$5:$S$960,"INCLUDE",Matrix!$AB$5:$AB$960,"LSTM / RNN (recurrent networks)") -> 5 | C48: =IF($B$2=0,"-",B48/$B$2) -> 0.022522523
A49: Transformer / Large Language Model (LLM) | B49: =COUNTIFS(Matrix!$S$5:$S$960,"INCLUDE",Matrix!$AB$5:$AB$960,"Transformer / Large Language Model (LLM)") -> 14 | C49: =IF($B$2=0,"-",B49/$B$2) -> 0.063063063
A50: Reinforcement Learning (RL) | B50: =COUNTIFS(Matrix!$S$5:$S$960,"INCLUDE",Matrix!$AB$5:$AB$960,"Reinforcement Learning (RL)") -> 3 | C50: =IF($B$2=0,"-",B50/$B$2) -> 0.013513514
A51: Bayesian / probabilistic | B51: =COUNTIFS(Matrix!$S$5:$S$960,"INCLUDE",Matrix!$AB$5:$AB$960,"Bayesian / probabilistic") -> 12 | C51: =IF($B$2=0,"-",B51/$B$2) -> 0.054054054
A52: Agent-based model (ABM) | B52: =COUNTIFS(Matrix!$S$5:$S$960,"INCLUDE",Matrix!$AB$5:$AB$960,"Agent-based model (ABM)") -> 6 | C52: =IF($B$2=0,"-",B52/$B$2) -> 0.027027027
A53: Finite Element Method / physics-based | B53: =COUNTIFS(Matrix!$S$5:$S$960,"INCLUDE",Matrix!$AB$5:$AB$960,"Finite Element Method / physics-based") -> 31 | C53: =IF($B$2=0,"-",B53/$B$2) -> 0.13963964
A54: Ontology / semantic | B54: =COUNTIFS(Matrix!$S$5:$S$960,"INCLUDE",Matrix!$AB$5:$AB$960,"Ontology / semantic") -> 11 | C54: =IF($B$2=0,"-",B54/$B$2) -> 0.04954955
A55: Statistical / change-point | B55: =COUNTIFS(Matrix!$S$5:$S$960,"INCLUDE",Matrix!$AB$5:$AB$960,"Statistical / change-point") -> 7 | C55: =IF($B$2=0,"-",B55/$B$2) -> 0.031531532
A56: Digital Twin platform (no machine learning) | B56: =COUNTIFS(Matrix!$S$5:$S$960,"INCLUDE",Matrix!$AB$5:$AB$960,"Digital Twin platform (no machine learning)") -> 41 | C56: =IF($B$2=0,"-",B56/$B$2) -> 0.18468468
A57: Other / Mixed | B57: =COUNTIFS(Matrix!$S$5:$S$960,"INCLUDE",Matrix!$AB$5:$AB$960,"Other / Mixed") -> 62 | C57: =IF($B$2=0,"-",B57/$B$2) -> 0.27927928
B58: =SUM(B46:B57) -> 222 | C58: =IF(B58=$B$2,"OK","MISMATCH") -> OK
A60: Lifecycle phase coverage (Gap 3)
A61: Coverage | B61: n
A62: Design (any) | B62: =COUNTIFS(Matrix!$S$5:$S$960,"INCLUDE",Matrix!$V$5:$V$960,1) -> 10
A63: Construction (any) | B63: =COUNTIFS(Matrix!$S$5:$S$960,"INCLUDE",Matrix!$W$5:$W$960,1) -> 97
A64: Operation (any) | B64: =COUNTIFS(Matrix!$S$5:$S$960,"INCLUDE",Matrix!$X$5:$X$960,1) -> 122 | C64: =SUM(B62:B64) -> 229
A65: Single-phase | B65: =COUNTIFS(Matrix!$S$5:$S$960,"INCLUDE",Matrix!$Y$5:$Y$960,"Single") -> 216
A66: Multi-phase (cross-phase) | B66: =COUNTIFS(Matrix!$S$5:$S$960,"INCLUDE",Matrix!$Y$5:$Y$960,"Multi") -> 6 | C66: =SUM(B65:B66) -> 222 | D66: =IF(C66=$B$2,"OK","MISMATCH") -> OK
A69: Gap 2 x Gap 4 cross-tab - is multimodal data converted into adaptive capability?
A70: Data modality \ Self-improvement | B70: =$A$15 -> None | C70: =$A$16 -> Mentioned only | D70: =$A$17 -> Implemented | E70: =$A$18 -> Convergence-characterised | F70: Total
A71: =$A$31 -> Single (one data type) | B71: =COUNTIFS(Matrix!$S$5:$S$960,"INCLUDE",Matrix!$AC$5:$AC$960,$A71,Matrix!$AA$5:$AA$960,B$70) -> 17 | C71: =COUNTIFS(Matrix!$S$5:$S$960,"INCLUDE",Matrix!$AC$5:$AC$960,$A71,Matrix!$AA$5:$AA$960,C$70) -> 0 | D71: =COUNTIFS(Matrix!$S$5:$S$960,"INCLUDE",Matrix!$AC$5:$AC$960,$A71,Matrix!$AA$5:$AA$960,D$70) -> 2 | E71: =COUNTIFS(Matrix!$S$5:$S$960,"INCLUDE",Matrix!$AC$5:$AC$960,$A71,Matrix!$AA$5:$AA$960,E$70) -> 0 | F71: =SUM(B71:E71) -> 19
A72: =$A$32 -> Multi (two or more data types) | B72: =COUNTIFS(Matrix!$S$5:$S$960,"INCLUDE",Matrix!$AC$5:$AC$960,$A72,Matrix!$AA$5:$AA$960,B$70) -> 168 | C72: =COUNTIFS(Matrix!$S$5:$S$960,"INCLUDE",Matrix!$AC$5:$AC$960,$A72,Matrix!$AA$5:$AA$960,C$70) -> 6 | D72: =COUNTIFS(Matrix!$S$5:$S$960,"INCLUDE",Matrix!$AC$5:$AC$960,$A72,Matrix!$AA$5:$AA$960,D$70) -> 29 | E72: =COUNTIFS(Matrix!$S$5:$S$960,"INCLUDE",Matrix!$AC$5:$AC$960,$A72,Matrix!$AA$5:$AA$960,E$70) -> 0 | F72: =SUM(B72:E72) -> 203
A73: Total | B73: =SUM(B71:B72) -> 185 | C73: =SUM(C71:C72) -> 6 | D73: =SUM(D71:D72) -> 31 | E73: =SUM(E71:E72) -> 0 | F73: =SUM(F71:F72) -> 222 | G73: =IF(F73=$B$2,"OK","MISMATCH") -> OK
A75: Same cross-tab as % of each modality row (does data richness become adaptive capability?)
A76: Data modality \ Self-improvement | B76: =B$70 -> None | C76: =C$70 -> Mentioned only | D76: =D$70 -> Implemented | E76: =E$70 -> Convergence-characterised | F76: Total
A77: =$A$71 -> Single (one data type) | B77: =IF($F71=0,"-",B71/$F71) -> 0.89473684 | C77: =IF($F71=0,"-",C71/$F71) -> 0 | D77: =IF($F71=0,"-",D71/$F71) -> 0.10526316 | E77: =IF($F71=0,"-",E71/$F71) -> 0 | F77: =IF($F71=0,"-",F71/$F71) -> 1
A78: =$A$72 -> Multi (two or more data types) | B78: =IF($F72=0,"-",B72/$F72) -> 0.82758621 | C78: =IF($F72=0,"-",C72/$F72) -> 0.02955665 | D78: =IF($F72=0,"-",D72/$F72) -> 0.14285714 | E78: =IF($F72=0,"-",E72/$F72) -> 0 | F78: =IF($F72=0,"-",F72/$F72) -> 1
A80: Cross-tab integrity check (grand total must equal total included studies)
A81: Cross-tab grand total | B81: =$F$73 -> 222
A82: Total included studies | B82: =$B$2 -> 222
A83: Reconciles? | B83: =IF($F$73=$B$2,"OK - "&TEXT($F$73,"0")&" studies fully cross-classified","MISMATCH: "&TEXT($F$73-$B$2,"+0;-0")&" - check for blank codes in Matrix AA/AC") -> OK - 222 studies fully cross-classified
A85: Headline (auto)
A86: ="Of the "&TEXT($F$72,"0")&" multimodal studies, "&TEXT($B$72,"0")&" ("&TEXT($B$72/$F$72,"0.0%")&") implement no self-improvement at all; only "&TEXT($D$72,"0")&" ("&TEXT($D$72/$F$72,"0.0%")&") implement it and "&TEXT($E$72,"0")&" characterise convergence." -> Of the 203 multimodal studies, 168 (82.8%) implement no self-improvement at all; only 29 (14.3%) implement it and 0 characterise convergence.
A88: Fusion depth (Gap 2b - how deeply are the data types actually integrated?) | E88: Fusion coding confidence
A89: Category | B89: n | C89: % of incl. | E89: Confidence | F89: n
A90: ='1_CodeLists'!$K$2 -> Single | B90: =COUNTIFS(Matrix!$S$5:$S$960,"INCLUDE",Matrix!$AJ$5:$AJ$960,$A90) -> 20 | C90: =IF($B$2=0,"-",B90/$B$2) -> 0.09009009 | E90: ='1_CodeLists'!$L$2 -> High | F90: =COUNTIFS(Matrix!$S$5:$S$960,"INCLUDE",Matrix!$AL$5:$AL$960,$E90) -> 124
A91: ='1_CodeLists'!$K$3 -> Co-present | B91: =COUNTIFS(Matrix!$S$5:$S$960,"INCLUDE",Matrix!$AJ$5:$AJ$960,$A91) -> 2 | C91: =IF($B$2=0,"-",B91/$B$2) -> 0.009009009 | E91: ='1_CodeLists'!$L$3 -> Medium | F91: =COUNTIFS(Matrix!$S$5:$S$960,"INCLUDE",Matrix!$AL$5:$AL$960,$E91) -> 90
A92: ='1_CodeLists'!$K$4 -> Aligned | B92: =COUNTIFS(Matrix!$S$5:$S$960,"INCLUDE",Matrix!$AJ$5:$AJ$960,$A92) -> 34 | C92: =IF($B$2=0,"-",B92/$B$2) -> 0.15315315 | E92: ='1_CodeLists'!$L$4 -> Low | F92: =COUNTIFS(Matrix!$S$5:$S$960,"INCLUDE",Matrix!$AL$5:$AL$960,$E92) -> 8
A93: ='1_CodeLists'!$K$5 -> Fused | B93: =COUNTIFS(Matrix!$S$5:$S$960,"INCLUDE",Matrix!$AJ$5:$AJ$960,$A93) -> 152 | C93: =IF($B$2=0,"-",B93/$B$2) -> 0.68468468 | E93: Rows flagged for review | F93: =COUNTIFS(Matrix!$S$5:$S$960,"INCLUDE",Matrix!$AM$5:$AM$960,"<>") -> 23
A94: ='1_CodeLists'!$K$6 -> Unclear | B94: =COUNTIFS(Matrix!$S$5:$S$960,"INCLUDE",Matrix!$AJ$5:$AJ$960,$A94) -> 14 | C94: =IF($B$2=0,"-",B94/$B$2) -> 0.063063063
A95: Total | B95: =SUM(B90:B94) -> 222 | C95: =IF($B$2=0,"-",B95/$B$2) -> 1
A97: Fusion depth x Gap 4 cross-tab - does deeper integration produce adaptive capability?
A98: Fusion depth \ Self-improvement | B98: =$A$15 -> None | C98: =$A$16 -> Mentioned only | D98: =$A$17 -> Implemented | E98: =$A$18 -> Convergence-characterised | F98: Total
A99: =$A$90 -> Single | B99: =COUNTIFS(Matrix!$S$5:$S$960,"INCLUDE",Matrix!$AJ$5:$AJ$960,$A99,Matrix!$AA$5:$AA$960,B$98) -> 18 | C99: =COUNTIFS(Matrix!$S$5:$S$960,"INCLUDE",Matrix!$AJ$5:$AJ$960,$A99,Matrix!$AA$5:$AA$960,C$98) -> 0 | D99: =COUNTIFS(Matrix!$S$5:$S$960,"INCLUDE",Matrix!$AJ$5:$AJ$960,$A99,Matrix!$AA$5:$AA$960,D$98) -> 2 | E99: =COUNTIFS(Matrix!$S$5:$S$960,"INCLUDE",Matrix!$AJ$5:$AJ$960,$A99,Matrix!$AA$5:$AA$960,E$98) -> 0 | F99: =SUM(B99:E99) -> 20
A100: =$A$91 -> Co-present | B100: =COUNTIFS(Matrix!$S$5:$S$960,"INCLUDE",Matrix!$AJ$5:$AJ$960,$A100,Matrix!$AA$5:$AA$960,B$98) -> 2 | C100: =COUNTIFS(Matrix!$S$5:$S$960,"INCLUDE",Matrix!$AJ$5:$AJ$960,$A100,Matrix!$AA$5:$AA$960,C$98) -> 0 | D100: =COUNTIFS(Matrix!$S$5:$S$960,"INCLUDE",Matrix!$AJ$5:$AJ$960,$A100,Matrix!$AA$5:$AA$960,D$98) -> 0 | E100: =COUNTIFS(Matrix!$S$5:$S$960,"INCLUDE",Matrix!$AJ$5:$AJ$960,$A100,Matrix!$AA$5:$AA$960,E$98) -> 0 | F100: =SUM(B100:E100) -> 2
A101: =$A$92 -> Aligned | B101: =COUNTIFS(Matrix!$S$5:$S$960,"INCLUDE",Matrix!$AJ$5:$AJ$960,$A101,Matrix!$AA$5:$AA$960,B$98) -> 32 | C101: =COUNTIFS(Matrix!$S$5:$S$960,"INCLUDE",Matrix!$AJ$5:$AJ$960,$A101,Matrix!$AA$5:$AA$960,C$98) -> 1 | D101: =COUNTIFS(Matrix!$S$5:$S$960,"INCLUDE",Matrix!$AJ$5:$AJ$960,$A101,Matrix!$AA$5:$AA$960,D$98) -> 1 | E101: =COUNTIFS(Matrix!$S$5:$S$960,"INCLUDE",Matrix!$AJ$5:$AJ$960,$A101,Matrix!$AA$5:$AA$960,E$98) -> 0 | F101: =SUM(B101:E101) -> 34
A102: =$A$93 -> Fused | B102: =COUNTIFS(Matrix!$S$5:$S$960,"INCLUDE",Matrix!$AJ$5:$AJ$960,$A102,Matrix!$AA$5:$AA$960,B$98) -> 121 | C102: =COUNTIFS(Matrix!$S$5:$S$960,"INCLUDE",Matrix!$AJ$5:$AJ$960,$A102,Matrix!$AA$5:$AA$960,C$98) -> 3 | D102: =COUNTIFS(Matrix!$S$5:$S$960,"INCLUDE",Matrix!$AJ$5:$AJ$960,$A102,Matrix!$AA$5:$AA$960,D$98) -> 28 | E102: =COUNTIFS(Matrix!$S$5:$S$960,"INCLUDE",Matrix!$AJ$5:$AJ$960,$A102,Matrix!$AA$5:$AA$960,E$98) -> 0 | F102: =SUM(B102:E102) -> 152
A103: =$A$94 -> Unclear | B103: =COUNTIFS(Matrix!$S$5:$S$960,"INCLUDE",Matrix!$AJ$5:$AJ$960,$A103,Matrix!$AA$5:$AA$960,B$98) -> 12 | C103: =COUNTIFS(Matrix!$S$5:$S$960,"INCLUDE",Matrix!$AJ$5:$AJ$960,$A103,Matrix!$AA$5:$AA$960,C$98) -> 2 | D103: =COUNTIFS(Matrix!$S$5:$S$960,"INCLUDE",Matrix!$AJ$5:$AJ$960,$A103,Matrix!$AA$5:$AA$960,D$98) -> 0 | E103: =COUNTIFS(Matrix!$S$5:$S$960,"INCLUDE",Matrix!$AJ$5:$AJ$960,$A103,Matrix!$AA$5:$AA$960,E$98) -> 0 | F103: =SUM(B103:E103) -> 14
A104: Total | B104: =SUM(B99:B103) -> 185 | C104: =SUM(C99:C103) -> 6 | D104: =SUM(D99:D103) -> 31 | E104: =SUM(E99:E103) -> 0 | F104: =SUM(F99:F103) -> 222
A106: Fusion coding integrity check
A107: Fusion cross-tab grand total | B107: =$F$104 -> 222
A108: Total included studies | B108: =$B$2 -> 222
A109: Reconciles? | B109: =IF($F$104=$B$2,"OK - "&TEXT($F$104,"0")&" studies fully fusion-coded","MISMATCH: "&TEXT($F$104-$B$2,"+0;-0")&" - check blanks in Matrix AJ") -> OK - 222 studies fully fusion-coded
A111: Headline (auto)
A112: ="Of the "&TEXT($B$32,"0")&" multimodal studies only "&TEXT($B$94+$B$93,"0")&" reach Fused or Aligned with genuine joint inference; "&TEXT($B$91,"0")&" remain merely Co-present and "&TEXT($B$94,"0")&" are Unclear. Deepest integration (Fused) = "&TEXT($B$93,"0")&" ("&TEXT($C$93,"0.0%")&" of all included)." -> Of the 203 multimodal studies only 166 reach Fused or Aligned with genuine joint inference; 2 remain merely Co-present and 14 are Unclear. Deepest integration (Fused) = 152 (68.5% of all included).
A113: ="Even among the "&TEXT($F$102,"0")&" Fused studies, "&TEXT($B$102,"0")&" ("&TEXT($B$102/$F$102,"0.0%")&") implement no self-improvement and "&TEXT($E$102,"0")&" characterise convergence - deep data integration does NOT translate into adaptive capability." -> Even among the 152 Fused studies, 121 (79.6%) implement no self-improvement and 0 characterise convergence - deep data integration does NOT translate into adaptive capability.

Sheet 2_DOI_Lookup
A1: ID | B1: DOI | C1: Source | D1: ID (title key) | E1: Full title (from SLR markdown, 2026-08-30)
A2: 1 | B2: 10.1108/SASBE-11-2023-0349 | C2: SLR summary matrix step 1.md (956-record merged corpus) | D2: 1 | E2: A scoping review of green Internet of Things in construction and smart cities: current applications, adoption strategies and future directions
A3: 2 | B3: 10.1016/j.eswa.2025.129330 | C3: SLR summary matrix step 1.md (956-record merged corpus) | D3: 2 | E3: Digital Twin development and implementation for the management of irrigation networks
A4: 3 | B4: 10.3390/s25196153 | C4: SLR summary matrix step 1.md (956-record merged corpus) | D4: 3 | E4: Research on Multi-Sensor Data Fusion Based Real-Scene 3D Reconstruction and Digital Twin Visualization Methodology for Coal Mine Tunnels
A5: 4 | B5: 10.1016/j.scs.2026.107413 | C5: SLR summary matrix step 1.md (956-record merged corpus) | D5: 4 | E5: Hazard-responsive digital twin for weather-driven urban resilience and affordability
A6: 5 | B6: 10.1186/s12967-026-07895-8 | C6: SLR summary matrix step 1.md (956-record merged corpus) | D6: 5 | E6: From prediction to intervention: causal digital twins for personalized clinical decision support
A7: 6 | B7: 10.1108/EC-09-2024-0900 | C7: SLR summary matrix step 1.md (956-record merged corpus) | D7: 6 | E7: Residual dynamic spatio-temporal graph attention network for enhanced urban traffic origin/destination demand calibration
A8: 7 | B8: 10.1016/j.tre.2025.104596 | C8: SLR summary matrix step 1.md (956-record merged corpus) | D8: 7 | E8: Digital twin-enabled cooperative autonomous truck platooning framework for modeling, cost estimation, and decision-making in transportation systems
A9: 8 | B9: 10.1016/j.autcon.2025.106353 | C9: SLR summary matrix step 1.md (956-record merged corpus) | D9: 8 | E9: Digital construction site layout planning and real-time trajectory analysis for proactive safety monitoring and control of struck-by hazards
A10: 9 | B10: 10.56318/as/1.2025.92 | C10: SLR summary matrix step 1.md (956-record merged corpus) | D10: 9 | E10: Optimising the construction process through digitalisation: Case studies of projects under unstable resource supply
A11: 10 | B11: 10.1016/j.autcon.2026.106980 | C11: SLR summary matrix step 1.md (956-record merged corpus) | D11: 10 | E11: From instance segmentation to physical quantification: High-resolution UAV-based dataset for façade defect assessment
A12: 11 | B12: 10.1038/s41598-025-94117-8 | C12: SLR summary matrix step 1.md (956-record merged corpus) | D12: 11 | E12: Digital twin-driven strategic demolition plan for circular asset management of bridge infrastructures
A13: 12 | B13: 10.3389/fbuil.2026.1748837 | C13: SLR summary matrix step 1.md (956-record merged corpus) | D13: 12 | E13: Enhancing resilience through environmental data integration in early construction planning: a cloud-based framework
... A957: 956 | B957: 10.1016/j.rineng.2026.111826 | C957: SLR summary matrix step 1.md (956-record merged corpus) | D957: 956 | E957: Hydrogen-powered electric vehicles: A state-of-the-art review

Sheet 3_Change_Log
A1: ID | B1: Title | C1: Change type | D1: Field | E1: Previous (v260930) | F1: New (DfS-only Step 3)
A2: 14 | B2: Reducing Latency in Digital Twins: A Framework for Near-Real-Time Progress and Quality Reporting | C2: Coding changed | D2: DfX target | E2: Both | F2: Design for Safety (DfS)
A3: 26 | B3: Construction Path of Shanghai Oriental Hub Municipal Pipeline Full Cycle Digital Twin Platform | C3: Coding changed | D3: DfX target | E3: Both | F3: Design for Safety (DfS)
A4: 31 | B4: Enhancing sensor data reliability in structural health monitoring systems using digital twin technology | C4: Newly coded (full text now available) | D4: Stage-2 decision | E4: (not coded) | F4: INCLUDE
A5: 72 | B5: Physics-based and data-driven long-term evolution of a landslide: From inversion to prediction | C5: Newly coded (full text now available) | D5: Stage-2 decision | E5: (not coded) | F5: INCLUDE
A6: 78 | B6: A visualization system for dam safety monitoring with application of digital twin platform | C6: Newly coded (full text now available) | D6: Stage-2 decision | E6: (not coded) | F6: INCLUDE
A7: 106 | B7: Automatic management of shield attitude: insights from sensor data analysis and hybrid machine learning | C7: Newly coded (full text now available) | D7: Stage-2 decision | E7: (not coded) | F7: INCLUDE
A8: 121 | B8: Digital twin-driven intelligent structural fault diagnosis and decision-making for earth-rock dams using large language models | C8: Newly coded (full text now available) | D8: Stage-2 decision | E8: (not coded) | F8: INCLUDE
A9: 128 | B9: Digital heritage preservation through drone surveying: Vulnerability analysis of Venetian church façades | C9: Newly coded (full text now available) | D9: Stage-2 decision | E9: (not coded) | F9: INCLUDE
A10: 133 | B10: Physics-guided multi-fidelity framework for probabilistic deformation prediction of concrete arch dams under digital twin-based monitoring | C10: Newly coded (full text now available) | D10: Stage-2 decision | E10: (not coded) | F10: INCLUDE
A11: 147 | B11: A methodology for sky-space-ground integrated remote sensing monitoring: A digital twin framework for multi-source Data-BIM integration in residential quality monitoring | C11: Stage-2 decision changed | D11: Stage-2 decision | E11: INCLUDE | F11: EXCLUDE
A12: 186 | B12: Historical Prediction Attention Mechanism-Based Trajectory Forecasting for Proactive Work Zone Safety in a Digital Twin Environment | C12: Newly coded (full text now available) | D12: Stage-2 decision | E12: (not coded) | F12: INCLUDE
A13: 212 | B13: Dynamic prediction and control of a tunnel boring machine with a particle swarm optimization–random forest algorithm and an integrated digital twin | C13: Newly coded (full text now available) | D13: Stage-2 decision | E13: (not coded) | F13: INCLUDE
... A44: 938 | B44: A Digital Twin With Material Characterisation and LLM as High-Level Orchestrator via Few-Shot In-Context Learning for Closed-Loop Control in Robotic Adaptive 3DCP | C44: Coding changed | D44: DfX target | E44: Both | F44: Design for Safety (DfS)
