Workbook

Sheet 0_Guide
B2: One Matrix - Four Steps (LLM-ready, no background assumed)
B3: A single progressive-disclosure matrix for screening, coding, deep-read analysis and reporting.
B5: CONTEXT PRIMER (read this before coding any paper)
B6: What is this review about | C6: This is a systematic literature review about DIGITAL TWINS used in the built-environment industry, specifically to improve SAFETY and QUALITY of designs. You are screening and coding academic papers.
B7: AECO | C7: AECO = Architecture, Engineering, Construction and Operations. It means the built-environment / construction industry (buildings, bridges, infrastructure, civil engineering). NOT manufacturing, automotive, aerospace, power/electrical equipment, healthcare, or agriculture.
B8: Digital Twin (DT) | C8: A Digital Twin is a live virtual replica of a physical asset that is connected to it by data. It is MORE than a static 3D/BIM model. If a paper only says the words 'digital twin' in passing but does not actually build or study one, treat DT as a buzzword (answer 'No').
B9: Design for Safety (DfS) | C9: Design for Safety = designing to prevent construction/operation safety incidents (e.g. fall from height, hazards, accident prevention).
B10: Design for Quality (DfQ) | C10: Design for Quality = designing to prevent defects, rework, or quality failures.
B11: Prevention through Design (PtD) | C11: Prevention through Design = the principle of eliminating risks at the design stage before construction begins. Closely related to DfS/DfQ.
B12: BIM | C12: BIM = Building Information Modelling. A static, design-stage digital model. A BIM model alone is NOT a Digital Twin (no live data link).
B13: bidirectional | C13: 'bidirectional' means data flows BOTH ways: physical->virtual AND virtual->physical (the twin can act back on the real asset). One-way data flow is only a 'digital shadow'.
B14: Answer format | C14: Every Stage-1 and Stage-2 question is answered strictly as 'Yes' or 'No'. If genuinely unsure from the abstract, answer 'No' (conservative) and add a note. Do not invent information not present in the text.
B15: One reason only | C15: When a paper is excluded, the matrix auto-picks ONE standardized reason by priority. You do not write the reason yourself.
B17: THE FOUR STEPS
B18: Step 1 (all 450 papers) | C18: An LLM or reviewer fills the AMBER Stage-1 columns (G-K) for EVERY paper, from the TITLE and ABSTRACT only. Column L auto-decides Include/Exclude; column M auto-writes the single exclusion reason.
B19: Step 2 (the matrix) | C19: This workbook IS the summary matrix. There is nothing separate to generate.
B20: Retrieval + PDF gateway | C20: For Stage-1 includes, first mark column N 'PDF full text on hand?'. This is the gateway: only papers with the PDF on hand can be deep-read. You can revisit later - when a PDF is found, change N from 'No' to 'Yes' and the paper becomes ready for Stage-2/3.
B21: Step 3 (deep read) | C21: For papers whose PDF is on hand, fill the RED Stage-2 columns (P-R) and then the GREEN synthesis 'angle' columns (U-AG). These are the evidence for your findings section.
B22: Step 4 (report) | C22: Open 'Step1_Report' (screening + PRISMA chain + exclusion reasons) and 'Step3_Report' (capability-tier / phase / method / modality / validation / self-improvement tables). Both auto-tally from the same rows.
B24: COLOUR KEY
B25: Bands | C25: AMBER = Stage-1 input (from abstract) · BLUE = PDF gateway · RED = Stage-2 input (from full text) · GREEN = Stage-3 deep-read input · BLUE-GREY = auto formula, do not edit.
B26: Golden rule | C26: Never delete a paper. A paper excluded at any stage stays in the matrix with its reason recorded. This is what makes the PRISMA flow reproducible.

Sheet 1_CodeLists
A1: YN | B1: Src | C1: Bin | D1: Tier | E1: DfX | F1: Self | G1: Method | H1: Modality | I1: Valid | J1: Cluster | K1: Fusion | L1: Conf
A2: Yes | B2: Scopus | C2: 0 | D2: Tier 1 - Digital Model (static, no live data) | E2: Design for Safety (DfS) | F2: None | G2: Computer Vision / CNN / object-detection | H2: Single (one data type) | I2: Conceptual (no test) | J2: BIM-to-Digital-Twin architecture | K2: Single | L2: High
A3: No | B3: Web of Science | C3: 1 | D3: Tier 2 - Digital Shadow (one-way physical to virtual) | E3: Design for Quality (DfQ) | F3: Mentioned only | G3: Graph Neural Network (GNN) | H3: Multi (two or more data types) | I3: Simulation | J3: Semantic interoperability | K3: Co-present | L3: Medium
B4: Lens.org | D4: Tier 3 - Digital Twin (bidirectional, two-way) | E4: Both | F4: Implemented | G4: LSTM / RNN (recurrent networks) | I4: Lab / scale-model experiment | J4: Perception / Computer Vision | K4: Aligned | L4: Low
B5: Backward-snowball | D5: Tier 4 - Cognitive / Self-improving | E5: Other | F5: Convergence-characterised | G5: Transformer / Large Language Model (LLM) | I5: Single case study | J5: Design for Safety | K5: Fused
B6: Forward-snowball | D6: Unclear | G6: Reinforcement Learning (RL) | I6: Cross-project (multiple real projects) | J6: Predictive analytics / decision support | K6: Unclear
G7: Bayesian / probabilistic | J7: Lifecycle / governance
G8: Agent-based model (ABM) | J8: Other
G9: Finite Element Method / physics-based
G10: Ontology / semantic
G11: Statistical / change-point
G12: Digital Twin platform (no machine learning)
G13: Other / Mixed

Sheet Matrix
P1: a | Q1: b | R1: c | T1: d - 2nd duplicate
G2: a | H2: b | I2: c | K2: e | L2: =COUNTIF(L4:L501,"Exclude") -> 262 | N2: =COUNTIF(N4:N469,"No") -> 2 | O2: =COUNTIF(O4:O469,"No") -> 2 | P2: =COUNTIF(P4:P469,"No") -> 10 | Q2: =COUNTIF(Q4:Q469,"No") -> 3 | R2: =COUNTIF(R4:R469,"No") -> 6 | S2: =COUNTIF(S4:S469,"Exclude") -> 13 | T2: 2
A3: =COUNTA(A5:A502) -> 429 | G3: =COUNTIF(G4:G469,"No") -> 99 | H3: =COUNTIF(H4:H469,"No") -> 133 | I3: =COUNTIF(I4:I469,"No") -> 101 | J3: =COUNTIF(J4:J469,"No") -> 0 | K3: =COUNTIF(K4:K469,"No") -> 59 | L3: =COUNTIF(L4:L469,"Include") -> 167 | N3: =COUNTIF(N4:N469,"Yes") -> 165 | O3: =COUNTIF(O4:O469,"Yes") -> 165 | P3: =COUNTIF(P4:P469,"Yes") -> 153 | Q3: =COUNTIF(Q4:Q469,"Yes") -> 160 | R3: =COUNTIF(R4:R469,"Yes") -> 157 | S3: =COUNTIF(S4:S469,"Include")-T2 -> 150
A4: ID | B4: Authors (year) | C4: Year | D4: Journal | E4: Title | F4: Source database | G4: Stage1: Domain is AECO (built environment)? | H4: Stage1: Digital Twin is core (not just a buzzword)? | I4: Stage1: About Design for Safety / Quality / Prevention through Design? | J4: Stage1: Publication type OK (journal/conference article, not editorial/erratum)? | K4: Stage1: Written in English (full text)? | L4: STAGE-1 decision | M4: Stage-1 exclusion reason (auto) | N4: GATEWAY: PDF full text on hand? (change to Yes when found) | O4: Full text retrieved for PRISMA? | P4: Stage2: Digital Twin is the actual subject (full text)? | Q4: Stage2: Design for Safety/Quality confirmed in full text? | R4: Stage2: Methodology is clear enough to code? | S4: STAGE-2 decision | T4: Stage-2 exclusion reason (auto) | U4: Deep-read: Digital Twin capability tier | V4: Phase: Design (1/0) | W4: Phase: Construction (1/0) | X4: Phase: Operation (1/0) | Y4: Cross-phase? (auto) | Z4: Deep-read: Design-for-X target | AA4: Deep-read: Self-improvement / convergence | AB4: Deep-read: Methodology | AC4: Deep-read: Data modality | AD4: Deep-read: Validation level | AE4: Deep-read: Quality appraisal score (0 to 5) | AF4: Deep-read: Thematic cluster | AG4: Deep-read: Key evidence / notes | AH4: Deep-read: Strength / research gap filled | AI4: Deep-read: Deficiencies & future work | AJ4: Deep-read: Fusion depth (AC1) | AK4: Deep-read: Fusion evidence (AC2) | AL4: Deep-read: Fusion confidence (AC3) | AM4: Fusion coding flag (review) | AN4: Full-text verification (date, source, outcome) | AO4: DOI
A5: 3566 | E5: =IF($A5="","",IFERROR(_xlfn.XLOOKUP($A5,'2_DOI_Lookup'!$D$2:$D$430,'2_DOI_Lookup'!$E$2:$E$430),"TITLE NOT IN SOURCE")) -> An association rule mining model for the application of construction technologies during COVID-19 | F5: Scopus | G5: Yes | H5: No | I5: No | J5: Yes | K5: Yes | L5: =IF(COUNTBLANK(G5:K5)=5,"",IF(COUNTIF(G5:K5,"No")>0,"EXCLUDE","INCLUDE")) -> EXCLUDE | M5: =IF(L5<>"EXCLUDE","",IF(G5="No","Wrong domain (non-AECO)",IF(H5="No","Digital Twin not core / buzzword",IF(I5="No","No Design for Safety/Quality/PtD",IF(J5="No","Wrong publication type",IF(K5="No","Non-English","")))))) -> Digital Twin not core / buzzword | S5: =IF(N5<>"Yes","",IF(COUNTBLANK(P5:R5)=3,"",IF(COUNTIF(P5:R5,"No")>0,"EXCLUDE","INCLUDE"))) | T5: =IF(S5<>"EXCLUDE","",IF(P5="No","Digital Twin mentioned only, not the subject",IF(Q5="No","No Design for Safety/Quality in full text",IF(R5="No","Methodology not codable","")))) | Y5: =IF(SUM(V5:X5)=0,"",IF(SUM(V5:X5)>=2,"Multi","Single")) | AG5: Tech-adoption survey (ARM); no DT, no DfS/DfQ focus | AO5: =IF($A5="","",IFERROR(_xlfn.XLOOKUP($A5,'2_DOI_Lookup'!$A$2:$A$430,'2_DOI_Lookup'!$B$2:$B$430),"NOT IN SOURCE")) -> 10.1080/15623599.2023.2212420
A6: 3741 | E6: =IF($A6="","",IFERROR(_xlfn.XLOOKUP($A6,'2_DOI_Lookup'!$D$2:$D$430,'2_DOI_Lookup'!$E$2:$E$430),"TITLE NOT IN SOURCE")) -> Digital twin and AI-driven smart adaptive walls for energy, comfort and carbon optimization in intelligent green buildings | F6: Scopus | G6: Yes | H6: Yes | I6: No | J6: Yes | K6: Yes | L6: =IF(COUNTBLANK(G6:K6)=5,"",IF(COUNTIF(G6:K6,"No")>0,"EXCLUDE","INCLUDE")) -> EXCLUDE | M6: =IF(L6<>"EXCLUDE","",IF(G6="No","Wrong domain (non-AECO)",IF(H6="No","Digital Twin not core / buzzword",IF(I6="No","No Design for Safety/Quality/PtD",IF(J6="No","Wrong publication type",IF(K6="No","Non-English","")))))) -> No Design for Safety/Quality/PtD | S6: =IF(N6<>"Yes","",IF(COUNTBLANK(P6:R6)=3,"",IF(COUNTIF(P6:R6,"No")>0,"EXCLUDE","INCLUDE"))) | T6: =IF(S6<>"EXCLUDE","",IF(P6="No","Digital Twin mentioned only, not the subject",IF(Q6="No","No Design for Safety/Quality in full text",IF(R6="No","Methodology not codable","")))) | Y6: =IF(SUM(V6:X6)=0,"",IF(SUM(V6:X6)>=2,"Multi","Single")) | AG6: Energy/comfort/carbon optimization; safety shield is control constraint (edge 5) | AO6: =IF($A6="","",IFERROR(_xlfn.XLOOKUP($A6,'2_DOI_Lookup'!$A$2:$A$430,'2_DOI_Lookup'!$B$2:$B$430),"NOT IN SOURCE")) -> 10.1016/j.energy.2026.140990
A7: 3665 | E7: =IF($A7="","",IFERROR(_xlfn.XLOOKUP($A7,'2_DOI_Lookup'!$D$2:$D$430,'2_DOI_Lookup'!$E$2:$E$430),"TITLE NOT IN SOURCE")) -> Enhancing attack resilience of cyber-physical systems through state dependency graph models | F7: Scopus | G7: No | H7: No | I7: No | J7: Yes | K7: Yes | L7: =IF(COUNTBLANK(G7:K7)=5,"",IF(COUNTIF(G7:K7,"No")>0,"EXCLUDE","INCLUDE")) -> EXCLUDE | M7: =IF(L7<>"EXCLUDE","",IF(G7="No","Wrong domain (non-AECO)",IF(H7="No","Digital Twin not core / buzzword",IF(I7="No","No Design for Safety/Quality/PtD",IF(J7="No","Wrong publication type",IF(K7="No","Non-English","")))))) -> Wrong domain (non-AECO) | S7: =IF(N7<>"Yes","",IF(COUNTBLANK(P7:R7)=3,"",IF(COUNTIF(P7:R7,"No")>0,"EXCLUDE","INCLUDE"))) | T7: =IF(S7<>"EXCLUDE","",IF(P7="No","Digital Twin mentioned only, not the subject",IF(Q7="No","No Design for Safety/Quality in full text",IF(R7="No","Methodology not codable","")))) | Y7: =IF(SUM(V7:X7)=0,"",IF(SUM(V7:X7)>=2,"Multi","Single")) | AG7: Cybersecurity of industrial CPS/SCADA; not AECO | AO7: =IF($A7="","",IFERROR(_xlfn.XLOOKUP($A7,'2_DOI_Lookup'!$A$2:$A$430,'2_DOI_Lookup'!$B$2:$B$430),"NOT IN SOURCE")) -> 10.1007/s10207-023-00731-w
A8: 3657 | E8: =IF($A8="","",IFERROR(_xlfn.XLOOKUP($A8,'2_DOI_Lookup'!$D$2:$D$430,'2_DOI_Lookup'!$E$2:$E$430),"TITLE NOT IN SOURCE")) -> IoT-Driven Resilience Monitoring: Case Study of a Cyber-Physical System | F8: Scopus | G8: No | H8: Yes | I8: No | J8: Yes | K8: Yes | L8: =IF(COUNTBLANK(G8:K8)=5,"",IF(COUNTIF(G8:K8,"No")>0,"EXCLUDE","INCLUDE")) -> EXCLUDE | M8: =IF(L8<>"EXCLUDE","",IF(G8="No","Wrong domain (non-AECO)",IF(H8="No","Digital Twin not core / buzzword",IF(I8="No","No Design for Safety/Quality/PtD",IF(J8="No","Wrong publication type",IF(K8="No","Non-English","")))))) -> Wrong domain (non-AECO) | S8: =IF(N8<>"Yes","",IF(COUNTBLANK(P8:R8)=3,"",IF(COUNTIF(P8:R8,"No")>0,"EXCLUDE","INCLUDE"))) | T8: =IF(S8<>"EXCLUDE","",IF(P8="No","Digital Twin mentioned only, not the subject",IF(Q8="No","No Design for Safety/Quality in full text",IF(R8="No","Methodology not codable","")))) | Y8: =IF(SUM(V8:X8)=0,"",IF(SUM(V8:X8)>=2,"Multi","Single")) | AG8: Smart energy systems CI; not built environment | AO8: =IF($A8="","",IFERROR(_xlfn.XLOOKUP($A8,'2_DOI_Lookup'!$A$2:$A$430,'2_DOI_Lookup'!$B$2:$B$430),"NOT IN SOURCE")) -> 10.3390/app15042092
A9: 3685 | E9: =IF($A9="","",IFERROR(_xlfn.XLOOKUP($A9,'2_DOI_Lookup'!$D$2:$D$430,'2_DOI_Lookup'!$E$2:$E$430),"TITLE NOT IN SOURCE")) -> Virtual Fencing for Safety-Critical Cyber-Physical Systems: Computer-Vision Enabled Digital Twins | F9: Scopus | G9: No | H9: Yes | I9: No | J9: Yes | K9: Yes | L9: =IF(COUNTBLANK(G9:K9)=5,"",IF(COUNTIF(G9:K9,"No")>0,"EXCLUDE","INCLUDE")) -> EXCLUDE | M9: =IF(L9<>"EXCLUDE","",IF(G9="No","Wrong domain (non-AECO)",IF(H9="No","Digital Twin not core / buzzword",IF(I9="No","No Design for Safety/Quality/PtD",IF(J9="No","Wrong publication type",IF(K9="No","Non-English","")))))) -> Wrong domain (non-AECO) | S9: =IF(N9<>"Yes","",IF(COUNTBLANK(P9:R9)=3,"",IF(COUNTIF(P9:R9,"No")>0,"EXCLUDE","INCLUDE"))) | T9: =IF(S9<>"EXCLUDE","",IF(P9="No","Digital Twin mentioned only, not the subject",IF(Q9="No","No Design for Safety/Quality in full text",IF(R9="No","Methodology not codable","")))) | Y9: =IF(SUM(V9:X9)=0,"",IF(SUM(V9:X9)>=2,"Multi","Single")) | AG9: Crowd management/surveillance; no built asset DfS/DfQ | AO9: =IF($A9="","",IFERROR(_xlfn.XLOOKUP($A9,'2_DOI_Lookup'!$A$2:$A$430,'2_DOI_Lookup'!$B$2:$B$430),"NOT IN SOURCE")) -> 10.1109/ACCESS.2025.3581041
A10: 3756 | B10: Ahmad (2025) | C10: 2025 | E10: =IF($A10="","",IFERROR(_xlfn.XLOOKUP($A10,'2_DOI_Lookup'!$D$2:$D$430,'2_DOI_Lookup'!$E$2:$E$430),"TITLE NOT IN SOURCE")) -> Lessons Learned from the Real-World Deployment of Multisensor Fusion for Proactive Work Zone Safety Application | F10: Scopus | G10: Yes | H10: Yes | I10: Yes | J10: Yes | K10: Yes | L10: =IF(COUNTBLANK(G10:K10)=5,"",IF(COUNTIF(G10:K10,"No")>0,"EXCLUDE","INCLUDE")) -> INCLUDE | M10: =IF(L10<>"EXCLUDE","",IF(G10="No","Wrong domain (non-AECO)",IF(H10="No","Digital Twin not core / buzzword",IF(I10="No","No Design for Safety/Quality/PtD",IF(J10="No","Wrong publication type",IF(K10="No","Non-English","")))))) | N10: Yes | O10: Yes | P10: Yes | Q10: Yes | R10: Yes | S10: =IF(N10<>"Yes","",IF(COUNTBLANK(P10:R10)=3,"",IF(COUNTIF(P10:R10,"No")>0,"EXCLUDE","INCLUDE"))) -> INCLUDE | T10: =IF(S10<>"EXCLUDE","",IF(P10="No","Digital Twin mentioned only, not the subject",IF(Q10="No","No Design for Safety/Quality in full text",IF(R10="No","Methodology not codable","")))) | U10: Tier 2 - Digital Shadow (one-way physical to virtual) | V10: 0 | W10: 1 | X10: 0 | Y10: =IF(SUM(V10:X10)=0,"",IF(SUM(V10:X10)>=2,"Multi","Single")) -> Single | Z10: Design for Safety (DfS) | AA10: None | AB10: Other / Mixed | AC10: Multi (two or more data types) | AD10: Single case study | AE10: 4 | AF10: Design for Safety | AG10: Deployed LiDAR+radar+camera fusion validated with RTK-GNSS at real work zone (lane-level accuracy); Predictive DT framework (Digital Shadow + Digital Sibling, TTC/PET conflict metrics, C-V2X warnings) proposed but not implemented — hence Tier 2, AA None. [Full-text source: arXiv OA preprint] | AH10: Fills the gap between work zone safety DT research and real-world deployment: LiDAR+radar+camera fusion validated with RTK-GNSS at a real work zone achieving lane-level accuracy, feeding a predictive DT framework pairing a Digital Shadow and Digital Sibling with TTC/PET conflict metrics and C-V2X warnings for proactive safety. | AI10: Deployment lessons rather than controlled validation: one real work zone, and the predictive framework (conflict metrics, C-V2X warnings) stays at framework level without demonstrated closed-loop actuation; no explicit future work is stated. | AJ10: Fused | AK10: Deployed LiDAR+radar+camera fusion validated with RTK-GNSS at lane-level accuracy at a real work zone (joint multi-sensor deployment feeding conflict metrics). | AL10: Medium | AM10: RESOLVED 2026-08-22: Year 2026 -> 2025 and author label updated. Verified full text is arXiv:2508.01599v1 [cs.OH] 3 Aug 2025, submission date August 5, 2025; no journal version of record found in the document | AN10: Verified 2026-08-22 (deep re-read) vs PDF. Lane-level tracking, RTK GNSS (NovAtel CPT7700), Digital Shadow/Digital Sibling, TTC/PET, C-V2X confirmed; "no explicit future work" confirmed (paper ends with CONCLUSION AND RECOMMENDATIONS). YEAR CORRECTED 2026 -> 2025: header reads "arXiv:2508.01599v1 [cs.OH] 3 Aug 2025" and "Submission Date: August 5, 2025"; the document contains no evidence of a 2026 version of record. | AO10: =IF($A10="","",IFERROR(_xlfn.XLOOKUP($A10,'2_DOI_Lookup'!$A$2:$A$430,'2_DOI_Lookup'!$B$2:$B$430),"NOT IN SOURCE")) -> 10.1177/03611981261441281
A11: 3978 | B11: Akanmu (2021) | C11: 2021 | E11: =IF($A11="","",IFERROR(_xlfn.XLOOKUP($A11,'2_DOI_Lookup'!$D$2:$D$430,'2_DOI_Lookup'!$E$2:$E$430),"TITLE NOT IN SOURCE")) -> TOWARDS NEXT GENERATION CYBER-PHYSICAL SYSTEMS AND DIGITAL TWINS FOR CONSTRUCTION | F11: Web of Science | G11: Yes | H11: Yes | I11: Yes | J11: Yes | K11: Yes | L11: =IF(COUNTBLANK(G11:K11)=5,"",IF(COUNTIF(G11:K11,"No")>0,"EXCLUDE","INCLUDE")) -> INCLUDE | M11: =IF(L11<>"EXCLUDE","",IF(G11="No","Wrong domain (non-AECO)",IF(H11="No","Digital Twin not core / buzzword",IF(I11="No","No Design for Safety/Quality/PtD",IF(J11="No","Wrong publication type",IF(K11="No","Non-English","")))))) | N11: Yes | O11: Yes | P11: Yes | Q11: Yes | R11: Yes | S11: =IF(N11<>"Yes","",IF(COUNTBLANK(P11:R11)=3,"",IF(COUNTIF(P11:R11,"No")>0,"EXCLUDE","INCLUDE"))) -> INCLUDE | T11: =IF(S11<>"EXCLUDE","",IF(P11="No","Digital Twin mentioned only, not the subject",IF(Q11="No","No Design for Safety/Quality in full text",IF(R11="No","Methodology not codable","")))) | U11: Tier 3 - Digital Twin (bidirectional, two-way) | V11: 0 | W11: 1 | X11: 1 | Y11: =IF(SUM(V11:X11)=0,"",IF(SUM(V11:X11)>=2,"Multi","Single")) -> Multi | Z11: Design for Safety (DfS) | AA11: Mentioned only | AB11: Digital Twin platform (no machine learning) | AC11: Multi (two or more data types) | AD11: Conceptual (no test) | AE11: 3 | AF11: BIM-to-Digital-Twin architecture | AG11: Perspective paper defining next-gen CPS/DT with explicit two-way mapping and passive/active control; scenarios (teleoperated drywall robot, postural tracking, near-miss prevention) illustrate bidirectional control but nothing implemented; ML training of movement data only suggested. [Full-text source: Endnote] | AH11: A perspective paper defining next-generation CPS and DT through two-way dynamic mapping between virtual models and the physical facility, distinguishing passive (model-based) from active (actuator-based) control, and illustrating scenarios: a teleoperated drywall robot controlled via wearable IMU motion capture, postural tracking with AR avatars and color-coded ergonomic risk feedback, and near-miss prediction using case-based reasoning and K-nearest neighbor. | AI11: Purely conceptual: none of the scenarios is implemented or validated, and the paper itself lists open challenges of a missing information model for DTs, missing version management guidelines, missing communication latency guidelines, and missing interoperability standards analogous to IFC. | AJ11: Unclear | AK11: Perspective paper defining next-gen CPS/DT; the bidirectional-control scenarios are illustrative only and no data-integration mechanism is implemented. | AL11: High | AN11: Verified 2026-08-22 vs PDF. Perspective paper: "two-way dynamic mapping between virtual models and physical components", drywall/near-miss scenarios with case-based reasoning described as opportunities, nothing implemented. Tier 3, AD Conceptual, AA Mentioned only all upheld. | AO11: =IF($A11="","",IFERROR(_xlfn.XLOOKUP($A11,'2_DOI_Lookup'!$A$2:$A$430,'2_DOI_Lookup'!$B$2:$B$430),"NOT IN SOURCE")) -> 10.36680/j.itcon.2021.027
A12: 3527 | E12: =IF($A12="","",IFERROR(_xlfn.XLOOKUP($A12,'2_DOI_Lookup'!$D$2:$D$430,'2_DOI_Lookup'!$E$2:$E$430),"TITLE NOT IN SOURCE")) -> A methodological approach to hybrid AI systems for real-time infrastructure monitoring in civil engineering | F12: Scopus | G12: Yes | H12: No | I12: Yes | J12: Yes | K12: Yes | L12: =IF(COUNTBLANK(G12:K12)=5,"",IF(COUNTIF(G12:K12,"No")>0,"EXCLUDE","INCLUDE")) -> EXCLUDE | M12: =IF(L12<>"EXCLUDE","",IF(G12="No","Wrong domain (non-AECO)",IF(H12="No","Digital Twin not core / buzzword",IF(I12="No","No Design for Safety/Quality/PtD",IF(J12="No","Wrong publication type",IF(K12="No","Non-English","")))))) -> Digital Twin not core / buzzword | S12: =IF(N12<>"Yes","",IF(COUNTBLANK(P12:R12)=3,"",IF(COUNTIF(P12:R12,"No")>0,"EXCLUDE","INCLUDE"))) | T12: =IF(S12<>"EXCLUDE","",IF(P12="No","Digital Twin mentioned only, not the subject",IF(Q12="No","No Design for Safety/Quality in full text",IF(R12="No","Methodology not codable","")))) | Y12: =IF(SUM(V12:X12)=0,"",IF(SUM(V12:X12)>=2,"Multi","Single")) | AG12: SHM hybrid AI; no DT built/proposed | AO12: =IF($A12="","",IFERROR(_xlfn.XLOOKUP($A12,'2_DOI_Lookup'!$A$2:$A$430,'2_DOI_Lookup'!$B$2:$B$430),"NOT IN SOURCE")) -> 10.1007/s42107-025-01409-5
A13: 3963 | E13: =IF($A13="","",IFERROR(_xlfn.XLOOKUP($A13,'2_DOI_Lookup'!$D$2:$D$430,'2_DOI_Lookup'!$E$2:$E$430),"TITLE NOT IN SOURCE")) -> Neural network-based metamodel for scaffolding behavior: Application for structural load analysis and safety enhancement | F13: Web of Science | G13: Yes | H13: No | I13: Yes | J13: Yes | K13: Yes | L13: =IF(COUNTBLANK(G13:K13)=5,"",IF(COUNTIF(G13:K13,"No")>0,"EXCLUDE","INCLUDE")) -> EXCLUDE | M13: =IF(L13<>"EXCLUDE","",IF(G13="No","Wrong domain (non-AECO)",IF(H13="No","Digital Twin not core / buzzword",IF(I13="No","No Design for Safety/Quality/PtD",IF(J13="No","Wrong publication type",IF(K13="No","Non-English","")))))) -> Digital Twin not core / buzzword | S13: =IF(N13<>"Yes","",IF(COUNTBLANK(P13:R13)=3,"",IF(COUNTIF(P13:R13,"No")>0,"EXCLUDE","INCLUDE"))) | T13: =IF(S13<>"EXCLUDE","",IF(P13="No","Digital Twin mentioned only, not the subject",IF(Q13="No","No Design for Safety/Quality in full text",IF(R13="No","Methodology not codable","")))) | Y13: =IF(SUM(V13:X13)=0,"",IF(SUM(V13:X13)>=2,"Multi","Single")) | AG13: FEM+NN metamodel; authors state not a full digital twin | AO13: =IF($A13="","",IFERROR(_xlfn.XLOOKUP($A13,'2_DOI_Lookup'!$A$2:$A$430,'2_DOI_Lookup'!$B$2:$B$430),"NOT IN SOURCE")) -> 10.1016/j.apples.2025.100240
A14: 3917 | E14: =IF($A14="","",IFERROR(_xlfn.XLOOKUP($A14,'2_DOI_Lookup'!$D$2:$D$430,'2_DOI_Lookup'!$E$2:$E$430),"TITLE NOT IN SOURCE")) -> Enhancing resilience through environmental data integration in early construction planning: a cloud-based framework | F14: Web of Science | G14: Yes | H14: No | I14: No | J14: Yes | K14: Yes | L14: =IF(COUNTBLANK(G14:K14)=5,"",IF(COUNTIF(G14:K14,"No")>0,"EXCLUDE","INCLUDE")) -> EXCLUDE | M14: =IF(L14<>"EXCLUDE","",IF(G14="No","Wrong domain (non-AECO)",IF(H14="No","Digital Twin not core / buzzword",IF(I14="No","No Design for Safety/Quality/PtD",IF(J14="No","Wrong publication type",IF(K14="No","Non-English","")))))) -> Digital Twin not core / buzzword | S14: =IF(N14<>"Yes","",IF(COUNTBLANK(P14:R14)=3,"",IF(COUNTIF(P14:R14,"No")>0,"EXCLUDE","INCLUDE"))) | T14: =IF(S14<>"EXCLUDE","",IF(P14="No","Digital Twin mentioned only, not the subject",IF(Q14="No","No Design for Safety/Quality in full text",IF(R14="No","Methodology not codable","")))) | Y14: =IF(SUM(V14:X14)=0,"",IF(SUM(V14:X14)>=2,"Multi","Single")) | AG14: BIM-ICDD semantic linking; no DT; compliance not DfQ | AO14: =IF($A14="","",IFERROR(_xlfn.XLOOKUP($A14,'2_DOI_Lookup'!$A$2:$A$430,'2_DOI_Lookup'!$B$2:$B$430),"NOT IN SOURCE")) -> 10.3389/fbuil.2026.1748837
A15: 3541 | E15: =IF($A15="","",IFERROR(_xlfn.XLOOKUP($A15,'2_DOI_Lookup'!$D$2:$D$430,'2_DOI_Lookup'!$E$2:$E$430),"TITLE NOT IN SOURCE")) -> Automation levels for nuclear reactor operations: A revised perspective | F15: Scopus | G15: No | H15: No | I15: No | J15: Yes | K15: Yes | L15: =IF(COUNTBLANK(G15:K15)=5,"",IF(COUNTIF(G15:K15,"No")>0,"EXCLUDE","INCLUDE")) -> EXCLUDE | M15: =IF(L15<>"EXCLUDE","",IF(G15="No","Wrong domain (non-AECO)",IF(H15="No","Digital Twin not core / buzzword",IF(I15="No","No Design for Safety/Quality/PtD",IF(J15="No","Wrong publication type",IF(K15="No","Non-English","")))))) -> Wrong domain (non-AECO) | S15: =IF(N15<>"Yes","",IF(COUNTBLANK(P15:R15)=3,"",IF(COUNTIF(P15:R15,"No")>0,"EXCLUDE","INCLUDE"))) | T15: =IF(S15<>"EXCLUDE","",IF(P15="No","Digital Twin mentioned only, not the subject",IF(Q15="No","No Design for Safety/Quality in full text",IF(R15="No","Methodology not codable","")))) | Y15: =IF(SUM(V15:X15)=0,"",IF(SUM(V15:X15)>=2,"Multi","Single")) | AG15: Nuclear power domain | AO15: =IF($A15="","",IFERROR(_xlfn.XLOOKUP($A15,'2_DOI_Lookup'!$A$2:$A$430,'2_DOI_Lookup'!$B$2:$B$430),"NOT IN SOURCE")) -> 10.1016/j.pnucene.2022.104559
A16: 3903 | E16: =IF($A16="","",IFERROR(_xlfn.XLOOKUP($A16,'2_DOI_Lookup'!$D$2:$D$430,'2_DOI_Lookup'!$E$2:$E$430),"TITLE NOT IN SOURCE")) -> BIM-GIS integrated hydrodynamic modeling for road flood risk assessment: A case study in Algeria's Chiffa Wadi | F16: Web of Science | G16: Yes | H16: No | I16: Yes | J16: Yes | K16: Yes | L16: =IF(COUNTBLANK(G16:K16)=5,"",IF(COUNTIF(G16:K16,"No")>0,"EXCLUDE","INCLUDE")) -> EXCLUDE | M16: =IF(L16<>"EXCLUDE","",IF(G16="No","Wrong domain (non-AECO)",IF(H16="No","Digital Twin not core / buzzword",IF(I16="No","No Design for Safety/Quality/PtD",IF(J16="No","Wrong publication type",IF(K16="No","Non-English","")))))) -> Digital Twin not core / buzzword | S16: =IF(N16<>"Yes","",IF(COUNTBLANK(P16:R16)=3,"",IF(COUNTIF(P16:R16,"No")>0,"EXCLUDE","INCLUDE"))) | T16: =IF(S16<>"EXCLUDE","",IF(P16="No","Digital Twin mentioned only, not the subject",IF(Q16="No","No Design for Safety/Quality in full text",IF(R16="No","Methodology not codable","")))) | Y16: =IF(SUM(V16:X16)=0,"",IF(SUM(V16:X16)>=2,"Multi","Single")) | AG16: BIM-HDM framework; DT only future early warning | AO16: =IF($A16="","",IFERROR(_xlfn.XLOOKUP($A16,'2_DOI_Lookup'!$A$2:$A$430,'2_DOI_Lookup'!$B$2:$B$430),"NOT IN SOURCE")) -> 10.1016/j.ress.2025.111906
A17: 3915 | B17: Almatared (2024) | C17: 2024 | E17: =IF($A17="","",IFERROR(_xlfn.XLOOKUP($A17,'2_DOI_Lookup'!$D$2:$D$430,'2_DOI_Lookup'!$E$2:$E$430),"TITLE NOT IN SOURCE")) -> Digital-Twin-Based Fire Safety Management Framework for Smart Buildings | F17: Web of Science | G17: Yes | H17: Yes | I17: Yes | J17: Yes | K17: Yes | L17: =IF(COUNTBLANK(G17:K17)=5,"",IF(COUNTIF(G17:K17,"No")>0,"EXCLUDE","INCLUDE")) -> INCLUDE | M17: =IF(L17<>"EXCLUDE","",IF(G17="No","Wrong domain (non-AECO)",IF(H17="No","Digital Twin not core / buzzword",IF(I17="No","No Design for Safety/Quality/PtD",IF(J17="No","Wrong publication type",IF(K17="No","Non-English","")))))) | N17: Yes | O17: Yes | P17: Yes | Q17: Yes | R17: Yes | S17: =IF(N17<>"Yes","",IF(COUNTBLANK(P17:R17)=3,"",IF(COUNTIF(P17:R17,"No")>0,"EXCLUDE","INCLUDE"))) -> INCLUDE | T17: =IF(S17<>"EXCLUDE","",IF(P17="No","Digital Twin mentioned only, not the subject",IF(Q17="No","No Design for Safety/Quality in full text",IF(R17="No","Methodology not codable","")))) | U17: Tier 3 - Digital Twin (bidirectional, two-way) | V17: 0 | W17: 0 | X17: 1 | Y17: =IF(SUM(V17:X17)=0,"",IF(SUM(V17:X17)>=2,"Multi","Single")) -> Single | Z17: Design for Safety (DfS) | AA17: Mentioned only | AB17: Digital Twin platform (no machine learning) | AC17: Multi (two or more data types) | AD17: Conceptual (no test) | AE17: 3 | AF17: Design for Safety | AG17: Four-layer DT-based fire-safety framework (physical/virtual/application/user-interaction) with explicit feedback "integrated back with the physical building layer for automatic control"; validated only via FM-professional questionnaire, no technical test; AI learning cited from literature, not implemented. [Full-text source: Endnote] | AH17: Addresses the underexplored application of DT to fire safety management: a four-layer framework (physical building, virtual building, application, and user interaction layers) combining BIM, IoT, AI, data fusion, blockchain, and AR, with virtual-layer decisions fed back to the physical building layer for automatic control and operation optimization while keeping FM professionals in the loop. | AI17: Conceptual only: the framework was validated through a thematic analysis of 37 studies and a survey of FM professionals (66 responses, 28 complete) rather than a live implementation; no prototype or sensor deployment is reported. Future work includes a Delphi study with a broader panel and involving firefighters as end users. | AJ17: Unclear | AK17: Four-layer fire-safety framework validated only through a thematic analysis and an FM-professional questionnaire; the layer integration mechanism is not implemented. | AL17: High | AN17: Verified 2026-08-22 vs PDF (Buildings 2024). Tier 3 supported verbatim: decisions "integrated back with the physical building layer for automatic control and operation optimization". Validation is a questionnaire of FM professionals only, so AD Conceptual and AA Mentioned only upheld. | AO17: =IF($A17="","",IFERROR(_xlfn.XLOOKUP($A17,'2_DOI_Lookup'!$A$2:$A$430,'2_DOI_Lookup'!$B$2:$B$430),"NOT IN SOURCE")) -> 10.3390/buildings14010004
A18: 3668 | B18: Alvaro (2025) | C18: 2025 | E18: =IF($A18="","",IFERROR(_xlfn.XLOOKUP($A18,'2_DOI_Lookup'!$D$2:$D$430,'2_DOI_Lookup'!$E$2:$E$430),"TITLE NOT IN SOURCE")) -> GUIDE2FR: A smart monitoring platform with a digital twin of a firefighter training tower for emergency scenarios | F18: Scopus | G18: Yes | H18: Yes | I18: Yes | J18: Yes | K18: Yes | L18: =IF(COUNTBLANK(G18:K18)=5,"",IF(COUNTIF(G18:K18,"No")>0,"EXCLUDE","INCLUDE")) -> INCLUDE | M18: =IF(L18<>"EXCLUDE","",IF(G18="No","Wrong domain (non-AECO)",IF(H18="No","Digital Twin not core / buzzword",IF(I18="No","No Design for Safety/Quality/PtD",IF(J18="No","Wrong publication type",IF(K18="No","Non-English","")))))) | N18: Yes | O18: Yes | P18: Yes | Q18: Yes | R18: Yes | S18: =IF(N18<>"Yes","",IF(COUNTBLANK(P18:R18)=3,"",IF(COUNTIF(P18:R18,"No")>0,"EXCLUDE","INCLUDE"))) -> INCLUDE | T18: =IF(S18<>"EXCLUDE","",IF(P18="No","Digital Twin mentioned only, not the subject",IF(Q18="No","No Design for Safety/Quality in full text",IF(R18="No","Methodology not codable","")))) | U18: Tier 2 - Digital Shadow (one-way physical to virtual) | V18: 0 | W18: 0 | X18: 1 | Y18: =IF(SUM(V18:X18)=0,"",IF(SUM(V18:X18)>=2,"Multi","Single")) -> Single | Z18: Design for Safety (DfS) | AA18: None | AB18: Other / Mixed | AC18: Multi (two or more data types) | AD18: Single case study | AE18: 4 | AF18: Design for Safety | AG18: GUIDE2FR emergency-monitoring DT of a firefighter training tower (Alcorcón): Wi-Fi/LoRa beacon network (temp, humidity, CO2, TVOC) + RTSP video synchronised in a Grafana plugin; offline-trained ML forecasting pipeline (SVR/RF/Huber/GPR, forward-chaining CV, tested on 4 beacons at Fire Station 9) visualised in the DT; one-way data flow to human decision-makers, no actuation and no online learning loop. [Full-text source: Endnote] | AH18: Fills the gap between fire-safety DT research and operational emergency response: a functioning building DT (GUIDE2FR) fusing Wi-Fi/LoRa environmental beacons with live RTSP video in a Grafana plugin, plus an offline-trained ML forecasting pipeline (SVR, Huber, Random Forest, Gaussian Process, forward-chaining CV, adaptive ensemble) tested on data from four beacons during firefighter training exercises at Fire Station 9 in Madrid. | AI18: No actuation or bidirectional link to building systems: forecasting models are offline-trained and never updated online. The platform relies on proprietary ArcGIS, assumes a reliable wireless network, and sensor accuracy under extreme conditions is unverified; future work targets open-source visualization and integration with more real assets for active response and evacuation mechanisms. | AJ18: Aligned | AK18: Each video segment is timestamped and the custom Grafana plugin cross-references RTSP video streams with time-series sensor data stored in MySQL, giving video and beacon data a shared temporal frame (inference still runs on sensor series only). | AL18: High | AN18: Verified 2026-08-22 vs PDF (Internet of Things, Elsevier). GUIDE2FR platform, firefighter training tower at CUS Alcorcon (Madrid), Grafana plugin synchronising RTSP video with sensor data, ArcGIS geolocation all confirmed. Tier 2, AA None upheld. | AO18: =IF($A18="","",IFERROR(_xlfn.XLOOKUP($A18,'2_DOI_Lookup'!$A$2:$A$430,'2_DOI_Lookup'!$B$2:$B$430),"NOT IN SOURCE")) -> 10.1016/j.iot.2025.101768
A19: 4053 | B19: Ammar (2024) | C19: 2024 | E19: =IF($A19="","",IFERROR(_xlfn.XLOOKUP($A19,'2_DOI_Lookup'!$D$2:$D$430,'2_DOI_Lookup'!$E$2:$E$430),"TITLE NOT IN SOURCE")) -> Practical Application of Digital Twins for Transportation Asset Data Management: Case Example of a Safety Hardware Asset | F19: Web of Science | G19: Yes | H19: Yes | I19: Yes | J19: Yes | K19: Yes | L19: =IF(COUNTBLANK(G19:K19)=5,"",IF(COUNTIF(G19:K19,"No")>0,"EXCLUDE","INCLUDE")) -> INCLUDE | M19: =IF(L19<>"EXCLUDE","",IF(G19="No","Wrong domain (non-AECO)",IF(H19="No","Digital Twin not core / buzzword",IF(I19="No","No Design for Safety/Quality/PtD",IF(J19="No","Wrong publication type",IF(K19="No","Non-English","")))))) | N19: Yes | O19: Yes | P19: No | Q19: Yes | R19: Yes | S19: =IF(N19<>"Yes","",IF(COUNTBLANK(P19:R19)=3,"",IF(COUNTIF(P19:R19,"No")>0,"EXCLUDE","INCLUDE"))) -> EXCLUDE | T19: =IF(S19<>"EXCLUDE","",IF(P19="No","Digital Twin mentioned only, not the subject",IF(Q19="No","No Design for Safety/Quality in full text",IF(R19="No","Methodology not codable","")))) -> Digital Twin mentioned only, not the subject | U19: Unclear | Y19: =IF(SUM(V19:X19)=0,"",IF(SUM(V19:X19)>=2,"Multi","Single")) | AG19: Survey + case study on guiderail data management for a transportation agency: investigates current practices and proposes a data architecture for information-rich analytical models using DTs, but no DT is actually built or evaluated - P=No -> Stage-2 exclude. [Full-text source: Endnote] | AN19: Verified 2026-08-22 vs PDF (Transportation Research Record 2678(10):114-130). Survey plus CTDOT subject-matter-expert interviews on guiderail asset data management and a proposed guiderail data architecture; DTs are discussed as potential rather than built or evaluated. Stage-2 EXCLUDE (P=No) upheld. | AO19: =IF($A19="","",IFERROR(_xlfn.XLOOKUP($A19,'2_DOI_Lookup'!$A$2:$A$430,'2_DOI_Lookup'!$B$2:$B$430),"NOT IN SOURCE")) -> 10.1177/03611981241231804
A20: 3579 | E20: =IF($A20="","",IFERROR(_xlfn.XLOOKUP($A20,'2_DOI_Lookup'!$D$2:$D$430,'2_DOI_Lookup'!$E$2:$E$430),"TITLE NOT IN SOURCE")) -> State regulation of the IoT in the Russian Federation: Fundamentals and challenges | F20: Scopus | G20: No | H20: No | I20: No | J20: Yes | K20: Yes | L20: =IF(COUNTBLANK(G20:K20)=5,"",IF(COUNTIF(G20:K20,"No")>0,"EXCLUDE","INCLUDE")) -> EXCLUDE | M20: =IF(L20<>"EXCLUDE","",IF(G20="No","Wrong domain (non-AECO)",IF(H20="No","Digital Twin not core / buzzword",IF(I20="No","No Design for Safety/Quality/PtD",IF(J20="No","Wrong publication type",IF(K20="No","Non-English","")))))) -> Wrong domain (non-AECO) | S20: =IF(N20<>"Yes","",IF(COUNTBLANK(P20:R20)=3,"",IF(COUNTIF(P20:R20,"No")>0,"EXCLUDE","INCLUDE"))) | T20: =IF(S20<>"EXCLUDE","",IF(P20="No","Digital Twin mentioned only, not the subject",IF(Q20="No","No Design for Safety/Quality in full text",IF(R20="No","Methodology not codable","")))) | Y20: =IF(SUM(V20:X20)=0,"",IF(SUM(V20:X20)>=2,"Multi","Single")) | AG20: Legal/regulatory IoT paper; not AECO | AO20: =IF($A20="","",IFERROR(_xlfn.XLOOKUP($A20,'2_DOI_Lookup'!$A$2:$A$430,'2_DOI_Lookup'!$B$2:$B$430),"NOT IN SOURCE")) -> 10.11591/ijece.v11i5.pp4542-4549
A21: 3838 | E21: =IF($A21="","",IFERROR(_xlfn.XLOOKUP($A21,'2_DOI_Lookup'!$D$2:$D$430,'2_DOI_Lookup'!$E$2:$E$430),"TITLE NOT IN SOURCE")) -> The Role of Artificial Intelligence in Shaping Intelligent Motorways: Opportunities, Challenges, and Real-World Implementations | F21: Scopus | G21: Yes | H21: No | I21: No | J21: Yes | K21: Yes | L21: =IF(COUNTBLANK(G21:K21)=5,"",IF(COUNTIF(G21:K21,"No")>0,"EXCLUDE","INCLUDE")) -> EXCLUDE | M21: =IF(L21<>"EXCLUDE","",IF(G21="No","Wrong domain (non-AECO)",IF(H21="No","Digital Twin not core / buzzword",IF(I21="No","No Design for Safety/Quality/PtD",IF(J21="No","Wrong publication type",IF(K21="No","Non-English","")))))) -> Digital Twin not core / buzzword | S21: =IF(N21<>"Yes","",IF(COUNTBLANK(P21:R21)=3,"",IF(COUNTIF(P21:R21,"No")>0,"EXCLUDE","INCLUDE"))) | T21: =IF(S21<>"EXCLUDE","",IF(P21="No","Digital Twin mentioned only, not the subject",IF(Q21="No","No Design for Safety/Quality in full text",IF(R21="No","Methodology not codable","")))) | Y21: =IF(SUM(V21:X21)=0,"",IF(SUM(V21:X21)>=2,"Multi","Single")) | AG21: AI-in-motorways review; DT one of many topics | AO21: =IF($A21="","",IFERROR(_xlfn.XLOOKUP($A21,'2_DOI_Lookup'!$A$2:$A$430,'2_DOI_Lookup'!$B$2:$B$430),"NOT IN SOURCE")) -> 10.1109/TITS.2025.3609972
A22: 4020 | E22: =IF($A22="","",IFERROR(_xlfn.XLOOKUP($A22,'2_DOI_Lookup'!$D$2:$D$430,'2_DOI_Lookup'!$E$2:$E$430),"TITLE NOT IN SOURCE")) -> FingerCI: Writing industrial process specifications from network traffic | F22: Web of Science | G22: No | H22: Yes | I22: No | J22: Yes | K22: Yes | L22: =IF(COUNTBLANK(G22:K22)=5,"",IF(COUNTIF(G22:K22,"No")>0,"EXCLUDE","INCLUDE")) -> EXCLUDE | M22: =IF(L22<>"EXCLUDE","",IF(G22="No","Wrong domain (non-AECO)",IF(H22="No","Digital Twin not core / buzzword",IF(I22="No","No Design for Safety/Quality/PtD",IF(J22="No","Wrong publication type",IF(K22="No","Non-English","")))))) -> Wrong domain (non-AECO) | S22: =IF(N22<>"Yes","",IF(COUNTBLANK(P22:R22)=3,"",IF(COUNTIF(P22:R22,"No")>0,"EXCLUDE","INCLUDE"))) | T22: =IF(S22<>"EXCLUDE","",IF(P22="No","Digital Twin mentioned only, not the subject",IF(Q22="No","No Design for Safety/Quality in full text",IF(R22="No","Methodology not codable","")))) | Y22: =IF(SUM(V22:X22)=0,"",IF(SUM(V22:X22)>=2,"Multi","Single")) | AG22: Cybersecurity; airport baggage system industrial testbed | AO22: =IF($A22="","",IFERROR(_xlfn.XLOOKUP($A22,'2_DOI_Lookup'!$A$2:$A$430,'2_DOI_Lookup'!$B$2:$B$430),"NOT IN SOURCE")) -> 10.1016/j.ijcip.2024.100725
A23: 3842 | B23: Aragon (2025) | C23: 2025 | E23: =IF($A23="","",IFERROR(_xlfn.XLOOKUP($A23,'2_DOI_Lookup'!$D$2:$D$430,'2_DOI_Lookup'!$E$2:$E$430),"TITLE NOT IN SOURCE")) -> Seeking a Definition of Digital Twins for Construction and Infrastructure Management | F23: Scopus | G23: Yes | H23: Yes | I23: Yes | J23: Yes | K23: Yes | L23: =IF(COUNTBLANK(G23:K23)=5,"",IF(COUNTIF(G23:K23,"No")>0,"EXCLUDE","INCLUDE")) -> INCLUDE | M23: =IF(L23<>"EXCLUDE","",IF(G23="No","Wrong domain (non-AECO)",IF(H23="No","Digital Twin not core / buzzword",IF(I23="No","No Design for Safety/Quality/PtD",IF(J23="No","Wrong publication type",IF(K23="No","Non-English","")))))) | N23: Yes | O23: Yes | P23: Yes | Q23: Yes | R23: Yes | S23: =IF(N23<>"Yes","",IF(COUNTBLANK(P23:R23)=3,"",IF(COUNTIF(P23:R23,"No")>0,"EXCLUDE","INCLUDE"))) -> INCLUDE | T23: =IF(S23<>"EXCLUDE","",IF(P23="No","Digital Twin mentioned only, not the subject",IF(Q23="No","No Design for Safety/Quality in full text",IF(R23="No","Methodology not codable","")))) | U23: Tier 1 - Digital Model (static, no live data) | V23: 0 | W23: 0 | X23: 1 | Y23: =IF(SUM(V23:X23)=0,"",IF(SUM(V23:X23)>=2,"Multi","Single")) -> Single | Z23: Design for Safety (DfS) | AA23: None | AB23: Digital Twin platform (no machine learning) | AC23: Multi (two or more data types) | AD23: Cross-project (multiple real projects) | AE23: 3 | AF23: Lifecycle / governance | AG23: Definition/standardisation position paper (CEN/TC 442/WG 9, ISO); two illustrative DT cases (Bidebieta-Basauri railway station, UPM civil engineering school) are management/visualisation platforms with real-time info integration but no analytics loop or learning; safety only a secondary use case. [Full-text source: Endnote] | AH23: A standardization position paper reviewing DT definitions and frameworks and reporting the creation of CEN/TC 442/WG 9, whose 34-use-case technical report CEN/TR 18077 and the resulting European standard aim to give the built environment a shared DT definition; it grounds its argument in two implemented management platforms, the Bidebieta-Basauri railway station and the UPM civil engineering school. | AI23: The two DT cases are management and visualization platforms lacking AI or simulation protocols, which the authors state are still under research, and the paper proposes definitions rather than new empirical validation; the European standard was still pending publication and no quantitative evaluation is offered. | AJ23: Unclear | AK23: Standardisation position paper (CEN/TC 442/WG 9); the two illustrative DT cases are management/visualisation platforms and no data-integration mechanism is specified. | AL23: High | AN23: Verified 2026-08-22 vs PDF (UPM / UNE / CEN). CEN/TC 442/WG 9 and CEN/TR 18077 confirmed; two implemented DT management platforms described - Bidebieta-Basauri railway station (Bilbao-Orduna network, Basque Country) and the UPM civil engineering school. AD Cross-project supported by two distinct real projects. Tier 1, AA None upheld. | AO23: =IF($A23="","",IFERROR(_xlfn.XLOOKUP($A23,'2_DOI_Lookup'!$A$2:$A$430,'2_DOI_Lookup'!$B$2:$B$430),"NOT IN SOURCE")) -> 10.3390/app15031557
A24: 4028 | B24: Araujo (2025) | C24: 2025 | E24: =IF($A24="","",IFERROR(_xlfn.XLOOKUP($A24,'2_DOI_Lookup'!$D$2:$D$430,'2_DOI_Lookup'!$E$2:$E$430),"TITLE NOT IN SOURCE")) -> Proposal of a conceptual model of digital twins for construction sites | F24: Web of Science | G24: Yes | H24: Yes | I24: Yes | J24: Yes | K24: Yes | L24: =IF(COUNTBLANK(G24:K24)=5,"",IF(COUNTIF(G24:K24,"No")>0,"EXCLUDE","INCLUDE")) -> INCLUDE | M24: =IF(L24<>"EXCLUDE","",IF(G24="No","Wrong domain (non-AECO)",IF(H24="No","Digital Twin not core / buzzword",IF(I24="No","No Design for Safety/Quality/PtD",IF(J24="No","Wrong publication type",IF(K24="No","Non-English","")))))) | N24: Yes | O24: Yes | P24: Yes | Q24: Yes | R24: Yes | S24: =IF(N24<>"Yes","",IF(COUNTBLANK(P24:R24)=3,"",IF(COUNTIF(P24:R24,"No")>0,"EXCLUDE","INCLUDE"))) -> INCLUDE | T24: =IF(S24<>"EXCLUDE","",IF(P24="No","Digital Twin mentioned only, not the subject",IF(Q24="No","No Design for Safety/Quality in full text",IF(R24="No","Methodology not codable","")))) | U24: Tier 2 - Digital Shadow (one-way physical to virtual) | V24: 0 | W24: 1 | X24: 0 | Y24: =IF(SUM(V24:X24)=0,"",IF(SUM(V24:X24)>=2,"Multi","Single")) -> Single | Z24: Design for Quality (DfQ) | AA24: None | AB24: Digital Twin platform (no machine learning) | AC24: Multi (two or more data types) | AD24: Conceptual (no test) | AE24: 3 | AF24: BIM-to-Digital-Twin architecture | AG24: DSR conceptual model (F1 data acquisition / F2 data analysis-simulation / F3 BIM transformation boxes) for DT on construction sites, generalised from the empirical Smart Twins 4.0 system (RFID+IoT+BIM tracking of metallic formwork in concrete wall construction; 151 panels inspected, 100% external defects, wear 42% — rework/quality control). Closed-loop is human-in-the-loop only; F2 simulation box proposed but NOT implemented (future Smart Twins 5.0); no ML and no self-improvement. [Full-text source: Endnote] | AH24: Proposes a closed-loop conceptual model of DTs for construction sites, structured as three functional boxes: F1 data acquisition (IoT/RFID), F2 data analysis and simulation, and F3 BIM transformation into a web-based model; it is grounded in the empirical Smart Twins 4.0 system, which tracked 151 formwork panels with RFID and a web-based BIM, finding 100% external and 98% internal defects. | AI24: Smart Twins 4.0 is limited to a single physical resource (formwork), has restricted data analysis capabilities and interoperability, and still requires manual steps in data collection; the model simplifies real-world complexity, omits human roles beyond decision-making, and the authors state it needs future testing in different contexts. | AJ24: Aligned | AK24: Smart Twins 4.0 links physical formworks to their virtual BIM counterparts through automatic database integration (RFID UHF tags read on Android, Firebase, Web-based Revit/Dynamo BIM), i.e. a shared object identity between tag data and BIM elements. | AL24: Medium | AN24: Verified 2026-08-22 vs PDF. Design Science Research methodology confirmed; Smart Twins 4.0 empirical study confirmed verbatim: "Through an inspection of 151 panels using Smart Twins, 100% exhibited external defects, and 98% exhibited internal defects", most common defect external wear (42%). Tier 2, AD Conceptual, AA None upheld. | AO24: =IF($A24="","",IFERROR(_xlfn.XLOOKUP($A24,'2_DOI_Lookup'!$A$2:$A$430,'2_DOI_Lookup'!$B$2:$B$430),"NOT IN SOURCE")) -> 10.7764/RIC.00168.21
A25: 3828 | B25: Arhrib (2026) | C25: 2026 | E25: =IF($A25="","",IFERROR(_xlfn.XLOOKUP($A25,'2_DOI_Lookup'!$D$2:$D$430,'2_DOI_Lookup'!$E$2:$E$430),"TITLE NOT IN SOURCE")) -> Serverless 3D Reconstruction and Spatial Anchoring for Cloud-Native Infrastructure Inspection | F25: Scopus | G25: Yes | H25: Yes | I25: Yes | J25: Yes | K25: Yes | L25: =IF(COUNTBLANK(G25:K25)=5,"",IF(COUNTIF(G25:K25,"No")>0,"EXCLUDE","INCLUDE")) -> INCLUDE | M25: =IF(L25<>"EXCLUDE","",IF(G25="No","Wrong domain (non-AECO)",IF(H25="No","Digital Twin not core / buzzword",IF(I25="No","No Design for Safety/Quality/PtD",IF(J25="No","Wrong publication type",IF(K25="No","Non-English","")))))) | N25: Yes | O25: Yes | P25: Yes | Q25: Yes | R25: Yes | S25: =IF(N25<>"Yes","",IF(COUNTBLANK(P25:R25)=3,"",IF(COUNTIF(P25:R25,"No")>0,"EXCLUDE","INCLUDE"))) -> INCLUDE | T25: =IF(S25<>"EXCLUDE","",IF(P25="No","Digital Twin mentioned only, not the subject",IF(Q25="No","No Design for Safety/Quality in full text",IF(R25="No","Methodology not codable","")))) | U25: Tier 1 - Digital Model (static, no live data) | V25: 0 | W25: 0 | X25: 1 | Y25: =IF(SUM(V25:X25)=0,"",IF(SUM(V25:X25)>=2,"Multi","Single")) -> Single | Z25: Design for Quality (DfQ) | AA25: None | AB25: Digital Twin platform (no machine learning) | AC25: Multi (two or more data types) | AD25: Cross-project (multiple real projects) | AE25: 4 | AF25: Perception / Computer Vision | AG25: Serverless SfM/MVS pipeline + PostGIS defect anchors on real inspection datasets; defects as georeferenced 3D anchors support DfQ traceability; authors explicitly position against passive Level-1 twins, but no live link/learning: periodic re-scan workflow. [Full-text source: Endnote] | AH25: Addresses fragmented inspection data by replacing desktop photogrammetry with a serverless spatial intelligence hub: timeout-resilient orchestration of SfM/MVS, PostGIS-anchored defect records linked to georeferenced 3D meshes via raycasting and frustum-based image retrieval, end-to-end reconstruction in under one hour, sub-25 ms query latency, and over 90% image retrieval accuracy on two real UAV inspection datasets. | AI25: No automated defect detection: annotations are manually created by human inspectors, which the authors call the main bottleneck for scaling; validation covers only two UAV datasets, hyperparameters are not systematically optimized, and the system assumes reliable connectivity. Future work includes automated detection, temporal change monitoring, 3D Gaussian Splatting visualization, and offline capabilities. | AJ25: Aligned | AK25: Defect records are anchored to georeferenced 3D meshes in PostGIS via raycasting and frustum-based image retrieval, putting imagery-derived geometry and defect annotations in one spatial reference frame. | AL25: High | AM25: RESOLVED 2026-08-22: AD Single case study -> Cross-project. Dataset A = The Mill building, London (167 UAV images); Dataset B = building roof at EPFL, Lausanne (85 images) - two distinct real assets in different countries | AN25: Verified 2026-08-22 (deep re-read) vs PDF (Buildings 2026, 16, 2433). Serverless orchestration, PostGIS anchors, sub-25 ms query latency and >90% image retrieval confirmed; explicit contrast with passive "Level 1" twins supports Tier 1. VALIDATION SCOPE RESOLVED: "experiments using two distinct datasets" - Dataset A is The Mill building in London (167 UAV images, nadir + single oblique pass) and Dataset B is a building roof structure at EPFL, Lausanne (85 images, circular oblique, Phantom FC330 at 30 m AGL). Two separate real assets => AD corrected to Cross-project. | AO25: =IF($A25="","",IFERROR(_xlfn.XLOOKUP($A25,'2_DOI_Lookup'!$A$2:$A$430,'2_DOI_Lookup'!$B$2:$B$430),"NOT IN SOURCE")) -> 10.3390/buildings16122433
A26: 3662 | B26: Armijo (2024) | C26: 2024 | E26: =IF($A26="","",IFERROR(_xlfn.XLOOKUP($A26,'2_DOI_Lookup'!$D$2:$D$430,'2_DOI_Lookup'!$E$2:$E$430),"TITLE NOT IN SOURCE")) -> Integration of Railway Bridge Structural Health Monitoring into the Internet of Things with a Digital Twin: A Case Study | F26: Scopus | G26: Yes | H26: Yes | I26: Yes | J26: Yes | K26: Yes | L26: =IF(COUNTBLANK(G26:K26)=5,"",IF(COUNTIF(G26:K26,"No")>0,"EXCLUDE","INCLUDE")) -> INCLUDE | M26: =IF(L26<>"EXCLUDE","",IF(G26="No","Wrong domain (non-AECO)",IF(H26="No","Digital Twin not core / buzzword",IF(I26="No","No Design for Safety/Quality/PtD",IF(J26="No","Wrong publication type",IF(K26="No","Non-English","")))))) | N26: Yes | O26: Yes | P26: Yes | Q26: Yes | R26: Yes | S26: =IF(N26<>"Yes","",IF(COUNTBLANK(P26:R26)=3,"",IF(COUNTIF(P26:R26,"No")>0,"EXCLUDE","INCLUDE"))) -> INCLUDE | T26: =IF(S26<>"EXCLUDE","",IF(P26="No","Digital Twin mentioned only, not the subject",IF(Q26="No","No Design for Safety/Quality in full text",IF(R26="No","Methodology not codable","")))) | U26: Tier 2 - Digital Shadow (one-way physical to virtual) | V26: 0 | W26: 0 | X26: 1 | Y26: =IF(SUM(V26:X26)=0,"",IF(SUM(V26:X26)>=2,"Multi","Single")) -> Single | Z26: Design for Safety (DfS) | AA26: Mentioned only | AB26: Other / Mixed | AC26: Single (one data type) | AD26: Single case study | AE26: 4 | AF26: Predictive analytics / decision support | AG26: 2-year in-service railway bridge pilot; unsupervised clustering of normal vibration + FEM-calibrated synthetic damage + LightGBM classifier (ROC-AUC 0.9999). SELF-IMPROVEMENT DOWNGRADED 2026-08-23 (slow full-text re-read, not keyword match): the "continuous learning through periodic retraining" wording sits in the GENERIC methodology (Step 7 of 7, Sec. 4.1.7), and the authors state "While not all seven steps were fully implemented for the pilot bridge in this work". The pilot sections (4.2) and Results (5) report ONE AutoML/MLflow training run on 8646 rows (60/20/20 split, best iteration 281, early stop 286) and no retraining event, no re-trained model, no accuracy-over-time series. The only adaptation actually reported - coping with seasonal vibration shifts - was an outlier filter whose "correction of this issue was carried out manually by accessing the sensors’ remote interfaces". Retraining is an architectural capability (Databricks/MLflow MLOps) that is described, not executed. AA = Mentioned only. [Full-text source: Endnote] | AH26: Demonstrates an operational digital twin for railway bridge SHM: low-cost wireless accelerometers (about EUR 300), hybrid edge-cloud processing with real-time FFT, unsupervised clustering of normal vibration, FEM-calibrated synthetic damage data, and a LightGBM classifier reaching ROC-AUC 0.9999 on two years of in-service vibration data from a bridge in the Basque Country. | AI26: Detection is anomaly-based rather than damage localization or quantification, which the authors list as future work; validation is limited to one short-span bridge pilot, and analytics still rely on middleware plus cloud, with plans to move FFT and inference onto energy-harvesting edge sensors and to extend to wind towers and broader production deployments. The advertised continuous-learning loop is never exercised: the paper concedes not all seven methodology steps were implemented for the pilot, reports a single model training, and handled the one observed distribution shift (seasonality) by a manual sensor-offset correction. | AJ26: Single | AK26: Only ambient-vibration time series from wireless accelerometers feed the analytics; FEM-calibrated synthetic damage is model-generated training data, not a second measured data type. | AL26: High | AM26: RESOLVED 2026-08-23: AA Implemented -> Mentioned only. Re-read of full text shows the periodic-retraining loop belongs to the generic 7-step reference methodology, which the authors say was not fully implemented for the pilot; no retraining is executed or measured anywhere in Sec. 4.2 or Sec. 5. | AN26: Verified 2026-08-22 vs PDF (Sensors 2024, 24, 2115). ROC-AUC 0.9999 and 2-year in-service pilot confirmed. RE-VERIFIED 2026-08-23 (self-improvement audit, full text, not keyword search): AA=Implemented OVERTURNED. The retraining language is confined to Sec. 4.1.7 of the GENERIC methodology; Sec. 4.1 states verbatim "While not all seven steps were fully implemented for the pilot bridge in this work" and "Validation and continuous learning" is step 7. The pilot (Sec. 4.2) and Results (Sec. 5) document a single Databricks AutoML/MLflow experiment (8646 rows, 60/20/20) with no repeat training, no updated model version and no performance-over-time evidence; the sole reported adaptation to seasonal drift was a manual sensor-offset correction. AA corrected to Mentioned only. | AO26: =IF($A26="","",IFERROR(_xlfn.XLOOKUP($A26,'2_DOI_Lookup'!$A$2:$A$430,'2_DOI_Lookup'!$B$2:$B$430),"NOT IN SOURCE")) -> 10.3390/s24072115
A27: 3975 | B27: Aroquipa (2025) | C27: 2025 | E27: =IF($A27="","",IFERROR(_xlfn.XLOOKUP($A27,'2_DOI_Lookup'!$D$2:$D$430,'2_DOI_Lookup'!$E$2:$E$430),"TITLE NOT IN SOURCE")) -> Methodological framework for integrating structural health monitoring and digital-twin models for seismic assessment of heritage buildings: Case study of Basilica Maria Auxiliadora, Lima, Peru | F27: Web of Science | G27: Yes | H27: Yes | I27: Yes | J27: Yes | K27: Yes | L27: =IF(COUNTBLANK(G27:K27)=5,"",IF(COUNTIF(G27:K27,"No")>0,"EXCLUDE","INCLUDE")) -> INCLUDE | M27: =IF(L27<>"EXCLUDE","",IF(G27="No","Wrong domain (non-AECO)",IF(H27="No","Digital Twin not core / buzzword",IF(I27="No","No Design for Safety/Quality/PtD",IF(J27="No","Wrong publication type",IF(K27="No","Non-English","")))))) | N27: Yes | O27: Yes | P27: Yes | Q27: Yes | R27: Yes | S27: =IF(N27<>"Yes","",IF(COUNTBLANK(P27:R27)=3,"",IF(COUNTIF(P27:R27,"No")>0,"EXCLUDE","INCLUDE"))) -> INCLUDE | T27: =IF(S27<>"EXCLUDE","",IF(P27="No","Digital Twin mentioned only, not the subject",IF(Q27="No","No Design for Safety/Quality in full text",IF(R27="No","Methodology not codable","")))) | U27: Tier 1 - Digital Model (static, no live data) | V27: 0 | W27: 0 | X27: 1 | Y27: =IF(SUM(V27:X27)=0,"",IF(SUM(V27:X27)>=2,"Multi","Single")) -> Single | Z27: Design for Safety (DfS) | AA27: None | AB27: Finite Element Method / physics-based | AC27: Multi (two or more data types) | AD27: Conceptual (no test) | AE27: 4 | AF27: BIM-to-Digital-Twin architecture | AG27: Methodological framework for integrating SHM with numerical DT models for seismic assessment of heritage buildings (Basilica Maria Auxiliadora, Lima): numerical models in 3DEC and SAP2000 (modal + time-history of 34 seismic ground-motion records) identify susceptible zones and recommended sensor locations; sensor deployment and validation against experimental models are explicitly future work - no DT implemented, no live data link, no learning loop. [Full-text source: Endnote] | AH27: Provides a methodology for integrating SHM with numerical DT models for seismic assessment of heritage buildings: a LiDAR-derived BIM of the Basilica Maria Auxiliadora in Lima fed calibrated SAP2000 and 3DEC models (about 4500 block elements, 161000 contact zones), modal analysis with 220 modes, time-history analysis reproducing the 2007 Pisco earthquake crack patterns, and 25 sensor control points selected via intensity-duration-frequency plots. | AI27: No sensors are yet deployed: the study covers only Building Virtualization and part of sensor data analysis, so the EWS and DT feedback loop remain pending; validation relies on historical damage reports and analytical consistency, with future research to include experimental models, tri-axial sensor installation, and ambient-vibration calibration of the numerical model. | AJ27: Aligned | AK27: The LiDAR point-cloud survey is converted into a BIM that is linked to the 3DEC/SAP2000 FEM models through an explicit BIM-FEM linking process, sharing one building geometry frame while each model analyses separately. | AL27: Medium | AN27: Verified 2026-08-22 vs PDF (Structures). 3DEC and SAP2000 models, "modal and time-history analyses for a set of 34 seismic ground motion records", and Basilica Maria Auxiliadora (Lima, Peru) all confirmed. Sensor integration and AVT-based calibration explicitly deferred: "AVT-based calibration will be considered in future work during the sensor integration phase" - Tier 1, AD Conceptual, AA None upheld. | AO27: =IF($A27="","",IFERROR(_xlfn.XLOOKUP($A27,'2_DOI_Lookup'!$A$2:$A$430,'2_DOI_Lookup'!$B$2:$B$430),"NOT IN SOURCE")) -> 10.1016/j.istruc.2025.110115
A28: 3996 | B28: Arowoiya (2024) | C28: 2024 | E28: =IF($A28="","",IFERROR(_xlfn.XLOOKUP($A28,'2_DOI_Lookup'!$D$2:$D$430,'2_DOI_Lookup'!$E$2:$E$430),"TITLE NOT IN SOURCE")) -> Driving Factors for the Adoption of Digital Twin Technology Implementation for Construction Project Performance in Nigeria | F28: Web of Science | G28: Yes | H28: Yes | I28: Yes | J28: Yes | K28: Yes | L28: =IF(COUNTBLANK(G28:K28)=5,"",IF(COUNTIF(G28:K28,"No")>0,"EXCLUDE","INCLUDE")) -> INCLUDE | M28: =IF(L28<>"EXCLUDE","",IF(G28="No","Wrong domain (non-AECO)",IF(H28="No","Digital Twin not core / buzzword",IF(I28="No","No Design for Safety/Quality/PtD",IF(J28="No","Wrong publication type",IF(K28="No","Non-English","")))))) | N28: Yes | O28: Yes | P28: No | Q28: Yes | R28: Yes | S28: =IF(N28<>"Yes","",IF(COUNTBLANK(P28:R28)=3,"",IF(COUNTIF(P28:R28,"No")>0,"EXCLUDE","INCLUDE"))) -> EXCLUDE | T28: =IF(S28<>"EXCLUDE","",IF(P28="No","Digital Twin mentioned only, not the subject",IF(Q28="No","No Design for Safety/Quality in full text",IF(R28="No","Methodology not codable","")))) -> Digital Twin mentioned only, not the subject | U28: Unclear | Y28: =IF(SUM(V28:X28)=0,"",IF(SUM(V28:X28)>=2,"Multi","Single")) | AG28: Questionnaire survey (Nigerian construction professionals, purposive+snowball) of drivers for adopting DTT; Shapiro-Wilk + Kruskal-Wallis H + factor analysis grouping drivers into innovation/operation/quality/performance/policy. No digital twin is built, evaluated or framed as a system — DT only appears as the technology whose adoption is surveyed. P=No → Stage-2 exclude. [Full-text source: Endnote] | AN28: Verified 2026-08-22 vs PDF (ASCE). Close-ended questionnaires to Nigerian professionals via purposive and snowball sampling, Shapiro-Wilk and Kruskal-Wallis analysis; no DT built or evaluated. Stage-2 EXCLUDE (P=No) upheld. | AO28: =IF($A28="","",IFERROR(_xlfn.XLOOKUP($A28,'2_DOI_Lookup'!$A$2:$A$430,'2_DOI_Lookup'!$B$2:$B$430),"NOT IN SOURCE")) -> 10.1061/JCEMD4.COENG-13659
A29: 4030 | E29: =IF($A29="","",IFERROR(_xlfn.XLOOKUP($A29,'2_DOI_Lookup'!$D$2:$D$430,'2_DOI_Lookup'!$E$2:$E$430),"TITLE NOT IN SOURCE")) -> Excavator 3D pose estimation using deep learning and hybrid datasets | F29: Web of Science | G29: Yes | H29: No | I29: Yes | J29: Yes | K29: Yes | L29: =IF(COUNTBLANK(G29:K29)=5,"",IF(COUNTIF(G29:K29,"No")>0,"EXCLUDE","INCLUDE")) -> EXCLUDE | M29: =IF(L29<>"EXCLUDE","",IF(G29="No","Wrong domain (non-AECO)",IF(H29="No","Digital Twin not core / buzzword",IF(I29="No","No Design for Safety/Quality/PtD",IF(J29="No","Wrong publication type",IF(K29="No","Non-English","")))))) -> Digital Twin not core / buzzword | S29: =IF(N29<>"Yes","",IF(COUNTBLANK(P29:R29)=3,"",IF(COUNTIF(P29:R29,"No")>0,"EXCLUDE","INCLUDE"))) | T29: =IF(S29<>"EXCLUDE","",IF(P29="No","Digital Twin mentioned only, not the subject",IF(Q29="No","No Design for Safety/Quality in full text",IF(R29="No","Methodology not codable","")))) | Y29: =IF(SUM(V29:X29)=0,"",IF(SUM(V29:X29)>=2,"Multi","Single")) | AG29: CV pose estimation; DT only synthesizes training data | AO29: =IF($A29="","",IFERROR(_xlfn.XLOOKUP($A29,'2_DOI_Lookup'!$A$2:$A$430,'2_DOI_Lookup'!$B$2:$B$430),"NOT IN SOURCE")) -> 10.1016/j.aei.2023.101875
A30: 3982 | E30: =IF($A30="","",IFERROR(_xlfn.XLOOKUP($A30,'2_DOI_Lookup'!$D$2:$D$430,'2_DOI_Lookup'!$E$2:$E$430),"TITLE NOT IN SOURCE")) -> Integrating Web-Based Weather Data into Building Information Modeling Models through Robot Process Automation | F30: Web of Science | G30: Yes | H30: No | I30: Yes | J30: Yes | K30: Yes | L30: =IF(COUNTBLANK(G30:K30)=5,"",IF(COUNTIF(G30:K30,"No")>0,"EXCLUDE","INCLUDE")) -> EXCLUDE | M30: =IF(L30<>"EXCLUDE","",IF(G30="No","Wrong domain (non-AECO)",IF(H30="No","Digital Twin not core / buzzword",IF(I30="No","No Design for Safety/Quality/PtD",IF(J30="No","Wrong publication type",IF(K30="No","Non-English","")))))) -> Digital Twin not core / buzzword | S30: =IF(N30<>"Yes","",IF(COUNTBLANK(P30:R30)=3,"",IF(COUNTIF(P30:R30,"No")>0,"EXCLUDE","INCLUDE"))) | T30: =IF(S30<>"EXCLUDE","",IF(P30="No","Digital Twin mentioned only, not the subject",IF(Q30="No","No Design for Safety/Quality in full text",IF(R30="No","Methodology not codable","")))) | Y30: =IF(SUM(V30:X30)=0,"",IF(SUM(V30:X30)>=2,"Multi","Single")) | AG30: BIM+RPA weather alerts; static BIM, no live DT | AO30: =IF($A30="","",IFERROR(_xlfn.XLOOKUP($A30,'2_DOI_Lookup'!$A$2:$A$430,'2_DOI_Lookup'!$B$2:$B$430),"NOT IN SOURCE")) -> 10.3390/app14199109
A31: 3940 | E31: =IF($A31="","",IFERROR(_xlfn.XLOOKUP($A31,'2_DOI_Lookup'!$D$2:$D$430,'2_DOI_Lookup'!$E$2:$E$430),"TITLE NOT IN SOURCE")) -> Circular economy in construction: The digital transformation perspective | F31: Web of Science | G31: Yes | H31: No | I31: No | J31: Yes | K31: Yes | L31: =IF(COUNTBLANK(G31:K31)=5,"",IF(COUNTIF(G31:K31,"No")>0,"EXCLUDE","INCLUDE")) -> EXCLUDE | M31: =IF(L31<>"EXCLUDE","",IF(G31="No","Wrong domain (non-AECO)",IF(H31="No","Digital Twin not core / buzzword",IF(I31="No","No Design for Safety/Quality/PtD",IF(J31="No","Wrong publication type",IF(K31="No","Non-English","")))))) -> Digital Twin not core / buzzword | S31: =IF(N31<>"Yes","",IF(COUNTBLANK(P31:R31)=3,"",IF(COUNTIF(P31:R31,"No")>0,"EXCLUDE","INCLUDE"))) | T31: =IF(S31<>"EXCLUDE","",IF(P31="No","Digital Twin mentioned only, not the subject",IF(Q31="No","No Design for Safety/Quality in full text",IF(R31="No","Methodology not codable","")))) | Y31: =IF(SUM(V31:X31)=0,"",IF(SUM(V31:X31)>=2,"Multi","Single")) | AG31: CE/digitalisation review; DT peripheral | AO31: =IF($A31="","",IFERROR(_xlfn.XLOOKUP($A31,'2_DOI_Lookup'!$A$2:$A$430,'2_DOI_Lookup'!$B$2:$B$430),"NOT IN SOURCE")) -> 10.1016/j.clet.2023.100715
A32: 4037 | B32: Bao (2026) | C32: 2026 | E32: =IF($A32="","",IFERROR(_xlfn.XLOOKUP($A32,'2_DOI_Lookup'!$D$2:$D$430,'2_DOI_Lookup'!$E$2:$E$430),"TITLE NOT IN SOURCE")) -> Intelligent technologies for tunnel construction and maintenance: A state-of-the-art review of methods and supporting platforms | F32: Web of Science | G32: Yes | H32: Yes | I32: Yes | J32: Yes | K32: Yes | L32: =IF(COUNTBLANK(G32:K32)=5,"",IF(COUNTIF(G32:K32,"No")>0,"EXCLUDE","INCLUDE")) -> INCLUDE | M32: =IF(L32<>"EXCLUDE","",IF(G32="No","Wrong domain (non-AECO)",IF(H32="No","Digital Twin not core / buzzword",IF(I32="No","No Design for Safety/Quality/PtD",IF(J32="No","Wrong publication type",IF(K32="No","Non-English","")))))) | N32: Yes | O32: Yes | P32: No | Q32: Yes | R32: Yes | S32: =IF(N32<>"Yes","",IF(COUNTBLANK(P32:R32)=3,"",IF(COUNTIF(P32:R32,"No")>0,"EXCLUDE","INCLUDE"))) -> EXCLUDE | T32: =IF(S32<>"EXCLUDE","",IF(P32="No","Digital Twin mentioned only, not the subject",IF(Q32="No","No Design for Safety/Quality in full text",IF(R32="No","Methodology not codable","")))) -> Digital Twin mentioned only, not the subject | U32: Unclear | Y32: =IF(SUM(V32:X32)=0,"",IF(SUM(V32:X32)>=2,"Multi","Single")) | AG32: State-of-the-art review of intelligent tunnel construction & O&M technologies (IoT, big data, AI, platforms) across design/construction/O&M; digital twins appear as one component (geological DTs, future DT co-simulation) but are not the actual subject of the paper. P=No → Stage-2 exclude. Safety/risk is a genuine theme (construction safety, real-time risk analysis). [Full-text source: Endnote] | AN32: Verified 2026-08-22 vs PDF (Tunnelling and Underground Space Technology 168:107207). Title confirms "A state-of-the-art review of methods and supporting platforms"; digital twins appear as one component among many rather than the subject. Stage-2 EXCLUDE (P=No) upheld. | AO32: =IF($A32="","",IFERROR(_xlfn.XLOOKUP($A32,'2_DOI_Lookup'!$A$2:$A$430,'2_DOI_Lookup'!$B$2:$B$430),"NOT IN SOURCE")) -> 10.1016/j.tust.2025.107207
A33: 3551 | E33: =IF($A33="","",IFERROR(_xlfn.XLOOKUP($A33,'2_DOI_Lookup'!$D$2:$D$430,'2_DOI_Lookup'!$E$2:$E$430),"TITLE NOT IN SOURCE")) -> Improving Organizational and Engineering Reliability during Dismantling of Buildings | F33: Scopus | G33: Yes | H33: No | I33: Yes | J33: Yes | K33: No | L33: =IF(COUNTBLANK(G33:K33)=5,"",IF(COUNTIF(G33:K33,"No")>0,"EXCLUDE","INCLUDE")) -> EXCLUDE | M33: =IF(L33<>"EXCLUDE","",IF(G33="No","Wrong domain (non-AECO)",IF(H33="No","Digital Twin not core / buzzword",IF(I33="No","No Design for Safety/Quality/PtD",IF(J33="No","Wrong publication type",IF(K33="No","Non-English","")))))) -> Digital Twin not core / buzzword | S33: =IF(N33<>"Yes","",IF(COUNTBLANK(P33:R33)=3,"",IF(COUNTIF(P33:R33,"No")>0,"EXCLUDE","INCLUDE"))) | T33: =IF(S33<>"EXCLUDE","",IF(P33="No","Digital Twin mentioned only, not the subject",IF(Q33="No","No Design for Safety/Quality in full text",IF(R33="No","Methodology not codable","")))) | Y33: =IF(SUM(V33:X33)=0,"",IF(SUM(V33:X33)>=2,"Multi","Single")) | AG33: Russian journal; BIM/DT mentioned, full text non-English | AO33: =IF($A33="","",IFERROR(_xlfn.XLOOKUP($A33,'2_DOI_Lookup'!$A$2:$A$430,'2_DOI_Lookup'!$B$2:$B$430),"NOT IN SOURCE")) -> 10.24000/0409-2961-2025-10-72-79
A34: 3571 | E34: =IF($A34="","",IFERROR(_xlfn.XLOOKUP($A34,'2_DOI_Lookup'!$D$2:$D$430,'2_DOI_Lookup'!$E$2:$E$430),"TITLE NOT IN SOURCE")) -> The Process of Digitalization of the Urban Environment for the Development of Sustainable and Circular Cities: A Case Study of Bologna, Italy | F34: Scopus | G34: Yes | H34: No | I34: No | J34: Yes | K34: Yes | L34: =IF(COUNTBLANK(G34:K34)=5,"",IF(COUNTIF(G34:K34,"No")>0,"EXCLUDE","INCLUDE")) -> EXCLUDE | M34: =IF(L34<>"EXCLUDE","",IF(G34="No","Wrong domain (non-AECO)",IF(H34="No","Digital Twin not core / buzzword",IF(I34="No","No Design for Safety/Quality/PtD",IF(J34="No","Wrong publication type",IF(K34="No","Non-English","")))))) -> Digital Twin not core / buzzword | S34: =IF(N34<>"Yes","",IF(COUNTBLANK(P34:R34)=3,"",IF(COUNTIF(P34:R34,"No")>0,"EXCLUDE","INCLUDE"))) | T34: =IF(S34<>"EXCLUDE","",IF(P34="No","Digital Twin mentioned only, not the subject",IF(Q34="No","No Design for Safety/Quality in full text",IF(R34="No","Methodology not codable","")))) | Y34: =IF(SUM(V34:X34)=0,"",IF(SUM(V34:X34)>=2,"Multi","Single")) | AG34: Urban regeneration protocol; DT as future archive | AO34: =IF($A34="","",IFERROR(_xlfn.XLOOKUP($A34,'2_DOI_Lookup'!$A$2:$A$430,'2_DOI_Lookup'!$B$2:$B$430),"NOT IN SOURCE")) -> 10.3390/su142113740
A35: 3707 | E35: =IF($A35="","",IFERROR(_xlfn.XLOOKUP($A35,'2_DOI_Lookup'!$D$2:$D$430,'2_DOI_Lookup'!$E$2:$E$430),"TITLE NOT IN SOURCE")) -> Construction and application of digital twin system for coal ports | F35: Scopus | G35: No | H35: Yes | I35: Yes | J35: Yes | K35: No | L35: =IF(COUNTBLANK(G35:K35)=5,"",IF(COUNTIF(G35:K35,"No")>0,"EXCLUDE","INCLUDE")) -> EXCLUDE | M35: =IF(L35<>"EXCLUDE","",IF(G35="No","Wrong domain (non-AECO)",IF(H35="No","Digital Twin not core / buzzword",IF(I35="No","No Design for Safety/Quality/PtD",IF(J35="No","Wrong publication type",IF(K35="No","Non-English","")))))) -> Wrong domain (non-AECO) | S35: =IF(N35<>"Yes","",IF(COUNTBLANK(P35:R35)=3,"",IF(COUNTIF(P35:R35,"No")>0,"EXCLUDE","INCLUDE"))) | T35: =IF(S35<>"EXCLUDE","",IF(P35="No","Digital Twin mentioned only, not the subject",IF(Q35="No","No Design for Safety/Quality in full text",IF(R35="No","Methodology not codable","")))) | Y35: =IF(SUM(V35:X35)=0,"",IF(SUM(V35:X35)>=2,"Multi","Single")) | AG35: Industrial port ops; Chinese journal, non-English | AO35: =IF($A35="","",IFERROR(_xlfn.XLOOKUP($A35,'2_DOI_Lookup'!$A$2:$A$430,'2_DOI_Lookup'!$B$2:$B$430),"NOT IN SOURCE")) -> 0
A36: 3613 | E36: =IF($A36="","",IFERROR(_xlfn.XLOOKUP($A36,'2_DOI_Lookup'!$D$2:$D$430,'2_DOI_Lookup'!$E$2:$E$430),"TITLE NOT IN SOURCE")) -> Incorporation of pre-existing longitudinal cracks in finite element analyses of corroded reinforced concrete beams failing in anchorage | F36: Scopus | G36: Yes | H36: No | I36: Yes | J36: Yes | K36: Yes | L36: =IF(COUNTBLANK(G36:K36)=5,"",IF(COUNTIF(G36:K36,"No")>0,"EXCLUDE","INCLUDE")) -> EXCLUDE | M36: =IF(L36<>"EXCLUDE","",IF(G36="No","Wrong domain (non-AECO)",IF(H36="No","Digital Twin not core / buzzword",IF(I36="No","No Design for Safety/Quality/PtD",IF(J36="No","Wrong publication type",IF(K36="No","Non-English","")))))) -> Digital Twin not core / buzzword | S36: =IF(N36<>"Yes","",IF(COUNTBLANK(P36:R36)=3,"",IF(COUNTIF(P36:R36,"No")>0,"EXCLUDE","INCLUDE"))) | T36: =IF(S36<>"EXCLUDE","",IF(P36="No","Digital Twin mentioned only, not the subject",IF(Q36="No","No Design for Safety/Quality in full text",IF(R36="No","Methodology not codable","")))) | Y36: =IF(SUM(V36:X36)=0,"",IF(SUM(V36:X36)>=2,"Multi","Single")) | AG36: Pure FEM structural analysis; no DT | AO36: =IF($A36="","",IFERROR(_xlfn.XLOOKUP($A36,'2_DOI_Lookup'!$A$2:$A$430,'2_DOI_Lookup'!$B$2:$B$430),"NOT IN SOURCE")) -> 10.1080/15732479.2020.1782444
A37: 3645 | E37: =IF($A37="","",IFERROR(_xlfn.XLOOKUP($A37,'2_DOI_Lookup'!$D$2:$D$430,'2_DOI_Lookup'!$E$2:$E$430),"TITLE NOT IN SOURCE")) -> The evolution of BIM work standards: current, best, and future practices from a BIM Manager's perspective | F37: Scopus | G37: Yes | H37: No | I37: No | J37: Yes | K37: Yes | L37: =IF(COUNTBLANK(G37:K37)=5,"",IF(COUNTIF(G37:K37,"No")>0,"EXCLUDE","INCLUDE")) -> EXCLUDE | M37: =IF(L37<>"EXCLUDE","",IF(G37="No","Wrong domain (non-AECO)",IF(H37="No","Digital Twin not core / buzzword",IF(I37="No","No Design for Safety/Quality/PtD",IF(J37="No","Wrong publication type",IF(K37="No","Non-English","")))))) -> Digital Twin not core / buzzword | S37: =IF(N37<>"Yes","",IF(COUNTBLANK(P37:R37)=3,"",IF(COUNTIF(P37:R37,"No")>0,"EXCLUDE","INCLUDE"))) | T37: =IF(S37<>"EXCLUDE","",IF(P37="No","Digital Twin mentioned only, not the subject",IF(Q37="No","No Design for Safety/Quality in full text",IF(R37="No","Methodology not codable","")))) | Y37: =IF(SUM(V37:X37)=0,"",IF(SUM(V37:X37)>=2,"Multi","Single")) | AG37: BIM-manager narrative review; no DT core | AO37: =IF($A37="","",IFERROR(_xlfn.XLOOKUP($A37,'2_DOI_Lookup'!$A$2:$A$430,'2_DOI_Lookup'!$B$2:$B$430),"NOT IN SOURCE")) -> 10.35784/bud-arch.9187
A38: 3807 | E38: =IF($A38="","",IFERROR(_xlfn.XLOOKUP($A38,'2_DOI_Lookup'!$D$2:$D$430,'2_DOI_Lookup'!$E$2:$E$430),"TITLE NOT IN SOURCE")) -> Railway condition information modelling in a BIM framework for maintenance applications | F38: Scopus | G38: Yes | H38: No | I38: Yes | J38: Yes | K38: Yes | L38: =IF(COUNTBLANK(G38:K38)=5,"",IF(COUNTIF(G38:K38,"No")>0,"EXCLUDE","INCLUDE")) -> EXCLUDE | M38: =IF(L38<>"EXCLUDE","",IF(G38="No","Wrong domain (non-AECO)",IF(H38="No","Digital Twin not core / buzzword",IF(I38="No","No Design for Safety/Quality/PtD",IF(J38="No","Wrong publication type",IF(K38="No","Non-English","")))))) -> Digital Twin not core / buzzword | S38: =IF(N38<>"Yes","",IF(COUNTBLANK(P38:R38)=3,"",IF(COUNTIF(P38:R38,"No")>0,"EXCLUDE","INCLUDE"))) | T38: =IF(S38<>"EXCLUDE","",IF(P38="No","Digital Twin mentioned only, not the subject",IF(Q38="No","No Design for Safety/Quality in full text",IF(R38="No","Methodology not codable","")))) | Y38: =IF(SUM(V38:X38)=0,"",IF(SUM(V38:X38)>=2,"Multi","Single")) | AG38: I-BIM maintenance framework; DT aspirational | AO38: =IF($A38="","",IFERROR(_xlfn.XLOOKUP($A38,'2_DOI_Lookup'!$A$2:$A$430,'2_DOI_Lookup'!$B$2:$B$430),"NOT IN SOURCE")) -> 10.1080/23248378.2024.2397660
A39: 3595 | B39: Brucherseifer (2021) | C39: 2021 | E39: =IF($A39="","",IFERROR(_xlfn.XLOOKUP($A39,'2_DOI_Lookup'!$D$2:$D$430,'2_DOI_Lookup'!$E$2:$E$430),"TITLE NOT IN SOURCE")) -> Digital Twin conceptual framework for improving critical infrastructure resilience | F39: Scopus | G39: Yes | H39: Yes | I39: Yes | J39: Yes | K39: Yes | L39: =IF(COUNTBLANK(G39:K39)=5,"",IF(COUNTIF(G39:K39,"No")>0,"EXCLUDE","INCLUDE")) -> INCLUDE | M39: =IF(L39<>"EXCLUDE","",IF(G39="No","Wrong domain (non-AECO)",IF(H39="No","Digital Twin not core / buzzword",IF(I39="No","No Design for Safety/Quality/PtD",IF(J39="No","Wrong publication type",IF(K39="No","Non-English","")))))) | N39: Yes | O39: Yes | P39: Yes | Q39: Yes | R39: Yes | S39: =IF(N39<>"Yes","",IF(COUNTBLANK(P39:R39)=3,"",IF(COUNTIF(P39:R39,"No")>0,"EXCLUDE","INCLUDE"))) -> INCLUDE | T39: =IF(S39<>"EXCLUDE","",IF(P39="No","Digital Twin mentioned only, not the subject",IF(Q39="No","No Design for Safety/Quality in full text",IF(R39="No","Methodology not codable","")))) | U39: Tier 1 - Digital Model (static, no live data) | V39: 0 | W39: 0 | X39: 1 | Y39: =IF(SUM(V39:X39)=0,"",IF(SUM(V39:X39)>=2,"Multi","Single")) -> Single | Z39: Design for Safety (DfS) | AA39: None | AB39: Digital Twin platform (no machine learning) | AC39: Multi (two or more data types) | AD39: Conceptual (no test) | AE39: 3 | AF39: Lifecycle / governance | AG39: Digital Twin Conceptual Framework for critical infrastructure resilience (DLR): comprehensive requirements analysis for infrastructure crisis management/resilience, deriving a conceptual framework (virtual replica, virtual clones, smart-tool toolbox, human-operated control center) with guiding principles for construction/planning phases and a conceptual DT model; resilience cycle with learning from past events is discussed conceptually but not implemented; no DT built or validated, no learning loop. [Full-text source: Endnote] | AH39: Derives a comprehensive requirements analysis for critical infrastructure crisis management and resilience and maps it onto a Digital Twin Conceptual Framework with four guiding principles (human-in-the-loop control, parsimony with accepted uncertainty, preparedness for complexity and emergence, safe experiments and training) plus a conceptual model of virtual replica, clones, toolbox, and control center. | AI39: Entirely conceptual: no implementation, prototype, or case evaluation is presented, so none of the requirements or tools is tested. The authors list open challenges of integrating uncertain data sources and heterogeneous models, evaluating intelligent tools for the resilience cycle, and IT scalability and reliability, proposing federated digital twins instead of monolithic implementations. | AJ39: Unclear | AK39: Conceptual resilience framework for critical infrastructure; no implementation, prototype or case evaluation, so no integration mechanism can be identified. | AL39: High | AN39: Verified 2026-08-22 vs PDF (at-Automatisierungstechnik 69(12):1062-1080). Requirements analysis mapped to a DT conceptual framework with virtual clones and control centre; no implementation or case evaluation. Tier 1, AA None, AD Conceptual upheld. | AO39: =IF($A39="","",IFERROR(_xlfn.XLOOKUP($A39,'2_DOI_Lookup'!$A$2:$A$430,'2_DOI_Lookup'!$B$2:$B$430),"NOT IN SOURCE")) -> 10.1515/auto-2021-0104
A40: 3888 | E40: =IF($A40="","",IFERROR(_xlfn.XLOOKUP($A40,'2_DOI_Lookup'!$D$2:$D$430,'2_DOI_Lookup'!$E$2:$E$430),"TITLE NOT IN SOURCE")) -> From BIM to Web3: A critical interpretive synthesis of present and emerging data management approaches in construction informatics | F40: Web of Science | G40: Yes | H40: No | I40: No | J40: Yes | K40: Yes | L40: =IF(COUNTBLANK(G40:K40)=5,"",IF(COUNTIF(G40:K40,"No")>0,"EXCLUDE","INCLUDE")) -> EXCLUDE | M40: =IF(L40<>"EXCLUDE","",IF(G40="No","Wrong domain (non-AECO)",IF(H40="No","Digital Twin not core / buzzword",IF(I40="No","No Design for Safety/Quality/PtD",IF(J40="No","Wrong publication type",IF(K40="No","Non-English","")))))) -> Digital Twin not core / buzzword | S40: =IF(N40<>"Yes","",IF(COUNTBLANK(P40:R40)=3,"",IF(COUNTIF(P40:R40,"No")>0,"EXCLUDE","INCLUDE"))) | T40: =IF(S40<>"EXCLUDE","",IF(P40="No","Digital Twin mentioned only, not the subject",IF(Q40="No","No Design for Safety/Quality in full text",IF(R40="No","Methodology not codable","")))) | Y40: =IF(SUM(V40:X40)=0,"",IF(SUM(V40:X40)>=2,"Multi","Single")) | AG40: Data-management review; no DT core, no safety/quality | AO40: =IF($A40="","",IFERROR(_xlfn.XLOOKUP($A40,'2_DOI_Lookup'!$A$2:$A$430,'2_DOI_Lookup'!$B$2:$B$430),"NOT IN SOURCE")) -> 10.1016/j.aei.2024.102884
A41: 3869 | E41: =IF($A41="","",IFERROR(_xlfn.XLOOKUP($A41,'2_DOI_Lookup'!$D$2:$D$430,'2_DOI_Lookup'!$E$2:$E$430),"TITLE NOT IN SOURCE")) -> Affective computing in smart city spaces: Research on emotion recognition and response mechanisms under a digital twin framework | F41: Scopus | G41: No | H41: No | I41: No | J41: Yes | K41: Yes | L41: =IF(COUNTBLANK(G41:K41)=5,"",IF(COUNTIF(G41:K41,"No")>0,"EXCLUDE","INCLUDE")) -> EXCLUDE | M41: =IF(L41<>"EXCLUDE","",IF(G41="No","Wrong domain (non-AECO)",IF(H41="No","Digital Twin not core / buzzword",IF(I41="No","No Design for Safety/Quality/PtD",IF(J41="No","Wrong publication type",IF(K41="No","Non-English","")))))) -> Wrong domain (non-AECO) | S41: =IF(N41<>"Yes","",IF(COUNTBLANK(P41:R41)=3,"",IF(COUNTIF(P41:R41,"No")>0,"EXCLUDE","INCLUDE"))) | T41: =IF(S41<>"EXCLUDE","",IF(P41="No","Digital Twin mentioned only, not the subject",IF(Q41="No","No Design for Safety/Quality in full text",IF(R41="No","Methodology not codable","")))) | Y41: =IF(SUM(V41:X41)=0,"",IF(SUM(V41:X41)>=2,"Multi","Single")) | AG41: Emotion recognition; no built asset, no safety/quality | AO41: =IF($A41="","",IFERROR(_xlfn.XLOOKUP($A41,'2_DOI_Lookup'!$A$2:$A$430,'2_DOI_Lookup'!$B$2:$B$430),"NOT IN SOURCE")) -> 10.1016/j.ijcce.2026.04.001
A42: 3702 | E42: =IF($A42="","",IFERROR(_xlfn.XLOOKUP($A42,'2_DOI_Lookup'!$D$2:$D$430,'2_DOI_Lookup'!$E$2:$E$430),"TITLE NOT IN SOURCE")) -> TunnelSDF-FilterNet: A Domain-Aware Neural Framework for High-Fidelity 3D Reconstruction of Railway Tunnels | F42: Scopus | G42: Yes | H42: No | I42: Yes | J42: Yes | K42: Yes | L42: =IF(COUNTBLANK(G42:K42)=5,"",IF(COUNTIF(G42:K42,"No")>0,"EXCLUDE","INCLUDE")) -> EXCLUDE | M42: =IF(L42<>"EXCLUDE","",IF(G42="No","Wrong domain (non-AECO)",IF(H42="No","Digital Twin not core / buzzword",IF(I42="No","No Design for Safety/Quality/PtD",IF(J42="No","Wrong publication type",IF(K42="No","Non-English","")))))) -> Digital Twin not core / buzzword | S42: =IF(N42<>"Yes","",IF(COUNTBLANK(P42:R42)=3,"",IF(COUNTIF(P42:R42,"No")>0,"EXCLUDE","INCLUDE"))) | T42: =IF(S42<>"EXCLUDE","",IF(P42="No","Digital Twin mentioned only, not the subject",IF(Q42="No","No Design for Safety/Quality in full text",IF(R42="No","Methodology not codable","")))) | Y42: =IF(SUM(V42:X42)=0,"",IF(SUM(V42:X42)>=2,"Multi","Single")) | AG42: Neural-SDF reconstruction; DT only downstream use | AO42: =IF($A42="","",IFERROR(_xlfn.XLOOKUP($A42,'2_DOI_Lookup'!$A$2:$A$430,'2_DOI_Lookup'!$B$2:$B$430),"NOT IN SOURCE")) -> 10.1007/s40864-026-00273-z
A43: 3901 | E43: =IF($A43="","",IFERROR(_xlfn.XLOOKUP($A43,'2_DOI_Lookup'!$D$2:$D$430,'2_DOI_Lookup'!$E$2:$E$430),"TITLE NOT IN SOURCE")) -> Methodology for 3D Management of University Faculties Using Integrated GIS and BIM Models: A Case Study | F43: Web of Science | G43: Yes | H43: No | I43: No | J43: Yes | K43: Yes | L43: =IF(COUNTBLANK(G43:K43)=5,"",IF(COUNTIF(G43:K43,"No")>0,"EXCLUDE","INCLUDE")) -> EXCLUDE | M43: =IF(L43<>"EXCLUDE","",IF(G43="No","Wrong domain (non-AECO)",IF(H43="No","Digital Twin not core / buzzword",IF(I43="No","No Design for Safety/Quality/PtD",IF(J43="No","Wrong publication type",IF(K43="No","Non-English","")))))) -> Digital Twin not core / buzzword | S43: =IF(N43<>"Yes","",IF(COUNTBLANK(P43:R43)=3,"",IF(COUNTIF(P43:R43,"No")>0,"EXCLUDE","INCLUDE"))) | T43: =IF(S43<>"EXCLUDE","",IF(P43="No","Digital Twin mentioned only, not the subject",IF(Q43="No","No Design for Safety/Quality in full text",IF(R43="No","Methodology not codable","")))) | Y43: =IF(SUM(V43:X43)=0,"",IF(SUM(V43:X43)>=2,"Multi","Single")) | AG43: Static GIS-BIM/CMMS-3D; no live DT | AO43: =IF($A43="","",IFERROR(_xlfn.XLOOKUP($A43,'2_DOI_Lookup'!$A$2:$A$430,'2_DOI_Lookup'!$B$2:$B$430),"NOT IN SOURCE")) -> 10.3390/buildings14113547
A44: 3889 | E44: =IF($A44="","",IFERROR(_xlfn.XLOOKUP($A44,'2_DOI_Lookup'!$D$2:$D$430,'2_DOI_Lookup'!$E$2:$E$430),"TITLE NOT IN SOURCE")) -> Integration of BIM Tools for the Facility Management of Railway Bridges | F44: Web of Science | G44: Yes | H44: No | I44: Yes | J44: Yes | K44: Yes | L44: =IF(COUNTBLANK(G44:K44)=5,"",IF(COUNTIF(G44:K44,"No")>0,"EXCLUDE","INCLUDE")) -> EXCLUDE | M44: =IF(L44<>"EXCLUDE","",IF(G44="No","Wrong domain (non-AECO)",IF(H44="No","Digital Twin not core / buzzword",IF(I44="No","No Design for Safety/Quality/PtD",IF(J44="No","Wrong publication type",IF(K44="No","Non-English","")))))) -> Digital Twin not core / buzzword | S44: =IF(N44<>"Yes","",IF(COUNTBLANK(P44:R44)=3,"",IF(COUNTIF(P44:R44,"No")>0,"EXCLUDE","INCLUDE"))) | T44: =IF(S44<>"EXCLUDE","",IF(P44="No","Digital Twin mentioned only, not the subject",IF(Q44="No","No Design for Safety/Quality in full text",IF(R44="No","Methodology not codable","")))) | Y44: =IF(SUM(V44:X44)=0,"",IF(SUM(V44:X44)>=2,"Multi","Single")) | AG44: BIM-Dynamo automation; initial step towards DT only | AO44: =IF($A44="","",IFERROR(_xlfn.XLOOKUP($A44,'2_DOI_Lookup'!$A$2:$A$430,'2_DOI_Lookup'!$B$2:$B$430),"NOT IN SOURCE")) -> 10.3390/app14146209
A45: 3555 | E45: =IF($A45="","",IFERROR(_xlfn.XLOOKUP($A45,'2_DOI_Lookup'!$D$2:$D$430,'2_DOI_Lookup'!$E$2:$E$430),"TITLE NOT IN SOURCE")) -> Climate Change Impacts on Reinforced Concrete Structures: A Bibliometric Analysis | F45: Scopus | G45: Yes | H45: No | I45: No | J45: Yes | K45: Yes | L45: =IF(COUNTBLANK(G45:K45)=5,"",IF(COUNTIF(G45:K45,"No")>0,"EXCLUDE","INCLUDE")) -> EXCLUDE | M45: =IF(L45<>"EXCLUDE","",IF(G45="No","Wrong domain (non-AECO)",IF(H45="No","Digital Twin not core / buzzword",IF(I45="No","No Design for Safety/Quality/PtD",IF(J45="No","Wrong publication type",IF(K45="No","Non-English","")))))) -> Digital Twin not core / buzzword | S45: =IF(N45<>"Yes","",IF(COUNTBLANK(P45:R45)=3,"",IF(COUNTIF(P45:R45,"No")>0,"EXCLUDE","INCLUDE"))) | T45: =IF(S45<>"EXCLUDE","",IF(P45="No","Digital Twin mentioned only, not the subject",IF(Q45="No","No Design for Safety/Quality in full text",IF(R45="No","Methodology not codable","")))) | Y45: =IF(SUM(V45:X45)=0,"",IF(SUM(V45:X45)>=2,"Multi","Single")) | AG45: Bibliometric; DT only a keyword trend | AO45: =IF($A45="","",IFERROR(_xlfn.XLOOKUP($A45,'2_DOI_Lookup'!$A$2:$A$430,'2_DOI_Lookup'!$B$2:$B$430),"NOT IN SOURCE")) -> 10.1080/10168664.2026.2649216
A46: 3658 | B46: Cervenka (2026) | C46: 2026 | E46: =IF($A46="","",IFERROR(_xlfn.XLOOKUP($A46,'2_DOI_Lookup'!$D$2:$D$430,'2_DOI_Lookup'!$E$2:$E$430),"TITLE NOT IN SOURCE")) -> AI based surrogate model for digital twins in structural health monitoring of reinforced concrete structures | F46: Scopus | G46: Yes | H46: Yes | I46: Yes | J46: Yes | K46: Yes | L46: =IF(COUNTBLANK(G46:K46)=5,"",IF(COUNTIF(G46:K46,"No")>0,"EXCLUDE","INCLUDE")) -> INCLUDE | M46: =IF(L46<>"EXCLUDE","",IF(G46="No","Wrong domain (non-AECO)",IF(H46="No","Digital Twin not core / buzzword",IF(I46="No","No Design for Safety/Quality/PtD",IF(J46="No","Wrong publication type",IF(K46="No","Non-English","")))))) | N46: Yes | O46: Yes | P46: Yes | Q46: Yes | R46: Yes | S46: =IF(N46<>"Yes","",IF(COUNTBLANK(P46:R46)=3,"",IF(COUNTIF(P46:R46,"No")>0,"EXCLUDE","INCLUDE"))) -> INCLUDE | T46: =IF(S46<>"EXCLUDE","",IF(P46="No","Digital Twin mentioned only, not the subject",IF(Q46="No","No Design for Safety/Quality in full text",IF(R46="No","Methodology not codable","")))) | U46: Tier 1 - Digital Model (static, no live data) | V46: 0 | W46: 0 | X46: 1 | Y46: =IF(SUM(V46:X46)=0,"",IF(SUM(V46:X46)>=2,"Multi","Single")) -> Single | Z46: Design for Safety (DfS) | AA46: None | AB46: Other / Mixed | AC46: Single (one data type) | AD46: Simulation | AE46: 3 | AF46: Design for Safety | AG46: AI-based ANN surrogate model for DTs in SHM of reinforced concrete bridges (Cervenka Consulting/CTU, RILEM SSCS 2025): ANN has two roles - calibrating the virtual twin to physical structure behavior, then deployment as fast-response surrogate providing safety information for ongoing SHM; physically informed deep learning trained from nonlinear FEM (ATENA) sensitivity analyses; demonstrated on Leonhardt shear-beam numerical example (100/400/1000-sample datasets) identifying material parameters (fc, ft, E, GF) from load-displacement diagrams. Numerical example only - no live data link to a real bridge, no actuation, no learning loop. [Full-text source: Endnote] | AH46: Assigns ANNs two roles in a DT for SHM of reinforced concrete bridges: first, physically informed deep learning calibrates the virtual twin by identifying material parameters (E, fc, ft, fracture energy) from ATENA nonlinear finite element sensitivity analyses, demonstrated on a Leonhardt shear beam with datasets of 100, 400, and 1000 samples; second, the trained ANN serves as a fast-response surrogate for real-time engineering interpretation of monitoring data. | AI46: A short conference-stage contribution: only parameter identification on a numerical shear beam example is demonstrated, with no deployed structure, no live sensor data, and no quantitative surrogate accuracy reported; the conclusion and future work sections remain essentially undeveloped, so the real-time SHM surrogate role is proposed rather than validated. | AJ46: Single | AK46: Only load-displacement curves generated by nonlinear ATENA finite-element sensitivity analyses feed the ANN surrogate; no measured sensor stream exists. | AL46: High | AN46: Verified 2026-08-22 vs PDF (RILEM SSCS2025, Cervenka Consulting/CTU). ATENA nonlinear FEM sensitivity analyses, Leonhardt shear-beam example, and 100/400/1000-sample datasets identifying E, fc, ft, GF all confirmed. Numerical example only - Tier 1, AD Simulation, AC Single upheld. | AO46: =IF($A46="","",IFERROR(_xlfn.XLOOKUP($A46,'2_DOI_Lookup'!$A$2:$A$430,'2_DOI_Lookup'!$B$2:$B$430),"NOT IN SOURCE")) -> 0
A47: 3958 | E47: =IF($A47="","",IFERROR(_xlfn.XLOOKUP($A47,'2_DOI_Lookup'!$D$2:$D$430,'2_DOI_Lookup'!$E$2:$E$430),"TITLE NOT IN SOURCE")) -> Integration of Emerging Technologies with Construction Practices in Australia | F47: Web of Science | G47: Yes | H47: No | I47: No | J47: Yes | K47: Yes | L47: =IF(COUNTBLANK(G47:K47)=5,"",IF(COUNTIF(G47:K47,"No")>0,"EXCLUDE","INCLUDE")) -> EXCLUDE | M47: =IF(L47<>"EXCLUDE","",IF(G47="No","Wrong domain (non-AECO)",IF(H47="No","Digital Twin not core / buzzword",IF(I47="No","No Design for Safety/Quality/PtD",IF(J47="No","Wrong publication type",IF(K47="No","Non-English","")))))) -> Digital Twin not core / buzzword | S47: =IF(N47<>"Yes","",IF(COUNTBLANK(P47:R47)=3,"",IF(COUNTIF(P47:R47,"No")>0,"EXCLUDE","INCLUDE"))) | T47: =IF(S47<>"EXCLUDE","",IF(P47="No","Digital Twin mentioned only, not the subject",IF(Q47="No","No Design for Safety/Quality in full text",IF(R47="No","Methodology not codable","")))) | Y47: =IF(SUM(V47:X47)=0,"",IF(SUM(V47:X47)>=2,"Multi","Single")) | AG47: Tech-adoption survey; DT one of many | AO47: =IF($A47="","",IFERROR(_xlfn.XLOOKUP($A47,'2_DOI_Lookup'!$A$2:$A$430,'2_DOI_Lookup'!$B$2:$B$430),"NOT IN SOURCE")) -> 10.3390/buildings15030396
A48: 3936 | B48: Chacon (2024) | C48: 2024 | E48: =IF($A48="","",IFERROR(_xlfn.XLOOKUP($A48,'2_DOI_Lookup'!$D$2:$D$430,'2_DOI_Lookup'!$E$2:$E$430),"TITLE NOT IN SOURCE")) -> Digital twinning of building construction processes. Case study: A reinforced concrete cast-in structure | F48: Web of Science | G48: Yes | H48: Yes | I48: Yes | J48: Yes | K48: Yes | L48: =IF(COUNTBLANK(G48:K48)=5,"",IF(COUNTIF(G48:K48,"No")>0,"EXCLUDE","INCLUDE")) -> INCLUDE | M48: =IF(L48<>"EXCLUDE","",IF(G48="No","Wrong domain (non-AECO)",IF(H48="No","Digital Twin not core / buzzword",IF(I48="No","No Design for Safety/Quality/PtD",IF(J48="No","Wrong publication type",IF(K48="No","Non-English","")))))) | N48: Yes | O48: Yes | P48: Yes | Q48: Yes | R48: Yes | S48: =IF(N48<>"Yes","",IF(COUNTBLANK(P48:R48)=3,"",IF(COUNTIF(P48:R48,"No")>0,"EXCLUDE","INCLUDE"))) -> INCLUDE | T48: =IF(S48<>"EXCLUDE","",IF(P48="No","Digital Twin mentioned only, not the subject",IF(Q48="No","No Design for Safety/Quality in full text",IF(R48="No","Methodology not codable","")))) | U48: Tier 2 - Digital Shadow (one-way physical to virtual) | V48: 0 | W48: 1 | X48: 0 | Y48: =IF(SUM(V48:X48)=0,"",IF(SUM(V48:X48)>=2,"Multi","Single")) -> Single | Z48: Both | AA48: None | AB48: Other / Mixed | AC48: Multi (two or more data types) | AD48: Single case study | AE48: 4 | AF48: BIM-to-Digital-Twin architecture | AG48: ASHVIN H2020 DT case study (RC office building, Barcelona): six independent information pipelines (IMU/temp/load sensors, TLS point clouds, equipment tracking) → knowledge-graph system → Unity dashboard with project-specific KPIs (construction safety, quality control, productivity); ML activity recognition (Naïve Bayes/DT/kNN/SVM on equipment sensors); data flows one-way physical→virtual for decision support; conclusions state it "has not permitted to act" on the site — no actuation, no learning loop. [Full-text source: Endnote] | AH48: Provides a real ASHVIN H2020 pilot of digital twinning during construction of an RC office building in Barcelona: six independent information pipelines (crane hook IMU/GPS tracking with Random Forest activity recognition at 93.27% accuracy, slab post-tensioning strains, laser-scan deflection checks, concrete maturity temperatures, formwork vibration accelerations, mobile-app progress monitoring) feeding a knowledge-graph-based Unity dashboard. | AI48: One-way digital shadow: the dashboard informs managers but does not control site operations, technology readiness did not permit acting weekly on extracted insights, and feedback came only after development. Bottlenecks include logistics, privacy, need for specialized crews, sensor fragility, and manual progress updates; automating data collection and treatment is future work. | AJ48: Co-present | AK48: Six independent information pipelines (crane-hook IMU/GPS, post-tensioning strains, laser-scan deflections, maturity temperatures, formwork-vibration accelerations, mobile-app progress) feed one knowledge-graph dashboard, each staying in its own pipeline. | AL48: High | AN48: Verified 2026-08-22 vs PDF (H2020 ASHVIN, office building in Poblenou, Barcelona). "A description of six different pipelines of information is provided" confirmed. Fusion=Co-present strongly supported: the authors state the study "has not permitted to act weekly using conclusions from the extracted information". Tier 2, AA None upheld. | AO48: =IF($A48="","",IFERROR(_xlfn.XLOOKUP($A48,'2_DOI_Lookup'!$A$2:$A$430,'2_DOI_Lookup'!$B$2:$B$430),"NOT IN SOURCE")) -> 10.1016/j.jobe.2024.108522
A49: 3795 | B49: Chan (2025) | C49: 2025 | E49: =IF($A49="","",IFERROR(_xlfn.XLOOKUP($A49,'2_DOI_Lookup'!$D$2:$D$430,'2_DOI_Lookup'!$E$2:$E$430),"TITLE NOT IN SOURCE")) -> Risk Mitigation of a Heritage Bridge Using Noninvasive Sensors | F49: Scopus | G49: Yes | H49: Yes | I49: Yes | J49: Yes | K49: Yes | L49: =IF(COUNTBLANK(G49:K49)=5,"",IF(COUNTIF(G49:K49,"No")>0,"EXCLUDE","INCLUDE")) -> INCLUDE | M49: =IF(L49<>"EXCLUDE","",IF(G49="No","Wrong domain (non-AECO)",IF(H49="No","Digital Twin not core / buzzword",IF(I49="No","No Design for Safety/Quality/PtD",IF(J49="No","Wrong publication type",IF(K49="No","Non-English","")))))) | N49: Yes | O49: Yes | P49: Yes | Q49: Yes | R49: Yes | S49: =IF(N49<>"Yes","",IF(COUNTBLANK(P49:R49)=3,"",IF(COUNTIF(P49:R49,"No")>0,"EXCLUDE","INCLUDE"))) -> INCLUDE | T49: =IF(S49<>"EXCLUDE","",IF(P49="No","Digital Twin mentioned only, not the subject",IF(Q49="No","No Design for Safety/Quality in full text",IF(R49="No","Methodology not codable","")))) | U49: Tier 2 - Digital Shadow (one-way physical to virtual) | V49: 0 | W49: 0 | X49: 1 | Y49: =IF(SUM(V49:X49)=0,"",IF(SUM(V49:X49)>=2,"Multi","Single")) -> Single | Z49: Design for Safety (DfS) | AA49: None | AB49: Finite Element Method / physics-based | AC49: Multi (two or more data types) | AD49: Single case study | AE49: 4 | AF49: Design for Safety | AG49: 120-yr heritage RC bridge; ambient vibration + laser displacement monitoring; FE-based DT validated against field data, used for what-if scenarios (overweight vehicles, scour loss); six-phase Incident Response Framework; model is updated/validated, not self-learning. [Full-text source: Endnote] | AH49: Fills the gap between heritage-bridge conservation and quantitative risk assessment: on a 120-year-old Australian reinforced concrete bridge, ambient vibration testing with ten wireless accelerometers plus laser displacement sensing feeds a Spacegass finite-element digital twin validated against measured natural frequencies (20.15 Hz versus 19.51 Hz, 3.2 percent difference), then used for what-if simulations of overweight vehicles and foundation scour. | AI49: Monitoring is campaign-based rather than live: the twin is an offline validated finite-element model with no continuous data link or actuation, higher-order modes are missed at the 100 Hz sampling rate, and the six-phase Incident Response Framework is proposed but not yet deployed; higher-rate testing is noted for the future. | AJ49: Aligned | AK49: Ambient-vibration accelerometers and laser displacement sensing both feed and validate one Spacegass FE twin of the bridge, sharing the structural model frame, with each quantity analysed separately. | AL49: Medium | AN49: Verified 2026-08-22 vs PDF. 120-year-old heritage RC bridge in Australia, ambient vibration testing, foundation scouring scenario, and the proposed six-phase Incident Response Framework all confirmed. Tier 2, AA None upheld. | AO49: =IF($A49="","",IFERROR(_xlfn.XLOOKUP($A49,'2_DOI_Lookup'!$A$2:$A$430,'2_DOI_Lookup'!$B$2:$B$430),"NOT IN SOURCE")) -> 10.3390/s25123727
A50: 3998 | B50: Chang (2024) | C50: 2024 | E50: =IF($A50="","",IFERROR(_xlfn.XLOOKUP($A50,'2_DOI_Lookup'!$D$2:$D$430,'2_DOI_Lookup'!$E$2:$E$430),"TITLE NOT IN SOURCE")) -> Autonomous dimensional inspection and issue tracking of rebar using semantically enriched 3D models | F50: Web of Science | G50: Yes | H50: Yes | I50: Yes | J50: Yes | K50: Yes | L50: =IF(COUNTBLANK(G50:K50)=5,"",IF(COUNTIF(G50:K50,"No")>0,"EXCLUDE","INCLUDE")) -> INCLUDE | M50: =IF(L50<>"EXCLUDE","",IF(G50="No","Wrong domain (non-AECO)",IF(H50="No","Digital Twin not core / buzzword",IF(I50="No","No Design for Safety/Quality/PtD",IF(J50="No","Wrong publication type",IF(K50="No","Non-English","")))))) | N50: Yes | O50: Yes | P50: Yes | Q50: Yes | R50: Yes | S50: =IF(N50<>"Yes","",IF(COUNTBLANK(P50:R50)=3,"",IF(COUNTIF(P50:R50,"No")>0,"EXCLUDE","INCLUDE"))) -> INCLUDE | T50: =IF(S50<>"EXCLUDE","",IF(P50="No","Digital Twin mentioned only, not the subject",IF(Q50="No","No Design for Safety/Quality in full text",IF(R50="No","Methodology not codable","")))) | U50: Tier 1 - Digital Model (static, no live data) | V50: 0 | W50: 1 | X50: 0 | Y50: =IF(SUM(V50:X50)=0,"",IF(SUM(V50:X50)>=2,"Multi","Single")) -> Single | Z50: Design for Quality (DfQ) | AA50: None | AB50: Computer Vision / CNN / object-detection | AC50: Multi (two or more data types) | AD50: Single case study | AE50: 4 | AF50: Perception / Computer Vision | AG50: Autonomous dimensional inspection and issue tracking of rebar using semantically enriched 3D models (NTU): DT generation from GoPro images via SfM-MVS point-cloud reconstruction (AprilTag scale calibration); segmentation via Mask R-CNN + 3D clustering (DBSCAN); inspection via 2D circular Hough transform (diameter accuracy 95.5%, spacing mean relative error 0.98%); issue identification/tracking via Scan-vs-BIM registration and comparison of semantically enriched 3D models with BIM across time. Single column rebar cage experiment. One-way inspection to BIM/Digital-Twin for DQC; no live data link and no learning loop. [Full-text source: Endnote] | AH50: Closes the automation gap between rebar reconstruction, segmentation, dimensional inspection and issue tracking: a GoPro-based SfM-MVS pipeline with AprilTag scale calibration builds a semantically enriched 3D model, Mask R-CNN plus DBSCAN segment rebars, and Scan-vs-BIM comparison identifies and tracks defects, reaching over 90 percent precision, over 97 percent recall, 95.5 percent diameter accuracy for large rebars and 0.98 percent mean relative spacing error. | AI50: Offline, camera-based pipeline with manual image capture and fiducial marker attachment; 2D segmentation precision averages only 50.4 percent, small-diameter rebar inspection reaches only 77.8 percent, and registration fails on geometrically indistinct structures; future work points to more training data, augmentation, unsupervised techniques and Point Transformer based classification. | AJ50: Aligned | AK50: SfM-MVS point clouds are registered to the BIM via Scan-vs-BIM comparison, and Mask R-CNN/DBSCAN segmentation and Hough-transform inspection run as separate stages on this shared model frame. | AL50: High | AN50: Verified 2026-08-22 vs PDF (NTU). AprilTag scale calibration, Mask R-CNN + DBSCAN clustering, "Diameter inspection achieves an accuracy of 95.5% for large-size rebars" and "Spacing inspection achieves a mean relative error of 0.98%" all confirmed. Tier 1, AA None upheld. | AO50: =IF($A50="","",IFERROR(_xlfn.XLOOKUP($A50,'2_DOI_Lookup'!$A$2:$A$430,'2_DOI_Lookup'!$B$2:$B$430),"NOT IN SOURCE")) -> 10.1016/j.autcon.2024.105303
A51: 3984 | B51: Chang (2026) | C51: 2026 | E51: =IF($A51="","",IFERROR(_xlfn.XLOOKUP($A51,'2_DOI_Lookup'!$D$2:$D$430,'2_DOI_Lookup'!$E$2:$E$430),"TITLE NOT IN SOURCE")) -> A transformer-based surrogate modeling strategy for tunnel digital twin in full-field displacement prediction under adjacent tunnel construction | F51: Web of Science | G51: Yes | H51: Yes | I51: Yes | J51: Yes | K51: Yes | L51: =IF(COUNTBLANK(G51:K51)=5,"",IF(COUNTIF(G51:K51,"No")>0,"EXCLUDE","INCLUDE")) -> INCLUDE | M51: =IF(L51<>"EXCLUDE","",IF(G51="No","Wrong domain (non-AECO)",IF(H51="No","Digital Twin not core / buzzword",IF(I51="No","No Design for Safety/Quality/PtD",IF(J51="No","Wrong publication type",IF(K51="No","Non-English","")))))) | N51: Yes | O51: Yes | P51: Yes | Q51: Yes | R51: Yes | S51: =IF(N51<>"Yes","",IF(COUNTBLANK(P51:R51)=3,"",IF(COUNTIF(P51:R51,"No")>0,"EXCLUDE","INCLUDE"))) -> INCLUDE | T51: =IF(S51<>"EXCLUDE","",IF(P51="No","Digital Twin mentioned only, not the subject",IF(Q51="No","No Design for Safety/Quality in full text",IF(R51="No","Methodology not codable","")))) | U51: Tier 2 - Digital Shadow (one-way physical to virtual) | V51: 0 | W51: 1 | X51: 0 | Y51: =IF(SUM(V51:X51)=0,"",IF(SUM(V51:X51)>=2,"Multi","Single")) -> Single | Z51: Design for Safety (DfS) | AA51: Implemented | AB51: Transformer / Large Language Model (LLM) | AC51: Multi (two or more data types) | AD51: Single case study | AE51: 4 | AF51: Predictive analytics / decision support | AG51: DT framework for predicting ground settlement and lining deformation of shield tunnels under adjacent excavation (NTU/Southeast U): hybrid surrogate model DF-STTN (Swin Transformer + TabTransformer) for full-field displacement prediction from spatial + non-spatial inputs; trained on high-fidelity FE data, then updated/validated on laboratory-scale tunnel excavation tests via a genetic-algorithm model-updating procedure that iteratively refines soil parameters using sparse test data (minimizing prediction error); outperforms convolution-based and single-fusion models; spatial info (3 measurement points) improves accuracy. One-way prediction with implemented GA-based model updating - no convergence criterion, no actuation. [Full-text source: Endnote] | AH51: Fills the sparse-point surrogate gap for tunnel digital twins: the DF-STTN hybrid surrogate, pairing Swin Transformer and TabTransformer with dual-stage fusion, predicts full-field ground settlement and lining deformation for shield tunnels under adjacent excavation, trained on 1000 parametric finite-element samples and reaching R2 0.9898 and 0.9951, outperforming six baseline networks, with genetic-algorithm back-analysis estimating soil parameters within 4 percent error. | AI51: Validation rests on a scaled laboratory testbed with simplified boundary conditions, not field monitoring; time-dependent processes like consolidation and creep are ignored, settlement and lining deformation are modeled separately, and no real-time sensor link exists; future work targets field monitoring data, spatio-temporal Transformers, layered soil and groundwater, coupled models and continuous model updating. | AJ51: Fused | AK51: The DF-STTN hybrid surrogate fuses Swin-Transformer spatial fields with TabTransformer non-spatial parameters via a dual-stage fusion module, and a GA model-updating procedure joins sparse laboratory test data with the FE-trained model. | AL51: High | AM51: DATA ISSUE 2026-08-22: cell F48 (Source database) contains "and " - not a valid value (expected Scopus / Web of Science / Lens.org / snowball). Cannot be recovered from the PDF because this is search provenance, not paper content. Please restore from your Endnote/search records. [Prior note] REVIEW (2nd coder): closest case to Convergence-characterised - Algorithm 1 sets a convergence threshold with break condition; threshold governs GA parameter search, not the DT loop; AA retained as Implemented | AN51: Verified 2026-08-22 vs PDF (Advanced Engineering Informatics 69:104045). RE-VERIFIED 2026-08-23 (self-improvement audit, full text): AA=Implemented UPHELD, but note the scope. Algorithm 1 "Model updating framework based on back analysis for soil properties" is executed, not proposed: the trained DF-STTN is inverted with a genetic algorithm against physical laboratory test data to minimise MSE between prediction and measurement, and "The updated surrogate model is then deployed for predictive analysis"; "This updated model serves as a new surrogate model, which can be applied to future prediction tasks". Demonstrated effect: recovered soil parameters within ~4% of measured values, corrected the overestimation of the baseline model (Fig. 16/17), and generalised to two held-out configurations (Tests 2 and 3). SCOPE CAVEAT: what is revised are the model INPUTS (soil parameters), not the network weights, and it is a one-pass offline recalibration - the authors state that integration with real-time sensor data "will enable continuous model updating and adaptive feedback" as FUTURE work. CONVERGENCE: Algorithm 1 lines 2/6-7 set threshold epsilon with a break, and Figs. 12/14 "GA convergence process during surrogate model updating" show fitness stabilising after ~20 generations (best 0.00098) - but this governs the GA parameter search, not a DT self-improvement loop, so Convergence-characterised is still not applied. Keep flagged for a second coder. | AO51: =IF($A51="","",IFERROR(_xlfn.XLOOKUP($A51,'2_DOI_Lookup'!$A$2:$A$430,'2_DOI_Lookup'!$B$2:$B$430),"NOT IN SOURCE")) -> 10.1016/j.aei.2025.104045
A52: 3601 | E52: =IF($A52="","",IFERROR(_xlfn.XLOOKUP($A52,'2_DOI_Lookup'!$D$2:$D$430,'2_DOI_Lookup'!$E$2:$E$430),"TITLE NOT IN SOURCE")) -> Digital twin-based experimental method for construction loads of adjacent works | F52: Scopus | G52: Yes | H52: Yes | I52: Yes | J52: Yes | K52: No | L52: =IF(COUNTBLANK(G52:K52)=5,"",IF(COUNTIF(G52:K52,"No")>0,"EXCLUDE","INCLUDE")) -> EXCLUDE | M52: =IF(L52<>"EXCLUDE","",IF(G52="No","Wrong domain (non-AECO)",IF(H52="No","Digital Twin not core / buzzword",IF(I52="No","No Design for Safety/Quality/PtD",IF(J52="No","Wrong publication type",IF(K52="No","Non-English","")))))) -> Non-English | S52: =IF(N52<>"Yes","",IF(COUNTBLANK(P52:R52)=3,"",IF(COUNTIF(P52:R52,"No")>0,"EXCLUDE","INCLUDE"))) | T52: =IF(S52<>"EXCLUDE","",IF(P52="No","Digital Twin mentioned only, not the subject",IF(Q52="No","No Design for Safety/Quality in full text",IF(R52="No","Methodology not codable","")))) | Y52: =IF(SUM(V52:X52)=0,"",IF(SUM(V52:X52)>=2,"Multi","Single")) | AG52: Chinese journal; full text non-English | AO52: =IF($A52="","",IFERROR(_xlfn.XLOOKUP($A52,'2_DOI_Lookup'!$A$2:$A$430,'2_DOI_Lookup'!$B$2:$B$430),"NOT IN SOURCE")) -> 0
A53: 3911 | B53: Chen (2025) | C53: 2025 | E53: =IF($A53="","",IFERROR(_xlfn.XLOOKUP($A53,'2_DOI_Lookup'!$D$2:$D$430,'2_DOI_Lookup'!$E$2:$E$430),"TITLE NOT IN SOURCE")) -> Digital Twin-Based and Knowledge Graph-Enhanced Emergency Response in Urban Infrastructure Construction | F53: Web of Science | G53: Yes | H53: Yes | I53: Yes | J53: Yes | K53: Yes | L53: =IF(COUNTBLANK(G53:K53)=5,"",IF(COUNTIF(G53:K53,"No")>0,"EXCLUDE","INCLUDE")) -> INCLUDE | M53: =IF(L53<>"EXCLUDE","",IF(G53="No","Wrong domain (non-AECO)",IF(H53="No","Digital Twin not core / buzzword",IF(I53="No","No Design for Safety/Quality/PtD",IF(J53="No","Wrong publication type",IF(K53="No","Non-English","")))))) | N53: Yes | O53: Yes | P53: Yes | Q53: Yes | R53: Yes | S53: =IF(N53<>"Yes","",IF(COUNTBLANK(P53:R53)=3,"",IF(COUNTIF(P53:R53,"No")>0,"EXCLUDE","INCLUDE"))) -> INCLUDE | T53: =IF(S53<>"EXCLUDE","",IF(P53="No","Digital Twin mentioned only, not the subject",IF(Q53="No","No Design for Safety/Quality in full text",IF(R53="No","Methodology not codable","")))) | U53: Tier 3 - Digital Twin (bidirectional, two-way) | V53: 0 | W53: 1 | X53: 0 | Y53: =IF(SUM(V53:X53)=0,"",IF(SUM(V53:X53)>=2,"Multi","Single")) -> Single | Z53: Design for Safety (DfS) | AA53: None | AB53: Ontology / semantic | AC53: Multi (two or more data types) | AD53: Single case study | AE53: 4 | AF53: Predictive analytics / decision support | AG53: Tunnel project in China; DT continuously integrates settlement/TBM/structural monitoring; KG rule-based reasoning infers hazards and mitigation; bidirectional DT-KG interaction visualised for decisions; prevention of further structural impact claimed in real emergency. [Full-text source: Endnote] | AH53: Addresses the reactive and static gap in tunnel construction emergency response: a digital twin continuously integrating settlement, TBM operational and structural monitoring data is coupled with a knowledge graph using SWRL rule-based reasoning to infer hazards, detect anomalies and suggest mitigations, with inference results visualized back in the twin; deployed on an urban tunnel project in Shanghai where it enabled early anomaly identification. | AI53: Data quality dependency is acknowledged: sensor noise, loss, calibration drift and delays can misclassify risk levels; the ontology and rules are manually built for Shanghai urban tunnels, limiting scalability; reasoning speed, throughput and prediction accuracy are not quantitatively benchmarked; single-project validation; future work includes confidence metrics, automated rule generation, dynamic learning and stress testing. | AJ53: Fused | AK53: Settlement, TBM-operational and structural monitoring data are continuously integrated in the DT and jointly reasoned over by a knowledge graph with SWRL rules to infer hazards and mitigation. | AL53: High | AN53: Verified 2026-08-22 vs PDF (Tongji University). Tier 3 CONFIRMED verbatim: "the knowledge graph feeds them back to the digital twin"; "This bidirectional interaction between the digital twin and the knowledge graph"; connections enable "real-time data exchange and control" (TBM operational control, grouting control). Rule-based reasoning, so AA None upheld. | AO53: =IF($A53="","",IFERROR(_xlfn.XLOOKUP($A53,'2_DOI_Lookup'!$A$2:$A$430,'2_DOI_Lookup'!$B$2:$B$430),"NOT IN SOURCE")) -> 10.3390/app15116009
A54: 3953 | B54: Chen (2026) | C54: 2026 | E54: =IF($A54="","",IFERROR(_xlfn.XLOOKUP($A54,'2_DOI_Lookup'!$D$2:$D$430,'2_DOI_Lookup'!$E$2:$E$430),"TITLE NOT IN SOURCE")) -> Digital Twin-Enabled Robust Parallel Control of Construction Engineering Equipment Under Uncertainty | F54: Web of Science | G54: Yes | H54: Yes | I54: Yes | J54: Yes | K54: Yes | L54: =IF(COUNTBLANK(G54:K54)=5,"",IF(COUNTIF(G54:K54,"No")>0,"EXCLUDE","INCLUDE")) -> INCLUDE | M54: =IF(L54<>"EXCLUDE","",IF(G54="No","Wrong domain (non-AECO)",IF(H54="No","Digital Twin not core / buzzword",IF(I54="No","No Design for Safety/Quality/PtD",IF(J54="No","Wrong publication type",IF(K54="No","Non-English","")))))) | N54: Yes | O54: Yes | P54: Yes | Q54: Yes | R54: Yes | S54: =IF(N54<>"Yes","",IF(COUNTBLANK(P54:R54)=3,"",IF(COUNTIF(P54:R54,"No")>0,"EXCLUDE","INCLUDE"))) -> INCLUDE | T54: =IF(S54<>"EXCLUDE","",IF(P54="No","Digital Twin mentioned only, not the subject",IF(Q54="No","No Design for Safety/Quality in full text",IF(R54="No","Methodology not codable","")))) | U54: Tier 3 - Digital Twin (bidirectional, two-way) | V54: 0 | W54: 1 | X54: 0 | Y54: =IF(SUM(V54:X54)=0,"",IF(SUM(V54:X54)>=2,"Multi","Single")) -> Single | Z54: Design for Safety (DfS) | AA54: Mentioned only | AB54: Other / Mixed | AC54: Multi (two or more data types) | AD54: Single case study | AE54: 4 | AF54: Design for Safety | AG54: Mobile gin pole (UHV construction): FEM kinetic analysis + TROA-ET surrogate (R2 0.9642) + NSGA-III safety-efficiency optimisation embedded in DT parallel-control architecture; bidirectional 4G/MQTT link (CANopen control commands) on real 110 kV project; safety risk -32.3%; surrogate is offline-trained, no online learning. [Full-text source: MDPI Buildings (Gold OA)] | AH54: Addresses robust parallel control of construction equipment under uncertainty: a mobile gin pole digital twin for UHV construction embeds finite-element kinetic analysis with a TROA-ET surrogate model (R2 0.9642) and NSGA-III safety-efficiency optimisation within a DT parallel-control architecture supported by bidirectional 4G and MQTT links. | AI54: The available record states no explicit future work; validation is documented only for the mobile gin pole application, and whether the TROA-ET surrogate is updated online, transferred to other equipment types, or tested against field disturbances beyond the stated scenario is not established. | AJ54: Aligned | AK54: Live operational data and the TROA-ET/FEM surrogate coexist in the DT parallel-control architecture over bidirectional 4G/MQTT links, but the surrogate is offline-trained and no joint inference across streams is stated. | AL54: Medium | AN54: Verified 2026-08-22 vs PDF (MDPI Buildings). Tier 3 supported: "Both the physical system and the virtual system generate control commands" with deviation comparison for temporal/spatial synchronisation. R2 0.9642 confirmed; real-world scenario is the 110 kV transmission project of a 220 kV substation. NOTE: the PDF states safety risks reduced "by up to 32.30%" and efficiency improved "by up to 42.73%" - AG cites -32.3% correctly. AA Mentioned only upheld (surrogate offline-trained). | AO54: =IF($A54="","",IFERROR(_xlfn.XLOOKUP($A54,'2_DOI_Lookup'!$A$2:$A$430,'2_DOI_Lookup'!$B$2:$B$430),"NOT IN SOURCE")) -> 10.3390/buildings16101982
A55: 3873 | E55: =IF($A55="","",IFERROR(_xlfn.XLOOKUP($A55,'2_DOI_Lookup'!$D$2:$D$430,'2_DOI_Lookup'!$E$2:$E$430),"TITLE NOT IN SOURCE")) -> Construction and application of Digital Twin model of pipeline | F55: Scopus | G55: No | H55: Yes | I55: Yes | J55: Yes | K55: No | L55: =IF(COUNTBLANK(G55:K55)=5,"",IF(COUNTIF(G55:K55,"No")>0,"EXCLUDE","INCLUDE")) -> EXCLUDE | M55: =IF(L55<>"EXCLUDE","",IF(G55="No","Wrong domain (non-AECO)",IF(H55="No","Digital Twin not core / buzzword",IF(I55="No","No Design for Safety/Quality/PtD",IF(J55="No","Wrong publication type",IF(K55="No","Non-English","")))))) -> Wrong domain (non-AECO) | S55: =IF(N55<>"Yes","",IF(COUNTBLANK(P55:R55)=3,"",IF(COUNTIF(P55:R55,"No")>0,"EXCLUDE","INCLUDE"))) | T55: =IF(S55<>"EXCLUDE","",IF(P55="No","Digital Twin mentioned only, not the subject",IF(Q55="No","No Design for Safety/Quality in full text",IF(R55="No","Methodology not codable","")))) | Y55: =IF(SUM(V55:X55)=0,"",IF(SUM(V55:X55)>=2,"Multi","Single")) | AG55: Oil/gas pipeline industry; Chinese journal, non-English | AO55: =IF($A55="","",IFERROR(_xlfn.XLOOKUP($A55,'2_DOI_Lookup'!$A$2:$A$430,'2_DOI_Lookup'!$B$2:$B$430),"NOT IN SOURCE")) -> 10.6047/j.issn.1000-8241.2021.06.006
A56: 3745 | E56: =IF($A56="","",IFERROR(_xlfn.XLOOKUP($A56,'2_DOI_Lookup'!$D$2:$D$430,'2_DOI_Lookup'!$E$2:$E$430),"TITLE NOT IN SOURCE")) -> Monitoring Construction and System Development of Bridge Horizontal Rotation "Traction-rotation" | F56: Scopus | G56: Yes | H56: Yes | I56: Yes | J56: Yes | K56: No | L56: =IF(COUNTBLANK(G56:K56)=5,"",IF(COUNTIF(G56:K56,"No")>0,"EXCLUDE","INCLUDE")) -> EXCLUDE | M56: =IF(L56<>"EXCLUDE","",IF(G56="No","Wrong domain (non-AECO)",IF(H56="No","Digital Twin not core / buzzword",IF(I56="No","No Design for Safety/Quality/PtD",IF(J56="No","Wrong publication type",IF(K56="No","Non-English","")))))) -> Non-English | S56: =IF(N56<>"Yes","",IF(COUNTBLANK(P56:R56)=3,"",IF(COUNTIF(P56:R56,"No")>0,"EXCLUDE","INCLUDE"))) | T56: =IF(S56<>"EXCLUDE","",IF(P56="No","Digital Twin mentioned only, not the subject",IF(Q56="No","No Design for Safety/Quality in full text",IF(R56="No","Methodology not codable","")))) | Y56: =IF(SUM(V56:X56)=0,"",IF(SUM(V56:X56)>=2,"Multi","Single")) | AG56: Chinese journal; non-English full text | AO56: =IF($A56="","",IFERROR(_xlfn.XLOOKUP($A56,'2_DOI_Lookup'!$A$2:$A$430,'2_DOI_Lookup'!$B$2:$B$430),"NOT IN SOURCE")) -> 10.19721/j.cnki.1001-7372.2025.06.006
A57: 3509 | E57: =IF($A57="","",IFERROR(_xlfn.XLOOKUP($A57,'2_DOI_Lookup'!$D$2:$D$430,'2_DOI_Lookup'!$E$2:$E$430),"TITLE NOT IN SOURCE")) -> Multi-Modal Excavator Activity Recognition Using Two-Stream CNN-LSTM with RGB and Point Cloud Inputs | F57: Scopus | G57: Yes | H57: No | I57: Yes | J57: Yes | K57: Yes | L57: =IF(COUNTBLANK(G57:K57)=5,"",IF(COUNTIF(G57:K57,"No")>0,"EXCLUDE","INCLUDE")) -> EXCLUDE | M57: =IF(L57<>"EXCLUDE","",IF(G57="No","Wrong domain (non-AECO)",IF(H57="No","Digital Twin not core / buzzword",IF(I57="No","No Design for Safety/Quality/PtD",IF(J57="No","Wrong publication type",IF(K57="No","Non-English","")))))) -> Digital Twin not core / buzzword | S57: =IF(N57<>"Yes","",IF(COUNTBLANK(P57:R57)=3,"",IF(COUNTIF(P57:R57,"No")>0,"EXCLUDE","INCLUDE"))) | T57: =IF(S57<>"EXCLUDE","",IF(P57="No","Digital Twin mentioned only, not the subject",IF(Q57="No","No Design for Safety/Quality in full text",IF(R57="No","Methodology not codable","")))) | Y57: =IF(SUM(V57:X57)=0,"",IF(SUM(V57:X57)>=2,"Multi","Single")) | AG57: CV activity recognition; DT integration future work | AO57: =IF($A57="","",IFERROR(_xlfn.XLOOKUP($A57,'2_DOI_Lookup'!$A$2:$A$430,'2_DOI_Lookup'!$B$2:$B$430),"NOT IN SOURCE")) -> 10.3390/app15158505
A58: 3529 | E58: =IF($A58="","",IFERROR(_xlfn.XLOOKUP($A58,'2_DOI_Lookup'!$D$2:$D$430,'2_DOI_Lookup'!$E$2:$E$430),"TITLE NOT IN SOURCE")) -> Guidance for Materials 4.0 to interact with a digital twin | F58: Scopus | G58: No | H58: Yes | I58: No | J58: Yes | K58: Yes | L58: =IF(COUNTBLANK(G58:K58)=5,"",IF(COUNTIF(G58:K58,"No")>0,"EXCLUDE","INCLUDE")) -> EXCLUDE | M58: =IF(L58<>"EXCLUDE","",IF(G58="No","Wrong domain (non-AECO)",IF(H58="No","Digital Twin not core / buzzword",IF(I58="No","No Design for Safety/Quality/PtD",IF(J58="No","Wrong publication type",IF(K58="No","Non-English","")))))) -> Wrong domain (non-AECO) | S58: =IF(N58<>"Yes","",IF(COUNTBLANK(P58:R58)=3,"",IF(COUNTIF(P58:R58,"No")>0,"EXCLUDE","INCLUDE"))) | T58: =IF(S58<>"EXCLUDE","",IF(P58="No","Digital Twin mentioned only, not the subject",IF(Q58="No","No Design for Safety/Quality in full text",IF(R58="No","Methodology not codable","")))) | Y58: =IF(SUM(V58:X58)=0,"",IF(SUM(V58:X58)>=2,"Multi","Single")) | AG58: Materials/manufacturing component DT; not AECO | AO58: =IF($A58="","",IFERROR(_xlfn.XLOOKUP($A58,'2_DOI_Lookup'!$A$2:$A$430,'2_DOI_Lookup'!$B$2:$B$430),"NOT IN SOURCE")) -> 10.1017/dce.2022.23
A59: 3660 | E59: =IF($A59="","",IFERROR(_xlfn.XLOOKUP($A59,'2_DOI_Lookup'!$D$2:$D$430,'2_DOI_Lookup'!$E$2:$E$430),"TITLE NOT IN SOURCE")) -> On-Site Safety Inspections Through Marker-Less Augmented Reality and Blockchain Notarization of BIM-Based Processes † | F59: Scopus | G59: Yes | H59: No | I59: Yes | J59: Yes | K59: Yes | L59: =IF(COUNTBLANK(G59:K59)=5,"",IF(COUNTIF(G59:K59,"No")>0,"EXCLUDE","INCLUDE")) -> EXCLUDE | M59: =IF(L59<>"EXCLUDE","",IF(G59="No","Wrong domain (non-AECO)",IF(H59="No","Digital Twin not core / buzzword",IF(I59="No","No Design for Safety/Quality/PtD",IF(J59="No","Wrong publication type",IF(K59="No","Non-English","")))))) -> Digital Twin not core / buzzword | S59: =IF(N59<>"Yes","",IF(COUNTBLANK(P59:R59)=3,"",IF(COUNTIF(P59:R59,"No")>0,"EXCLUDE","INCLUDE"))) | T59: =IF(S59<>"EXCLUDE","",IF(P59="No","Digital Twin mentioned only, not the subject",IF(Q59="No","No Design for Safety/Quality in full text",IF(R59="No","Methodology not codable","")))) | Y59: =IF(SUM(V59:X59)=0,"",IF(SUM(V59:X59)>=2,"Multi","Single")) | AG59: BIM+AR safety inspection; no DT (duplicate of #56) | AO59: =IF($A59="","",IFERROR(_xlfn.XLOOKUP($A59,'2_DOI_Lookup'!$A$2:$A$430,'2_DOI_Lookup'!$B$2:$B$430),"NOT IN SOURCE")) -> 10.3390/buildings15132318
A60: 3931 | E60: =IF($A60="","",IFERROR(_xlfn.XLOOKUP($A60,'2_DOI_Lookup'!$D$2:$D$430,'2_DOI_Lookup'!$E$2:$E$430),"TITLE NOT IN SOURCE")) -> On-Site Safety Inspections Through Marker-Less Augmented Reality and Blockchain Notarization of BIM-Based Processes | F60: Web of Science | G60: Yes | H60: No | I60: Yes | J60: Yes | K60: Yes | L60: =IF(COUNTBLANK(G60:K60)=5,"",IF(COUNTIF(G60:K60,"No")>0,"EXCLUDE","INCLUDE")) -> EXCLUDE | M60: =IF(L60<>"EXCLUDE","",IF(G60="No","Wrong domain (non-AECO)",IF(H60="No","Digital Twin not core / buzzword",IF(I60="No","No Design for Safety/Quality/PtD",IF(J60="No","Wrong publication type",IF(K60="No","Non-English","")))))) -> Digital Twin not core / buzzword | S60: =IF(N60<>"Yes","",IF(COUNTBLANK(P60:R60)=3,"",IF(COUNTIF(P60:R60,"No")>0,"EXCLUDE","INCLUDE"))) | T60: =IF(S60<>"EXCLUDE","",IF(P60="No","Digital Twin mentioned only, not the subject",IF(Q60="No","No Design for Safety/Quality in full text",IF(R60="No","Methodology not codable","")))) | Y60: =IF(SUM(V60:X60)=0,"",IF(SUM(V60:X60)>=2,"Multi","Single")) | AG60: Duplicate of ID 3660 (WoS copy); BIM-based, no DT | AO60: =IF($A60="","",IFERROR(_xlfn.XLOOKUP($A60,'2_DOI_Lookup'!$A$2:$A$430,'2_DOI_Lookup'!$B$2:$B$430),"NOT IN SOURCE")) -> 10.3390/buildings15132318
A61: 3679 | E61: =IF($A61="","",IFERROR(_xlfn.XLOOKUP($A61,'2_DOI_Lookup'!$D$2:$D$430,'2_DOI_Lookup'!$E$2:$E$430),"TITLE NOT IN SOURCE")) -> Intelligent Transportation Systems Using Roadside Infrastructure: A Literature Survey | F61: Scopus | G61: No | H61: No | I61: No | J61: Yes | K61: Yes | L61: =IF(COUNTBLANK(G61:K61)=5,"",IF(COUNTIF(G61:K61,"No")>0,"EXCLUDE","INCLUDE")) -> EXCLUDE | M61: =IF(L61<>"EXCLUDE","",IF(G61="No","Wrong domain (non-AECO)",IF(H61="No","Digital Twin not core / buzzword",IF(I61="No","No Design for Safety/Quality/PtD",IF(J61="No","Wrong publication type",IF(K61="No","Non-English","")))))) -> Wrong domain (non-AECO) | S61: =IF(N61<>"Yes","",IF(COUNTBLANK(P61:R61)=3,"",IF(COUNTIF(P61:R61,"No")>0,"EXCLUDE","INCLUDE"))) | T61: =IF(S61<>"EXCLUDE","",IF(P61="No","Digital Twin mentioned only, not the subject",IF(Q61="No","No Design for Safety/Quality in full text",IF(R61="No","Methodology not codable","")))) | Y61: =IF(SUM(V61:X61)=0,"",IF(SUM(V61:X61)>=2,"Multi","Single")) | AG61: Traffic ITS survey; DT only future distribution topic | AO61: =IF($A61="","",IFERROR(_xlfn.XLOOKUP($A61,'2_DOI_Lookup'!$A$2:$A$430,'2_DOI_Lookup'!$B$2:$B$430),"NOT IN SOURCE")) -> 10.1109/TITS.2023.3343434
A62: 3651 | E62: =IF($A62="","",IFERROR(_xlfn.XLOOKUP($A62,'2_DOI_Lookup'!$D$2:$D$430,'2_DOI_Lookup'!$E$2:$E$430),"TITLE NOT IN SOURCE")) -> The role of the foundation flexibility on the seismic response of a modern tall building: Vertically incident plane waves | F62: Scopus | G62: Yes | H62: No | I62: Yes | J62: Yes | K62: Yes | L62: =IF(COUNTBLANK(G62:K62)=5,"",IF(COUNTIF(G62:K62,"No")>0,"EXCLUDE","INCLUDE")) -> EXCLUDE | M62: =IF(L62<>"EXCLUDE","",IF(G62="No","Wrong domain (non-AECO)",IF(H62="No","Digital Twin not core / buzzword",IF(I62="No","No Design for Safety/Quality/PtD",IF(J62="No","Wrong publication type",IF(K62="No","Non-English","")))))) -> Digital Twin not core / buzzword | S62: =IF(N62<>"Yes","",IF(COUNTBLANK(P62:R62)=3,"",IF(COUNTIF(P62:R62,"No")>0,"EXCLUDE","INCLUDE"))) | T62: =IF(S62<>"EXCLUDE","",IF(P62="No","Digital Twin mentioned only, not the subject",IF(Q62="No","No Design for Safety/Quality in full text",IF(R62="No","Methodology not codable","")))) | Y62: =IF(SUM(V62:X62)=0,"",IF(SUM(V62:X62)>=2,"Multi","Single")) | AG62: Pure FE soil-structure interaction study; no DT | AO62: =IF($A62="","",IFERROR(_xlfn.XLOOKUP($A62,'2_DOI_Lookup'!$A$2:$A$430,'2_DOI_Lookup'!$B$2:$B$430),"NOT IN SOURCE")) -> 10.1016/j.soildyn.2024.108819
A63: 3830 | E63: =IF($A63="","",IFERROR(_xlfn.XLOOKUP($A63,'2_DOI_Lookup'!$D$2:$D$430,'2_DOI_Lookup'!$E$2:$E$430),"TITLE NOT IN SOURCE")) -> For how large soil shear wave velocity the soil-structure interaction effects on a tall building can be neglected? – A case study | F63: Scopus | G63: Yes | H63: No | I63: Yes | J63: Yes | K63: Yes | L63: =IF(COUNTBLANK(G63:K63)=5,"",IF(COUNTIF(G63:K63,"No")>0,"EXCLUDE","INCLUDE")) -> EXCLUDE | M63: =IF(L63<>"EXCLUDE","",IF(G63="No","Wrong domain (non-AECO)",IF(H63="No","Digital Twin not core / buzzword",IF(I63="No","No Design for Safety/Quality/PtD",IF(J63="No","Wrong publication type",IF(K63="No","Non-English","")))))) -> Digital Twin not core / buzzword | S63: =IF(N63<>"Yes","",IF(COUNTBLANK(P63:R63)=3,"",IF(COUNTIF(P63:R63,"No")>0,"EXCLUDE","INCLUDE"))) | T63: =IF(S63<>"EXCLUDE","",IF(P63="No","Digital Twin mentioned only, not the subject",IF(Q63="No","No Design for Safety/Quality in full text",IF(R63="No","Methodology not codable","")))) | Y63: =IF(SUM(V63:X63)=0,"",IF(SUM(V63:X63)>=2,"Multi","Single")) | AG63: Pure FE seismic SSI analysis; no DT | AO63: =IF($A63="","",IFERROR(_xlfn.XLOOKUP($A63,'2_DOI_Lookup'!$A$2:$A$430,'2_DOI_Lookup'!$B$2:$B$430),"NOT IN SOURCE")) -> 10.1016/j.soildyn.2024.108845
A64: 3793 | E64: =IF($A64="","",IFERROR(_xlfn.XLOOKUP($A64,'2_DOI_Lookup'!$D$2:$D$430,'2_DOI_Lookup'!$E$2:$E$430),"TITLE NOT IN SOURCE")) -> Online traffic load identification of high-speed railway bridge using time integration of strain monitoring data | F64: Scopus | G64: Yes | H64: No | I64: Yes | J64: Yes | K64: Yes | L64: =IF(COUNTBLANK(G64:K64)=5,"",IF(COUNTIF(G64:K64,"No")>0,"EXCLUDE","INCLUDE")) -> EXCLUDE | M64: =IF(L64<>"EXCLUDE","",IF(G64="No","Wrong domain (non-AECO)",IF(H64="No","Digital Twin not core / buzzword",IF(I64="No","No Design for Safety/Quality/PtD",IF(J64="No","Wrong publication type",IF(K64="No","Non-English","")))))) -> Digital Twin not core / buzzword | S64: =IF(N64<>"Yes","",IF(COUNTBLANK(P64:R64)=3,"",IF(COUNTIF(P64:R64,"No")>0,"EXCLUDE","INCLUDE"))) | T64: =IF(S64<>"EXCLUDE","",IF(P64="No","Digital Twin mentioned only, not the subject",IF(Q64="No","No Design for Safety/Quality in full text",IF(R64="No","Methodology not codable","")))) | Y64: =IF(SUM(V64:X64)=0,"",IF(SUM(V64:X64)>=2,"Multi","Single")) | AG64: Load-identification method; DT only data consumer | AO64: =IF($A64="","",IFERROR(_xlfn.XLOOKUP($A64,'2_DOI_Lookup'!$A$2:$A$430,'2_DOI_Lookup'!$B$2:$B$430),"NOT IN SOURCE")) -> 10.1016/j.measurement.2026.120781
A65: 3802 | B65: Dan (2022) | C65: 2022 | E65: =IF($A65="","",IFERROR(_xlfn.XLOOKUP($A65,'2_DOI_Lookup'!$D$2:$D$430,'2_DOI_Lookup'!$E$2:$E$430),"TITLE NOT IN SOURCE")) -> Digital Twin System of Bridges Group Based on Machine Vision Fusion Monitoring of Bridge Traffic Load | F65: Scopus | G65: Yes | H65: Yes | I65: Yes | J65: Yes | K65: Yes | L65: =IF(COUNTBLANK(G65:K65)=5,"",IF(COUNTIF(G65:K65,"No")>0,"EXCLUDE","INCLUDE")) -> INCLUDE | M65: =IF(L65<>"EXCLUDE","",IF(G65="No","Wrong domain (non-AECO)",IF(H65="No","Digital Twin not core / buzzword",IF(I65="No","No Design for Safety/Quality/PtD",IF(J65="No","Wrong publication type",IF(K65="No","Non-English","")))))) | N65: Yes | O65: Yes | P65: Yes | Q65: Yes | R65: Yes | S65: =IF(N65<>"Yes","",IF(COUNTBLANK(P65:R65)=3,"",IF(COUNTIF(P65:R65,"No")>0,"EXCLUDE","INCLUDE"))) -> INCLUDE | T65: =IF(S65<>"EXCLUDE","",IF(P65="No","Digital Twin mentioned only, not the subject",IF(Q65="No","No Design for Safety/Quality in full text",IF(R65="No","Methodology not codable","")))) | U65: Tier 2 - Digital Shadow (one-way physical to virtual) | V65: 0 | W65: 0 | X65: 1 | Y65: =IF(SUM(V65:X65)=0,"",IF(SUM(V65:X65)>=2,"Multi","Single")) -> Single | Z65: Design for Safety (DfS) | AA65: None | AB65: Computer Vision / CNN / object-detection | AC65: Multi (two or more data types) | AD65: Single case study | AE65: 4 | AF65: Predictive analytics / decision support | AG65: Digital twin system for a regional bridges group (Shanghai, Tongji U): physical space - WIM + multi-source machine vision traffic-load monitoring on target bridge + lightweight sensors on bridge group; digital space - mechanical analysis models per bridge linked by measured traffic loads for working-condition perception and safety warning across the regional network; preliminarily implemented in a Shanghai bridges group. One-way monitoring to analysis to warning for operators; no actuation and no learning loop. [Full-text source: Endnote] | AH65: Fills the group-level gap in bridge digital twins: for a regional bridge network around Shanghai, weigh-in-motion and multi-source machine vision fusion measure full-bridge traffic loads on a target bridge, lightweight sensors capture responses on group bridges, and measured loads drive mechanical models in digital space, enabling working-condition perception and safety warning across the whole network, demonstrated with Monte Carlo and Intelligent Driver Model simulations on the Yongjiang cable-stayed bridge. | AI65: One-way implementation: digital models are loaded with measured traffic loads but no feedback or control channel back to physical bridges exists, and deriving bridge health status from simulation results to form more interaction tasks between the two spaces is left as future exploration. | AJ65: Fused | AK65: Weigh-in-motion and multi-source machine-vision monitoring are fused to measure full-bridge traffic loads, which then drive the mechanical analysis models of a regional bridge group. | AL65: High | AN65: Verified 2026-08-22 vs PDF (IEEE T-ITS 23(11), 2022). WIM + multi-source machine-vision traffic-load fusion, lightweight sensors on the bridges group, and preliminary implementation in a bridges group around Shanghai all confirmed. Tier 2, AA None upheld. | AO65: =IF($A65="","",IFERROR(_xlfn.XLOOKUP($A65,'2_DOI_Lookup'!$A$2:$A$430,'2_DOI_Lookup'!$B$2:$B$430),"NOT IN SOURCE")) -> 10.1109/TITS.2021.3130025
A66: 4007 | E66: =IF($A66="","",IFERROR(_xlfn.XLOOKUP($A66,'2_DOI_Lookup'!$D$2:$D$430,'2_DOI_Lookup'!$E$2:$E$430),"TITLE NOT IN SOURCE")) -> Assessing the Suitability of Damage Indexes for Digital Twin Applications in RC Buildings Considering Masonry Infills | F66: Web of Science | G66: Yes | H66: No | I66: Yes | J66: Yes | K66: Yes | L66: =IF(COUNTBLANK(G66:K66)=5,"",IF(COUNTIF(G66:K66,"No")>0,"EXCLUDE","INCLUDE")) -> EXCLUDE | M66: =IF(L66<>"EXCLUDE","",IF(G66="No","Wrong domain (non-AECO)",IF(H66="No","Digital Twin not core / buzzword",IF(I66="No","No Design for Safety/Quality/PtD",IF(J66="No","Wrong publication type",IF(K66="No","Non-English","")))))) -> Digital Twin not core / buzzword | S66: =IF(N66<>"Yes","",IF(COUNTBLANK(P66:R66)=3,"",IF(COUNTIF(P66:R66,"No")>0,"EXCLUDE","INCLUDE"))) | T66: =IF(S66<>"EXCLUDE","",IF(P66="No","Digital Twin mentioned only, not the subject",IF(Q66="No","No Design for Safety/Quality in full text",IF(R66="No","Methodology not codable","")))) | Y66: =IF(SUM(V66:X66)=0,"",IF(SUM(V66:X66)>=2,"Multi","Single")) | AG66: Damage-index benchmarking; DT only future use | AO66: =IF($A66="","",IFERROR(_xlfn.XLOOKUP($A66,'2_DOI_Lookup'!$A$2:$A$430,'2_DOI_Lookup'!$B$2:$B$430),"NOT IN SOURCE")) -> 10.3390/app15041999
A67: 3708 | E67: =IF($A67="","",IFERROR(_xlfn.XLOOKUP($A67,'2_DOI_Lookup'!$D$2:$D$430,'2_DOI_Lookup'!$E$2:$E$430),"TITLE NOT IN SOURCE")) -> The role of the marine research infrastructures in the European marine observation landscape: present and future perspectives | F67: Scopus | G67: No | H67: No | I67: No | J67: Yes | K67: Yes | L67: =IF(COUNTBLANK(G67:K67)=5,"",IF(COUNTIF(G67:K67,"No")>0,"EXCLUDE","INCLUDE")) -> EXCLUDE | M67: =IF(L67<>"EXCLUDE","",IF(G67="No","Wrong domain (non-AECO)",IF(H67="No","Digital Twin not core / buzzword",IF(I67="No","No Design for Safety/Quality/PtD",IF(J67="No","Wrong publication type",IF(K67="No","Non-English","")))))) -> Wrong domain (non-AECO) | S67: =IF(N67<>"Yes","",IF(COUNTBLANK(P67:R67)=3,"",IF(COUNTIF(P67:R67,"No")>0,"EXCLUDE","INCLUDE"))) | T67: =IF(S67<>"EXCLUDE","",IF(P67="No","Digital Twin mentioned only, not the subject",IF(Q67="No","No Design for Safety/Quality in full text",IF(R67="No","Methodology not codable","")))) | Y67: =IF(SUM(V67:X67)=0,"",IF(SUM(V67:X67)>=2,"Multi","Single")) | AG67: Marine science RIs; not AECO | AO67: =IF($A67="","",IFERROR(_xlfn.XLOOKUP($A67,'2_DOI_Lookup'!$A$2:$A$430,'2_DOI_Lookup'!$B$2:$B$430),"NOT IN SOURCE")) -> 10.3389/fmars.2023.1047251
A68: 3631 | E68: =IF($A68="","",IFERROR(_xlfn.XLOOKUP($A68,'2_DOI_Lookup'!$D$2:$D$430,'2_DOI_Lookup'!$E$2:$E$430),"TITLE NOT IN SOURCE")) -> Enhancing Operational Resilience of Critical Infrastructure Processes Through Chaos Engineering | F68: Scopus | G68: No | H68: Yes | I68: No | J68: Yes | K68: Yes | L68: =IF(COUNTBLANK(G68:K68)=5,"",IF(COUNTIF(G68:K68,"No")>0,"EXCLUDE","INCLUDE")) -> EXCLUDE | M68: =IF(L68<>"EXCLUDE","",IF(G68="No","Wrong domain (non-AECO)",IF(H68="No","Digital Twin not core / buzzword",IF(I68="No","No Design for Safety/Quality/PtD",IF(J68="No","Wrong publication type",IF(K68="No","Non-English","")))))) -> Wrong domain (non-AECO) | S68: =IF(N68<>"Yes","",IF(COUNTBLANK(P68:R68)=3,"",IF(COUNTIF(P68:R68,"No")>0,"EXCLUDE","INCLUDE"))) | T68: =IF(S68<>"EXCLUDE","",IF(P68="No","Digital Twin mentioned only, not the subject",IF(Q68="No","No Design for Safety/Quality in full text",IF(R68="No","Methodology not codable","")))) | Y68: =IF(SUM(V68:X68)=0,"",IF(SUM(V68:X68)>=2,"Multi","Single")) | AG68: Oil-refinery process CPS; industrial | AO68: =IF($A68="","",IFERROR(_xlfn.XLOOKUP($A68,'2_DOI_Lookup'!$A$2:$A$430,'2_DOI_Lookup'!$B$2:$B$430),"NOT IN SOURCE")) -> 10.1109/ACCESS.2023.3316028
A69: 3626 | B69: Delhibabu (2026) | C69: 2026 | E69: =IF($A69="","",IFERROR(_xlfn.XLOOKUP($A69,'2_DOI_Lookup'!$D$2:$D$430,'2_DOI_Lookup'!$E$2:$E$430),"TITLE NOT IN SOURCE")) -> Interconnected digital twins of subway stations for decision support systems | F69: Scopus | G69: Yes | H69: Yes | I69: Yes | J69: Yes | K69: Yes | L69: =IF(COUNTBLANK(G69:K69)=5,"",IF(COUNTIF(G69:K69,"No")>0,"EXCLUDE","INCLUDE")) -> INCLUDE | M69: =IF(L69<>"EXCLUDE","",IF(G69="No","Wrong domain (non-AECO)",IF(H69="No","Digital Twin not core / buzzword",IF(I69="No","No Design for Safety/Quality/PtD",IF(J69="No","Wrong publication type",IF(K69="No","Non-English","")))))) | N69: Yes | O69: Yes | P69: Yes | Q69: Yes | R69: Yes | S69: =IF(N69<>"Yes","",IF(COUNTBLANK(P69:R69)=3,"",IF(COUNTIF(P69:R69,"No")>0,"EXCLUDE","INCLUDE"))) -> INCLUDE | T69: =IF(S69<>"EXCLUDE","",IF(P69="No","Digital Twin mentioned only, not the subject",IF(Q69="No","No Design for Safety/Quality in full text",IF(R69="No","Methodology not codable","")))) | U69: Tier 2 - Digital Shadow (one-way physical to virtual) | V69: 0 | W69: 0 | X69: 1 | Y69: =IF(SUM(V69:X69)=0,"",IF(SUM(V69:X69)>=2,"Multi","Single")) -> Single | Z69: Design for Safety (DfS) | AA69: None | AB69: Computer Vision / CNN / object-detection | AC69: Multi (two or more data types) | AD69: Single case study | AE69: 4 | AF69: Predictive analytics / decision support | AG69: Interconnected digital twins of subway stations for decision support (VIT/FRC RAS): per-station DTs interconnected to interact during operational scenarios; cameras, microphones, sensors processed in fog computing; mobile app with intelligent assistant displays detected events and answers queries via voice; event detection for hazardous situations (fire/explosion); implementation improved personnel response time by 17.4% vs REPEAT platform. One-way monitoring to event detection to decision support for operators; no actuation and no learning loop. [Full-text source: Endnote] | AH69: Fills the incident-response gap of subway station digital twins: interconnected per-station twins process camera, microphone and sensor data in a fog computing environment, a fine-tuned YOLOv8 detector (mAP 0.5 of 92.4 percent) spots events shown on a mobile app with a voice assistant, and personnel response times improved by 17.4 percent versus the REPEAT platform across 50 simulated trials. | AI69: Results come from simulated emergency scenarios, and continuous TCP/IP connectivity is assumed, so deep subterranean network degradation could break the fog-to-mobile pipeline; speech recognition reaches only a 14.2 percent word error rate under 85 dB noise, and the app runs only on Android and Linux; future plans include signaling and control integration to automatically stop trains and escalators. | AJ69: Co-present | AK69: Camera feeds drive YOLOv8 event detection while microphone and sensor streams support a separate voice-assistant pipeline in the same fog-computing platform, with no common representation stated. | AL69: Medium | AN69: Verified 2026-08-22 vs PDF (Results in Engineering, VIT/FRC RAS). 17.4% response-time improvement vs REPEAT platform, fog computing, cameras/microphones/sensors and voice intelligent assistant all confirmed. Tier 2, AA None upheld. | AO69: =IF($A69="","",IFERROR(_xlfn.XLOOKUP($A69,'2_DOI_Lookup'!$A$2:$A$430,'2_DOI_Lookup'!$B$2:$B$430),"NOT IN SOURCE")) -> 10.1016/j.rineng.2026.110745
A70: 3967 | B70: Deng (2025) | C70: 2025 | E70: =IF($A70="","",IFERROR(_xlfn.XLOOKUP($A70,'2_DOI_Lookup'!$D$2:$D$430,'2_DOI_Lookup'!$E$2:$E$430),"TITLE NOT IN SOURCE")) -> Structural Analysis of Construction Risk Management Assessment Model Based on Digital Twins | F70: Web of Science | G70: Yes | H70: Yes | I70: Yes | J70: Yes | K70: Yes | L70: =IF(COUNTBLANK(G70:K70)=5,"",IF(COUNTIF(G70:K70,"No")>0,"EXCLUDE","INCLUDE")) -> INCLUDE | M70: =IF(L70<>"EXCLUDE","",IF(G70="No","Wrong domain (non-AECO)",IF(H70="No","Digital Twin not core / buzzword",IF(I70="No","No Design for Safety/Quality/PtD",IF(J70="No","Wrong publication type",IF(K70="No","Non-English","")))))) | N70: Yes | O70: Yes | P70: Yes | Q70: Yes | R70: Yes | S70: =IF(N70<>"Yes","",IF(COUNTBLANK(P70:R70)=3,"",IF(COUNTIF(P70:R70,"No")>0,"EXCLUDE","INCLUDE"))) -> INCLUDE | T70: =IF(S70<>"EXCLUDE","",IF(P70="No","Digital Twin mentioned only, not the subject",IF(Q70="No","No Design for Safety/Quality in full text",IF(R70="No","Methodology not codable","")))) | U70: Tier 2 - Digital Shadow (one-way physical to virtual) | V70: 0 | W70: 1 | X70: 0 | Y70: =IF(SUM(V70:X70)=0,"",IF(SUM(V70:X70)>=2,"Multi","Single")) -> Single | Z70: Both | AA70: None | AB70: Other / Mixed | AC70: Multi (two or more data types) | AD70: Single case study | AE70: 3 | AF70: Predictive analytics / decision support | AG70: DTCRAM: five-layer DT construction-risk assessment model (physical twin / data twin / twin model / data analysis / decision feedback) built via 3-round Delphi (9 experts, 15 risks incl. worker safety A1, equipment safety A2, construction quality A3) + case study (Thames Tidal Tunnel); real-time sensor data feeds simulation/risk prediction; claimed ~1% risk-probability reduction per project (A2 5%->3%, C1 3%->2%) but figures are estimates; feedback/optimisation loop described conceptually, not a demonstrated learning mechanism. [Full-text source: Endnote] | AH70: Responds to the lack of practical construction risk models: DTCRAM combines a three-round Delphi study with nine industry experts, identifying 15 construction risks and 15 countermeasures classified into 12 strategy types, with a five-layer digital twin structure (physical twin, data twin, twin model, data analysis, decision feedback) for dynamic monitoring and risk prediction, verified on the Thames Tidal Tunnel case with over 1 percent probability reduction per project. | AI70: Expert-driven and weakly operationalized: only nine Delphi experts limit objectivity, results are tied to one specific project, and the model remains at a development stage with unquantified technical and methodological challenges; future research targets higher applicability and accuracy, larger samples across project types, and artificial intelligence and big data integration. | AJ70: Unclear | AK70: The five-layer DTCRAM risk model is built from a Delphi study and a case study in which sensor-fed simulation and feedback loops are described only conceptually, so no implemented integration mechanism can be identified. | AL70: High | AN70: Verified 2026-08-22 vs PDF. DTCRAM five-layer model built on Delphi, and the Thames Tidal Tunnel case (25 km London sewer/stormwater project) confirmed. Tier 2, AD Single case study, AA None upheld. | AO70: =IF($A70="","",IFERROR(_xlfn.XLOOKUP($A70,'2_DOI_Lookup'!$A$2:$A$430,'2_DOI_Lookup'!$B$2:$B$430),"NOT IN SOURCE")) -> 10.21315/jcdc.2025.30.s2.10
A71: 4036 | B71: Deng (2025) | C71: 2025 | E71: =IF($A71="","",IFERROR(_xlfn.XLOOKUP($A71,'2_DOI_Lookup'!$D$2:$D$430,'2_DOI_Lookup'!$E$2:$E$430),"TITLE NOT IN SOURCE")) -> Real-time bridge disaster management: Enabling technology and application framework | F71: Web of Science | G71: Yes | H71: Yes | I71: Yes | J71: Yes | K71: Yes | L71: =IF(COUNTBLANK(G71:K71)=5,"",IF(COUNTIF(G71:K71,"No")>0,"EXCLUDE","INCLUDE")) -> INCLUDE | M71: =IF(L71<>"EXCLUDE","",IF(G71="No","Wrong domain (non-AECO)",IF(H71="No","Digital Twin not core / buzzword",IF(I71="No","No Design for Safety/Quality/PtD",IF(J71="No","Wrong publication type",IF(K71="No","Non-English","")))))) | N71: Yes | O71: Yes | P71: Yes | Q71: Yes | R71: Yes | S71: =IF(N71<>"Yes","",IF(COUNTBLANK(P71:R71)=3,"",IF(COUNTIF(P71:R71,"No")>0,"EXCLUDE","INCLUDE"))) -> INCLUDE | T71: =IF(S71<>"EXCLUDE","",IF(P71="No","Digital Twin mentioned only, not the subject",IF(Q71="No","No Design for Safety/Quality in full text",IF(R71="No","Methodology not codable","")))) | U71: Tier 1 - Digital Model (static, no live data) | V71: 0 | W71: 0 | X71: 1 | Y71: =IF(SUM(V71:X71)=0,"",IF(SUM(V71:X71)>=2,"Multi","Single")) -> Single | Z71: Design for Safety (DfS) | AA71: None | AB71: Digital Twin platform (no machine learning) | AC71: Multi (two or more data types) | AD71: Conceptual (no test) | AE71: 3 | AF71: BIM-to-Digital-Twin architecture | AG71: Systematic review (146 articles) of bridge disaster management + proposed Real-time Bridge Disaster Management (RtBDM) framework: dynamic adaptation + digitalisation (BIM/DT integration for full-lifecycle data management and automated decision-making) + disaster cycle (pre-warning, real-time response, post-disaster recovery); addresses interoperability, delayed response, and coordination gaps. Framework only - no DT built or validated; no live data link and no learning loop. [Full-text source: Endnote] | AH71: Synthesizes 146 bridge disaster management articles to expose fragmented technology integration, delayed response and poor coordination, then proposes the RtBDM framework combining dynamic adaptation, digitalisation and a disaster-cycle component that integrates BIM and digital twin technologies with sensors, big data analytics, IoT and artificial intelligence for real-time monitoring, early warning, response and recovery across pre-disaster to post-disaster phases. | AI71: Purely conceptual: the framework is built only on literature analysis and existing tools, has not been validated in any real-world scenario, and needs ongoing updates to track technology; future research should run pilot implementations and case studies across regions, disaster types and bridge systems, and improve technology integration and data management. | AJ71: Unclear | AK71: A review-based RtBDM framework proposes BIM/DT integration with sensors and AI for real-time bridge disaster management, but no system is built or validated, so no integration mechanism is demonstrated. | AL71: High | AN71: Verified 2026-08-22 vs PDF. "This paper systematically reviews 146 research articles on bridge disaster management" and the proposed Real-time Bridge Disaster Management (RtBDM) framework both confirmed; framework only, nothing built. Tier 1, AD Conceptual, AA None upheld. | AO71: =IF($A71="","",IFERROR(_xlfn.XLOOKUP($A71,'2_DOI_Lookup'!$A$2:$A$430,'2_DOI_Lookup'!$B$2:$B$430),"NOT IN SOURCE")) -> 10.1016/j.autcon.2025.106150
A72: 3760 | B72: Deng (2026) | C72: 2026 | E72: =IF($A72="","",IFERROR(_xlfn.XLOOKUP($A72,'2_DOI_Lookup'!$D$2:$D$430,'2_DOI_Lookup'!$E$2:$E$430),"TITLE NOT IN SOURCE")) -> Integrating LLMs and Digital Twins for Adaptive Multi-Robot Task Allocation in Construction | F72: Scopus | G72: Yes | H72: Yes | I72: Yes | J72: Yes | K72: Yes | L72: =IF(COUNTBLANK(G72:K72)=5,"",IF(COUNTIF(G72:K72,"No")>0,"EXCLUDE","INCLUDE")) -> INCLUDE | M72: =IF(L72<>"EXCLUDE","",IF(G72="No","Wrong domain (non-AECO)",IF(H72="No","Digital Twin not core / buzzword",IF(I72="No","No Design for Safety/Quality/PtD",IF(J72="No","Wrong publication type",IF(K72="No","Non-English","")))))) | N72: Yes | O72: Yes | P72: Yes | Q72: Yes | R72: Yes | S72: =IF(N72<>"Yes","",IF(COUNTBLANK(P72:R72)=3,"",IF(COUNTIF(P72:R72,"No")>0,"EXCLUDE","INCLUDE"))) -> INCLUDE | T72: =IF(S72<>"EXCLUDE","",IF(P72="No","Digital Twin mentioned only, not the subject",IF(Q72="No","No Design for Safety/Quality in full text",IF(R72="No","Methodology not codable","")))) | U72: Tier 3 - Digital Twin (bidirectional, two-way) | V72: 0 | W72: 1 | X72: 0 | Y72: =IF(SUM(V72:X72)=0,"",IF(SUM(V72:X72)>=2,"Multi","Single")) -> Single | Z72: Design for Safety (DfS) | AA72: None | AB72: Transformer / Large Language Model (LLM) | AC72: Multi (two or more data types) | AD72: Single case study | AE72: 4 | AF72: Predictive analytics / decision support | AG72: Adaptive multi-robot task allocation framework (UTK/Amazon/TAMU): DT system enables real-time synchronization between physical operations and digital representations as user interface, creating closed-loop feedback; Integer Programming models task allocation (dependencies, heterogeneity, scheduling, replanning); LLM interprets natural-language inputs to autonomously update optimization constraints (97% accuracy in constraint/parameter extraction) without manual programming; case study demonstrates computational efficiency and LLM reasoning. Closed-loop feedback + LLM-based constraint adaptation -> Tier 3; no learning loop (LLM is inference-time, not self-improving). [Full-text source: Endnote] | AH72: Addresses static, code-bound multi-robot scheduling: a closed-loop digital twin in Unity, synchronized with ROS and Gazebo, supports integer-programming task allocation whose constraints are updated by an LLM interpreting plain-language site narratives, achieving over 97 percent constraint and parameter extraction accuracy with GPT-4.1, optimal plans within about one second and 0.08-second replanning across 1024 scenarios of 27 tasks and 15 robots. | AI72: Validated only in simulation: Gazebo idealizes robot-human collaboration and material handling, human worker actions are not modeled, and the LLM is limited to constraint extraction; extending to further construction scenarios, proactive conflict detection and pre-optimization reasoning are future work, with physical robot deployment still pending. | AJ72: Fused | AK72: An LLM interprets natural-language site narratives into integer-programming constraints that jointly determine task allocation together with the Unity DT state synchronised with ROS/Gazebo. | AL72: High | AN72: Verified 2026-08-22 vs PDF. Tier 3 supported: DT "serves as the user interface, creating a closed-loop feedback mechanism"; "closed-loop digital twin system" in methodology. LLM constraint/parameter extraction "over 97% accuracy" confirmed. Validation is a Gazebo simulation case study; AA None upheld (LLM is inference-time, not self-improving). | AO72: =IF($A72="","",IFERROR(_xlfn.XLOOKUP($A72,'2_DOI_Lookup'!$A$2:$A$430,'2_DOI_Lookup'!$B$2:$B$430),"NOT IN SOURCE")) -> 10.1109/TASE.2026.3697962
A73: 3521 | E73: =IF($A73="","",IFERROR(_xlfn.XLOOKUP($A73,'2_DOI_Lookup'!$D$2:$D$430,'2_DOI_Lookup'!$E$2:$E$430),"TITLE NOT IN SOURCE")) -> Application Benefit Analysis of Digital Twin Technology in Tunnel Construction Based on DEMATEL and System Dynamics | F73: Scopus | G73: Yes | H73: Yes | I73: Yes | J73: Yes | K73: No | L73: =IF(COUNTBLANK(G73:K73)=5,"",IF(COUNTIF(G73:K73,"No")>0,"EXCLUDE","INCLUDE")) -> EXCLUDE | M73: =IF(L73<>"EXCLUDE","",IF(G73="No","Wrong domain (non-AECO)",IF(H73="No","Digital Twin not core / buzzword",IF(I73="No","No Design for Safety/Quality/PtD",IF(J73="No","Wrong publication type",IF(K73="No","Non-English","")))))) -> Non-English | S73: =IF(N73<>"Yes","",IF(COUNTBLANK(P73:R73)=3,"",IF(COUNTIF(P73:R73,"No")>0,"EXCLUDE","INCLUDE"))) | T73: =IF(S73<>"EXCLUDE","",IF(P73="No","Digital Twin mentioned only, not the subject",IF(Q73="No","No Design for Safety/Quality in full text",IF(R73="No","Methodology not codable","")))) | Y73: =IF(SUM(V73:X73)=0,"",IF(SUM(V73:X73)>=2,"Multi","Single")) | AG73: Chinese journal (Tunnel Construction); non-English | AO73: =IF($A73="","",IFERROR(_xlfn.XLOOKUP($A73,'2_DOI_Lookup'!$A$2:$A$430,'2_DOI_Lookup'!$B$2:$B$430),"NOT IN SOURCE")) -> 10.3973/j.issn.2096-4498.2024.S1.021
A74: 4002 | E74: =IF($A74="","",IFERROR(_xlfn.XLOOKUP($A74,'2_DOI_Lookup'!$D$2:$D$430,'2_DOI_Lookup'!$E$2:$E$430),"TITLE NOT IN SOURCE")) -> Smart building evacuation by tracking multi-camera network and explainable Re-identification model | F74: Web of Science | G74: Yes | H74: No | I74: Yes | J74: Yes | K74: Yes | L74: =IF(COUNTBLANK(G74:K74)=5,"",IF(COUNTIF(G74:K74,"No")>0,"EXCLUDE","INCLUDE")) -> EXCLUDE | M74: =IF(L74<>"EXCLUDE","",IF(G74="No","Wrong domain (non-AECO)",IF(H74="No","Digital Twin not core / buzzword",IF(I74="No","No Design for Safety/Quality/PtD",IF(J74="No","Wrong publication type",IF(K74="No","Non-English","")))))) -> Digital Twin not core / buzzword | S74: =IF(N74<>"Yes","",IF(COUNTBLANK(P74:R74)=3,"",IF(COUNTIF(P74:R74,"No")>0,"EXCLUDE","INCLUDE"))) | T74: =IF(S74<>"EXCLUDE","",IF(P74="No","Digital Twin mentioned only, not the subject",IF(Q74="No","No Design for Safety/Quality in full text",IF(R74="No","Methodology not codable","")))) | Y74: =IF(SUM(V74:X74)=0,"",IF(SUM(V74:X74)>=2,"Multi","Single")) | AG74: CV tracking framework; DT as end-goal only | AO74: =IF($A74="","",IFERROR(_xlfn.XLOOKUP($A74,'2_DOI_Lookup'!$A$2:$A$430,'2_DOI_Lookup'!$B$2:$B$430),"NOT IN SOURCE")) -> 10.1016/j.engappai.2025.110394
A75: 3528 | E75: =IF($A75="","",IFERROR(_xlfn.XLOOKUP($A75,'2_DOI_Lookup'!$D$2:$D$430,'2_DOI_Lookup'!$E$2:$E$430),"TITLE NOT IN SOURCE")) -> Digital twin system construction method for evaluating load carrying capacity of crane structures | F75: Scopus | G75: Yes | H75: Yes | I75: Yes | J75: Yes | K75: No | L75: =IF(COUNTBLANK(G75:K75)=5,"",IF(COUNTIF(G75:K75,"No")>0,"EXCLUDE","INCLUDE")) -> EXCLUDE | M75: =IF(L75<>"EXCLUDE","",IF(G75="No","Wrong domain (non-AECO)",IF(H75="No","Digital Twin not core / buzzword",IF(I75="No","No Design for Safety/Quality/PtD",IF(J75="No","Wrong publication type",IF(K75="No","Non-English","")))))) -> Non-English | S75: =IF(N75<>"Yes","",IF(COUNTBLANK(P75:R75)=3,"",IF(COUNTIF(P75:R75,"No")>0,"EXCLUDE","INCLUDE"))) | T75: =IF(S75<>"EXCLUDE","",IF(P75="No","Digital Twin mentioned only, not the subject",IF(Q75="No","No Design for Safety/Quality in full text",IF(R75="No","Methodology not codable","")))) | Y75: =IF(SUM(V75:X75)=0,"",IF(SUM(V75:X75)>=2,"Multi","Single")) | AG75: Chinese journal (CIMS); non-English full text | AO75: =IF($A75="","",IFERROR(_xlfn.XLOOKUP($A75,'2_DOI_Lookup'!$A$2:$A$430,'2_DOI_Lookup'!$B$2:$B$430),"NOT IN SOURCE")) -> 10.13196/j.cims.2023.0391
A76: 3736 | B76: Doukari (2026) | C76: 2026 | E76: =IF($A76="","",IFERROR(_xlfn.XLOOKUP($A76,'2_DOI_Lookup'!$D$2:$D$430,'2_DOI_Lookup'!$E$2:$E$430),"TITLE NOT IN SOURCE")) -> Stakeholder-informed renovation digital twin for multi-domain monitoring: Pilot implementation and acceptance evaluation | F76: Scopus | G76: Yes | H76: Yes | I76: Yes | J76: Yes | K76: Yes | L76: =IF(COUNTBLANK(G76:K76)=5,"",IF(COUNTIF(G76:K76,"No")>0,"EXCLUDE","INCLUDE")) -> INCLUDE | M76: =IF(L76<>"EXCLUDE","",IF(G76="No","Wrong domain (non-AECO)",IF(H76="No","Digital Twin not core / buzzword",IF(I76="No","No Design for Safety/Quality/PtD",IF(J76="No","Wrong publication type",IF(K76="No","Non-English","")))))) | N76: Yes | O76: Yes | P76: Yes | Q76: Yes | R76: Yes | S76: =IF(N76<>"Yes","",IF(COUNTBLANK(P76:R76)=3,"",IF(COUNTIF(P76:R76,"No")>0,"EXCLUDE","INCLUDE"))) -> INCLUDE | T76: =IF(S76<>"EXCLUDE","",IF(P76="No","Digital Twin mentioned only, not the subject",IF(Q76="No","No Design for Safety/Quality in full text",IF(R76="No","Methodology not codable","")))) | U76: Tier 2 - Digital Shadow (one-way physical to virtual) | V76: 0 | W76: 1 | X76: 0 | Y76: =IF(SUM(V76:X76)=0,"",IF(SUM(V76:X76)>=2,"Multi","Single")) -> Single | Z76: Both | AA76: None | AB76: Digital Twin platform (no machine learning) | AC76: Multi (two or more data types) | AD76: Single case study | AE76: 4 | AF76: Lifecycle / governance | AG76: Renovation Digital Twin (RDT) platform (Northumbria U, RINNO Project): pilot implementation on French demonstration site; real-time data + dashboards monitoring 13 KPIs across 5 domains (cost, schedule, quality, safety, environment); TAM evaluation (102 professionals, Attitude Toward Use RII 0.894); 73% emissions reduction achieved but economic viability challenges. One-way monitoring→dashboard→decision support; no actuation and no learning loop. [Full-text source: Endnote] | AH76: Fills the renovation-phase gap in digital twins: a stakeholder-informed Renovation Digital Twin built with Design Science Research in the RINNO project monitors 13 KPIs across cost, schedule, quality, safety and environment on the Project Sarrazins demo site in Lille, and a Technology Acceptance Model survey of 102 professionals gave attitude toward use RII 0.894 while the site achieved a 73 percent emissions reduction. | AI76: Proof-of-concept scope: a single renovation project, functional verification only, no quantified cost, schedule or safety improvements, a short evaluation period, a TAM sample biased to early-career professionals, manual data entry, and no AI or predictive analytics beyond historical KPI visualization; future work calls for multi-site validation, longitudinal studies, IoT automation, deep-learning prediction and cognitive twin capabilities. | AJ76: Co-present | AK76: Real-time data and dashboards monitor 13 KPIs across five domains (cost, schedule, quality, safety, environment) in one renovation DT platform, without a stated shared reference frame joining the domains. | AL76: Medium | AN76: Verified 2026-08-22 vs PDF. RINNO Renovation Digital Twin, 13 KPIs, TAM survey of 102 professionals (Attitude Toward Use RII 0.894), French demonstration site with 73% emissions reduction all confirmed. Tier 2, AA None upheld. | AO76: =IF($A76="","",IFERROR(_xlfn.XLOOKUP($A76,'2_DOI_Lookup'!$A$2:$A$430,'2_DOI_Lookup'!$B$2:$B$430),"NOT IN SOURCE")) -> 10.1016/j.enbuild.2026.116979
A77: 3625 | E77: =IF($A77="","",IFERROR(_xlfn.XLOOKUP($A77,'2_DOI_Lookup'!$D$2:$D$430,'2_DOI_Lookup'!$E$2:$E$430),"TITLE NOT IN SOURCE")) -> Digital twin-driven on-line monitoring method of metal selective laser melting building process | F77: Scopus | G77: No | H77: Yes | I77: Yes | J77: Yes | K77: No | L77: =IF(COUNTBLANK(G77:K77)=5,"",IF(COUNTIF(G77:K77,"No")>0,"EXCLUDE","INCLUDE")) -> EXCLUDE | M77: =IF(L77<>"EXCLUDE","",IF(G77="No","Wrong domain (non-AECO)",IF(H77="No","Digital Twin not core / buzzword",IF(I77="No","No Design for Safety/Quality/PtD",IF(J77="No","Wrong publication type",IF(K77="No","Non-English","")))))) -> Wrong domain (non-AECO) | S77: =IF(N77<>"Yes","",IF(COUNTBLANK(P77:R77)=3,"",IF(COUNTIF(P77:R77,"No")>0,"EXCLUDE","INCLUDE"))) | T77: =IF(S77<>"EXCLUDE","",IF(P77="No","Digital Twin mentioned only, not the subject",IF(Q77="No","No Design for Safety/Quality in full text",IF(R77="No","Methodology not codable","")))) | Y77: =IF(SUM(V77:X77)=0,"",IF(SUM(V77:X77)>=2,"Multi","Single")) | AG77: Additive manufacturing; Chinese journal, non-English | AO77: =IF($A77="","",IFERROR(_xlfn.XLOOKUP($A77,'2_DOI_Lookup'!$A$2:$A$430,'2_DOI_Lookup'!$B$2:$B$430),"NOT IN SOURCE")) -> 10.13196/j.cims.2021.02.008
A78: 3906 | B78: ElDin (2022) | C78: 2022 | E78: =IF($A78="","",IFERROR(_xlfn.XLOOKUP($A78,'2_DOI_Lookup'!$D$2:$D$430,'2_DOI_Lookup'!$E$2:$E$430),"TITLE NOT IN SOURCE")) -> Digital Twins for Construction Assets Using BIM Standard Specifications | F78: Web of Science | G78: Yes | H78: Yes | I78: Yes | J78: Yes | K78: Yes | L78: =IF(COUNTBLANK(G78:K78)=5,"",IF(COUNTIF(G78:K78,"No")>0,"EXCLUDE","INCLUDE")) -> INCLUDE | M78: =IF(L78<>"EXCLUDE","",IF(G78="No","Wrong domain (non-AECO)",IF(H78="No","Digital Twin not core / buzzword",IF(I78="No","No Design for Safety/Quality/PtD",IF(J78="No","Wrong publication type",IF(K78="No","Non-English","")))))) | N78: Yes | O78: Yes | P78: Yes | Q78: Yes | R78: Yes | S78: =IF(N78<>"Yes","",IF(COUNTBLANK(P78:R78)=3,"",IF(COUNTIF(P78:R78,"No")>0,"EXCLUDE","INCLUDE"))) -> INCLUDE | T78: =IF(S78<>"EXCLUDE","",IF(P78="No","Digital Twin mentioned only, not the subject",IF(Q78="No","No Design for Safety/Quality in full text",IF(R78="No","Methodology not codable","")))) | U78: Unclear | V78: 1 | W78: 1 | X78: 1 | Y78: =IF(SUM(V78:X78)=0,"",IF(SUM(V78:X78)>=2,"Multi","Single")) -> Multi | Z78: Both | AA78: None | AB78: Digital Twin platform (no machine learning) | AC78: Multi (two or more data types) | AD78: Conceptual (no test) | AE78: 3 | AF78: BIM-to-Digital-Twin architecture | AG78: SLR (229 pubs) + conceptual DT development framework grounded in ISO 19650; no implementation or experiment; DfS/DfQ appear as application potentials, not demonstrated. [Full-text source: Endnote] | AH78: Diagnoses the standardization gap in AEC digital twins through a systematic review of 229 publications (2016 to 2021) from four databases, showing DTs remain application-driven and vendor-dependent, then proposes a conceptual DT development framework built on the ISO 19650 series: PIM and AIM information containers federated in a CDE, IoT and WSN monitoring, and machine learning for decisions and actuator actions. | AI78: Conceptual only, with no implementation or validation; the framework is a recommendation that still awaits application, and the authors state it must be proven through multiple case studies with diverse asset uses and complexities, recommending energy efficiency and indoor environmental quality as neglected test fields. | AJ78: Unclear | AK78: An SLR-based ISO 19650 DT development framework (PIM/AIM containers, CDE, IoT/WSN, ML) is proposed without any implementation, so no integration mechanism can be coded. | AL78: High | AN78: Verified 2026-08-22 vs PDF. Systematic review "resulting in 229 publications after applying the proposed criteria" and the ISO 19650-based conceptual DT development framework both confirmed; no implementation. Tier Unclear, AD Conceptual, AA None upheld. | AO78: =IF($A78="","",IFERROR(_xlfn.XLOOKUP($A78,'2_DOI_Lookup'!$A$2:$A$430,'2_DOI_Lookup'!$B$2:$B$430),"NOT IN SOURCE")) -> 10.3390/buildings12122155
A79: 3921 | E79: =IF($A79="","",IFERROR(_xlfn.XLOOKUP($A79,'2_DOI_Lookup'!$D$2:$D$430,'2_DOI_Lookup'!$E$2:$E$430),"TITLE NOT IN SOURCE")) -> Predictive digital monitoring of construction resources: an integrated digital twin solution | F79: Web of Science | G79: Yes | H79: Yes | I79: No | J79: Yes | K79: Yes | L79: =IF(COUNTBLANK(G79:K79)=5,"",IF(COUNTIF(G79:K79,"No")>0,"EXCLUDE","INCLUDE")) -> EXCLUDE | M79: =IF(L79<>"EXCLUDE","",IF(G79="No","Wrong domain (non-AECO)",IF(H79="No","Digital Twin not core / buzzword",IF(I79="No","No Design for Safety/Quality/PtD",IF(J79="No","Wrong publication type",IF(K79="No","Non-English","")))))) -> No Design for Safety/Quality/PtD | S79: =IF(N79<>"Yes","",IF(COUNTBLANK(P79:R79)=3,"",IF(COUNTIF(P79:R79,"No")>0,"EXCLUDE","INCLUDE"))) | T79: =IF(S79<>"EXCLUDE","",IF(P79="No","Digital Twin mentioned only, not the subject",IF(Q79="No","No Design for Safety/Quality in full text",IF(R79="No","Methodology not codable","")))) | Y79: =IF(SUM(V79:X79)=0,"",IF(SUM(V79:X79)>=2,"Multi","Single")) | AG79: DTSRM for cost/time/resources; safety only as extension | AO79: =IF($A79="","",IFERROR(_xlfn.XLOOKUP($A79,'2_DOI_Lookup'!$A$2:$A$430,'2_DOI_Lookup'!$B$2:$B$430),"NOT IN SOURCE")) -> 10.1108/ECAM-04-2025-0604
A80: 4046 | B80: Ellul (2024) | C80: 2024 | E80: =IF($A80="","",IFERROR(_xlfn.XLOOKUP($A80,'2_DOI_Lookup'!$D$2:$D$430,'2_DOI_Lookup'!$E$2:$E$430),"TITLE NOT IN SOURCE")) -> Exploring Data for Construction Digital Twins: Building Health and Safety and Progress Monitoring Twins Using the Unreal Gaming Engine | F80: Web of Science | G80: Yes | H80: Yes | I80: Yes | J80: Yes | K80: Yes | L80: =IF(COUNTBLANK(G80:K80)=5,"",IF(COUNTIF(G80:K80,"No")>0,"EXCLUDE","INCLUDE")) -> INCLUDE | M80: =IF(L80<>"EXCLUDE","",IF(G80="No","Wrong domain (non-AECO)",IF(H80="No","Digital Twin not core / buzzword",IF(I80="No","No Design for Safety/Quality/PtD",IF(J80="No","Wrong publication type",IF(K80="No","Non-English","")))))) | N80: Yes | O80: Yes | P80: Yes | Q80: Yes | R80: Yes | S80: =IF(N80<>"Yes","",IF(COUNTBLANK(P80:R80)=3,"",IF(COUNTIF(P80:R80,"No")>0,"EXCLUDE","INCLUDE"))) -> INCLUDE | T80: =IF(S80<>"EXCLUDE","",IF(P80="No","Digital Twin mentioned only, not the subject",IF(Q80="No","No Design for Safety/Quality in full text",IF(R80="No","Methodology not codable","")))) | U80: Tier 3 - Digital Twin (bidirectional, two-way) | V80: 0 | W80: 1 | X80: 0 | Y80: =IF(SUM(V80:X80)=0,"",IF(SUM(V80:X80)>=2,"Multi","Single")) -> Single | Z80: Design for Safety (DfS) | AA80: None | AB80: Digital Twin platform (no machine learning) | AC80: Multi (two or more data types) | AD80: Cross-project (multiple real projects) | AE80: 3 | AF80: BIM-to-Digital-Twin architecture | AG80: Construction digital twin demonstrators (health & safety + progress monitoring) using Unreal Gaming Engine + CesiumJS mapping on a highway project (Skanska/UCL): location data integrates diverse sources; no-code approach for DT development; two case studies demonstrate 4D data presentation; explicitly described as human-in-the-loop DT (two-way communication with manual decision making) — virtual model changes reflect real-world changes, and humans act back on the physical site via decisions. Predictive capabilities discussed but not implemented; no learning loop. [Full-text source: Endnote] | AH80: Demonstrates location-enabled construction digital twins on a live Skanska highway project, building health and safety and progress monitoring twins in Unreal Engine 5 with CesiumJS georeferencing. The health and safety twin delivers site walk-throughs, clickable asset inspection records, color-coded hazard and risk boxes, and 1-metre danger-zone alerts around machinery built with no-code Blueprints. | AI80: The prototypes are proof of concept: only a small subset of live sensor data was explored, no analytics or prediction were incorporated, asset placement was manual with positional errors up to 1 metre, and no formal usability tests were run. Future work includes automated progress quantification, live worker tracking with wearables, analytics, data security and Datasmith scalability trials. | AJ80: Aligned | AK80: Location-enabled twins georeference diverse data sources through CesiumJS and place them in Unreal Engine scenes, linking hazard boxes and asset inspection records to site coordinates. | AL80: High | AN80: Verified 2026-08-22 vs PDF (Buildings, UCL / Skanska). Unreal Gaming Engine + CesiumJS location-enabled DT, no-code approach, and "two case studies-health and safety and construction monitoring" on a highway construction project all confirmed. Tier 3 supported by the authors' own framing: "A middle ground between the two - human-in-the-loop DT (two-way with manual decision making) have been demonstrated in this research". AD Cross-project supported by two distinct demonstrators. AA None upheld. | AO80: =IF($A80="","",IFERROR(_xlfn.XLOOKUP($A80,'2_DOI_Lookup'!$A$2:$A$430,'2_DOI_Lookup'!$B$2:$B$430),"NOT IN SOURCE")) -> 10.3390/buildings14072216
A81: 3912 | E81: =IF($A81="","",IFERROR(_xlfn.XLOOKUP($A81,'2_DOI_Lookup'!$D$2:$D$430,'2_DOI_Lookup'!$E$2:$E$430),"TITLE NOT IN SOURCE")) -> Seismic Failure Mechanism Shift in RC Buildings Revealed by NDT-Supported, Field-Calibrated BIM-Based Models | F81: Web of Science | G81: Yes | H81: No | I81: Yes | J81: Yes | K81: Yes | L81: =IF(COUNTBLANK(G81:K81)=5,"",IF(COUNTIF(G81:K81,"No")>0,"EXCLUDE","INCLUDE")) -> EXCLUDE | M81: =IF(L81<>"EXCLUDE","",IF(G81="No","Wrong domain (non-AECO)",IF(H81="No","Digital Twin not core / buzzword",IF(I81="No","No Design for Safety/Quality/PtD",IF(J81="No","Wrong publication type",IF(K81="No","Non-English","")))))) -> Digital Twin not core / buzzword | S81: =IF(N81<>"Yes","",IF(COUNTBLANK(P81:R81)=3,"",IF(COUNTIF(P81:R81,"No")>0,"EXCLUDE","INCLUDE"))) | T81: =IF(S81<>"EXCLUDE","",IF(P81="No","Digital Twin mentioned only, not the subject",IF(Q81="No","No Design for Safety/Quality in full text",IF(R81="No","Methodology not codable","")))) | Y81: =IF(SUM(V81:X81)=0,"",IF(SUM(V81:X81)>=2,"Multi","Single")) | AG81: Level-2 static twin = calibrated BIM; no live data link | AO81: =IF($A81="","",IFERROR(_xlfn.XLOOKUP($A81,'2_DOI_Lookup'!$A$2:$A$430,'2_DOI_Lookup'!$B$2:$B$430),"NOT IN SOURCE")) -> 10.3390/app16010455
A82: 4029 | B82: Fang (2023) | C82: 2023 | E82: =IF($A82="","",IFERROR(_xlfn.XLOOKUP($A82,'2_DOI_Lookup'!$D$2:$D$430,'2_DOI_Lookup'!$E$2:$E$430),"TITLE NOT IN SOURCE")) -> Intervention and management of construction workers' unsafe behavior: A simulation digital twin model | F82: Web of Science | G82: Yes | H82: Yes | I82: Yes | J82: Yes | K82: Yes | L82: =IF(COUNTBLANK(G82:K82)=5,"",IF(COUNTIF(G82:K82,"No")>0,"EXCLUDE","INCLUDE")) -> INCLUDE | M82: =IF(L82<>"EXCLUDE","",IF(G82="No","Wrong domain (non-AECO)",IF(H82="No","Digital Twin not core / buzzword",IF(I82="No","No Design for Safety/Quality/PtD",IF(J82="No","Wrong publication type",IF(K82="No","Non-English","")))))) | N82: Yes | O82: Yes | P82: Yes | Q82: Yes | R82: Yes | S82: =IF(N82<>"Yes","",IF(COUNTBLANK(P82:R82)=3,"",IF(COUNTIF(P82:R82,"No")>0,"EXCLUDE","INCLUDE"))) -> INCLUDE | T82: =IF(S82<>"EXCLUDE","",IF(P82="No","Digital Twin mentioned only, not the subject",IF(Q82="No","No Design for Safety/Quality in full text",IF(R82="No","Methodology not codable","")))) | U82: Tier 1 - Digital Model (static, no live data) | V82: 0 | W82: 1 | X82: 0 | Y82: =IF(SUM(V82:X82)=0,"",IF(SUM(V82:X82)>=2,"Multi","Single")) -> Single | Z82: Design for Safety (DfS) | AA82: None | AB82: Agent-based model (ABM) | AC82: Single (one data type) | AD82: Simulation | AE82: 4 | AF82: Predictive analytics / decision support | AG82: Hybrid simulation digital twin model for construction worker unsafe-behavior intervention (Central South U): closed-loop structured model with control panel, proactive management panel, and reactive panel; simulates workers behavioral safety under different intervention strategies using dual-attitude theory and reinforcement theory; proactive management maintains behavioral safety longer than reactive management. Simulation model only - no live data link to a real site, no actuation, no learning loop. [Full-text source: Endnote] | AH82: Fills the behavioral-psychology gap in worker unsafe-behavior research by building a closed-loop hybrid simulation digital twin in AnyLogic that couples agent-based, system dynamics and discrete-event models with dual attitude theory and reinforcement learning. Calibrated with 84 valid questionnaires (Cronbach alpha 0.868), experiments with 84 worker agents show proactive management sustains safety after withdrawal while reactive management decays fast. | AI82: No live site data link; the model is a static simulation whose parameters come from a limited questionnaire sample, and its reliability and predictive capability are acknowledged as weaker than data-driven methods. Authors propose larger samples, EEG and eye-tracking for psychophysiological data, and adding agent-to-agent interactions as future work. | AJ82: Single | AK82: Only questionnaire-calibrated agent parameters (84 valid questionnaires, Cronbach alpha 0.868) feed the AnyLogic hybrid simulation; no second measured data type exists. | AL82: High | AN82: Verified 2026-08-22 vs PDF (Central South U). Agent-based model of worker unsafe behaviours in AnyLogic, dual-attitude theory, and proactive versus reactive management strategies all confirmed. NOTE: the survey yielded "90 survey questionnaires and received 84 valid responses" - AG cites 84 valid, which matches. Tier 1, AC Single, AD Simulation, AA None upheld. | AO82: =IF($A82="","",IFERROR(_xlfn.XLOOKUP($A82,'2_DOI_Lookup'!$A$2:$A$430,'2_DOI_Lookup'!$B$2:$B$430),"NOT IN SOURCE")) -> 10.1016/j.aei.2023.102182
A83: 3782 | E83: =IF($A83="","",IFERROR(_xlfn.XLOOKUP($A83,'2_DOI_Lookup'!$D$2:$D$430,'2_DOI_Lookup'!$E$2:$E$430),"TITLE NOT IN SOURCE")) -> A scientometric analysis of drone-based structural health monitoring and new technologies | F83: Scopus | G83: Yes | H83: No | I83: Yes | J83: Yes | K83: Yes | L83: =IF(COUNTBLANK(G83:K83)=5,"",IF(COUNTIF(G83:K83,"No")>0,"EXCLUDE","INCLUDE")) -> EXCLUDE | M83: =IF(L83<>"EXCLUDE","",IF(G83="No","Wrong domain (non-AECO)",IF(H83="No","Digital Twin not core / buzzword",IF(I83="No","No Design for Safety/Quality/PtD",IF(J83="No","Wrong publication type",IF(K83="No","Non-English","")))))) -> Digital Twin not core / buzzword | S83: =IF(N83<>"Yes","",IF(COUNTBLANK(P83:R83)=3,"",IF(COUNTIF(P83:R83,"No")>0,"EXCLUDE","INCLUDE"))) | T83: =IF(S83<>"EXCLUDE","",IF(P83="No","Digital Twin mentioned only, not the subject",IF(Q83="No","No Design for Safety/Quality in full text",IF(R83="No","Methodology not codable","")))) | Y83: =IF(SUM(V83:X83)=0,"",IF(SUM(V83:X83)>=2,"Multi","Single")) | AG83: Scientometric review; DT only integration trend | AO83: =IF($A83="","",IFERROR(_xlfn.XLOOKUP($A83,'2_DOI_Lookup'!$A$2:$A$430,'2_DOI_Lookup'!$B$2:$B$430),"NOT IN SOURCE")) -> 10.1177/13694332241255734
A84: 3955 | E84: =IF($A84="","",IFERROR(_xlfn.XLOOKUP($A84,'2_DOI_Lookup'!$D$2:$D$430,'2_DOI_Lookup'!$E$2:$E$430),"TITLE NOT IN SOURCE")) -> Development of a BIM and IoT-Based Smart Lighting Maintenance System Prototype for Universities' FM Sector | F84: Web of Science | G84: Yes | H84: Yes | I84: No | J84: Yes | K84: Yes | L84: =IF(COUNTBLANK(G84:K84)=5,"",IF(COUNTIF(G84:K84,"No")>0,"EXCLUDE","INCLUDE")) -> EXCLUDE | M84: =IF(L84<>"EXCLUDE","",IF(G84="No","Wrong domain (non-AECO)",IF(H84="No","Digital Twin not core / buzzword",IF(I84="No","No Design for Safety/Quality/PtD",IF(J84="No","Wrong publication type",IF(K84="No","Non-English","")))))) -> No Design for Safety/Quality/PtD | S84: =IF(N84<>"Yes","",IF(COUNTBLANK(P84:R84)=3,"",IF(COUNTIF(P84:R84,"No")>0,"EXCLUDE","INCLUDE"))) | T84: =IF(S84<>"EXCLUDE","",IF(P84="No","Digital Twin mentioned only, not the subject",IF(Q84="No","No Design for Safety/Quality in full text",IF(R84="No","Methodology not codable","")))) | Y84: =IF(SUM(V84:X84)=0,"",IF(SUM(V84:X84)>=2,"Multi","Single")) | AG84: FM reactive maintenance; safety incidental | AO84: =IF($A84="","",IFERROR(_xlfn.XLOOKUP($A84,'2_DOI_Lookup'!$A$2:$A$430,'2_DOI_Lookup'!$B$2:$B$430),"NOT IN SOURCE")) -> 10.3390/buildings12020099
A85: 3632 | E85: =IF($A85="","",IFERROR(_xlfn.XLOOKUP($A85,'2_DOI_Lookup'!$D$2:$D$430,'2_DOI_Lookup'!$E$2:$E$430),"TITLE NOT IN SOURCE")) -> Machine learning for design and analysis of steel frame halls | F85: Scopus | G85: Yes | H85: No | I85: No | J85: Yes | K85: Yes | L85: =IF(COUNTBLANK(G85:K85)=5,"",IF(COUNTIF(G85:K85,"No")>0,"EXCLUDE","INCLUDE")) -> EXCLUDE | M85: =IF(L85<>"EXCLUDE","",IF(G85="No","Wrong domain (non-AECO)",IF(H85="No","Digital Twin not core / buzzword",IF(I85="No","No Design for Safety/Quality/PtD",IF(J85="No","Wrong publication type",IF(K85="No","Non-English","")))))) -> Digital Twin not core / buzzword | S85: =IF(N85<>"Yes","",IF(COUNTBLANK(P85:R85)=3,"",IF(COUNTIF(P85:R85,"No")>0,"EXCLUDE","INCLUDE"))) | T85: =IF(S85<>"EXCLUDE","",IF(P85="No","Digital Twin mentioned only, not the subject",IF(Q85="No","No Design for Safety/Quality in full text",IF(R85="No","Methodology not codable","")))) | Y85: =IF(SUM(V85:X85)=0,"",IF(SUM(V85:X85)>=2,"Multi","Single")) | AG85: AI design co-pilot; no DT | AO85: =IF($A85="","",IFERROR(_xlfn.XLOOKUP($A85,'2_DOI_Lookup'!$A$2:$A$430,'2_DOI_Lookup'!$B$2:$B$430),"NOT IN SOURCE")) -> 10.1002/stab.202200054
A86: 4048 | E86: =IF($A86="","",IFERROR(_xlfn.XLOOKUP($A86,'2_DOI_Lookup'!$D$2:$D$430,'2_DOI_Lookup'!$E$2:$E$430),"TITLE NOT IN SOURCE")) -> Maschinelles Lernen beim Entwurf und der Bemessung von Stahlrahmenhallen | F86: Web of Science | G86: Yes | H86: No | I86: No | J86: Yes | K86: No | L86: =IF(COUNTBLANK(G86:K86)=5,"",IF(COUNTIF(G86:K86,"No")>0,"EXCLUDE","INCLUDE")) -> EXCLUDE | M86: =IF(L86<>"EXCLUDE","",IF(G86="No","Wrong domain (non-AECO)",IF(H86="No","Digital Twin not core / buzzword",IF(I86="No","No Design for Safety/Quality/PtD",IF(J86="No","Wrong publication type",IF(K86="No","Non-English","")))))) -> Digital Twin not core / buzzword | S86: =IF(N86<>"Yes","",IF(COUNTBLANK(P86:R86)=3,"",IF(COUNTIF(P86:R86,"No")>0,"EXCLUDE","INCLUDE"))) | T86: =IF(S86<>"EXCLUDE","",IF(P86="No","Digital Twin mentioned only, not the subject",IF(Q86="No","No Design for Safety/Quality in full text",IF(R86="No","Methodology not codable","")))) | Y86: =IF(SUM(V86:X86)=0,"",IF(SUM(V86:X86)>=2,"Multi","Single")) | AG86: German duplicate of ID 3632; non-English | AO86: =IF($A86="","",IFERROR(_xlfn.XLOOKUP($A86,'2_DOI_Lookup'!$A$2:$A$430,'2_DOI_Lookup'!$B$2:$B$430),"NOT IN SOURCE")) -> 10.1002/stab.202200054
A87: 3824 | E87: =IF($A87="","",IFERROR(_xlfn.XLOOKUP($A87,'2_DOI_Lookup'!$D$2:$D$430,'2_DOI_Lookup'!$E$2:$E$430),"TITLE NOT IN SOURCE")) -> Preliminary architecture design for human-in-the-loop control of robotic equipment in remote handling tasks: Case study on the NEFERTARI project | F87: Scopus | G87: No | H87: Yes | I87: No | J87: Yes | K87: Yes | L87: =IF(COUNTBLANK(G87:K87)=5,"",IF(COUNTIF(G87:K87,"No")>0,"EXCLUDE","INCLUDE")) -> EXCLUDE | M87: =IF(L87<>"EXCLUDE","",IF(G87="No","Wrong domain (non-AECO)",IF(H87="No","Digital Twin not core / buzzword",IF(I87="No","No Design for Safety/Quality/PtD",IF(J87="No","Wrong publication type",IF(K87="No","Non-English","")))))) -> Wrong domain (non-AECO) | S87: =IF(N87<>"Yes","",IF(COUNTBLANK(P87:R87)=3,"",IF(COUNTIF(P87:R87,"No")>0,"EXCLUDE","INCLUDE"))) | T87: =IF(S87<>"EXCLUDE","",IF(P87="No","Digital Twin mentioned only, not the subject",IF(Q87="No","No Design for Safety/Quality in full text",IF(R87="No","Methodology not codable","")))) | Y87: =IF(SUM(V87:X87)=0,"",IF(SUM(V87:X87)>=2,"Multi","Single")) | AG87: Fusion-reactor maintenance robotics; not AECO | AO87: =IF($A87="","",IFERROR(_xlfn.XLOOKUP($A87,'2_DOI_Lookup'!$A$2:$A$430,'2_DOI_Lookup'!$B$2:$B$430),"NOT IN SOURCE")) -> 10.1016/j.fusengdes.2024.114586
A88: 3493 | B88: Franciosi (2024) | C88: 2024 | E88: =IF($A88="","",IFERROR(_xlfn.XLOOKUP($A88,'2_DOI_Lookup'!$D$2:$D$430,'2_DOI_Lookup'!$E$2:$E$430),"TITLE NOT IN SOURCE")) -> Digital twins in bridge engineering for streamlined maintenance and enhanced sustainability | F88: Scopus | G88: Yes | H88: Yes | I88: Yes | J88: Yes | K88: Yes | L88: =IF(COUNTBLANK(G88:K88)=5,"",IF(COUNTIF(G88:K88,"No")>0,"EXCLUDE","INCLUDE")) -> INCLUDE | M88: =IF(L88<>"EXCLUDE","",IF(G88="No","Wrong domain (non-AECO)",IF(H88="No","Digital Twin not core / buzzword",IF(I88="No","No Design for Safety/Quality/PtD",IF(J88="No","Wrong publication type",IF(K88="No","Non-English","")))))) | N88: Yes | O88: Yes | P88: Yes | Q88: Yes | R88: Yes | S88: =IF(N88<>"Yes","",IF(COUNTBLANK(P88:R88)=3,"",IF(COUNTIF(P88:R88,"No")>0,"EXCLUDE","INCLUDE"))) -> INCLUDE | T88: =IF(S88<>"EXCLUDE","",IF(P88="No","Digital Twin mentioned only, not the subject",IF(Q88="No","No Design for Safety/Quality in full text",IF(R88="No","Methodology not codable","")))) | U88: Tier 2 - Digital Shadow (one-way physical to virtual) | V88: 0 | W88: 0 | X88: 1 | Y88: =IF(SUM(V88:X88)=0,"",IF(SUM(V88:X88)>=2,"Multi","Single")) -> Single | Z88: Design for Safety (DfS) | AA88: None | AB88: Finite Element Method / physics-based | AC88: Multi (two or more data types) | AD88: Single case study | AE88: 4 | AF88: Lifecycle / governance | AG88: Adaptable digital twin methodology for existing bridge management (HEIG-VD): integrates BIM + IFC (open interoperable formats) + ontology + FE models; laser-scanned 3D model converted to DT via IFC; enables structural analysis and what-if scenario simulations for maintenance decision-making; differential evolution algorithm for optimized FE model; case study demonstrates feasibility; cradle-to-cradle approach for end-of-life. One-way monitoring/analysis→maintenance decisions; no actuation and no learning loop (updates are manual inspection-based). [Full-text source: Endnote] | AH88: Establishes an adaptable methodology for existing-bridge digital twins addressing software obsolescence and interoperability: laser-scanned geometry (RIEGL VZ-2000i) converted to IFC 4.3 BIM and enriched from the KUBA database, then imported into SCIA Engineer for what-if corrosion scenarios on the 377.60 m Praz bridge and DE-algorithm FE updating against DIC measurements on the Grandson bridge. | AI88: Scan-to-BIM remains semi-automated and the DT provides no automatic defect detection; updates come in batch from inspections rather than a real-time link. Future work covers a method to integrate inspection and monitoring results into DTs, extension to new bridges during design, and linking DTs into networks for whole transport corridors. | AJ88: Aligned | AK88: RIEGL VZ-2000i laser-scanned geometry is converted to IFC 4.3 BIM, and the SCIA Engineer FE model is updated against DIC measurements, linking scan geometry and measurement data through the shared bridge model. | AL88: High | AN88: Verified 2026-08-20 vs PDF (Automation in Construction 168:105834). IFC/ontology/FE, laser-scan-to-DT and differential-evolution optimisation all confirmed. Tier 2, AA None upheld. | AO88: =IF($A88="","",IFERROR(_xlfn.XLOOKUP($A88,'2_DOI_Lookup'!$A$2:$A$430,'2_DOI_Lookup'!$B$2:$B$430),"NOT IN SOURCE")) -> 10.1016/j.autcon.2024.105834
A89: 4032 | E89: =IF($A89="","",IFERROR(_xlfn.XLOOKUP($A89,'2_DOI_Lookup'!$D$2:$D$430,'2_DOI_Lookup'!$E$2:$E$430),"TITLE NOT IN SOURCE")) -> Resilient ventilation network construction in complex underground mining environments: A holistic strategy from resilience perception to resilience enhancement | F89: Web of Science | G89: No | H89: Yes | I89: Yes | J89: Yes | K89: Yes | L89: =IF(COUNTBLANK(G89:K89)=5,"",IF(COUNTIF(G89:K89,"No")>0,"EXCLUDE","INCLUDE")) -> EXCLUDE | M89: =IF(L89<>"EXCLUDE","",IF(G89="No","Wrong domain (non-AECO)",IF(H89="No","Digital Twin not core / buzzword",IF(I89="No","No Design for Safety/Quality/PtD",IF(J89="No","Wrong publication type",IF(K89="No","Non-English","")))))) -> Wrong domain (non-AECO) | S89: =IF(N89<>"Yes","",IF(COUNTBLANK(P89:R89)=3,"",IF(COUNTIF(P89:R89,"No")>0,"EXCLUDE","INCLUDE"))) | T89: =IF(S89<>"EXCLUDE","",IF(P89="No","Digital Twin mentioned only, not the subject",IF(Q89="No","No Design for Safety/Quality in full text",IF(R89="No","Methodology not codable","")))) | Y89: =IF(SUM(V89:X89)=0,"",IF(SUM(V89:X89)>=2,"Multi","Single")) | AG89: Mining ventilation; not AECO built environment | AO89: =IF($A89="","",IFERROR(_xlfn.XLOOKUP($A89,'2_DOI_Lookup'!$A$2:$A$430,'2_DOI_Lookup'!$B$2:$B$430),"NOT IN SOURCE")) -> 10.1016/j.ress.2026.112634
A90: 3775 | B90: Gao (2025) | C90: 2025 | E90: =IF($A90="","",IFERROR(_xlfn.XLOOKUP($A90,'2_DOI_Lookup'!$D$2:$D$430,'2_DOI_Lookup'!$E$2:$E$430),"TITLE NOT IN SOURCE")) -> Digital twin-based vibration displacement sensing and recognition technology for large engineering structures | F90: Scopus | G90: Yes | H90: Yes | I90: Yes | J90: Yes | K90: Yes | L90: =IF(COUNTBLANK(G90:K90)=5,"",IF(COUNTIF(G90:K90,"No")>0,"EXCLUDE","INCLUDE")) -> INCLUDE | M90: =IF(L90<>"EXCLUDE","",IF(G90="No","Wrong domain (non-AECO)",IF(H90="No","Digital Twin not core / buzzword",IF(I90="No","No Design for Safety/Quality/PtD",IF(J90="No","Wrong publication type",IF(K90="No","Non-English","")))))) | N90: Yes | O90: Yes | P90: Yes | Q90: Yes | R90: Yes | S90: =IF(N90<>"Yes","",IF(COUNTBLANK(P90:R90)=3,"",IF(COUNTIF(P90:R90,"No")>0,"EXCLUDE","INCLUDE"))) -> INCLUDE | T90: =IF(S90<>"EXCLUDE","",IF(P90="No","Digital Twin mentioned only, not the subject",IF(Q90="No","No Design for Safety/Quality in full text",IF(R90="No","Methodology not codable","")))) | U90: Tier 2 - Digital Shadow (one-way physical to virtual) | V90: 0 | W90: 1 | X90: 0 | Y90: =IF(SUM(V90:X90)=0,"",IF(SUM(V90:X90)>=2,"Multi","Single")) -> Single | Z90: Design for Safety (DfS) | AA90: None | AB90: Other / Mixed | AC90: Single (one data type) | AD90: Simulation | AE90: 3 | AF90: Predictive analytics / decision support | AG90: DT-based construction safety-management model for large engineering structures (48 m-span steel roof): DT generates real-time structural state samples that train a PSO-optimised BP neural network for vibration displacement / stress prediction (vertical displacement PA 98.2%, cable stress PA 99.1%, EV 0.978); validated only on a numerical model under 5 simulated working conditions; monitoring-and-warning only, no actuation, offline-trained predictor, no learning loop. [Full-text source: Endnote] | AH90: Combines a digital twin construction-safety model with a PSO-optimized BP neural network for vibration displacement sensing and recognition of large structures: the twin generates real-time structural state training samples and the model reaches 98.2 percent prediction accuracy overall, 99.1 percent for tension-cable stress, with eigenvalue EV 0.978 and correct critical-component identification on a 48 m span steel roof model. | AI90: Validation is numerical, using a 48 m steel roof structural model with five working conditions rather than a monitored real project; the paper reports no live site data or actuation and no explicit limitations section. Future direction stated is only to deepen digital twin research for construction safety assessment and structural optimization design. | AJ90: Single | AK90: Only twin-generated structural-state samples (numerical 48 m steel roof under five working conditions) train the PSO-BP predictor; no live measured data exists. | AL90: High | AN90: Verified 2026-08-22 vs PDF. 48 m span steel roof experimental model, PSO-BP algorithm, prediction accuracy 98.2% (displacement) and 99.1% (cable stress), EV 0.978 all confirmed. Numerical/experimental model only - Tier 2, AC Single, AD Simulation, AA None upheld. | AO90: =IF($A90="","",IFERROR(_xlfn.XLOOKUP($A90,'2_DOI_Lookup'!$A$2:$A$430,'2_DOI_Lookup'!$B$2:$B$430),"NOT IN SOURCE")) -> 10.24425/ace.2025.156179
A91: 3826 | E91: =IF($A91="","",IFERROR(_xlfn.XLOOKUP($A91,'2_DOI_Lookup'!$D$2:$D$430,'2_DOI_Lookup'!$E$2:$E$430),"TITLE NOT IN SOURCE")) -> Cooperative Localization in Transportation 5.0 | F91: Scopus | G91: No | H91: No | I91: No | J91: Yes | K91: Yes | L91: =IF(COUNTBLANK(G91:K91)=5,"",IF(COUNTIF(G91:K91,"No")>0,"EXCLUDE","INCLUDE")) -> EXCLUDE | M91: =IF(L91<>"EXCLUDE","",IF(G91="No","Wrong domain (non-AECO)",IF(H91="No","Digital Twin not core / buzzword",IF(I91="No","No Design for Safety/Quality/PtD",IF(J91="No","Wrong publication type",IF(K91="No","Non-English","")))))) -> Wrong domain (non-AECO) | S91: =IF(N91<>"Yes","",IF(COUNTBLANK(P91:R91)=3,"",IF(COUNTIF(P91:R91,"No")>0,"EXCLUDE","INCLUDE"))) | T91: =IF(S91<>"EXCLUDE","",IF(P91="No","Digital Twin mentioned only, not the subject",IF(Q91="No","No Design for Safety/Quality in full text",IF(R91="No","Methodology not codable","")))) | Y91: =IF(SUM(V91:X91)=0,"",IF(SUM(V91:X91)>=2,"Multi","Single")) | AG91: Vehicle localization framework; not AECO | AO91: =IF($A91="","",IFERROR(_xlfn.XLOOKUP($A91,'2_DOI_Lookup'!$A$2:$A$430,'2_DOI_Lookup'!$B$2:$B$430),"NOT IN SOURCE")) -> 10.1109/TIV.2024.3377163
A92: 3876 | B92: Gao (2024) | C92: 2024 | E92: =IF($A92="","",IFERROR(_xlfn.XLOOKUP($A92,'2_DOI_Lookup'!$D$2:$D$430,'2_DOI_Lookup'!$E$2:$E$430),"TITLE NOT IN SOURCE")) -> Bridge Digital Twin for Practical Bridge Operation and Maintenance by Integrating GIS and BIM | F92: Web of Science | G92: Yes | H92: Yes | I92: Yes | J92: Yes | K92: Yes | L92: =IF(COUNTBLANK(G92:K92)=5,"",IF(COUNTIF(G92:K92,"No")>0,"EXCLUDE","INCLUDE")) -> INCLUDE | M92: =IF(L92<>"EXCLUDE","",IF(G92="No","Wrong domain (non-AECO)",IF(H92="No","Digital Twin not core / buzzword",IF(I92="No","No Design for Safety/Quality/PtD",IF(J92="No","Wrong publication type",IF(K92="No","Non-English","")))))) | N92: Yes | O92: Yes | P92: Yes | Q92: Yes | R92: Yes | S92: =IF(N92<>"Yes","",IF(COUNTBLANK(P92:R92)=3,"",IF(COUNTIF(P92:R92,"No")>0,"EXCLUDE","INCLUDE"))) -> INCLUDE | T92: =IF(S92<>"EXCLUDE","",IF(P92="No","Digital Twin mentioned only, not the subject",IF(Q92="No","No Design for Safety/Quality in full text",IF(R92="No","Methodology not codable","")))) | U92: Tier 2 - Digital Shadow (one-way physical to virtual) | V92: 0 | W92: 0 | X92: 1 | Y92: =IF(SUM(V92:X92)=0,"",IF(SUM(V92:X92)>=2,"Multi","Single")) -> Single | Z92: Design for Safety (DfS) | AA92: None | AB92: Digital Twin platform (no machine learning) | AC92: Multi (two or more data types) | AD92: Single case study | AE92: 4 | AF92: Lifecycle / governance | AG92: Integrated bridge DT system (Cardiff U): combines WebGIS (Cesium), WebBIM (Xeokit), and graph algorithms (Neo4j) in a three-layer architecture with a common data environment (CDE); enables real-time monitoring, drone-enabled inspection, maintenance planning, traffic diversion, and logistics optimization; adaptive data structure with JSON-based bridge defect information modeling and triple-based roadmap graphs; SHM system flags structural issues and triggers alerts/traffic redirection; defects from drone inspection inform maintenance planning. One-way monitoring→analysis→decision support; no actuation and no learning loop. [Full-text source: Endnote] | AH92: Integrates WebGIS (Cesium), WebBIM (Xeokit) and graph algorithms (Neo4j) in a three-layer bridge DT with a common data environment, JSON-based defect modeling and triple-based roadmap graphs, enabling real-time monitoring, drone inspection, traffic diversion and maintenance planning; validated on the River Neath Swing Bridge with regional operation and individual maintenance case studies. | AI92: Defect information modeling relies on custom JSON files that lack extensibility, and the multi-module stack risks cross-platform compatibility issues as functionality grows. Future work targets redefining defect and damage data in IFC format, improving cross-platform interoperability and scalability for more advanced bridge DT applications. | AJ92: Aligned | AK92: WebGIS (Cesium), WebBIM (Xeokit) and Neo4j graph algorithms are integrated in a three-layer architecture with a common data environment, spatially linking GIS, BIM and defect data for the River Neath Swing Bridge. | AL92: High | AN92: Verified 2026-08-22 vs PDF (Cardiff University, BIM for Smart Engineering Centre). CesiumJS WebGIS, Xeokit WebBIM, Neo4j graph database and three-layer CDE architecture all confirmed. Tier 2, AA None upheld. | AO92: =IF($A92="","",IFERROR(_xlfn.XLOOKUP($A92,'2_DOI_Lookup'!$A$2:$A$430,'2_DOI_Lookup'!$B$2:$B$430),"NOT IN SOURCE")) -> 10.3390/buildings14123731
A93: 3786 | E93: =IF($A93="","",IFERROR(_xlfn.XLOOKUP($A93,'2_DOI_Lookup'!$D$2:$D$430,'2_DOI_Lookup'!$E$2:$E$430),"TITLE NOT IN SOURCE")) -> Virtual and Augmented Reality Use Cases for Fusion Design Engineering | F93: Scopus | G93: No | H93: No | I93: No | J93: Yes | K93: Yes | L93: =IF(COUNTBLANK(G93:K93)=5,"",IF(COUNTIF(G93:K93,"No")>0,"EXCLUDE","INCLUDE")) -> EXCLUDE | M93: =IF(L93<>"EXCLUDE","",IF(G93="No","Wrong domain (non-AECO)",IF(H93="No","Digital Twin not core / buzzword",IF(I93="No","No Design for Safety/Quality/PtD",IF(J93="No","Wrong publication type",IF(K93="No","Non-English","")))))) -> Wrong domain (non-AECO) | S93: =IF(N93<>"Yes","",IF(COUNTBLANK(P93:R93)=3,"",IF(COUNTIF(P93:R93,"No")>0,"EXCLUDE","INCLUDE"))) | T93: =IF(S93<>"EXCLUDE","",IF(P93="No","Digital Twin mentioned only, not the subject",IF(Q93="No","No Design for Safety/Quality in full text",IF(R93="No","Methodology not codable","")))) | Y93: =IF(SUM(V93:X93)=0,"",IF(SUM(V93:X93)>=2,"Multi","Single")) | AG93: Fusion-energy facility design; not AECO | AO93: =IF($A93="","",IFERROR(_xlfn.XLOOKUP($A93,'2_DOI_Lookup'!$A$2:$A$430,'2_DOI_Lookup'!$B$2:$B$430),"NOT IN SOURCE")) -> 10.1016/j.fusengdes.2021.112780
A94: 3778 | E94: =IF($A94="","",IFERROR(_xlfn.XLOOKUP($A94,'2_DOI_Lookup'!$D$2:$D$430,'2_DOI_Lookup'!$E$2:$E$430),"TITLE NOT IN SOURCE")) -> Digital twin for smart coal mining workface: Technological frame and construction | F94: Scopus | G94: No | H94: Yes | I94: Yes | J94: Yes | K94: No | L94: =IF(COUNTBLANK(G94:K94)=5,"",IF(COUNTIF(G94:K94,"No")>0,"EXCLUDE","INCLUDE")) -> EXCLUDE | M94: =IF(L94<>"EXCLUDE","",IF(G94="No","Wrong domain (non-AECO)",IF(H94="No","Digital Twin not core / buzzword",IF(I94="No","No Design for Safety/Quality/PtD",IF(J94="No","Wrong publication type",IF(K94="No","Non-English","")))))) -> Wrong domain (non-AECO) | S94: =IF(N94<>"Yes","",IF(COUNTBLANK(P94:R94)=3,"",IF(COUNTIF(P94:R94,"No")>0,"EXCLUDE","INCLUDE"))) | T94: =IF(S94<>"EXCLUDE","",IF(P94="No","Digital Twin mentioned only, not the subject",IF(Q94="No","No Design for Safety/Quality in full text",IF(R94="No","Methodology not codable","")))) | Y94: =IF(SUM(V94:X94)=0,"",IF(SUM(V94:X94)>=2,"Multi","Single")) | AG94: Mining; Chinese journal, non-English | AO94: =IF($A94="","",IFERROR(_xlfn.XLOOKUP($A94,'2_DOI_Lookup'!$A$2:$A$430,'2_DOI_Lookup'!$B$2:$B$430),"NOT IN SOURCE")) -> 10.13225/j.cnki.jccs.ZN20.0327
A95: 3797 | E95: =IF($A95="","",IFERROR(_xlfn.XLOOKUP($A95,'2_DOI_Lookup'!$D$2:$D$430,'2_DOI_Lookup'!$E$2:$E$430),"TITLE NOT IN SOURCE")) -> Construction of Autonomous Collaborative Resource Control System for Electric Vehicles Based on Intelligent Sensing Internet of Vehicles | F95: Scopus | G95: No | H95: Yes | I95: No | J95: Yes | K95: Yes | L95: =IF(COUNTBLANK(G95:K95)=5,"",IF(COUNTIF(G95:K95,"No")>0,"EXCLUDE","INCLUDE")) -> EXCLUDE | M95: =IF(L95<>"EXCLUDE","",IF(G95="No","Wrong domain (non-AECO)",IF(H95="No","Digital Twin not core / buzzword",IF(I95="No","No Design for Safety/Quality/PtD",IF(J95="No","Wrong publication type",IF(K95="No","Non-English","")))))) -> Wrong domain (non-AECO) | S95: =IF(N95<>"Yes","",IF(COUNTBLANK(P95:R95)=3,"",IF(COUNTIF(P95:R95,"No")>0,"EXCLUDE","INCLUDE"))) | T95: =IF(S95<>"EXCLUDE","",IF(P95="No","Digital Twin mentioned only, not the subject",IF(Q95="No","No Design for Safety/Quality in full text",IF(R95="No","Methodology not codable","")))) | Y95: =IF(SUM(V95:X95)=0,"",IF(SUM(V95:X95)>=2,"Multi","Single")) | AG95: EV charging/IoV scheduling; not AECO | AO95: =IF($A95="","",IFERROR(_xlfn.XLOOKUP($A95,'2_DOI_Lookup'!$A$2:$A$430,'2_DOI_Lookup'!$B$2:$B$430),"NOT IN SOURCE")) -> 10.1007/s13177-026-00684-z
A96: 3979 | B96: Geng (2025) | C96: 2025 | E96: =IF($A96="","",IFERROR(_xlfn.XLOOKUP($A96,'2_DOI_Lookup'!$D$2:$D$430,'2_DOI_Lookup'!$E$2:$E$430),"TITLE NOT IN SOURCE")) -> Integrating multi-source data for life-cycle risk assessment of bridge networks: a system digital twin framework | F96: Web of Science | G96: Yes | H96: Yes | I96: Yes | J96: Yes | K96: Yes | L96: =IF(COUNTBLANK(G96:K96)=5,"",IF(COUNTIF(G96:K96,"No")>0,"EXCLUDE","INCLUDE")) -> INCLUDE | M96: =IF(L96<>"EXCLUDE","",IF(G96="No","Wrong domain (non-AECO)",IF(H96="No","Digital Twin not core / buzzword",IF(I96="No","No Design for Safety/Quality/PtD",IF(J96="No","Wrong publication type",IF(K96="No","Non-English","")))))) | N96: Yes | O96: Yes | P96: Yes | Q96: Yes | R96: Yes | S96: =IF(N96<>"Yes","",IF(COUNTBLANK(P96:R96)=3,"",IF(COUNTIF(P96:R96,"No")>0,"EXCLUDE","INCLUDE"))) -> INCLUDE | T96: =IF(S96<>"EXCLUDE","",IF(P96="No","Digital Twin mentioned only, not the subject",IF(Q96="No","No Design for Safety/Quality in full text",IF(R96="No","Methodology not codable","")))) | U96: Tier 2 - Digital Shadow (one-way physical to virtual) | V96: 0 | W96: 0 | X96: 1 | Y96: =IF(SUM(V96:X96)=0,"",IF(SUM(V96:X96)>=2,"Multi","Single")) -> Single | Z96: Design for Safety (DfS) | AA96: None | AB96: Bayesian / probabilistic | AC96: Multi (two or more data types) | AD96: Single case study | AE96: 4 | AF96: Predictive analytics / decision support | AG96: System digital twin (SDT) for life-cycle risk assessment of bridge networks: Bayesian network (BN) integrates multi-source data (NBI bridge inspections, FDOT traffic/AADT, USGS river gage) to update bridge failure risk (superstructure + scour) over time via automated Bayesian inference (indicator matrix for annual updates; network risk profile trends up as data update reduces uncertainty). Miami-Dade County case: 1,034 bridges, 6,478 nodes, 10,584 edges; 3 flexibility scenarios (new bridge, decommissioning, climate-change flood with CPT recalibration). Updating is implemented Bayesian inference — but authors state framework "has not yet been validated"; CPT refits are manual, no autonomous learning loop. [Full-text source: Endnote] | AH96: Proposes a Bayesian-network system digital twin for county-scale life-cycle risk assessment of bridge networks, fusing NBI inspection ratings, traffic monitoring and river gage data across 1,034 bridges, 1,261 traffic stations and 10 river gages in Miami-Dade County, with a 6,478-node, 10,584-edge graph capturing component, system and cross-system correlations for scenario-based risk updating. | AI96: The framework has not yet been validated with field or laboratory tests, and its large Bayesian network demands 97,484.8 MB of memory just to store conditional probability tables, limiting practical scale-up. Future work includes custom Bayesian networks to cut computation, validation through field coring and lab testing, and adding restoration and resilience modelling. | AJ96: Fused | AK96: A Bayesian network fuses NBI inspection ratings, FDOT traffic monitoring and USGS river-gage data into one 6,478-node, 10,584-edge network that updates bridge failure risk through automated Bayesian inference. | AL96: High | AM96: RESOLVED 2026-08-23 (user-identified, agreed): AA Implemented -> None. Full text contains zero occurrences of self-improve / self-learn / self-adapt / retrain. What is "updated" is the DIGITAL STATE (annual Bayesian inference over new inspection, AADT and river-gage evidence), not the model: the BN structure and CPTs are fixed, elicited once via EM/MLE and domain expertise. Authors also state "the current framework has not yet been validated". | AN96: Verified 2026-08-22 vs PDF (J Infrastruct Preserv Resil 6:9). Bayesian network over Miami-Dade bridge network with annual risk updating from NBI/FDOT/USGS sources confirmed. CRITICAL: "converg" appears 0 times, and the authors state "the current framework has NOT YET BEEN VALIDATED. Future work should focus on assessing the performance and quality of the SDT". AA=Implemented is therefore weak - the annual Bayesian update is a designed procedure rather than a demonstrated running learning loop, and AD Single case study may overstate an unvalidated framework. RECOMMEND REVIEW of AA and AD. [RE-VERIFIED 2026-08-23 at user request: AA corrected Implemented -> None. Evidence: "self-improv/self-learn/self-correct/self-adapt" = 0 hits; "retrain" = 0 hits. The paper updates the DIGITAL STATE via Bayesian inference on an annual cycle (bridge condition ratings every two years, AADT every three years, river data annually, coordinated by a binary indicator matrix), which is state estimation, not model self-improvement. BN structure and CPTs are elicited once from data/domain expertise (EM or maximum likelihood) and are not revised from accumulated experience.] | AO96: =IF($A96="","",IFERROR(_xlfn.XLOOKUP($A96,'2_DOI_Lookup'!$A$2:$A$430,'2_DOI_Lookup'!$B$2:$B$430),"NOT IN SOURCE")) -> 10.1186/s43065-025-00121-7
A97: 3962 | E97: =IF($A97="","",IFERROR(_xlfn.XLOOKUP($A97,'2_DOI_Lookup'!$D$2:$D$430,'2_DOI_Lookup'!$E$2:$E$430),"TITLE NOT IN SOURCE")) -> Federation of non-destructive testing data for bridge asset management | F97: Web of Science | G97: Yes | H97: No | I97: Yes | J97: Yes | K97: Yes | L97: =IF(COUNTBLANK(G97:K97)=5,"",IF(COUNTIF(G97:K97,"No")>0,"EXCLUDE","INCLUDE")) -> EXCLUDE | M97: =IF(L97<>"EXCLUDE","",IF(G97="No","Wrong domain (non-AECO)",IF(H97="No","Digital Twin not core / buzzword",IF(I97="No","No Design for Safety/Quality/PtD",IF(J97="No","Wrong publication type",IF(K97="No","Non-English","")))))) -> Digital Twin not core / buzzword | S97: =IF(N97<>"Yes","",IF(COUNTBLANK(P97:R97)=3,"",IF(COUNTIF(P97:R97,"No")>0,"EXCLUDE","INCLUDE"))) | T97: =IF(S97<>"EXCLUDE","",IF(P97="No","Digital Twin mentioned only, not the subject",IF(Q97="No","No Design for Safety/Quality in full text",IF(R97="No","Methodology not codable","")))) | Y97: =IF(SUM(V97:X97)=0,"",IF(SUM(V97:X97)>=2,"Multi","Single")) | AG97: NDT data federation in Revit; DT as future tool | AO97: =IF($A97="","",IFERROR(_xlfn.XLOOKUP($A97,'2_DOI_Lookup'!$A$2:$A$430,'2_DOI_Lookup'!$B$2:$B$430),"NOT IN SOURCE")) -> 10.1680/jcien.25.00463
A98: 3542 | E98: =IF($A98="","",IFERROR(_xlfn.XLOOKUP($A98,'2_DOI_Lookup'!$D$2:$D$430,'2_DOI_Lookup'!$E$2:$E$430),"TITLE NOT IN SOURCE")) -> Construction of damage-free digital twin of damaged aero-engine blades for repair volume generation in remanufacturing | F98: Scopus | G98: No | H98: Yes | I98: No | J98: Yes | K98: Yes | L98: =IF(COUNTBLANK(G98:K98)=5,"",IF(COUNTIF(G98:K98,"No")>0,"EXCLUDE","INCLUDE")) -> EXCLUDE | M98: =IF(L98<>"EXCLUDE","",IF(G98="No","Wrong domain (non-AECO)",IF(H98="No","Digital Twin not core / buzzword",IF(I98="No","No Design for Safety/Quality/PtD",IF(J98="No","Wrong publication type",IF(K98="No","Non-English","")))))) -> Wrong domain (non-AECO) | S98: =IF(N98<>"Yes","",IF(COUNTBLANK(P98:R98)=3,"",IF(COUNTIF(P98:R98,"No")>0,"EXCLUDE","INCLUDE"))) | T98: =IF(S98<>"EXCLUDE","",IF(P98="No","Digital Twin mentioned only, not the subject",IF(Q98="No","No Design for Safety/Quality in full text",IF(R98="No","Methodology not codable","")))) | Y98: =IF(SUM(V98:X98)=0,"",IF(SUM(V98:X98)>=2,"Multi","Single")) | AG98: Aerospace remanufacturing | AO98: =IF($A98="","",IFERROR(_xlfn.XLOOKUP($A98,'2_DOI_Lookup'!$A$2:$A$430,'2_DOI_Lookup'!$B$2:$B$430),"NOT IN SOURCE")) -> 10.1016/j.rcim.2022.102335
A99: 3580 | E99: =IF($A99="","",IFERROR(_xlfn.XLOOKUP($A99,'2_DOI_Lookup'!$D$2:$D$430,'2_DOI_Lookup'!$E$2:$E$430),"TITLE NOT IN SOURCE")) -> The Conventional Construction Scenario and the Emergence of Advance Technologies in the Bridge Construction: Implementation, Impediments, and Case Study | F99: Scopus | G99: Yes | H99: No | I99: No | J99: Yes | K99: Yes | L99: =IF(COUNTBLANK(G99:K99)=5,"",IF(COUNTIF(G99:K99,"No")>0,"EXCLUDE","INCLUDE")) -> EXCLUDE | M99: =IF(L99<>"EXCLUDE","",IF(G99="No","Wrong domain (non-AECO)",IF(H99="No","Digital Twin not core / buzzword",IF(I99="No","No Design for Safety/Quality/PtD",IF(J99="No","Wrong publication type",IF(K99="No","Non-English","")))))) -> Digital Twin not core / buzzword | S99: =IF(N99<>"Yes","",IF(COUNTBLANK(P99:R99)=3,"",IF(COUNTIF(P99:R99,"No")>0,"EXCLUDE","INCLUDE"))) | T99: =IF(S99<>"EXCLUDE","",IF(P99="No","Digital Twin mentioned only, not the subject",IF(Q99="No","No Design for Safety/Quality in full text",IF(R99="No","Methodology not codable","")))) | Y99: =IF(SUM(V99:X99)=0,"",IF(SUM(V99:X99)>=2,"Multi","Single")) | AG99: Tech-adoption survey; DT one item in a list | AO99: =IF($A99="","",IFERROR(_xlfn.XLOOKUP($A99,'2_DOI_Lookup'!$A$2:$A$430,'2_DOI_Lookup'!$B$2:$B$430),"NOT IN SOURCE")) -> 10.1007/s40030-023-00732-x
A100: 3611 | E100: =IF($A100="","",IFERROR(_xlfn.XLOOKUP($A100,'2_DOI_Lookup'!$D$2:$D$430,'2_DOI_Lookup'!$E$2:$E$430),"TITLE NOT IN SOURCE")) -> Digital twin driven airflow intelligent control system for the air outlet of heading face | F100: Scopus | G100: No | H100: Yes | I100: Yes | J100: Yes | K100: No | L100: =IF(COUNTBLANK(G100:K100)=5,"",IF(COUNTIF(G100:K100,"No")>0,"EXCLUDE","INCLUDE")) -> EXCLUDE | M100: =IF(L100<>"EXCLUDE","",IF(G100="No","Wrong domain (non-AECO)",IF(H100="No","Digital Twin not core / buzzword",IF(I100="No","No Design for Safety/Quality/PtD",IF(J100="No","Wrong publication type",IF(K100="No","Non-English","")))))) -> Wrong domain (non-AECO) | S100: =IF(N100<>"Yes","",IF(COUNTBLANK(P100:R100)=3,"",IF(COUNTIF(P100:R100,"No")>0,"EXCLUDE","INCLUDE"))) | T100: =IF(S100<>"EXCLUDE","",IF(P100="No","Digital Twin mentioned only, not the subject",IF(Q100="No","No Design for Safety/Quality in full text",IF(R100="No","Methodology not codable","")))) | Y100: =IF(SUM(V100:X100)=0,"",IF(SUM(V100:X100)>=2,"Multi","Single")) | AG100: Mining ventilation; Chinese journal, non-English | AO100: =IF($A100="","",IFERROR(_xlfn.XLOOKUP($A100,'2_DOI_Lookup'!$A$2:$A$430,'2_DOI_Lookup'!$B$2:$B$430),"NOT IN SOURCE")) -> 10.13225/j.cnki.jccs.2020.0963
...

Sheet Step1_Report
A1: STEP 1 & PRISMA - screening outcomes (auto)
A3: PRISMA stage | B3: n
A4: Records identified (in matrix) | B4: =COUNTA(Matrix!$A$5:$A$454) -> 429
A5: Records screened (Stage-1 decided) | B5: =COUNTIF(Matrix!$L$5:$L$454,"INCLUDE")+COUNTIF(Matrix!$L$5:$L$454,"EXCLUDE") -> 429
A6: Excluded at Stage-1 (title/abstract) | B6: =COUNTIF(Matrix!$L$5:$L$454,"EXCLUDE") -> 262
A7: Stage-1 INCLUDE -> sought for retrieval | B7: =COUNTIF(Matrix!$L$5:$L$454,"INCLUDE") -> 167
A8: PDF full text on hand (gateway = Yes) | B8: =COUNTIFS(Matrix!$L$5:$L$454,"INCLUDE",Matrix!$N$5:$N$454,"Yes") -> 165
A9: PDF not yet on hand (revisit later) | B9: =COUNTIFS(Matrix!$L$5:$L$454,"INCLUDE",Matrix!$N$5:$N$454,"No") -> 2
A10: Reports assessed for eligibility (full text) | B10: =COUNTIFS(Matrix!$N$5:$N$454,"Yes",Matrix!$S$5:$S$454,"INCLUDE")+COUNTIFS(Matrix!$N$5:$N$454,"Yes",Matrix!$S$5:$S$454,"EXCLUDE") -> 165
A11: Excluded at Stage-2 (full text, with reasons) | B11: =COUNTIF(Matrix!$S$5:$S$454,"EXCLUDE") -> 13
A12: STUDIES INCLUDED IN SYNTHESIS | B12: =COUNTIF(Matrix!$S$5:$S$454,"INCLUDE") -> 152
A14: Stage-1 exclusion reasons
A15: Reason | B15: n
A16: Wrong domain (non-AECO) | B16: =COUNTIF(Matrix!$M$5:$M$454,"Wrong domain (non-AECO)") -> 99
A17: Digital Twin not core / buzzword | B17: =COUNTIF(Matrix!$M$5:$M$454,"Digital Twin not core / buzzword") -> 112
A18: No Design for Safety/Quality/PtD | B18: =COUNTIF(Matrix!$M$5:$M$454,"No Design for Safety/Quality/PtD") -> 21
