Workbook

Sheet 0_Guide
B2: One Matrix - Four Steps (LLM-ready, no background assumed)
B3: A single progressive-disclosure matrix for screening, coding, deep-read analysis and reporting.
B5: CONTEXT PRIMER (read this before coding any paper)
B6: What is this review about | C6: This is a systematic literature review about DIGITAL TWINS used in the built-environment industry, specifically to improve SAFETY and QUALITY of designs. You are screening and coding academic papers.
B7: AECO | C7: AECO = Architecture, Engineering, Construction and Operations. It means the built-environment / construction industry (buildings, bridges, infrastructure, civil engineering). NOT manufacturing, automotive, aerospace, power/electrical equipment, healthcare, or agriculture.
B8: Digital Twin (DT) | C8: A Digital Twin is a live virtual replica of a physical asset that is connected to it by data. It is MORE than a static 3D/BIM model. If a paper only says the words 'digital twin' in passing but does not actually build or study one, treat DT as a buzzword (answer 'No').
B9: Design for Safety (DfS) | C9: Design for Safety = designing to prevent construction/operation safety incidents (e.g. fall from height, hazards, accident prevention).
B10: Design for Quality (DfQ) | C10: Design for Quality = designing to prevent defects, rework, or quality failures.
B11: Prevention through Design (PtD) | C11: Prevention through Design = the principle of eliminating risks at the design stage before construction begins. Closely related to DfS/DfQ.
B12: BIM | C12: BIM = Building Information Modelling. A static, design-stage digital model. A BIM model alone is NOT a Digital Twin (no live data link).
B13: bidirectional | C13: 'bidirectional' means data flows BOTH ways: physical->virtual AND virtual->physical (the twin can act back on the real asset). One-way data flow is only a 'digital shadow'.
B14: Answer format | C14: Every Stage-1 and Stage-2 question is answered strictly as 'Yes' or 'No'. If genuinely unsure from the abstract, answer 'No' (conservative) and add a note. Do not invent information not present in the text.
B15: One reason only | C15: When a paper is excluded, the matrix auto-picks ONE standardized reason by priority. You do not write the reason yourself.
B17: THE FOUR STEPS
B18: Step 1 (all 450 papers) | C18: An LLM or reviewer fills the AMBER Stage-1 columns (G-K) for EVERY paper, from the TITLE and ABSTRACT only. Column L auto-decides Include/Exclude; column M auto-writes the single exclusion reason.
B19: Step 2 (the matrix) | C19: This workbook IS the summary matrix. There is nothing separate to generate.
B20: Retrieval + PDF gateway | C20: For Stage-1 includes, first mark column N 'PDF full text on hand?'. This is the gateway: only papers with the PDF on hand can be deep-read. You can revisit later - when a PDF is found, change N from 'No' to 'Yes' and the paper becomes ready for Stage-2/3.
B21: Step 3 (deep read) | C21: For papers whose PDF is on hand, fill the RED Stage-2 columns (P-R) and then the GREEN synthesis 'angle' columns (U-AG). These are the evidence for your findings section.
B22: Step 4 (report) | C22: Open 'Step1_Report' (screening + PRISMA chain + exclusion reasons) and 'Step3_Report' (capability-tier / phase / method / modality / validation / self-improvement tables). Both auto-tally from the same rows.
B24: COLOUR KEY
B25: Bands | C25: AMBER = Stage-1 input (from abstract) · BLUE = PDF gateway · RED = Stage-2 input (from full text) · GREEN = Stage-3 deep-read input · BLUE-GREY = auto formula, do not edit.
B26: Golden rule | C26: Never delete a paper. A paper excluded at any stage stays in the matrix with its reason recorded. This is what makes the PRISMA flow reproducible.

Sheet 1_CodeLists
A1: YN | B1: Src | C1: Bin | D1: Tier | E1: DfX | F1: Self | G1: Method | H1: Modality | I1: Valid | J1: Cluster | K1: Fusion | L1: Conf
A2: Yes | B2: Scopus | C2: 0 | D2: Tier 1 - Digital Model (static, no live data) | E2: Design for Safety (DfS) | F2: None | G2: Computer Vision / CNN / object-detection | H2: Single (one data type) | I2: Conceptual (no test) | J2: BIM-to-Digital-Twin architecture | K2: Single | L2: High
A3: No | B3: Web of Science | C3: 1 | D3: Tier 2 - Digital Shadow (one-way physical to virtual) | E3: Design for Quality (DfQ) | F3: Mentioned only | G3: Graph Neural Network (GNN) | H3: Multi (two or more data types) | I3: Simulation | J3: Semantic interoperability | K3: Co-present | L3: Medium
B4: Lens.org | D4: Tier 3 - Digital Twin (bidirectional, two-way) | E4: Both | F4: Implemented | G4: LSTM / RNN (recurrent networks) | I4: Single case study | J4: Perception / Computer Vision | K4: Aligned | L4: Low
B5: Backward-snowball | D5: Tier 4 - Cognitive / Self-improving | E5: Other | F5: Convergence-characterised | G5: Transformer / Large Language Model (LLM) | I5: Cross-project (multiple real projects) | J5: Design for Safety | K5: Fused
B6: Forward-snowball | D6: Unclear | G6: Reinforcement Learning (RL) | J6: Predictive analytics / decision support | K6: Unclear
G7: Bayesian / probabilistic | J7: Lifecycle / governance
G8: Agent-based model (ABM) | J8: Other
G9: Finite Element Method / physics-based
G10: Ontology / semantic
G11: Statistical / change-point
G12: Digital Twin platform (no machine learning)
G13: Other / Mixed

Sheet Matrix
A1: ID | B1: Authors (year) | C1: Year | D1: Journal | E1: Title | F1: Source database | G1: Stage1: Domain is AECO (built environment)? | H1: Stage1: Digital Twin is core (not just a buzzword)? | I1: Stage1: About Design for Safety / Quality / Prevention through Design? | J1: Stage1: Publication type OK (journal/conference article, not editorial/erratum)? | K1: Stage1: Written in English (full text)? | L1: STAGE-1 decision | M1: Stage-1 exclusion reason (auto) | N1: GATEWAY: PDF full text on hand? (change to Yes when found) | O1: Full text retrieved for PRISMA? | P1: Stage2: Digital Twin is the actual subject (full text)? | Q1: Stage2: Design for Safety/Quality confirmed in full text? | R1: Stage2: Methodology is clear enough to code? | S1: STAGE-2 decision | T1: Stage-2 exclusion reason (auto) | U1: Deep-read: Digital Twin capability tier | V1: Phase: Design (1/0) | W1: Phase: Construction (1/0) | X1: Phase: Operation (1/0) | Y1: Cross-phase? (auto) | Z1: Deep-read: Design-for-X target | AA1: Deep-read: Self-improvement / convergence | AB1: Deep-read: Methodology | AC1: Deep-read: Data modality | AD1: Deep-read: Validation level | AE1: Deep-read: Quality appraisal score (0 to 5) | AF1: Deep-read: Thematic cluster | AG1: Deep-read: Key evidence / notes | AH1: Deep-read: Strength / research gap filled | AI1: Deep-read: Deficiencies & future work | AJ1: Deep-read: Fusion depth (AC1) | AK1: Deep-read: Fusion evidence (AC2) | AL1: Deep-read: Fusion confidence (AC3) | AM1: Fusion coding flag (review)
A2: 3566 | E2: An association rule mining model for the application of construction t… | F2: Scopus | G2: Yes | H2: No | I2: No | J2: Yes | K2: Yes | L2: =IF(COUNTBLANK(G2:K2)=5,"",IF(COUNTIF(G2:K2,"No")>0,"EXCLUDE","INCLUDE")) -> EXCLUDE | M2: =IF(L2<>"EXCLUDE","",IF(G2="No","Wrong domain (non-AECO)",IF(H2="No","Digital Twin not core / buzzword",IF(I2="No","No Design for Safety/Quality/PtD",IF(J2="No","Wrong publication type",IF(K2="No","Non-English","")))))) -> Digital Twin not core / buzzword | S2: =IF(N2<>"Yes","",IF(COUNTBLANK(P2:R2)=3,"",IF(COUNTIF(P2:R2,"No")>0,"EXCLUDE","INCLUDE"))) | T2: =IF(S2<>"EXCLUDE","",IF(P2="No","Digital Twin mentioned only, not the subject",IF(Q2="No","No Design for Safety/Quality in full text",IF(R2="No","Methodology not codable","")))) | Y2: =IF(SUM(V2:X2)=0,"",IF(SUM(V2:X2)>=2,"Multi","Single")) | AG2: Tech-adoption survey (ARM); no DT, no DfS/DfQ focus
A3: 3741 | E3: Digital twin and AI-driven smart adaptive walls for energy, comfort an… | F3: Scopus | G3: Yes | H3: Yes | I3: No | J3: Yes | K3: Yes | L3: =IF(COUNTBLANK(G3:K3)=5,"",IF(COUNTIF(G3:K3,"No")>0,"EXCLUDE","INCLUDE")) -> EXCLUDE | M3: =IF(L3<>"EXCLUDE","",IF(G3="No","Wrong domain (non-AECO)",IF(H3="No","Digital Twin not core / buzzword",IF(I3="No","No Design for Safety/Quality/PtD",IF(J3="No","Wrong publication type",IF(K3="No","Non-English","")))))) -> No Design for Safety/Quality/PtD | S3: =IF(N3<>"Yes","",IF(COUNTBLANK(P3:R3)=3,"",IF(COUNTIF(P3:R3,"No")>0,"EXCLUDE","INCLUDE"))) | T3: =IF(S3<>"EXCLUDE","",IF(P3="No","Digital Twin mentioned only, not the subject",IF(Q3="No","No Design for Safety/Quality in full text",IF(R3="No","Methodology not codable","")))) | Y3: =IF(SUM(V3:X3)=0,"",IF(SUM(V3:X3)>=2,"Multi","Single")) | AG3: Energy/comfort/carbon optimization; safety shield is control constraint (edge 5)
A4: 3665 | E4: Enhancing attack resilience of cyber-physical systems through state de… | F4: Scopus | G4: No | H4: No | I4: No | J4: Yes | K4: Yes | L4: =IF(COUNTBLANK(G4:K4)=5,"",IF(COUNTIF(G4:K4,"No")>0,"EXCLUDE","INCLUDE")) -> EXCLUDE | M4: =IF(L4<>"EXCLUDE","",IF(G4="No","Wrong domain (non-AECO)",IF(H4="No","Digital Twin not core / buzzword",IF(I4="No","No Design for Safety/Quality/PtD",IF(J4="No","Wrong publication type",IF(K4="No","Non-English","")))))) -> Wrong domain (non-AECO) | S4: =IF(N4<>"Yes","",IF(COUNTBLANK(P4:R4)=3,"",IF(COUNTIF(P4:R4,"No")>0,"EXCLUDE","INCLUDE"))) | T4: =IF(S4<>"EXCLUDE","",IF(P4="No","Digital Twin mentioned only, not the subject",IF(Q4="No","No Design for Safety/Quality in full text",IF(R4="No","Methodology not codable","")))) | Y4: =IF(SUM(V4:X4)=0,"",IF(SUM(V4:X4)>=2,"Multi","Single")) | AG4: Cybersecurity of industrial CPS/SCADA; not AECO
A5: 3657 | E5: IoT-Driven Resilience Monitoring: Case Study of a Cyber-Physical Syste… | F5: Scopus | G5: No | H5: Yes | I5: No | J5: Yes | K5: Yes | L5: =IF(COUNTBLANK(G5:K5)=5,"",IF(COUNTIF(G5:K5,"No")>0,"EXCLUDE","INCLUDE")) -> EXCLUDE | M5: =IF(L5<>"EXCLUDE","",IF(G5="No","Wrong domain (non-AECO)",IF(H5="No","Digital Twin not core / buzzword",IF(I5="No","No Design for Safety/Quality/PtD",IF(J5="No","Wrong publication type",IF(K5="No","Non-English","")))))) -> Wrong domain (non-AECO) | S5: =IF(N5<>"Yes","",IF(COUNTBLANK(P5:R5)=3,"",IF(COUNTIF(P5:R5,"No")>0,"EXCLUDE","INCLUDE"))) | T5: =IF(S5<>"EXCLUDE","",IF(P5="No","Digital Twin mentioned only, not the subject",IF(Q5="No","No Design for Safety/Quality in full text",IF(R5="No","Methodology not codable","")))) | Y5: =IF(SUM(V5:X5)=0,"",IF(SUM(V5:X5)>=2,"Multi","Single")) | AG5: Smart energy systems CI; not built environment
A6: 3685 | E6: Virtual Fencing for Safety-Critical Cyber-Physical Systems: Computer-V… | F6: Scopus | G6: No | H6: Yes | I6: No | J6: Yes | K6: Yes | L6: =IF(COUNTBLANK(G6:K6)=5,"",IF(COUNTIF(G6:K6,"No")>0,"EXCLUDE","INCLUDE")) -> EXCLUDE | M6: =IF(L6<>"EXCLUDE","",IF(G6="No","Wrong domain (non-AECO)",IF(H6="No","Digital Twin not core / buzzword",IF(I6="No","No Design for Safety/Quality/PtD",IF(J6="No","Wrong publication type",IF(K6="No","Non-English","")))))) -> Wrong domain (non-AECO) | S6: =IF(N6<>"Yes","",IF(COUNTBLANK(P6:R6)=3,"",IF(COUNTIF(P6:R6,"No")>0,"EXCLUDE","INCLUDE"))) | T6: =IF(S6<>"EXCLUDE","",IF(P6="No","Digital Twin mentioned only, not the subject",IF(Q6="No","No Design for Safety/Quality in full text",IF(R6="No","Methodology not codable","")))) | Y6: =IF(SUM(V6:X6)=0,"",IF(SUM(V6:X6)>=2,"Multi","Single")) | AG6: Crowd management/surveillance; no built asset DfS/DfQ
A7: 3756 | B7: Ahmad (2026) | C7: 2026 | E7: Lessons Learned from the Real-World Deployment of Multisensor Fusion f… | F7: Scopus | G7: Yes | H7: Yes | I7: Yes | J7: Yes | K7: Yes | L7: =IF(COUNTBLANK(G7:K7)=5,"",IF(COUNTIF(G7:K7,"No")>0,"EXCLUDE","INCLUDE")) -> INCLUDE | M7: =IF(L7<>"EXCLUDE","",IF(G7="No","Wrong domain (non-AECO)",IF(H7="No","Digital Twin not core / buzzword",IF(I7="No","No Design for Safety/Quality/PtD",IF(J7="No","Wrong publication type",IF(K7="No","Non-English","")))))) | N7: Yes | O7: Yes | P7: Yes | Q7: Yes | R7: Yes | S7: =IF(N7<>"Yes","",IF(COUNTBLANK(P7:R7)=3,"",IF(COUNTIF(P7:R7,"No")>0,"EXCLUDE","INCLUDE"))) -> INCLUDE | T7: =IF(S7<>"EXCLUDE","",IF(P7="No","Digital Twin mentioned only, not the subject",IF(Q7="No","No Design for Safety/Quality in full text",IF(R7="No","Methodology not codable","")))) | U7: Tier 2 - Digital Shadow (one-way physical to virtual) | V7: 0 | W7: 1 | X7: 0 | Y7: =IF(SUM(V7:X7)=0,"",IF(SUM(V7:X7)>=2,"Multi","Single")) -> Single | Z7: Design for Safety (DfS) | AA7: None | AB7: Other / Mixed | AC7: Multi (two or more data types) | AD7: Single case study | AE7: 4 | AF7: Design for Safety | AG7: Deployed LiDAR+radar+camera fusion validated with RTK-GNSS at real work zone (lane-level accuracy); Predictive DT framework (Digital Shadow + Digital Sibling, TTC/PET conflict metrics, C-V2X warnings) proposed but not implemented — hence Tier 2, AA None. [Full-text source: arXiv OA preprint] | AH7: Fills the gap between work zone safety DT research and real-world deployment: LiDAR+radar+camera fusion validated with RTK-GNSS at a real work zone achieving lane-level accuracy, feeding a predictive DT framework pairing a Digital Shadow and Digital Sibling with TTC/PET conflict metrics and C-V2X warnings for proactive safety. | AI7: Deployment lessons rather than controlled validation: one real work zone, and the predictive framework (conflict metrics, C-V2X warnings) stays at framework level without demonstrated closed-loop actuation; no explicit future work is stated. | AJ7: Fused | AK7: Deployed LiDAR+radar+camera fusion validated with RTK-GNSS at lane-level accuracy at a real work zone (joint multi-sensor deployment feeding conflict metrics). | AL7: Medium
A8: 3978 | B8: Akanmu (2021) | C8: 2021 | E8: TOWARDS NEXT GENERATION CYBER-PHYSICAL SYSTEMS AND DIGITAL TWINS FOR C… | F8: Web of Science | G8: Yes | H8: Yes | I8: Yes | J8: Yes | K8: Yes | L8: =IF(COUNTBLANK(G8:K8)=5,"",IF(COUNTIF(G8:K8,"No")>0,"EXCLUDE","INCLUDE")) -> INCLUDE | M8: =IF(L8<>"EXCLUDE","",IF(G8="No","Wrong domain (non-AECO)",IF(H8="No","Digital Twin not core / buzzword",IF(I8="No","No Design for Safety/Quality/PtD",IF(J8="No","Wrong publication type",IF(K8="No","Non-English","")))))) | N8: Yes | O8: Yes | P8: Yes | Q8: Yes | R8: Yes | S8: =IF(N8<>"Yes","",IF(COUNTBLANK(P8:R8)=3,"",IF(COUNTIF(P8:R8,"No")>0,"EXCLUDE","INCLUDE"))) -> INCLUDE | T8: =IF(S8<>"EXCLUDE","",IF(P8="No","Digital Twin mentioned only, not the subject",IF(Q8="No","No Design for Safety/Quality in full text",IF(R8="No","Methodology not codable","")))) | U8: Tier 3 - Digital Twin (bidirectional, two-way) | V8: 0 | W8: 1 | X8: 1 | Y8: =IF(SUM(V8:X8)=0,"",IF(SUM(V8:X8)>=2,"Multi","Single")) -> Multi | Z8: Design for Safety (DfS) | AA8: Mentioned only | AB8: Digital Twin platform (no machine learning) | AC8: Multi (two or more data types) | AD8: Conceptual (no test) | AE8: 3 | AF8: BIM-to-Digital-Twin architecture | AG8: Perspective paper defining next-gen CPS/DT with explicit two-way mapping and passive/active control; scenarios (teleoperated drywall robot, postural tracking, near-miss prevention) illustrate bidirectional control but nothing implemented; ML training of movement data only suggested. [Full-text source: Endnote] | AH8: A perspective paper defining next-generation CPS and DT through two-way dynamic mapping between virtual models and the physical facility, distinguishing passive (model-based) from active (actuator-based) control, and illustrating scenarios: a teleoperated drywall robot controlled via wearable IMU motion capture, postural tracking with AR avatars and color-coded ergonomic risk feedback, and near-miss prediction using case-based reasoning and K-nearest neighbor. | AI8: Purely conceptual: none of the scenarios is implemented or validated, and the paper itself lists open challenges of a missing information model for DTs, missing version management guidelines, missing communication latency guidelines, and missing interoperability standards analogous to IFC. | AJ8: Unclear | AK8: Perspective paper defining next-gen CPS/DT; the bidirectional-control scenarios are illustrative only and no data-integration mechanism is implemented. | AL8: High
A9: 3527 | E9: A methodological approach to hybrid AI systems for real-time infrastru… | F9: Scopus | G9: Yes | H9: No | I9: Yes | J9: Yes | K9: Yes | L9: =IF(COUNTBLANK(G9:K9)=5,"",IF(COUNTIF(G9:K9,"No")>0,"EXCLUDE","INCLUDE")) -> EXCLUDE | M9: =IF(L9<>"EXCLUDE","",IF(G9="No","Wrong domain (non-AECO)",IF(H9="No","Digital Twin not core / buzzword",IF(I9="No","No Design for Safety/Quality/PtD",IF(J9="No","Wrong publication type",IF(K9="No","Non-English","")))))) -> Digital Twin not core / buzzword | S9: =IF(N9<>"Yes","",IF(COUNTBLANK(P9:R9)=3,"",IF(COUNTIF(P9:R9,"No")>0,"EXCLUDE","INCLUDE"))) | T9: =IF(S9<>"EXCLUDE","",IF(P9="No","Digital Twin mentioned only, not the subject",IF(Q9="No","No Design for Safety/Quality in full text",IF(R9="No","Methodology not codable","")))) | Y9: =IF(SUM(V9:X9)=0,"",IF(SUM(V9:X9)>=2,"Multi","Single")) | AG9: SHM hybrid AI; no DT built/proposed
A10: 3963 | E10: Neural network-based metamodel for scaffolding behavior: Application f… | F10: Web of Science | G10: Yes | H10: No | I10: Yes | J10: Yes | K10: Yes | L10: =IF(COUNTBLANK(G10:K10)=5,"",IF(COUNTIF(G10:K10,"No")>0,"EXCLUDE","INCLUDE")) -> EXCLUDE | M10: =IF(L10<>"EXCLUDE","",IF(G10="No","Wrong domain (non-AECO)",IF(H10="No","Digital Twin not core / buzzword",IF(I10="No","No Design for Safety/Quality/PtD",IF(J10="No","Wrong publication type",IF(K10="No","Non-English","")))))) -> Digital Twin not core / buzzword | S10: =IF(N10<>"Yes","",IF(COUNTBLANK(P10:R10)=3,"",IF(COUNTIF(P10:R10,"No")>0,"EXCLUDE","INCLUDE"))) | T10: =IF(S10<>"EXCLUDE","",IF(P10="No","Digital Twin mentioned only, not the subject",IF(Q10="No","No Design for Safety/Quality in full text",IF(R10="No","Methodology not codable","")))) | Y10: =IF(SUM(V10:X10)=0,"",IF(SUM(V10:X10)>=2,"Multi","Single")) | AG10: FEM+NN metamodel; authors state not a full digital twin
A11: 3917 | E11: Enhancing resilience through environmental data integration in early c… | F11: Web of Science | G11: Yes | H11: No | I11: No | J11: Yes | K11: Yes | L11: =IF(COUNTBLANK(G11:K11)=5,"",IF(COUNTIF(G11:K11,"No")>0,"EXCLUDE","INCLUDE")) -> EXCLUDE | M11: =IF(L11<>"EXCLUDE","",IF(G11="No","Wrong domain (non-AECO)",IF(H11="No","Digital Twin not core / buzzword",IF(I11="No","No Design for Safety/Quality/PtD",IF(J11="No","Wrong publication type",IF(K11="No","Non-English","")))))) -> Digital Twin not core / buzzword | S11: =IF(N11<>"Yes","",IF(COUNTBLANK(P11:R11)=3,"",IF(COUNTIF(P11:R11,"No")>0,"EXCLUDE","INCLUDE"))) | T11: =IF(S11<>"EXCLUDE","",IF(P11="No","Digital Twin mentioned only, not the subject",IF(Q11="No","No Design for Safety/Quality in full text",IF(R11="No","Methodology not codable","")))) | Y11: =IF(SUM(V11:X11)=0,"",IF(SUM(V11:X11)>=2,"Multi","Single")) | AG11: BIM-ICDD semantic linking; no DT; compliance not DfQ
A12: 3541 | E12: Automation levels for nuclear reactor operations: A revised perspectiv… | F12: Scopus | G12: No | H12: No | I12: No | J12: Yes | K12: Yes | L12: =IF(COUNTBLANK(G12:K12)=5,"",IF(COUNTIF(G12:K12,"No")>0,"EXCLUDE","INCLUDE")) -> EXCLUDE | M12: =IF(L12<>"EXCLUDE","",IF(G12="No","Wrong domain (non-AECO)",IF(H12="No","Digital Twin not core / buzzword",IF(I12="No","No Design for Safety/Quality/PtD",IF(J12="No","Wrong publication type",IF(K12="No","Non-English","")))))) -> Wrong domain (non-AECO) | S12: =IF(N12<>"Yes","",IF(COUNTBLANK(P12:R12)=3,"",IF(COUNTIF(P12:R12,"No")>0,"EXCLUDE","INCLUDE"))) | T12: =IF(S12<>"EXCLUDE","",IF(P12="No","Digital Twin mentioned only, not the subject",IF(Q12="No","No Design for Safety/Quality in full text",IF(R12="No","Methodology not codable","")))) | Y12: =IF(SUM(V12:X12)=0,"",IF(SUM(V12:X12)>=2,"Multi","Single")) | AG12: Nuclear power domain
A13: 3903 | E13: BIM-GIS integrated hydrodynamic modeling for road flood risk assessmen… | F13: Web of Science | G13: Yes | H13: No | I13: Yes | J13: Yes | K13: Yes | L13: =IF(COUNTBLANK(G13:K13)=5,"",IF(COUNTIF(G13:K13,"No")>0,"EXCLUDE","INCLUDE")) -> EXCLUDE | M13: =IF(L13<>"EXCLUDE","",IF(G13="No","Wrong domain (non-AECO)",IF(H13="No","Digital Twin not core / buzzword",IF(I13="No","No Design for Safety/Quality/PtD",IF(J13="No","Wrong publication type",IF(K13="No","Non-English","")))))) -> Digital Twin not core / buzzword | S13: =IF(N13<>"Yes","",IF(COUNTBLANK(P13:R13)=3,"",IF(COUNTIF(P13:R13,"No")>0,"EXCLUDE","INCLUDE"))) | T13: =IF(S13<>"EXCLUDE","",IF(P13="No","Digital Twin mentioned only, not the subject",IF(Q13="No","No Design for Safety/Quality in full text",IF(R13="No","Methodology not codable","")))) | Y13: =IF(SUM(V13:X13)=0,"",IF(SUM(V13:X13)>=2,"Multi","Single")) | AG13: BIM-HDM framework; DT only future early warning
A14: 3915 | B14: Almatared (2024) | C14: 2024 | E14: Digital-Twin-Based Fire Safety Management Framework for Smart Building… | F14: Web of Science | G14: Yes | H14: Yes | I14: Yes | J14: Yes | K14: Yes | L14: =IF(COUNTBLANK(G14:K14)=5,"",IF(COUNTIF(G14:K14,"No")>0,"EXCLUDE","INCLUDE")) -> INCLUDE | M14: =IF(L14<>"EXCLUDE","",IF(G14="No","Wrong domain (non-AECO)",IF(H14="No","Digital Twin not core / buzzword",IF(I14="No","No Design for Safety/Quality/PtD",IF(J14="No","Wrong publication type",IF(K14="No","Non-English","")))))) | N14: Yes | O14: Yes | P14: Yes | Q14: Yes | R14: Yes | S14: =IF(N14<>"Yes","",IF(COUNTBLANK(P14:R14)=3,"",IF(COUNTIF(P14:R14,"No")>0,"EXCLUDE","INCLUDE"))) -> INCLUDE | T14: =IF(S14<>"EXCLUDE","",IF(P14="No","Digital Twin mentioned only, not the subject",IF(Q14="No","No Design for Safety/Quality in full text",IF(R14="No","Methodology not codable","")))) | U14: Tier 3 - Digital Twin (bidirectional, two-way) | V14: 0 | W14: 0 | X14: 1 | Y14: =IF(SUM(V14:X14)=0,"",IF(SUM(V14:X14)>=2,"Multi","Single")) -> Single | Z14: Design for Safety (DfS) | AA14: Mentioned only | AB14: Digital Twin platform (no machine learning) | AC14: Multi (two or more data types) | AD14: Conceptual (no test) | AE14: 3 | AF14: Design for Safety | AG14: Four-layer DT-based fire-safety framework (physical/virtual/application/user-interaction) with explicit feedback "integrated back with the physical building layer for automatic control"; validated only via FM-professional questionnaire, no technical test; AI learning cited from literature, not implemented. [Full-text source: Endnote] | AH14: Addresses the underexplored application of DT to fire safety management: a four-layer framework (physical building, virtual building, application, and user interaction layers) combining BIM, IoT, AI, data fusion, blockchain, and AR, with virtual-layer decisions fed back to the physical building layer for automatic control and operation optimization while keeping FM professionals in the loop. | AI14: Conceptual only: the framework was validated through a thematic analysis of 37 studies and a survey of FM professionals (66 responses, 28 complete) rather than a live implementation; no prototype or sensor deployment is reported. Future work includes a Delphi study with a broader panel and involving firefighters as end users. | AJ14: Unclear | AK14: Four-layer fire-safety framework validated only through a thematic analysis and an FM-professional questionnaire; the layer integration mechanism is not implemented. | AL14: High
A15: 3668 | B15: Alvaro (2025) | C15: 2025 | E15: GUIDE2FR: A smart monitoring platform with a digital twin of a firefig… | F15: Scopus | G15: Yes | H15: Yes | I15: Yes | J15: Yes | K15: Yes | L15: =IF(COUNTBLANK(G15:K15)=5,"",IF(COUNTIF(G15:K15,"No")>0,"EXCLUDE","INCLUDE")) -> INCLUDE | M15: =IF(L15<>"EXCLUDE","",IF(G15="No","Wrong domain (non-AECO)",IF(H15="No","Digital Twin not core / buzzword",IF(I15="No","No Design for Safety/Quality/PtD",IF(J15="No","Wrong publication type",IF(K15="No","Non-English","")))))) | N15: Yes | O15: Yes | P15: Yes | Q15: Yes | R15: Yes | S15: =IF(N15<>"Yes","",IF(COUNTBLANK(P15:R15)=3,"",IF(COUNTIF(P15:R15,"No")>0,"EXCLUDE","INCLUDE"))) -> INCLUDE | T15: =IF(S15<>"EXCLUDE","",IF(P15="No","Digital Twin mentioned only, not the subject",IF(Q15="No","No Design for Safety/Quality in full text",IF(R15="No","Methodology not codable","")))) | U15: Tier 2 - Digital Shadow (one-way physical to virtual) | V15: 0 | W15: 0 | X15: 1 | Y15: =IF(SUM(V15:X15)=0,"",IF(SUM(V15:X15)>=2,"Multi","Single")) -> Single | Z15: Design for Safety (DfS) | AA15: None | AB15: Other / Mixed | AC15: Multi (two or more data types) | AD15: Single case study | AE15: 4 | AF15: Design for Safety | AG15: GUIDE2FR emergency-monitoring DT of a firefighter training tower (Alcorcón): Wi-Fi/LoRa beacon network (temp, humidity, CO2, TVOC) + RTSP video synchronised in a Grafana plugin; offline-trained ML forecasting pipeline (SVR/RF/Huber/GPR, forward-chaining CV, tested on 4 beacons at Fire Station 9) visualised in the DT; one-way data flow to human decision-makers, no actuation and no online learning loop. [Full-text source: Endnote] | AH15: Fills the gap between fire-safety DT research and operational emergency response: a functioning building DT (GUIDE2FR) fusing Wi-Fi/LoRa environmental beacons with live RTSP video in a Grafana plugin, plus an offline-trained ML forecasting pipeline (SVR, Huber, Random Forest, Gaussian Process, forward-chaining CV, adaptive ensemble) tested on data from four beacons during firefighter training exercises at Fire Station 9 in Madrid. | AI15: No actuation or bidirectional link to building systems: forecasting models are offline-trained and never updated online. The platform relies on proprietary ArcGIS, assumes a reliable wireless network, and sensor accuracy under extreme conditions is unverified; future work targets open-source visualization and integration with more real assets for active response and evacuation mechanisms. | AJ15: Aligned | AK15: Each video segment is timestamped and the custom Grafana plugin cross-references RTSP video streams with time-series sensor data stored in MySQL, giving video and beacon data a shared temporal frame (inference still runs on sensor series only). | AL15: High
A16: 4053 | B16: Ammar (2024) | C16: 2024 | E16: Practical Application of Digital Twins for Transportation Asset Data M… | F16: Web of Science | G16: Yes | H16: Yes | I16: Yes | J16: Yes | K16: Yes | L16: =IF(COUNTBLANK(G16:K16)=5,"",IF(COUNTIF(G16:K16,"No")>0,"EXCLUDE","INCLUDE")) -> INCLUDE | M16: =IF(L16<>"EXCLUDE","",IF(G16="No","Wrong domain (non-AECO)",IF(H16="No","Digital Twin not core / buzzword",IF(I16="No","No Design for Safety/Quality/PtD",IF(J16="No","Wrong publication type",IF(K16="No","Non-English","")))))) | N16: Yes | O16: Yes | P16: No | Q16: Yes | R16: Yes | S16: =IF(N16<>"Yes","",IF(COUNTBLANK(P16:R16)=3,"",IF(COUNTIF(P16:R16,"No")>0,"EXCLUDE","INCLUDE"))) -> EXCLUDE | T16: =IF(S16<>"EXCLUDE","",IF(P16="No","Digital Twin mentioned only, not the subject",IF(Q16="No","No Design for Safety/Quality in full text",IF(R16="No","Methodology not codable","")))) -> Digital Twin mentioned only, not the subject | U16: Unclear | Y16: =IF(SUM(V16:X16)=0,"",IF(SUM(V16:X16)>=2,"Multi","Single")) | AG16: Survey + case study on guiderail data management for a transportation agency: investigates current practices and proposes a data architecture for information-rich analytical models using DTs, but no DT is actually built or evaluated - P=No -> Stage-2 exclude. [Full-text source: Endnote]
A17: 3579 | E17: State regulation of the IoT in the Russian Federation: Fundamentals an… | F17: Scopus | G17: No | H17: No | I17: No | J17: Yes | K17: Yes | L17: =IF(COUNTBLANK(G17:K17)=5,"",IF(COUNTIF(G17:K17,"No")>0,"EXCLUDE","INCLUDE")) -> EXCLUDE | M17: =IF(L17<>"EXCLUDE","",IF(G17="No","Wrong domain (non-AECO)",IF(H17="No","Digital Twin not core / buzzword",IF(I17="No","No Design for Safety/Quality/PtD",IF(J17="No","Wrong publication type",IF(K17="No","Non-English","")))))) -> Wrong domain (non-AECO) | S17: =IF(N17<>"Yes","",IF(COUNTBLANK(P17:R17)=3,"",IF(COUNTIF(P17:R17,"No")>0,"EXCLUDE","INCLUDE"))) | T17: =IF(S17<>"EXCLUDE","",IF(P17="No","Digital Twin mentioned only, not the subject",IF(Q17="No","No Design for Safety/Quality in full text",IF(R17="No","Methodology not codable","")))) | Y17: =IF(SUM(V17:X17)=0,"",IF(SUM(V17:X17)>=2,"Multi","Single")) | AG17: Legal/regulatory IoT paper; not AECO
A18: 3838 | E18: The Role of Artificial Intelligence in Shaping Intelligent Motorways: … | F18: Scopus | G18: Yes | H18: No | I18: No | J18: Yes | K18: Yes | L18: =IF(COUNTBLANK(G18:K18)=5,"",IF(COUNTIF(G18:K18,"No")>0,"EXCLUDE","INCLUDE")) -> EXCLUDE | M18: =IF(L18<>"EXCLUDE","",IF(G18="No","Wrong domain (non-AECO)",IF(H18="No","Digital Twin not core / buzzword",IF(I18="No","No Design for Safety/Quality/PtD",IF(J18="No","Wrong publication type",IF(K18="No","Non-English","")))))) -> Digital Twin not core / buzzword | S18: =IF(N18<>"Yes","",IF(COUNTBLANK(P18:R18)=3,"",IF(COUNTIF(P18:R18,"No")>0,"EXCLUDE","INCLUDE"))) | T18: =IF(S18<>"EXCLUDE","",IF(P18="No","Digital Twin mentioned only, not the subject",IF(Q18="No","No Design for Safety/Quality in full text",IF(R18="No","Methodology not codable","")))) | Y18: =IF(SUM(V18:X18)=0,"",IF(SUM(V18:X18)>=2,"Multi","Single")) | AG18: AI-in-motorways review; DT one of many topics
A19: 4020 | E19: FingerCI: Writing industrial process specifications from network traff… | F19: Web of Science | G19: No | H19: Yes | I19: No | J19: Yes | K19: Yes | L19: =IF(COUNTBLANK(G19:K19)=5,"",IF(COUNTIF(G19:K19,"No")>0,"EXCLUDE","INCLUDE")) -> EXCLUDE | M19: =IF(L19<>"EXCLUDE","",IF(G19="No","Wrong domain (non-AECO)",IF(H19="No","Digital Twin not core / buzzword",IF(I19="No","No Design for Safety/Quality/PtD",IF(J19="No","Wrong publication type",IF(K19="No","Non-English","")))))) -> Wrong domain (non-AECO) | S19: =IF(N19<>"Yes","",IF(COUNTBLANK(P19:R19)=3,"",IF(COUNTIF(P19:R19,"No")>0,"EXCLUDE","INCLUDE"))) | T19: =IF(S19<>"EXCLUDE","",IF(P19="No","Digital Twin mentioned only, not the subject",IF(Q19="No","No Design for Safety/Quality in full text",IF(R19="No","Methodology not codable","")))) | Y19: =IF(SUM(V19:X19)=0,"",IF(SUM(V19:X19)>=2,"Multi","Single")) | AG19: Cybersecurity; airport baggage system industrial testbed
A20: 3842 | B20: Aragon (2025) | C20: 2025 | E20: Seeking a Definition of Digital Twins for Construction and Infrastruct… | F20: Scopus | G20: Yes | H20: Yes | I20: Yes | J20: Yes | K20: Yes | L20: =IF(COUNTBLANK(G20:K20)=5,"",IF(COUNTIF(G20:K20,"No")>0,"EXCLUDE","INCLUDE")) -> INCLUDE | M20: =IF(L20<>"EXCLUDE","",IF(G20="No","Wrong domain (non-AECO)",IF(H20="No","Digital Twin not core / buzzword",IF(I20="No","No Design for Safety/Quality/PtD",IF(J20="No","Wrong publication type",IF(K20="No","Non-English","")))))) | N20: Yes | O20: Yes | P20: Yes | Q20: Yes | R20: Yes | S20: =IF(N20<>"Yes","",IF(COUNTBLANK(P20:R20)=3,"",IF(COUNTIF(P20:R20,"No")>0,"EXCLUDE","INCLUDE"))) -> INCLUDE | T20: =IF(S20<>"EXCLUDE","",IF(P20="No","Digital Twin mentioned only, not the subject",IF(Q20="No","No Design for Safety/Quality in full text",IF(R20="No","Methodology not codable","")))) | U20: Tier 1 - Digital Model (static, no live data) | V20: 0 | W20: 0 | X20: 1 | Y20: =IF(SUM(V20:X20)=0,"",IF(SUM(V20:X20)>=2,"Multi","Single")) -> Single | Z20: Design for Safety (DfS) | AA20: None | AB20: Digital Twin platform (no machine learning) | AC20: Multi (two or more data types) | AD20: Cross-project (multiple real projects) | AE20: 3 | AF20: Lifecycle / governance | AG20: Definition/standardisation position paper (CEN/TC 442/WG 9, ISO); two illustrative DT cases (Bidebieta-Basauri railway station, UPM civil engineering school) are management/visualisation platforms with real-time info integration but no analytics loop or learning; safety only a secondary use case. [Full-text source: Endnote] | AH20: A standardization position paper reviewing DT definitions and frameworks and reporting the creation of CEN/TC 442/WG 9, whose 34-use-case technical report CEN/TR 18077 and the resulting European standard aim to give the built environment a shared DT definition; it grounds its argument in two implemented management platforms, the Bidebieta-Basauri railway station and the UPM civil engineering school. | AI20: The two DT cases are management and visualization platforms lacking AI or simulation protocols, which the authors state are still under research, and the paper proposes definitions rather than new empirical validation; the European standard was still pending publication and no quantitative evaluation is offered. | AJ20: Unclear | AK20: Standardisation position paper (CEN/TC 442/WG 9); the two illustrative DT cases are management/visualisation platforms and no data-integration mechanism is specified. | AL20: High
A21: 4028 | B21: Araujo (2025) | C21: 2025 | E21: Proposal of a conceptual model of digital twins for construction sites | F21: Web of Science | G21: Yes | H21: Yes | I21: Yes | J21: Yes | K21: Yes | L21: =IF(COUNTBLANK(G21:K21)=5,"",IF(COUNTIF(G21:K21,"No")>0,"EXCLUDE","INCLUDE")) -> INCLUDE | M21: =IF(L21<>"EXCLUDE","",IF(G21="No","Wrong domain (non-AECO)",IF(H21="No","Digital Twin not core / buzzword",IF(I21="No","No Design for Safety/Quality/PtD",IF(J21="No","Wrong publication type",IF(K21="No","Non-English","")))))) | N21: Yes | O21: Yes | P21: Yes | Q21: Yes | R21: Yes | S21: =IF(N21<>"Yes","",IF(COUNTBLANK(P21:R21)=3,"",IF(COUNTIF(P21:R21,"No")>0,"EXCLUDE","INCLUDE"))) -> INCLUDE | T21: =IF(S21<>"EXCLUDE","",IF(P21="No","Digital Twin mentioned only, not the subject",IF(Q21="No","No Design for Safety/Quality in full text",IF(R21="No","Methodology not codable","")))) | U21: Tier 2 - Digital Shadow (one-way physical to virtual) | V21: 0 | W21: 1 | X21: 0 | Y21: =IF(SUM(V21:X21)=0,"",IF(SUM(V21:X21)>=2,"Multi","Single")) -> Single | Z21: Design for Quality (DfQ) | AA21: None | AB21: Digital Twin platform (no machine learning) | AC21: Multi (two or more data types) | AD21: Conceptual (no test) | AE21: 3 | AF21: BIM-to-Digital-Twin architecture | AG21: DSR conceptual model (F1 data acquisition / F2 data analysis-simulation / F3 BIM transformation boxes) for DT on construction sites, generalised from the empirical Smart Twins 4.0 system (RFID+IoT+BIM tracking of metallic formwork in concrete wall construction; 151 panels inspected, 100% external defects, wear 42% — rework/quality control). Closed-loop is human-in-the-loop only; F2 simulation box proposed but NOT implemented (future Smart Twins 5.0); no ML and no self-improvement. [Full-text source: Endnote] | AH21: Proposes a closed-loop conceptual model of DTs for construction sites, structured as three functional boxes: F1 data acquisition (IoT/RFID), F2 data analysis and simulation, and F3 BIM transformation into a web-based model; it is grounded in the empirical Smart Twins 4.0 system, which tracked 151 formwork panels with RFID and a web-based BIM, finding 100% external and 98% internal defects. | AI21: Smart Twins 4.0 is limited to a single physical resource (formwork), has restricted data analysis capabilities and interoperability, and still requires manual steps in data collection; the model simplifies real-world complexity, omits human roles beyond decision-making, and the authors state it needs future testing in different contexts. | AJ21: Aligned | AK21: Smart Twins 4.0 links physical formworks to their virtual BIM counterparts through automatic database integration (RFID UHF tags read on Android, Firebase, Web-based Revit/Dynamo BIM), i.e. a shared object identity between tag data and BIM elements. | AL21: Medium
A22: 3828 | B22: Arhrib (2026) | C22: 2026 | E22: Serverless 3D Reconstruction and Spatial Anchoring for Cloud-Native In… | F22: Scopus | G22: Yes | H22: Yes | I22: Yes | J22: Yes | K22: Yes | L22: =IF(COUNTBLANK(G22:K22)=5,"",IF(COUNTIF(G22:K22,"No")>0,"EXCLUDE","INCLUDE")) -> INCLUDE | M22: =IF(L22<>"EXCLUDE","",IF(G22="No","Wrong domain (non-AECO)",IF(H22="No","Digital Twin not core / buzzword",IF(I22="No","No Design for Safety/Quality/PtD",IF(J22="No","Wrong publication type",IF(K22="No","Non-English","")))))) | N22: Yes | O22: Yes | P22: Yes | Q22: Yes | R22: Yes | S22: =IF(N22<>"Yes","",IF(COUNTBLANK(P22:R22)=3,"",IF(COUNTIF(P22:R22,"No")>0,"EXCLUDE","INCLUDE"))) -> INCLUDE | T22: =IF(S22<>"EXCLUDE","",IF(P22="No","Digital Twin mentioned only, not the subject",IF(Q22="No","No Design for Safety/Quality in full text",IF(R22="No","Methodology not codable","")))) | U22: Tier 1 - Digital Model (static, no live data) | V22: 0 | W22: 0 | X22: 1 | Y22: =IF(SUM(V22:X22)=0,"",IF(SUM(V22:X22)>=2,"Multi","Single")) -> Single | Z22: Design for Quality (DfQ) | AA22: None | AB22: Digital Twin platform (no machine learning) | AC22: Multi (two or more data types) | AD22: Single case study | AE22: 4 | AF22: Perception / Computer Vision | AG22: Serverless SfM/MVS pipeline + PostGIS defect anchors on real inspection datasets; defects as georeferenced 3D anchors support DfQ traceability; authors explicitly position against passive Level-1 twins, but no live link/learning: periodic re-scan workflow. [Full-text source: Endnote] | AH22: Addresses fragmented inspection data by replacing desktop photogrammetry with a serverless spatial intelligence hub: timeout-resilient orchestration of SfM/MVS, PostGIS-anchored defect records linked to georeferenced 3D meshes via raycasting and frustum-based image retrieval, end-to-end reconstruction in under one hour, sub-25 ms query latency, and over 90% image retrieval accuracy on two real UAV inspection datasets. | AI22: No automated defect detection: annotations are manually created by human inspectors, which the authors call the main bottleneck for scaling; validation covers only two UAV datasets, hyperparameters are not systematically optimized, and the system assumes reliable connectivity. Future work includes automated detection, temporal change monitoring, 3D Gaussian Splatting visualization, and offline capabilities. | AJ22: Aligned | AK22: Defect records are anchored to georeferenced 3D meshes in PostGIS via raycasting and frustum-based image retrieval, putting imagery-derived geometry and defect annotations in one spatial reference frame. | AL22: High
A23: 3662 | B23: Armijo (2024) | C23: 2024 | E23: Integration of Railway Bridge Structural Health Monitoring into the In… | F23: Scopus | G23: Yes | H23: Yes | I23: Yes | J23: Yes | K23: Yes | L23: =IF(COUNTBLANK(G23:K23)=5,"",IF(COUNTIF(G23:K23,"No")>0,"EXCLUDE","INCLUDE")) -> INCLUDE | M23: =IF(L23<>"EXCLUDE","",IF(G23="No","Wrong domain (non-AECO)",IF(H23="No","Digital Twin not core / buzzword",IF(I23="No","No Design for Safety/Quality/PtD",IF(J23="No","Wrong publication type",IF(K23="No","Non-English","")))))) | N23: Yes | O23: Yes | P23: Yes | Q23: Yes | R23: Yes | S23: =IF(N23<>"Yes","",IF(COUNTBLANK(P23:R23)=3,"",IF(COUNTIF(P23:R23,"No")>0,"EXCLUDE","INCLUDE"))) -> INCLUDE | T23: =IF(S23<>"EXCLUDE","",IF(P23="No","Digital Twin mentioned only, not the subject",IF(Q23="No","No Design for Safety/Quality in full text",IF(R23="No","Methodology not codable","")))) | U23: Tier 2 - Digital Shadow (one-way physical to virtual) | V23: 0 | W23: 0 | X23: 1 | Y23: =IF(SUM(V23:X23)=0,"",IF(SUM(V23:X23)>=2,"Multi","Single")) -> Single | Z23: Design for Safety (DfS) | AA23: Implemented | AB23: Other / Mixed | AC23: Single (one data type) | AD23: Single case study | AE23: 4 | AF23: Predictive analytics / decision support | AG23: 2-year in-service railway bridge pilot; unsupervised clustering of normal vibration + FEM-calibrated synthetic damage + LightGBM classifier (ROC-AUC 0.9999); periodic retraining of the model on accumulated data = implemented learning loop, but no convergence criterion/metric. [Full-text source: Endnote] | AH23: Demonstrates an operational digital twin for railway bridge SHM: low-cost wireless accelerometers (about EUR 300), hybrid edge-cloud processing with real-time FFT, unsupervised clustering of normal vibration, FEM-calibrated synthetic damage data, and a LightGBM classifier reaching ROC-AUC 0.9999 on two years of in-service vibration data from a bridge in the Basque Country. | AI23: Detection is anomaly-based rather than damage localization or quantification, which the authors list as future work; validation is limited to one short-span bridge pilot, and analytics still rely on middleware plus cloud, with plans to move FFT and inference onto energy-harvesting edge sensors and to extend to wind towers and broader production deployments. | AJ23: Single | AK23: Only ambient-vibration time series from wireless accelerometers feed the analytics; FEM-calibrated synthetic damage is model-generated training data, not a second measured data type. | AL23: High
A24: 3975 | B24: Aroquipa (2025) | C24: 2025 | E24: Methodological framework for integrating structural health monitoring … | F24: Web of Science | G24: Yes | H24: Yes | I24: Yes | J24: Yes | K24: Yes | L24: =IF(COUNTBLANK(G24:K24)=5,"",IF(COUNTIF(G24:K24,"No")>0,"EXCLUDE","INCLUDE")) -> INCLUDE | M24: =IF(L24<>"EXCLUDE","",IF(G24="No","Wrong domain (non-AECO)",IF(H24="No","Digital Twin not core / buzzword",IF(I24="No","No Design for Safety/Quality/PtD",IF(J24="No","Wrong publication type",IF(K24="No","Non-English","")))))) | N24: Yes | O24: Yes | P24: Yes | Q24: Yes | R24: Yes | S24: =IF(N24<>"Yes","",IF(COUNTBLANK(P24:R24)=3,"",IF(COUNTIF(P24:R24,"No")>0,"EXCLUDE","INCLUDE"))) -> INCLUDE | T24: =IF(S24<>"EXCLUDE","",IF(P24="No","Digital Twin mentioned only, not the subject",IF(Q24="No","No Design for Safety/Quality in full text",IF(R24="No","Methodology not codable","")))) | U24: Tier 1 - Digital Model (static, no live data) | V24: 0 | W24: 0 | X24: 1 | Y24: =IF(SUM(V24:X24)=0,"",IF(SUM(V24:X24)>=2,"Multi","Single")) -> Single | Z24: Design for Safety (DfS) | AA24: None | AB24: Finite Element Method / physics-based | AC24: Multi (two or more data types) | AD24: Conceptual (no test) | AE24: 4 | AF24: BIM-to-Digital-Twin architecture | AG24: Methodological framework for integrating SHM with numerical DT models for seismic assessment of heritage buildings (Basilica Maria Auxiliadora, Lima): numerical models in 3DEC and SAP2000 (modal + time-history of 34 seismic ground-motion records) identify susceptible zones and recommended sensor locations; sensor deployment and validation against experimental models are explicitly future work - no DT implemented, no live data link, no learning loop. [Full-text source: Endnote] | AH24: Provides a methodology for integrating SHM with numerical DT models for seismic assessment of heritage buildings: a LiDAR-derived BIM of the Basilica Maria Auxiliadora in Lima fed calibrated SAP2000 and 3DEC models (about 4500 block elements, 161000 contact zones), modal analysis with 220 modes, time-history analysis reproducing the 2007 Pisco earthquake crack patterns, and 25 sensor control points selected via intensity-duration-frequency plots. | AI24: No sensors are yet deployed: the study covers only Building Virtualization and part of sensor data analysis, so the EWS and DT feedback loop remain pending; validation relies on historical damage reports and analytical consistency, with future research to include experimental models, tri-axial sensor installation, and ambient-vibration calibration of the numerical model. | AJ24: Aligned | AK24: The LiDAR point-cloud survey is converted into a BIM that is linked to the 3DEC/SAP2000 FEM models through an explicit BIM-FEM linking process, sharing one building geometry frame while each model analyses separately. | AL24: Medium
A25: 3996 | B25: Arowoiya (2024) | C25: 2024 | E25: Driving Factors for the Adoption of Digital Twin Technology Implementa… | F25: Web of Science | G25: Yes | H25: Yes | I25: Yes | J25: Yes | K25: Yes | L25: =IF(COUNTBLANK(G25:K25)=5,"",IF(COUNTIF(G25:K25,"No")>0,"EXCLUDE","INCLUDE")) -> INCLUDE | M25: =IF(L25<>"EXCLUDE","",IF(G25="No","Wrong domain (non-AECO)",IF(H25="No","Digital Twin not core / buzzword",IF(I25="No","No Design for Safety/Quality/PtD",IF(J25="No","Wrong publication type",IF(K25="No","Non-English","")))))) | N25: Yes | O25: Yes | P25: No | Q25: Yes | R25: Yes | S25: =IF(N25<>"Yes","",IF(COUNTBLANK(P25:R25)=3,"",IF(COUNTIF(P25:R25,"No")>0,"EXCLUDE","INCLUDE"))) -> EXCLUDE | T25: =IF(S25<>"EXCLUDE","",IF(P25="No","Digital Twin mentioned only, not the subject",IF(Q25="No","No Design for Safety/Quality in full text",IF(R25="No","Methodology not codable","")))) -> Digital Twin mentioned only, not the subject | U25: Unclear | Y25: =IF(SUM(V25:X25)=0,"",IF(SUM(V25:X25)>=2,"Multi","Single")) | AG25: Questionnaire survey (Nigerian construction professionals, purposive+snowball) of drivers for adopting DTT; Shapiro-Wilk + Kruskal-Wallis H + factor analysis grouping drivers into innovation/operation/quality/performance/policy. No digital twin is built, evaluated or framed as a system — DT only appears as the technology whose adoption is surveyed. P=No → Stage-2 exclude. [Full-text source: Endnote]
A26: 4030 | E26: Excavator 3D pose estimation using deep learning and hybrid datasets | F26: Web of Science | G26: Yes | H26: No | I26: Yes | J26: Yes | K26: Yes | L26: =IF(COUNTBLANK(G26:K26)=5,"",IF(COUNTIF(G26:K26,"No")>0,"EXCLUDE","INCLUDE")) -> EXCLUDE | M26: =IF(L26<>"EXCLUDE","",IF(G26="No","Wrong domain (non-AECO)",IF(H26="No","Digital Twin not core / buzzword",IF(I26="No","No Design for Safety/Quality/PtD",IF(J26="No","Wrong publication type",IF(K26="No","Non-English","")))))) -> Digital Twin not core / buzzword | S26: =IF(N26<>"Yes","",IF(COUNTBLANK(P26:R26)=3,"",IF(COUNTIF(P26:R26,"No")>0,"EXCLUDE","INCLUDE"))) | T26: =IF(S26<>"EXCLUDE","",IF(P26="No","Digital Twin mentioned only, not the subject",IF(Q26="No","No Design for Safety/Quality in full text",IF(R26="No","Methodology not codable","")))) | Y26: =IF(SUM(V26:X26)=0,"",IF(SUM(V26:X26)>=2,"Multi","Single")) | AG26: CV pose estimation; DT only synthesizes training data
A27: 3982 | E27: Integrating Web-Based Weather Data into Building Information Modeling … | F27: Web of Science | G27: Yes | H27: No | I27: Yes | J27: Yes | K27: Yes | L27: =IF(COUNTBLANK(G27:K27)=5,"",IF(COUNTIF(G27:K27,"No")>0,"EXCLUDE","INCLUDE")) -> EXCLUDE | M27: =IF(L27<>"EXCLUDE","",IF(G27="No","Wrong domain (non-AECO)",IF(H27="No","Digital Twin not core / buzzword",IF(I27="No","No Design for Safety/Quality/PtD",IF(J27="No","Wrong publication type",IF(K27="No","Non-English","")))))) -> Digital Twin not core / buzzword | S27: =IF(N27<>"Yes","",IF(COUNTBLANK(P27:R27)=3,"",IF(COUNTIF(P27:R27,"No")>0,"EXCLUDE","INCLUDE"))) | T27: =IF(S27<>"EXCLUDE","",IF(P27="No","Digital Twin mentioned only, not the subject",IF(Q27="No","No Design for Safety/Quality in full text",IF(R27="No","Methodology not codable","")))) | Y27: =IF(SUM(V27:X27)=0,"",IF(SUM(V27:X27)>=2,"Multi","Single")) | AG27: BIM+RPA weather alerts; static BIM, no live DT
A28: 3940 | E28: Circular economy in construction: The digital transformation perspecti… | F28: Web of Science | G28: Yes | H28: No | I28: No | J28: Yes | K28: Yes | L28: =IF(COUNTBLANK(G28:K28)=5,"",IF(COUNTIF(G28:K28,"No")>0,"EXCLUDE","INCLUDE")) -> EXCLUDE | M28: =IF(L28<>"EXCLUDE","",IF(G28="No","Wrong domain (non-AECO)",IF(H28="No","Digital Twin not core / buzzword",IF(I28="No","No Design for Safety/Quality/PtD",IF(J28="No","Wrong publication type",IF(K28="No","Non-English","")))))) -> Digital Twin not core / buzzword | S28: =IF(N28<>"Yes","",IF(COUNTBLANK(P28:R28)=3,"",IF(COUNTIF(P28:R28,"No")>0,"EXCLUDE","INCLUDE"))) | T28: =IF(S28<>"EXCLUDE","",IF(P28="No","Digital Twin mentioned only, not the subject",IF(Q28="No","No Design for Safety/Quality in full text",IF(R28="No","Methodology not codable","")))) | Y28: =IF(SUM(V28:X28)=0,"",IF(SUM(V28:X28)>=2,"Multi","Single")) | AG28: CE/digitalisation review; DT peripheral
A29: 4037 | B29: Bao (2026) | C29: 2026 | E29: Intelligent technologies for tunnel construction and maintenance: A st… | F29: Web of Science | G29: Yes | H29: Yes | I29: Yes | J29: Yes | K29: Yes | L29: =IF(COUNTBLANK(G29:K29)=5,"",IF(COUNTIF(G29:K29,"No")>0,"EXCLUDE","INCLUDE")) -> INCLUDE | M29: =IF(L29<>"EXCLUDE","",IF(G29="No","Wrong domain (non-AECO)",IF(H29="No","Digital Twin not core / buzzword",IF(I29="No","No Design for Safety/Quality/PtD",IF(J29="No","Wrong publication type",IF(K29="No","Non-English","")))))) | N29: Yes | O29: Yes | P29: No | Q29: Yes | R29: Yes | S29: =IF(N29<>"Yes","",IF(COUNTBLANK(P29:R29)=3,"",IF(COUNTIF(P29:R29,"No")>0,"EXCLUDE","INCLUDE"))) -> EXCLUDE | T29: =IF(S29<>"EXCLUDE","",IF(P29="No","Digital Twin mentioned only, not the subject",IF(Q29="No","No Design for Safety/Quality in full text",IF(R29="No","Methodology not codable","")))) -> Digital Twin mentioned only, not the subject | U29: Unclear | Y29: =IF(SUM(V29:X29)=0,"",IF(SUM(V29:X29)>=2,"Multi","Single")) | AG29: State-of-the-art review of intelligent tunnel construction & O&M technologies (IoT, big data, AI, platforms) across design/construction/O&M; digital twins appear as one component (geological DTs, future DT co-simulation) but are not the actual subject of the paper. P=No → Stage-2 exclude. Safety/risk is a genuine theme (construction safety, real-time risk analysis). [Full-text source: Endnote]
A30: 3551 | E30: Improving Organizational and Engineering Reliability during Dismantlin… | F30: Scopus | G30: Yes | H30: No | I30: Yes | J30: Yes | K30: No | L30: =IF(COUNTBLANK(G30:K30)=5,"",IF(COUNTIF(G30:K30,"No")>0,"EXCLUDE","INCLUDE")) -> EXCLUDE | M30: =IF(L30<>"EXCLUDE","",IF(G30="No","Wrong domain (non-AECO)",IF(H30="No","Digital Twin not core / buzzword",IF(I30="No","No Design for Safety/Quality/PtD",IF(J30="No","Wrong publication type",IF(K30="No","Non-English","")))))) -> Digital Twin not core / buzzword | S30: =IF(N30<>"Yes","",IF(COUNTBLANK(P30:R30)=3,"",IF(COUNTIF(P30:R30,"No")>0,"EXCLUDE","INCLUDE"))) | T30: =IF(S30<>"EXCLUDE","",IF(P30="No","Digital Twin mentioned only, not the subject",IF(Q30="No","No Design for Safety/Quality in full text",IF(R30="No","Methodology not codable","")))) | Y30: =IF(SUM(V30:X30)=0,"",IF(SUM(V30:X30)>=2,"Multi","Single")) | AG30: Russian journal; BIM/DT mentioned, full text non-English
A31: 3571 | E31: The Process of Digitalization of the Urban Environment for the Develop… | F31: Scopus | G31: Yes | H31: No | I31: No | J31: Yes | K31: Yes | L31: =IF(COUNTBLANK(G31:K31)=5,"",IF(COUNTIF(G31:K31,"No")>0,"EXCLUDE","INCLUDE")) -> EXCLUDE | M31: =IF(L31<>"EXCLUDE","",IF(G31="No","Wrong domain (non-AECO)",IF(H31="No","Digital Twin not core / buzzword",IF(I31="No","No Design for Safety/Quality/PtD",IF(J31="No","Wrong publication type",IF(K31="No","Non-English","")))))) -> Digital Twin not core / buzzword | S31: =IF(N31<>"Yes","",IF(COUNTBLANK(P31:R31)=3,"",IF(COUNTIF(P31:R31,"No")>0,"EXCLUDE","INCLUDE"))) | T31: =IF(S31<>"EXCLUDE","",IF(P31="No","Digital Twin mentioned only, not the subject",IF(Q31="No","No Design for Safety/Quality in full text",IF(R31="No","Methodology not codable","")))) | Y31: =IF(SUM(V31:X31)=0,"",IF(SUM(V31:X31)>=2,"Multi","Single")) | AG31: Urban regeneration protocol; DT as future archive
A32: 3707 | E32: Construction and application of digital twin system for coal ports | F32: Scopus | G32: No | H32: Yes | I32: Yes | J32: Yes | K32: No | L32: =IF(COUNTBLANK(G32:K32)=5,"",IF(COUNTIF(G32:K32,"No")>0,"EXCLUDE","INCLUDE")) -> EXCLUDE | M32: =IF(L32<>"EXCLUDE","",IF(G32="No","Wrong domain (non-AECO)",IF(H32="No","Digital Twin not core / buzzword",IF(I32="No","No Design for Safety/Quality/PtD",IF(J32="No","Wrong publication type",IF(K32="No","Non-English","")))))) -> Wrong domain (non-AECO) | S32: =IF(N32<>"Yes","",IF(COUNTBLANK(P32:R32)=3,"",IF(COUNTIF(P32:R32,"No")>0,"EXCLUDE","INCLUDE"))) | T32: =IF(S32<>"EXCLUDE","",IF(P32="No","Digital Twin mentioned only, not the subject",IF(Q32="No","No Design for Safety/Quality in full text",IF(R32="No","Methodology not codable","")))) | Y32: =IF(SUM(V32:X32)=0,"",IF(SUM(V32:X32)>=2,"Multi","Single")) | AG32: Industrial port ops; Chinese journal, non-English
A33: 3613 | E33: Incorporation of pre-existing longitudinal cracks in finite element an… | F33: Scopus | G33: Yes | H33: No | I33: Yes | J33: Yes | K33: Yes | L33: =IF(COUNTBLANK(G33:K33)=5,"",IF(COUNTIF(G33:K33,"No")>0,"EXCLUDE","INCLUDE")) -> EXCLUDE | M33: =IF(L33<>"EXCLUDE","",IF(G33="No","Wrong domain (non-AECO)",IF(H33="No","Digital Twin not core / buzzword",IF(I33="No","No Design for Safety/Quality/PtD",IF(J33="No","Wrong publication type",IF(K33="No","Non-English","")))))) -> Digital Twin not core / buzzword | S33: =IF(N33<>"Yes","",IF(COUNTBLANK(P33:R33)=3,"",IF(COUNTIF(P33:R33,"No")>0,"EXCLUDE","INCLUDE"))) | T33: =IF(S33<>"EXCLUDE","",IF(P33="No","Digital Twin mentioned only, not the subject",IF(Q33="No","No Design for Safety/Quality in full text",IF(R33="No","Methodology not codable","")))) | Y33: =IF(SUM(V33:X33)=0,"",IF(SUM(V33:X33)>=2,"Multi","Single")) | AG33: Pure FEM structural analysis; no DT
A34: 3645 | E34: The evolution of BIM work standards: current, best, and future practic… | F34: Scopus | G34: Yes | H34: No | I34: No | J34: Yes | K34: Yes | L34: =IF(COUNTBLANK(G34:K34)=5,"",IF(COUNTIF(G34:K34,"No")>0,"EXCLUDE","INCLUDE")) -> EXCLUDE | M34: =IF(L34<>"EXCLUDE","",IF(G34="No","Wrong domain (non-AECO)",IF(H34="No","Digital Twin not core / buzzword",IF(I34="No","No Design for Safety/Quality/PtD",IF(J34="No","Wrong publication type",IF(K34="No","Non-English","")))))) -> Digital Twin not core / buzzword | S34: =IF(N34<>"Yes","",IF(COUNTBLANK(P34:R34)=3,"",IF(COUNTIF(P34:R34,"No")>0,"EXCLUDE","INCLUDE"))) | T34: =IF(S34<>"EXCLUDE","",IF(P34="No","Digital Twin mentioned only, not the subject",IF(Q34="No","No Design for Safety/Quality in full text",IF(R34="No","Methodology not codable","")))) | Y34: =IF(SUM(V34:X34)=0,"",IF(SUM(V34:X34)>=2,"Multi","Single")) | AG34: BIM-manager narrative review; no DT core
A35: 3807 | E35: Railway condition information modelling in a BIM framework for mainten… | F35: Scopus | G35: Yes | H35: No | I35: Yes | J35: Yes | K35: Yes | L35: =IF(COUNTBLANK(G35:K35)=5,"",IF(COUNTIF(G35:K35,"No")>0,"EXCLUDE","INCLUDE")) -> EXCLUDE | M35: =IF(L35<>"EXCLUDE","",IF(G35="No","Wrong domain (non-AECO)",IF(H35="No","Digital Twin not core / buzzword",IF(I35="No","No Design for Safety/Quality/PtD",IF(J35="No","Wrong publication type",IF(K35="No","Non-English","")))))) -> Digital Twin not core / buzzword | S35: =IF(N35<>"Yes","",IF(COUNTBLANK(P35:R35)=3,"",IF(COUNTIF(P35:R35,"No")>0,"EXCLUDE","INCLUDE"))) | T35: =IF(S35<>"EXCLUDE","",IF(P35="No","Digital Twin mentioned only, not the subject",IF(Q35="No","No Design for Safety/Quality in full text",IF(R35="No","Methodology not codable","")))) | Y35: =IF(SUM(V35:X35)=0,"",IF(SUM(V35:X35)>=2,"Multi","Single")) | AG35: I-BIM maintenance framework; DT aspirational
A36: 3595 | B36: Brucherseifer (2021) | C36: 2021 | E36: Digital Twin conceptual framework for improving critical infrastructur… | F36: Scopus | G36: Yes | H36: Yes | I36: Yes | J36: Yes | K36: Yes | L36: =IF(COUNTBLANK(G36:K36)=5,"",IF(COUNTIF(G36:K36,"No")>0,"EXCLUDE","INCLUDE")) -> INCLUDE | M36: =IF(L36<>"EXCLUDE","",IF(G36="No","Wrong domain (non-AECO)",IF(H36="No","Digital Twin not core / buzzword",IF(I36="No","No Design for Safety/Quality/PtD",IF(J36="No","Wrong publication type",IF(K36="No","Non-English","")))))) | N36: Yes | O36: Yes | P36: Yes | Q36: Yes | R36: Yes | S36: =IF(N36<>"Yes","",IF(COUNTBLANK(P36:R36)=3,"",IF(COUNTIF(P36:R36,"No")>0,"EXCLUDE","INCLUDE"))) -> INCLUDE | T36: =IF(S36<>"EXCLUDE","",IF(P36="No","Digital Twin mentioned only, not the subject",IF(Q36="No","No Design for Safety/Quality in full text",IF(R36="No","Methodology not codable","")))) | U36: Tier 1 - Digital Model (static, no live data) | V36: 0 | W36: 0 | X36: 1 | Y36: =IF(SUM(V36:X36)=0,"",IF(SUM(V36:X36)>=2,"Multi","Single")) -> Single | Z36: Design for Safety (DfS) | AA36: None | AB36: Digital Twin platform (no machine learning) | AC36: Multi (two or more data types) | AD36: Conceptual (no test) | AE36: 3 | AF36: Lifecycle / governance | AG36: Digital Twin Conceptual Framework for critical infrastructure resilience (DLR): comprehensive requirements analysis for infrastructure crisis management/resilience, deriving a conceptual framework (virtual replica, virtual clones, smart-tool toolbox, human-operated control center) with guiding principles for construction/planning phases and a conceptual DT model; resilience cycle with learning from past events is discussed conceptually but not implemented; no DT built or validated, no learning loop. [Full-text source: Endnote] | AH36: Derives a comprehensive requirements analysis for critical infrastructure crisis management and resilience and maps it onto a Digital Twin Conceptual Framework with four guiding principles (human-in-the-loop control, parsimony with accepted uncertainty, preparedness for complexity and emergence, safe experiments and training) plus a conceptual model of virtual replica, clones, toolbox, and control center. | AI36: Entirely conceptual: no implementation, prototype, or case evaluation is presented, so none of the requirements or tools is tested. The authors list open challenges of integrating uncertain data sources and heterogeneous models, evaluating intelligent tools for the resilience cycle, and IT scalability and reliability, proposing federated digital twins instead of monolithic implementations. | AJ36: Unclear | AK36: Conceptual resilience framework for critical infrastructure; no implementation, prototype or case evaluation, so no integration mechanism can be identified. | AL36: High
A37: 3888 | E37: From BIM to Web3: A critical interpretive synthesis of present and eme… | F37: Web of Science | G37: Yes | H37: No | I37: No | J37: Yes | K37: Yes | L37: =IF(COUNTBLANK(G37:K37)=5,"",IF(COUNTIF(G37:K37,"No")>0,"EXCLUDE","INCLUDE")) -> EXCLUDE | M37: =IF(L37<>"EXCLUDE","",IF(G37="No","Wrong domain (non-AECO)",IF(H37="No","Digital Twin not core / buzzword",IF(I37="No","No Design for Safety/Quality/PtD",IF(J37="No","Wrong publication type",IF(K37="No","Non-English","")))))) -> Digital Twin not core / buzzword | S37: =IF(N37<>"Yes","",IF(COUNTBLANK(P37:R37)=3,"",IF(COUNTIF(P37:R37,"No")>0,"EXCLUDE","INCLUDE"))) | T37: =IF(S37<>"EXCLUDE","",IF(P37="No","Digital Twin mentioned only, not the subject",IF(Q37="No","No Design for Safety/Quality in full text",IF(R37="No","Methodology not codable","")))) | Y37: =IF(SUM(V37:X37)=0,"",IF(SUM(V37:X37)>=2,"Multi","Single")) | AG37: Data-management review; no DT core, no safety/quality
A38: 3869 | E38: Affective computing in smart city spaces: Research on emotion recognit… | F38: Scopus | G38: No | H38: No | I38: No | J38: Yes | K38: Yes | L38: =IF(COUNTBLANK(G38:K38)=5,"",IF(COUNTIF(G38:K38,"No")>0,"EXCLUDE","INCLUDE")) -> EXCLUDE | M38: =IF(L38<>"EXCLUDE","",IF(G38="No","Wrong domain (non-AECO)",IF(H38="No","Digital Twin not core / buzzword",IF(I38="No","No Design for Safety/Quality/PtD",IF(J38="No","Wrong publication type",IF(K38="No","Non-English","")))))) -> Wrong domain (non-AECO) | S38: =IF(N38<>"Yes","",IF(COUNTBLANK(P38:R38)=3,"",IF(COUNTIF(P38:R38,"No")>0,"EXCLUDE","INCLUDE"))) | T38: =IF(S38<>"EXCLUDE","",IF(P38="No","Digital Twin mentioned only, not the subject",IF(Q38="No","No Design for Safety/Quality in full text",IF(R38="No","Methodology not codable","")))) | Y38: =IF(SUM(V38:X38)=0,"",IF(SUM(V38:X38)>=2,"Multi","Single")) | AG38: Emotion recognition; no built asset, no safety/quality
A39: 3702 | E39: TunnelSDF-FilterNet: A Domain-Aware Neural Framework for High-Fidelity… | F39: Scopus | G39: Yes | H39: No | I39: Yes | J39: Yes | K39: Yes | L39: =IF(COUNTBLANK(G39:K39)=5,"",IF(COUNTIF(G39:K39,"No")>0,"EXCLUDE","INCLUDE")) -> EXCLUDE | M39: =IF(L39<>"EXCLUDE","",IF(G39="No","Wrong domain (non-AECO)",IF(H39="No","Digital Twin not core / buzzword",IF(I39="No","No Design for Safety/Quality/PtD",IF(J39="No","Wrong publication type",IF(K39="No","Non-English","")))))) -> Digital Twin not core / buzzword | S39: =IF(N39<>"Yes","",IF(COUNTBLANK(P39:R39)=3,"",IF(COUNTIF(P39:R39,"No")>0,"EXCLUDE","INCLUDE"))) | T39: =IF(S39<>"EXCLUDE","",IF(P39="No","Digital Twin mentioned only, not the subject",IF(Q39="No","No Design for Safety/Quality in full text",IF(R39="No","Methodology not codable","")))) | Y39: =IF(SUM(V39:X39)=0,"",IF(SUM(V39:X39)>=2,"Multi","Single")) | AG39: Neural-SDF reconstruction; DT only downstream use
A40: 3901 | E40: Methodology for 3D Management of University Faculties Using Integrated… | F40: Web of Science | G40: Yes | H40: No | I40: No | J40: Yes | K40: Yes | L40: =IF(COUNTBLANK(G40:K40)=5,"",IF(COUNTIF(G40:K40,"No")>0,"EXCLUDE","INCLUDE")) -> EXCLUDE | M40: =IF(L40<>"EXCLUDE","",IF(G40="No","Wrong domain (non-AECO)",IF(H40="No","Digital Twin not core / buzzword",IF(I40="No","No Design for Safety/Quality/PtD",IF(J40="No","Wrong publication type",IF(K40="No","Non-English","")))))) -> Digital Twin not core / buzzword | S40: =IF(N40<>"Yes","",IF(COUNTBLANK(P40:R40)=3,"",IF(COUNTIF(P40:R40,"No")>0,"EXCLUDE","INCLUDE"))) | T40: =IF(S40<>"EXCLUDE","",IF(P40="No","Digital Twin mentioned only, not the subject",IF(Q40="No","No Design for Safety/Quality in full text",IF(R40="No","Methodology not codable","")))) | Y40: =IF(SUM(V40:X40)=0,"",IF(SUM(V40:X40)>=2,"Multi","Single")) | AG40: Static GIS-BIM/CMMS-3D; no live DT
A41: 3889 | E41: Integration of BIM Tools for the Facility Management of Railway Bridge… | F41: Web of Science | G41: Yes | H41: No | I41: Yes | J41: Yes | K41: Yes | L41: =IF(COUNTBLANK(G41:K41)=5,"",IF(COUNTIF(G41:K41,"No")>0,"EXCLUDE","INCLUDE")) -> EXCLUDE | M41: =IF(L41<>"EXCLUDE","",IF(G41="No","Wrong domain (non-AECO)",IF(H41="No","Digital Twin not core / buzzword",IF(I41="No","No Design for Safety/Quality/PtD",IF(J41="No","Wrong publication type",IF(K41="No","Non-English","")))))) -> Digital Twin not core / buzzword | S41: =IF(N41<>"Yes","",IF(COUNTBLANK(P41:R41)=3,"",IF(COUNTIF(P41:R41,"No")>0,"EXCLUDE","INCLUDE"))) | T41: =IF(S41<>"EXCLUDE","",IF(P41="No","Digital Twin mentioned only, not the subject",IF(Q41="No","No Design for Safety/Quality in full text",IF(R41="No","Methodology not codable","")))) | Y41: =IF(SUM(V41:X41)=0,"",IF(SUM(V41:X41)>=2,"Multi","Single")) | AG41: BIM-Dynamo automation; initial step towards DT only
A42: 3555 | E42: Climate Change Impacts on Reinforced Concrete Structures: A Bibliometr… | F42: Scopus | G42: Yes | H42: No | I42: No | J42: Yes | K42: Yes | L42: =IF(COUNTBLANK(G42:K42)=5,"",IF(COUNTIF(G42:K42,"No")>0,"EXCLUDE","INCLUDE")) -> EXCLUDE | M42: =IF(L42<>"EXCLUDE","",IF(G42="No","Wrong domain (non-AECO)",IF(H42="No","Digital Twin not core / buzzword",IF(I42="No","No Design for Safety/Quality/PtD",IF(J42="No","Wrong publication type",IF(K42="No","Non-English","")))))) -> Digital Twin not core / buzzword | S42: =IF(N42<>"Yes","",IF(COUNTBLANK(P42:R42)=3,"",IF(COUNTIF(P42:R42,"No")>0,"EXCLUDE","INCLUDE"))) | T42: =IF(S42<>"EXCLUDE","",IF(P42="No","Digital Twin mentioned only, not the subject",IF(Q42="No","No Design for Safety/Quality in full text",IF(R42="No","Methodology not codable","")))) | Y42: =IF(SUM(V42:X42)=0,"",IF(SUM(V42:X42)>=2,"Multi","Single")) | AG42: Bibliometric; DT only a keyword trend
A43: 3658 | B43: Cervenka (2026) | C43: 2026 | E43: AI based surrogate model for digital twins in structural health monito… | F43: Scopus | G43: Yes | H43: Yes | I43: Yes | J43: Yes | K43: Yes | L43: =IF(COUNTBLANK(G43:K43)=5,"",IF(COUNTIF(G43:K43,"No")>0,"EXCLUDE","INCLUDE")) -> INCLUDE | M43: =IF(L43<>"EXCLUDE","",IF(G43="No","Wrong domain (non-AECO)",IF(H43="No","Digital Twin not core / buzzword",IF(I43="No","No Design for Safety/Quality/PtD",IF(J43="No","Wrong publication type",IF(K43="No","Non-English","")))))) | N43: Yes | O43: Yes | P43: Yes | Q43: Yes | R43: Yes | S43: =IF(N43<>"Yes","",IF(COUNTBLANK(P43:R43)=3,"",IF(COUNTIF(P43:R43,"No")>0,"EXCLUDE","INCLUDE"))) -> INCLUDE | T43: =IF(S43<>"EXCLUDE","",IF(P43="No","Digital Twin mentioned only, not the subject",IF(Q43="No","No Design for Safety/Quality in full text",IF(R43="No","Methodology not codable","")))) | U43: Tier 1 - Digital Model (static, no live data) | V43: 0 | W43: 0 | X43: 1 | Y43: =IF(SUM(V43:X43)=0,"",IF(SUM(V43:X43)>=2,"Multi","Single")) -> Single | Z43: Design for Safety (DfS) | AA43: None | AB43: Other / Mixed | AC43: Single (one data type) | AD43: Simulation | AE43: 3 | AF43: Design for Safety | AG43: AI-based ANN surrogate model for DTs in SHM of reinforced concrete bridges (Cervenka Consulting/CTU, RILEM SSCS 2025): ANN has two roles - calibrating the virtual twin to physical structure behavior, then deployment as fast-response surrogate providing safety information for ongoing SHM; physically informed deep learning trained from nonlinear FEM (ATENA) sensitivity analyses; demonstrated on Leonhardt shear-beam numerical example (100/400/1000-sample datasets) identifying material parameters (fc, ft, E, GF) from load-displacement diagrams. Numerical example only - no live data link to a real bridge, no actuation, no learning loop. [Full-text source: Endnote] | AH43: Assigns ANNs two roles in a DT for SHM of reinforced concrete bridges: first, physically informed deep learning calibrates the virtual twin by identifying material parameters (E, fc, ft, fracture energy) from ATENA nonlinear finite element sensitivity analyses, demonstrated on a Leonhardt shear beam with datasets of 100, 400, and 1000 samples; second, the trained ANN serves as a fast-response surrogate for real-time engineering interpretation of monitoring data. | AI43: A short conference-stage contribution: only parameter identification on a numerical shear beam example is demonstrated, with no deployed structure, no live sensor data, and no quantitative surrogate accuracy reported; the conclusion and future work sections remain essentially undeveloped, so the real-time SHM surrogate role is proposed rather than validated. | AJ43: Single | AK43: Only load-displacement curves generated by nonlinear ATENA finite-element sensitivity analyses feed the ANN surrogate; no measured sensor stream exists. | AL43: High
A44: 3958 | E44: Integration of Emerging Technologies with Construction Practices in Au… | F44: Web of Science | G44: Yes | H44: No | I44: No | J44: Yes | K44: Yes | L44: =IF(COUNTBLANK(G44:K44)=5,"",IF(COUNTIF(G44:K44,"No")>0,"EXCLUDE","INCLUDE")) -> EXCLUDE | M44: =IF(L44<>"EXCLUDE","",IF(G44="No","Wrong domain (non-AECO)",IF(H44="No","Digital Twin not core / buzzword",IF(I44="No","No Design for Safety/Quality/PtD",IF(J44="No","Wrong publication type",IF(K44="No","Non-English","")))))) -> Digital Twin not core / buzzword | S44: =IF(N44<>"Yes","",IF(COUNTBLANK(P44:R44)=3,"",IF(COUNTIF(P44:R44,"No")>0,"EXCLUDE","INCLUDE"))) | T44: =IF(S44<>"EXCLUDE","",IF(P44="No","Digital Twin mentioned only, not the subject",IF(Q44="No","No Design for Safety/Quality in full text",IF(R44="No","Methodology not codable","")))) | Y44: =IF(SUM(V44:X44)=0,"",IF(SUM(V44:X44)>=2,"Multi","Single")) | AG44: Tech-adoption survey; DT one of many
A45: 3936 | B45: Chacon (2024) | C45: 2024 | E45: Digital twinning of building construction processes. Case study: A rei… | F45: Web of Science | G45: Yes | H45: Yes | I45: Yes | J45: Yes | K45: Yes | L45: =IF(COUNTBLANK(G45:K45)=5,"",IF(COUNTIF(G45:K45,"No")>0,"EXCLUDE","INCLUDE")) -> INCLUDE | M45: =IF(L45<>"EXCLUDE","",IF(G45="No","Wrong domain (non-AECO)",IF(H45="No","Digital Twin not core / buzzword",IF(I45="No","No Design for Safety/Quality/PtD",IF(J45="No","Wrong publication type",IF(K45="No","Non-English","")))))) | N45: Yes | O45: Yes | P45: Yes | Q45: Yes | R45: Yes | S45: =IF(N45<>"Yes","",IF(COUNTBLANK(P45:R45)=3,"",IF(COUNTIF(P45:R45,"No")>0,"EXCLUDE","INCLUDE"))) -> INCLUDE | T45: =IF(S45<>"EXCLUDE","",IF(P45="No","Digital Twin mentioned only, not the subject",IF(Q45="No","No Design for Safety/Quality in full text",IF(R45="No","Methodology not codable","")))) | U45: Tier 2 - Digital Shadow (one-way physical to virtual) | V45: 0 | W45: 1 | X45: 0 | Y45: =IF(SUM(V45:X45)=0,"",IF(SUM(V45:X45)>=2,"Multi","Single")) -> Single | Z45: Both | AA45: None | AB45: Other / Mixed | AC45: Multi (two or more data types) | AD45: Single case study | AE45: 4 | AF45: BIM-to-Digital-Twin architecture | AG45: ASHVIN H2020 DT case study (RC office building, Barcelona): six independent information pipelines (IMU/temp/load sensors, TLS point clouds, equipment tracking) → knowledge-graph system → Unity dashboard with project-specific KPIs (construction safety, quality control, productivity); ML activity recognition (Naïve Bayes/DT/kNN/SVM on equipment sensors); data flows one-way physical→virtual for decision support; conclusions state it "has not permitted to act" on the site — no actuation, no learning loop. [Full-text source: Endnote] | AH45: Provides a real ASHVIN H2020 pilot of digital twinning during construction of an RC office building in Barcelona: six independent information pipelines (crane hook IMU/GPS tracking with Random Forest activity recognition at 93.27% accuracy, slab post-tensioning strains, laser-scan deflection checks, concrete maturity temperatures, formwork vibration accelerations, mobile-app progress monitoring) feeding a knowledge-graph-based Unity dashboard. | AI45: One-way digital shadow: the dashboard informs managers but does not control site operations, technology readiness did not permit acting weekly on extracted insights, and feedback came only after development. Bottlenecks include logistics, privacy, need for specialized crews, sensor fragility, and manual progress updates; automating data collection and treatment is future work. | AJ45: Co-present | AK45: Six independent information pipelines (crane-hook IMU/GPS, post-tensioning strains, laser-scan deflections, maturity temperatures, formwork-vibration accelerations, mobile-app progress) feed one knowledge-graph dashboard, each staying in its own pipeline. | AL45: High
A46: 3795 | B46: Chan (2025) | C46: 2025 | E46: Risk Mitigation of a Heritage Bridge Using Noninvasive Sensors | F46: Scopus | G46: Yes | H46: Yes | I46: Yes | J46: Yes | K46: Yes | L46: =IF(COUNTBLANK(G46:K46)=5,"",IF(COUNTIF(G46:K46,"No")>0,"EXCLUDE","INCLUDE")) -> INCLUDE | M46: =IF(L46<>"EXCLUDE","",IF(G46="No","Wrong domain (non-AECO)",IF(H46="No","Digital Twin not core / buzzword",IF(I46="No","No Design for Safety/Quality/PtD",IF(J46="No","Wrong publication type",IF(K46="No","Non-English","")))))) | N46: Yes | O46: Yes | P46: Yes | Q46: Yes | R46: Yes | S46: =IF(N46<>"Yes","",IF(COUNTBLANK(P46:R46)=3,"",IF(COUNTIF(P46:R46,"No")>0,"EXCLUDE","INCLUDE"))) -> INCLUDE | T46: =IF(S46<>"EXCLUDE","",IF(P46="No","Digital Twin mentioned only, not the subject",IF(Q46="No","No Design for Safety/Quality in full text",IF(R46="No","Methodology not codable","")))) | U46: Tier 2 - Digital Shadow (one-way physical to virtual) | V46: 0 | W46: 0 | X46: 1 | Y46: =IF(SUM(V46:X46)=0,"",IF(SUM(V46:X46)>=2,"Multi","Single")) -> Single | Z46: Design for Safety (DfS) | AA46: None | AB46: Finite Element Method / physics-based | AC46: Multi (two or more data types) | AD46: Single case study | AE46: 4 | AF46: Design for Safety | AG46: 120-yr heritage RC bridge; ambient vibration + laser displacement monitoring; FE-based DT validated against field data, used for what-if scenarios (overweight vehicles, scour loss); six-phase Incident Response Framework; model is updated/validated, not self-learning. [Full-text source: Endnote] | AH46: Fills the gap between heritage-bridge conservation and quantitative risk assessment: on a 120-year-old Australian reinforced concrete bridge, ambient vibration testing with ten wireless accelerometers plus laser displacement sensing feeds a Spacegass finite-element digital twin validated against measured natural frequencies (20.15 Hz versus 19.51 Hz, 3.2 percent difference), then used for what-if simulations of overweight vehicles and foundation scour. | AI46: Monitoring is campaign-based rather than live: the twin is an offline validated finite-element model with no continuous data link or actuation, higher-order modes are missed at the 100 Hz sampling rate, and the six-phase Incident Response Framework is proposed but not yet deployed; higher-rate testing is noted for the future. | AJ46: Aligned | AK46: Ambient-vibration accelerometers and laser displacement sensing both feed and validate one Spacegass FE twin of the bridge, sharing the structural model frame, with each quantity analysed separately. | AL46: Medium
A47: 3998 | B47: Chang (2024) | C47: 2024 | E47: Autonomous dimensional inspection and issue tracking of rebar using se… | F47: Web of Science | G47: Yes | H47: Yes | I47: Yes | J47: Yes | K47: Yes | L47: =IF(COUNTBLANK(G47:K47)=5,"",IF(COUNTIF(G47:K47,"No")>0,"EXCLUDE","INCLUDE")) -> INCLUDE | M47: =IF(L47<>"EXCLUDE","",IF(G47="No","Wrong domain (non-AECO)",IF(H47="No","Digital Twin not core / buzzword",IF(I47="No","No Design for Safety/Quality/PtD",IF(J47="No","Wrong publication type",IF(K47="No","Non-English","")))))) | N47: Yes | O47: Yes | P47: Yes | Q47: Yes | R47: Yes | S47: =IF(N47<>"Yes","",IF(COUNTBLANK(P47:R47)=3,"",IF(COUNTIF(P47:R47,"No")>0,"EXCLUDE","INCLUDE"))) -> INCLUDE | T47: =IF(S47<>"EXCLUDE","",IF(P47="No","Digital Twin mentioned only, not the subject",IF(Q47="No","No Design for Safety/Quality in full text",IF(R47="No","Methodology not codable","")))) | U47: Tier 1 - Digital Model (static, no live data) | V47: 0 | W47: 1 | X47: 0 | Y47: =IF(SUM(V47:X47)=0,"",IF(SUM(V47:X47)>=2,"Multi","Single")) -> Single | Z47: Design for Quality (DfQ) | AA47: None | AB47: Perception / Computer Vision | AC47: Multi (two or more data types) | AD47: Single case study | AE47: 4 | AF47: Perception / Computer Vision | AG47: Autonomous dimensional inspection and issue tracking of rebar using semantically enriched 3D models (NTU): DT generation from GoPro images via SfM-MVS point-cloud reconstruction (AprilTag scale calibration); segmentation via Mask R-CNN + 3D clustering (DBSCAN); inspection via 2D circular Hough transform (diameter accuracy 95.5%, spacing mean relative error 0.98%); issue identification/tracking via Scan-vs-BIM registration and comparison of semantically enriched 3D models with BIM across time. Single column rebar cage experiment. One-way inspection to BIM/Digital-Twin for DQC; no live data link and no learning loop. [Full-text source: Endnote] | AH47: Closes the automation gap between rebar reconstruction, segmentation, dimensional inspection and issue tracking: a GoPro-based SfM-MVS pipeline with AprilTag scale calibration builds a semantically enriched 3D model, Mask R-CNN plus DBSCAN segment rebars, and Scan-vs-BIM comparison identifies and tracks defects, reaching over 90 percent precision, over 97 percent recall, 95.5 percent diameter accuracy for large rebars and 0.98 percent mean relative spacing error. | AI47: Offline, camera-based pipeline with manual image capture and fiducial marker attachment; 2D segmentation precision averages only 50.4 percent, small-diameter rebar inspection reaches only 77.8 percent, and registration fails on geometrically indistinct structures; future work points to more training data, augmentation, unsupervised techniques and Point Transformer based classification. | AJ47: Aligned | AK47: SfM-MVS point clouds are registered to the BIM via Scan-vs-BIM comparison, and Mask R-CNN/DBSCAN segmentation and Hough-transform inspection run as separate stages on this shared model frame. | AL47: High
A48: 3984 | B48: Chang (2026) | C48: 2026 | E48: A transformer-based surrogate modeling strategy for tunnel digital twi… | F48: Web of Science | G48: Yes | H48: Yes | I48: Yes | J48: Yes | K48: Yes | L48: =IF(COUNTBLANK(G48:K48)=5,"",IF(COUNTIF(G48:K48,"No")>0,"EXCLUDE","INCLUDE")) -> INCLUDE | M48: =IF(L48<>"EXCLUDE","",IF(G48="No","Wrong domain (non-AECO)",IF(H48="No","Digital Twin not core / buzzword",IF(I48="No","No Design for Safety/Quality/PtD",IF(J48="No","Wrong publication type",IF(K48="No","Non-English","")))))) | N48: Yes | O48: Yes | P48: Yes | Q48: Yes | R48: Yes | S48: =IF(N48<>"Yes","",IF(COUNTBLANK(P48:R48)=3,"",IF(COUNTIF(P48:R48,"No")>0,"EXCLUDE","INCLUDE"))) -> INCLUDE | T48: =IF(S48<>"EXCLUDE","",IF(P48="No","Digital Twin mentioned only, not the subject",IF(Q48="No","No Design for Safety/Quality in full text",IF(R48="No","Methodology not codable","")))) | U48: Tier 2 - Digital Shadow (one-way physical to virtual) | V48: 0 | W48: 1 | X48: 0 | Y48: =IF(SUM(V48:X48)=0,"",IF(SUM(V48:X48)>=2,"Multi","Single")) -> Single | Z48: Design for Safety (DfS) | AA48: Implemented | AB48: Transformer / Large Language Model (LLM) | AC48: Multi (two or more data types) | AD48: Single case study | AE48: 4 | AF48: Predictive analytics / decision support | AG48: DT framework for predicting ground settlement and lining deformation of shield tunnels under adjacent excavation (NTU/Southeast U): hybrid surrogate model DF-STTN (Swin Transformer + TabTransformer) for full-field displacement prediction from spatial + non-spatial inputs; trained on high-fidelity FE data, then updated/validated on laboratory-scale tunnel excavation tests via a genetic-algorithm model-updating procedure that iteratively refines soil parameters using sparse test data (minimizing prediction error); outperforms convolution-based and single-fusion models; spatial info (3 measurement points) improves accuracy. One-way prediction with implemented GA-based model updating - no convergence criterion, no actuation. [Full-text source: Endnote] | AH48: Fills the sparse-point surrogate gap for tunnel digital twins: the DF-STTN hybrid surrogate, pairing Swin Transformer and TabTransformer with dual-stage fusion, predicts full-field ground settlement and lining deformation for shield tunnels under adjacent excavation, trained on 1000 parametric finite-element samples and reaching R2 0.9898 and 0.9951, outperforming six baseline networks, with genetic-algorithm back-analysis estimating soil parameters within 4 percent error. | AI48: Validation rests on a scaled laboratory testbed with simplified boundary conditions, not field monitoring; time-dependent processes like consolidation and creep are ignored, settlement and lining deformation are modeled separately, and no real-time sensor link exists; future work targets field monitoring data, spatio-temporal Transformers, layered soil and groundwater, coupled models and continuous model updating. | AJ48: Fused | AK48: The DF-STTN hybrid surrogate fuses Swin-Transformer spatial fields with TabTransformer non-spatial parameters via a dual-stage fusion module, and a GA model-updating procedure joins sparse laboratory test data with the FE-trained model. | AL48: High
A49: 3601 | E49: Digital twin-based experimental method for construction loads of adjac… | F49: Scopus | G49: Yes | H49: Yes | I49: Yes | J49: Yes | K49: No | L49: =IF(COUNTBLANK(G49:K49)=5,"",IF(COUNTIF(G49:K49,"No")>0,"EXCLUDE","INCLUDE")) -> EXCLUDE | M49: =IF(L49<>"EXCLUDE","",IF(G49="No","Wrong domain (non-AECO)",IF(H49="No","Digital Twin not core / buzzword",IF(I49="No","No Design for Safety/Quality/PtD",IF(J49="No","Wrong publication type",IF(K49="No","Non-English","")))))) -> Non-English | S49: =IF(N49<>"Yes","",IF(COUNTBLANK(P49:R49)=3,"",IF(COUNTIF(P49:R49,"No")>0,"EXCLUDE","INCLUDE"))) | T49: =IF(S49<>"EXCLUDE","",IF(P49="No","Digital Twin mentioned only, not the subject",IF(Q49="No","No Design for Safety/Quality in full text",IF(R49="No","Methodology not codable","")))) | Y49: =IF(SUM(V49:X49)=0,"",IF(SUM(V49:X49)>=2,"Multi","Single")) | AG49: Chinese journal; full text non-English
A50: 3911 | B50: Chen (2025) | C50: 2025 | E50: Digital Twin-Based and Knowledge Graph-Enhanced Emergency Response in … | F50: Web of Science | G50: Yes | H50: Yes | I50: Yes | J50: Yes | K50: Yes | L50: =IF(COUNTBLANK(G50:K50)=5,"",IF(COUNTIF(G50:K50,"No")>0,"EXCLUDE","INCLUDE")) -> INCLUDE | M50: =IF(L50<>"EXCLUDE","",IF(G50="No","Wrong domain (non-AECO)",IF(H50="No","Digital Twin not core / buzzword",IF(I50="No","No Design for Safety/Quality/PtD",IF(J50="No","Wrong publication type",IF(K50="No","Non-English","")))))) | N50: Yes | O50: Yes | P50: Yes | Q50: Yes | R50: Yes | S50: =IF(N50<>"Yes","",IF(COUNTBLANK(P50:R50)=3,"",IF(COUNTIF(P50:R50,"No")>0,"EXCLUDE","INCLUDE"))) -> INCLUDE | T50: =IF(S50<>"EXCLUDE","",IF(P50="No","Digital Twin mentioned only, not the subject",IF(Q50="No","No Design for Safety/Quality in full text",IF(R50="No","Methodology not codable","")))) | U50: Tier 3 - Digital Twin (bidirectional, two-way) | V50: 0 | W50: 1 | X50: 0 | Y50: =IF(SUM(V50:X50)=0,"",IF(SUM(V50:X50)>=2,"Multi","Single")) -> Single | Z50: Design for Safety (DfS) | AA50: None | AB50: Ontology / semantic | AC50: Multi (two or more data types) | AD50: Single case study | AE50: 4 | AF50: Predictive analytics / decision support | AG50: Tunnel project in China; DT continuously integrates settlement/TBM/structural monitoring; KG rule-based reasoning infers hazards and mitigation; bidirectional DT-KG interaction visualised for decisions; prevention of further structural impact claimed in real emergency. [Full-text source: Endnote] | AH50: Addresses the reactive and static gap in tunnel construction emergency response: a digital twin continuously integrating settlement, TBM operational and structural monitoring data is coupled with a knowledge graph using SWRL rule-based reasoning to infer hazards, detect anomalies and suggest mitigations, with inference results visualized back in the twin; deployed on an urban tunnel project in Shanghai where it enabled early anomaly identification. | AI50: Data quality dependency is acknowledged: sensor noise, loss, calibration drift and delays can misclassify risk levels; the ontology and rules are manually built for Shanghai urban tunnels, limiting scalability; reasoning speed, throughput and prediction accuracy are not quantitatively benchmarked; single-project validation; future work includes confidence metrics, automated rule generation, dynamic learning and stress testing. | AJ50: Fused | AK50: Settlement, TBM-operational and structural monitoring data are continuously integrated in the DT and jointly reasoned over by a knowledge graph with SWRL rules to infer hazards and mitigation. | AL50: High
A51: 3953 | B51: Chen (2026) | C51: 2026 | E51: Digital Twin-Enabled Robust Parallel Control of Construction Engineeri… | F51: Web of Science | G51: Yes | H51: Yes | I51: Yes | J51: Yes | K51: Yes | L51: =IF(COUNTBLANK(G51:K51)=5,"",IF(COUNTIF(G51:K51,"No")>0,"EXCLUDE","INCLUDE")) -> INCLUDE | M51: =IF(L51<>"EXCLUDE","",IF(G51="No","Wrong domain (non-AECO)",IF(H51="No","Digital Twin not core / buzzword",IF(I51="No","No Design for Safety/Quality/PtD",IF(J51="No","Wrong publication type",IF(K51="No","Non-English","")))))) | N51: Yes | O51: Yes | P51: Yes | Q51: Yes | R51: Yes | S51: =IF(N51<>"Yes","",IF(COUNTBLANK(P51:R51)=3,"",IF(COUNTIF(P51:R51,"No")>0,"EXCLUDE","INCLUDE"))) -> INCLUDE | T51: =IF(S51<>"EXCLUDE","",IF(P51="No","Digital Twin mentioned only, not the subject",IF(Q51="No","No Design for Safety/Quality in full text",IF(R51="No","Methodology not codable","")))) | U51: Tier 3 - Digital Twin (bidirectional, two-way) | V51: 0 | W51: 1 | X51: 0 | Y51: =IF(SUM(V51:X51)=0,"",IF(SUM(V51:X51)>=2,"Multi","Single")) -> Single | Z51: Design for Safety (DfS) | AA51: Mentioned only | AB51: Other / Mixed | AC51: Multi (two or more data types) | AD51: Single case study | AE51: 4 | AF51: Design for Safety | AG51: Mobile gin pole (UHV construction): FEM kinetic analysis + TROA-ET surrogate (R2 0.9642) + NSGA-III safety-efficiency optimisation embedded in DT parallel-control architecture; bidirectional 4G/MQTT link (CANopen control commands) on real 110 kV project; safety risk -32.3%; surrogate is offline-trained, no online learning. [Full-text source: MDPI Buildings (Gold OA)] | AH51: Addresses robust parallel control of construction equipment under uncertainty: a mobile gin pole digital twin for UHV construction embeds finite-element kinetic analysis with a TROA-ET surrogate model (R2 0.9642) and NSGA-III safety-efficiency optimisation within a DT parallel-control architecture supported by bidirectional 4G and MQTT links. | AI51: The available record states no explicit future work; validation is documented only for the mobile gin pole application, and whether the TROA-ET surrogate is updated online, transferred to other equipment types, or tested against field disturbances beyond the stated scenario is not established. | AJ51: Aligned | AK51: Live operational data and the TROA-ET/FEM surrogate coexist in the DT parallel-control architecture over bidirectional 4G/MQTT links, but the surrogate is offline-trained and no joint inference across streams is stated. | AL51: Medium
A52: 3873 | E52: Construction and application of Digital Twin model of pipeline | F52: Scopus | G52: No | H52: Yes | I52: Yes | J52: Yes | K52: No | L52: =IF(COUNTBLANK(G52:K52)=5,"",IF(COUNTIF(G52:K52,"No")>0,"EXCLUDE","INCLUDE")) -> EXCLUDE | M52: =IF(L52<>"EXCLUDE","",IF(G52="No","Wrong domain (non-AECO)",IF(H52="No","Digital Twin not core / buzzword",IF(I52="No","No Design for Safety/Quality/PtD",IF(J52="No","Wrong publication type",IF(K52="No","Non-English","")))))) -> Wrong domain (non-AECO) | S52: =IF(N52<>"Yes","",IF(COUNTBLANK(P52:R52)=3,"",IF(COUNTIF(P52:R52,"No")>0,"EXCLUDE","INCLUDE"))) | T52: =IF(S52<>"EXCLUDE","",IF(P52="No","Digital Twin mentioned only, not the subject",IF(Q52="No","No Design for Safety/Quality in full text",IF(R52="No","Methodology not codable","")))) | Y52: =IF(SUM(V52:X52)=0,"",IF(SUM(V52:X52)>=2,"Multi","Single")) | AG52: Oil/gas pipeline industry; Chinese journal, non-English
A53: 3745 | E53: Monitoring Construction and System Development of Bridge Horizontal Ro… | F53: Scopus | G53: Yes | H53: Yes | I53: Yes | J53: Yes | K53: No | L53: =IF(COUNTBLANK(G53:K53)=5,"",IF(COUNTIF(G53:K53,"No")>0,"EXCLUDE","INCLUDE")) -> EXCLUDE | M53: =IF(L53<>"EXCLUDE","",IF(G53="No","Wrong domain (non-AECO)",IF(H53="No","Digital Twin not core / buzzword",IF(I53="No","No Design for Safety/Quality/PtD",IF(J53="No","Wrong publication type",IF(K53="No","Non-English","")))))) -> Non-English | S53: =IF(N53<>"Yes","",IF(COUNTBLANK(P53:R53)=3,"",IF(COUNTIF(P53:R53,"No")>0,"EXCLUDE","INCLUDE"))) | T53: =IF(S53<>"EXCLUDE","",IF(P53="No","Digital Twin mentioned only, not the subject",IF(Q53="No","No Design for Safety/Quality in full text",IF(R53="No","Methodology not codable","")))) | Y53: =IF(SUM(V53:X53)=0,"",IF(SUM(V53:X53)>=2,"Multi","Single")) | AG53: Chinese journal; non-English full text
A54: 3509 | E54: Multi-Modal Excavator Activity Recognition Using Two-Stream CNN-LSTM w… | F54: Scopus | G54: Yes | H54: No | I54: Yes | J54: Yes | K54: Yes | L54: =IF(COUNTBLANK(G54:K54)=5,"",IF(COUNTIF(G54:K54,"No")>0,"EXCLUDE","INCLUDE")) -> EXCLUDE | M54: =IF(L54<>"EXCLUDE","",IF(G54="No","Wrong domain (non-AECO)",IF(H54="No","Digital Twin not core / buzzword",IF(I54="No","No Design for Safety/Quality/PtD",IF(J54="No","Wrong publication type",IF(K54="No","Non-English","")))))) -> Digital Twin not core / buzzword | S54: =IF(N54<>"Yes","",IF(COUNTBLANK(P54:R54)=3,"",IF(COUNTIF(P54:R54,"No")>0,"EXCLUDE","INCLUDE"))) | T54: =IF(S54<>"EXCLUDE","",IF(P54="No","Digital Twin mentioned only, not the subject",IF(Q54="No","No Design for Safety/Quality in full text",IF(R54="No","Methodology not codable","")))) | Y54: =IF(SUM(V54:X54)=0,"",IF(SUM(V54:X54)>=2,"Multi","Single")) | AG54: CV activity recognition; DT integration future work
A55: 3529 | E55: Guidance for Materials 4.0 to interact with a digital twin | F55: Scopus | G55: No | H55: Yes | I55: No | J55: Yes | K55: Yes | L55: =IF(COUNTBLANK(G55:K55)=5,"",IF(COUNTIF(G55:K55,"No")>0,"EXCLUDE","INCLUDE")) -> EXCLUDE | M55: =IF(L55<>"EXCLUDE","",IF(G55="No","Wrong domain (non-AECO)",IF(H55="No","Digital Twin not core / buzzword",IF(I55="No","No Design for Safety/Quality/PtD",IF(J55="No","Wrong publication type",IF(K55="No","Non-English","")))))) -> Wrong domain (non-AECO) | S55: =IF(N55<>"Yes","",IF(COUNTBLANK(P55:R55)=3,"",IF(COUNTIF(P55:R55,"No")>0,"EXCLUDE","INCLUDE"))) | T55: =IF(S55<>"EXCLUDE","",IF(P55="No","Digital Twin mentioned only, not the subject",IF(Q55="No","No Design for Safety/Quality in full text",IF(R55="No","Methodology not codable","")))) | Y55: =IF(SUM(V55:X55)=0,"",IF(SUM(V55:X55)>=2,"Multi","Single")) | AG55: Materials/manufacturing component DT; not AECO
A56: 3660 | E56: On-Site Safety Inspections Through Marker-Less Augmented Reality and B… | F56: Scopus | G56: Yes | H56: No | I56: Yes | J56: Yes | K56: Yes | L56: =IF(COUNTBLANK(G56:K56)=5,"",IF(COUNTIF(G56:K56,"No")>0,"EXCLUDE","INCLUDE")) -> EXCLUDE | M56: =IF(L56<>"EXCLUDE","",IF(G56="No","Wrong domain (non-AECO)",IF(H56="No","Digital Twin not core / buzzword",IF(I56="No","No Design for Safety/Quality/PtD",IF(J56="No","Wrong publication type",IF(K56="No","Non-English","")))))) -> Digital Twin not core / buzzword | S56: =IF(N56<>"Yes","",IF(COUNTBLANK(P56:R56)=3,"",IF(COUNTIF(P56:R56,"No")>0,"EXCLUDE","INCLUDE"))) | T56: =IF(S56<>"EXCLUDE","",IF(P56="No","Digital Twin mentioned only, not the subject",IF(Q56="No","No Design for Safety/Quality in full text",IF(R56="No","Methodology not codable","")))) | Y56: =IF(SUM(V56:X56)=0,"",IF(SUM(V56:X56)>=2,"Multi","Single")) | AG56: BIM+AR safety inspection; no DT (duplicate of #56)
A57: 3931 | E57: On-Site Safety Inspections Through Marker-Less Augmented Reality and B… | F57: Web of Science | G57: Yes | H57: No | I57: Yes | J57: Yes | K57: Yes | L57: =IF(COUNTBLANK(G57:K57)=5,"",IF(COUNTIF(G57:K57,"No")>0,"EXCLUDE","INCLUDE")) -> EXCLUDE | M57: =IF(L57<>"EXCLUDE","",IF(G57="No","Wrong domain (non-AECO)",IF(H57="No","Digital Twin not core / buzzword",IF(I57="No","No Design for Safety/Quality/PtD",IF(J57="No","Wrong publication type",IF(K57="No","Non-English","")))))) -> Digital Twin not core / buzzword | S57: =IF(N57<>"Yes","",IF(COUNTBLANK(P57:R57)=3,"",IF(COUNTIF(P57:R57,"No")>0,"EXCLUDE","INCLUDE"))) | T57: =IF(S57<>"EXCLUDE","",IF(P57="No","Digital Twin mentioned only, not the subject",IF(Q57="No","No Design for Safety/Quality in full text",IF(R57="No","Methodology not codable","")))) | Y57: =IF(SUM(V57:X57)=0,"",IF(SUM(V57:X57)>=2,"Multi","Single")) | AG57: Duplicate of ID 3660 (WoS copy); BIM-based, no DT
A58: 3679 | E58: Intelligent Transportation Systems Using Roadside Infrastructure: A Li… | F58: Scopus | G58: No | H58: No | I58: No | J58: Yes | K58: Yes | L58: =IF(COUNTBLANK(G58:K58)=5,"",IF(COUNTIF(G58:K58,"No")>0,"EXCLUDE","INCLUDE")) -> EXCLUDE | M58: =IF(L58<>"EXCLUDE","",IF(G58="No","Wrong domain (non-AECO)",IF(H58="No","Digital Twin not core / buzzword",IF(I58="No","No Design for Safety/Quality/PtD",IF(J58="No","Wrong publication type",IF(K58="No","Non-English","")))))) -> Wrong domain (non-AECO) | S58: =IF(N58<>"Yes","",IF(COUNTBLANK(P58:R58)=3,"",IF(COUNTIF(P58:R58,"No")>0,"EXCLUDE","INCLUDE"))) | T58: =IF(S58<>"EXCLUDE","",IF(P58="No","Digital Twin mentioned only, not the subject",IF(Q58="No","No Design for Safety/Quality in full text",IF(R58="No","Methodology not codable","")))) | Y58: =IF(SUM(V58:X58)=0,"",IF(SUM(V58:X58)>=2,"Multi","Single")) | AG58: Traffic ITS survey; DT only future distribution topic
A59: 3651 | E59: The role of the foundation flexibility on the seismic response of a mo… | F59: Scopus | G59: Yes | H59: No | I59: Yes | J59: Yes | K59: Yes | L59: =IF(COUNTBLANK(G59:K59)=5,"",IF(COUNTIF(G59:K59,"No")>0,"EXCLUDE","INCLUDE")) -> EXCLUDE | M59: =IF(L59<>"EXCLUDE","",IF(G59="No","Wrong domain (non-AECO)",IF(H59="No","Digital Twin not core / buzzword",IF(I59="No","No Design for Safety/Quality/PtD",IF(J59="No","Wrong publication type",IF(K59="No","Non-English","")))))) -> Digital Twin not core / buzzword | S59: =IF(N59<>"Yes","",IF(COUNTBLANK(P59:R59)=3,"",IF(COUNTIF(P59:R59,"No")>0,"EXCLUDE","INCLUDE"))) | T59: =IF(S59<>"EXCLUDE","",IF(P59="No","Digital Twin mentioned only, not the subject",IF(Q59="No","No Design for Safety/Quality in full text",IF(R59="No","Methodology not codable","")))) | Y59: =IF(SUM(V59:X59)=0,"",IF(SUM(V59:X59)>=2,"Multi","Single")) | AG59: Pure FE soil-structure interaction study; no DT
A60: 3830 | E60: For how large soil shear wave velocity the soil-structure interaction … | F60: Scopus | G60: Yes | H60: No | I60: Yes | J60: Yes | K60: Yes | L60: =IF(COUNTBLANK(G60:K60)=5,"",IF(COUNTIF(G60:K60,"No")>0,"EXCLUDE","INCLUDE")) -> EXCLUDE | M60: =IF(L60<>"EXCLUDE","",IF(G60="No","Wrong domain (non-AECO)",IF(H60="No","Digital Twin not core / buzzword",IF(I60="No","No Design for Safety/Quality/PtD",IF(J60="No","Wrong publication type",IF(K60="No","Non-English","")))))) -> Digital Twin not core / buzzword | S60: =IF(N60<>"Yes","",IF(COUNTBLANK(P60:R60)=3,"",IF(COUNTIF(P60:R60,"No")>0,"EXCLUDE","INCLUDE"))) | T60: =IF(S60<>"EXCLUDE","",IF(P60="No","Digital Twin mentioned only, not the subject",IF(Q60="No","No Design for Safety/Quality in full text",IF(R60="No","Methodology not codable","")))) | Y60: =IF(SUM(V60:X60)=0,"",IF(SUM(V60:X60)>=2,"Multi","Single")) | AG60: Pure FE seismic SSI analysis; no DT
A61: 3793 | E61: Online traffic load identification of high-speed railway bridge using … | F61: Scopus | G61: Yes | H61: No | I61: Yes | J61: Yes | K61: Yes | L61: =IF(COUNTBLANK(G61:K61)=5,"",IF(COUNTIF(G61:K61,"No")>0,"EXCLUDE","INCLUDE")) -> EXCLUDE | M61: =IF(L61<>"EXCLUDE","",IF(G61="No","Wrong domain (non-AECO)",IF(H61="No","Digital Twin not core / buzzword",IF(I61="No","No Design for Safety/Quality/PtD",IF(J61="No","Wrong publication type",IF(K61="No","Non-English","")))))) -> Digital Twin not core / buzzword | S61: =IF(N61<>"Yes","",IF(COUNTBLANK(P61:R61)=3,"",IF(COUNTIF(P61:R61,"No")>0,"EXCLUDE","INCLUDE"))) | T61: =IF(S61<>"EXCLUDE","",IF(P61="No","Digital Twin mentioned only, not the subject",IF(Q61="No","No Design for Safety/Quality in full text",IF(R61="No","Methodology not codable","")))) | Y61: =IF(SUM(V61:X61)=0,"",IF(SUM(V61:X61)>=2,"Multi","Single")) | AG61: Load-identification method; DT only data consumer
A62: 3802 | B62: Dan (2022) | C62: 2022 | E62: Digital Twin System of Bridges Group Based on Machine Vision Fusion Mo… | F62: Scopus | G62: Yes | H62: Yes | I62: Yes | J62: Yes | K62: Yes | L62: =IF(COUNTBLANK(G62:K62)=5,"",IF(COUNTIF(G62:K62,"No")>0,"EXCLUDE","INCLUDE")) -> INCLUDE | M62: =IF(L62<>"EXCLUDE","",IF(G62="No","Wrong domain (non-AECO)",IF(H62="No","Digital Twin not core / buzzword",IF(I62="No","No Design for Safety/Quality/PtD",IF(J62="No","Wrong publication type",IF(K62="No","Non-English","")))))) | N62: Yes | O62: Yes | P62: Yes | Q62: Yes | R62: Yes | S62: =IF(N62<>"Yes","",IF(COUNTBLANK(P62:R62)=3,"",IF(COUNTIF(P62:R62,"No")>0,"EXCLUDE","INCLUDE"))) -> INCLUDE | T62: =IF(S62<>"EXCLUDE","",IF(P62="No","Digital Twin mentioned only, not the subject",IF(Q62="No","No Design for Safety/Quality in full text",IF(R62="No","Methodology not codable","")))) | U62: Tier 2 - Digital Shadow (one-way physical to virtual) | V62: 0 | W62: 0 | X62: 1 | Y62: =IF(SUM(V62:X62)=0,"",IF(SUM(V62:X62)>=2,"Multi","Single")) -> Single | Z62: Design for Safety (DfS) | AA62: None | AB62: Perception / Computer Vision | AC62: Multi (two or more data types) | AD62: Single case study | AE62: 4 | AF62: Predictive analytics / decision support | AG62: Digital twin system for a regional bridges group (Shanghai, Tongji U): physical space - WIM + multi-source machine vision traffic-load monitoring on target bridge + lightweight sensors on bridge group; digital space - mechanical analysis models per bridge linked by measured traffic loads for working-condition perception and safety warning across the regional network; preliminarily implemented in a Shanghai bridges group. One-way monitoring to analysis to warning for operators; no actuation and no learning loop. [Full-text source: Endnote] | AH62: Fills the group-level gap in bridge digital twins: for a regional bridge network around Shanghai, weigh-in-motion and multi-source machine vision fusion measure full-bridge traffic loads on a target bridge, lightweight sensors capture responses on group bridges, and measured loads drive mechanical models in digital space, enabling working-condition perception and safety warning across the whole network, demonstrated with Monte Carlo and Intelligent Driver Model simulations on the Yongjiang cable-stayed bridge. | AI62: One-way implementation: digital models are loaded with measured traffic loads but no feedback or control channel back to physical bridges exists, and deriving bridge health status from simulation results to form more interaction tasks between the two spaces is left as future exploration. | AJ62: Fused | AK62: Weigh-in-motion and multi-source machine-vision monitoring are fused to measure full-bridge traffic loads, which then drive the mechanical analysis models of a regional bridge group. | AL62: High
A63: 4007 | E63: Assessing the Suitability of Damage Indexes for Digital Twin Applicati… | F63: Web of Science | G63: Yes | H63: No | I63: Yes | J63: Yes | K63: Yes | L63: =IF(COUNTBLANK(G63:K63)=5,"",IF(COUNTIF(G63:K63,"No")>0,"EXCLUDE","INCLUDE")) -> EXCLUDE | M63: =IF(L63<>"EXCLUDE","",IF(G63="No","Wrong domain (non-AECO)",IF(H63="No","Digital Twin not core / buzzword",IF(I63="No","No Design for Safety/Quality/PtD",IF(J63="No","Wrong publication type",IF(K63="No","Non-English","")))))) -> Digital Twin not core / buzzword | S63: =IF(N63<>"Yes","",IF(COUNTBLANK(P63:R63)=3,"",IF(COUNTIF(P63:R63,"No")>0,"EXCLUDE","INCLUDE"))) | T63: =IF(S63<>"EXCLUDE","",IF(P63="No","Digital Twin mentioned only, not the subject",IF(Q63="No","No Design for Safety/Quality in full text",IF(R63="No","Methodology not codable","")))) | Y63: =IF(SUM(V63:X63)=0,"",IF(SUM(V63:X63)>=2,"Multi","Single")) | AG63: Damage-index benchmarking; DT only future use
A64: 3708 | E64: The role of the marine research infrastructures in the European marine… | F64: Scopus | G64: No | H64: No | I64: No | J64: Yes | K64: Yes | L64: =IF(COUNTBLANK(G64:K64)=5,"",IF(COUNTIF(G64:K64,"No")>0,"EXCLUDE","INCLUDE")) -> EXCLUDE | M64: =IF(L64<>"EXCLUDE","",IF(G64="No","Wrong domain (non-AECO)",IF(H64="No","Digital Twin not core / buzzword",IF(I64="No","No Design for Safety/Quality/PtD",IF(J64="No","Wrong publication type",IF(K64="No","Non-English","")))))) -> Wrong domain (non-AECO) | S64: =IF(N64<>"Yes","",IF(COUNTBLANK(P64:R64)=3,"",IF(COUNTIF(P64:R64,"No")>0,"EXCLUDE","INCLUDE"))) | T64: =IF(S64<>"EXCLUDE","",IF(P64="No","Digital Twin mentioned only, not the subject",IF(Q64="No","No Design for Safety/Quality in full text",IF(R64="No","Methodology not codable","")))) | Y64: =IF(SUM(V64:X64)=0,"",IF(SUM(V64:X64)>=2,"Multi","Single")) | AG64: Marine science RIs; not AECO
A65: 3631 | E65: Enhancing Operational Resilience of Critical Infrastructure Processes … | F65: Scopus | G65: No | H65: Yes | I65: No | J65: Yes | K65: Yes | L65: =IF(COUNTBLANK(G65:K65)=5,"",IF(COUNTIF(G65:K65,"No")>0,"EXCLUDE","INCLUDE")) -> EXCLUDE | M65: =IF(L65<>"EXCLUDE","",IF(G65="No","Wrong domain (non-AECO)",IF(H65="No","Digital Twin not core / buzzword",IF(I65="No","No Design for Safety/Quality/PtD",IF(J65="No","Wrong publication type",IF(K65="No","Non-English","")))))) -> Wrong domain (non-AECO) | S65: =IF(N65<>"Yes","",IF(COUNTBLANK(P65:R65)=3,"",IF(COUNTIF(P65:R65,"No")>0,"EXCLUDE","INCLUDE"))) | T65: =IF(S65<>"EXCLUDE","",IF(P65="No","Digital Twin mentioned only, not the subject",IF(Q65="No","No Design for Safety/Quality in full text",IF(R65="No","Methodology not codable","")))) | Y65: =IF(SUM(V65:X65)=0,"",IF(SUM(V65:X65)>=2,"Multi","Single")) | AG65: Oil-refinery process CPS; industrial
A66: 3626 | B66: Delhibabu (2026) | C66: 2026 | E66: Interconnected digital twins of subway stations for decision support s… | F66: Scopus | G66: Yes | H66: Yes | I66: Yes | J66: Yes | K66: Yes | L66: =IF(COUNTBLANK(G66:K66)=5,"",IF(COUNTIF(G66:K66,"No")>0,"EXCLUDE","INCLUDE")) -> INCLUDE | M66: =IF(L66<>"EXCLUDE","",IF(G66="No","Wrong domain (non-AECO)",IF(H66="No","Digital Twin not core / buzzword",IF(I66="No","No Design for Safety/Quality/PtD",IF(J66="No","Wrong publication type",IF(K66="No","Non-English","")))))) | N66: Yes | O66: Yes | P66: Yes | Q66: Yes | R66: Yes | S66: =IF(N66<>"Yes","",IF(COUNTBLANK(P66:R66)=3,"",IF(COUNTIF(P66:R66,"No")>0,"EXCLUDE","INCLUDE"))) -> INCLUDE | T66: =IF(S66<>"EXCLUDE","",IF(P66="No","Digital Twin mentioned only, not the subject",IF(Q66="No","No Design for Safety/Quality in full text",IF(R66="No","Methodology not codable","")))) | U66: Tier 2 - Digital Shadow (one-way physical to virtual) | V66: 0 | W66: 0 | X66: 1 | Y66: =IF(SUM(V66:X66)=0,"",IF(SUM(V66:X66)>=2,"Multi","Single")) -> Single | Z66: Design for Safety (DfS) | AA66: None | AB66: Perception / Computer Vision | AC66: Multi (two or more data types) | AD66: Single case study | AE66: 4 | AF66: Predictive analytics / decision support | AG66: Interconnected digital twins of subway stations for decision support (VIT/FRC RAS): per-station DTs interconnected to interact during operational scenarios; cameras, microphones, sensors processed in fog computing; mobile app with intelligent assistant displays detected events and answers queries via voice; event detection for hazardous situations (fire/explosion); implementation improved personnel response time by 17.4% vs REPEAT platform. One-way monitoring to event detection to decision support for operators; no actuation and no learning loop. [Full-text source: Endnote] | AH66: Fills the incident-response gap of subway station digital twins: interconnected per-station twins process camera, microphone and sensor data in a fog computing environment, a fine-tuned YOLOv8 detector (mAP 0.5 of 92.4 percent) spots events shown on a mobile app with a voice assistant, and personnel response times improved by 17.4 percent versus the REPEAT platform across 50 simulated trials. | AI66: Results come from simulated emergency scenarios, and continuous TCP/IP connectivity is assumed, so deep subterranean network degradation could break the fog-to-mobile pipeline; speech recognition reaches only a 14.2 percent word error rate under 85 dB noise, and the app runs only on Android and Linux; future plans include signaling and control integration to automatically stop trains and escalators. | AJ66: Co-present | AK66: Camera feeds drive YOLOv8 event detection while microphone and sensor streams support a separate voice-assistant pipeline in the same fog-computing platform, with no common representation stated. | AL66: Medium
A67: 3967 | B67: Deng (2025) | C67: 2025 | E67: Structural Analysis of Construction Risk Management Assessment Model B… | F67: Web of Science | G67: Yes | H67: Yes | I67: Yes | J67: Yes | K67: Yes | L67: =IF(COUNTBLANK(G67:K67)=5,"",IF(COUNTIF(G67:K67,"No")>0,"EXCLUDE","INCLUDE")) -> INCLUDE | M67: =IF(L67<>"EXCLUDE","",IF(G67="No","Wrong domain (non-AECO)",IF(H67="No","Digital Twin not core / buzzword",IF(I67="No","No Design for Safety/Quality/PtD",IF(J67="No","Wrong publication type",IF(K67="No","Non-English","")))))) | N67: Yes | O67: Yes | P67: Yes | Q67: Yes | R67: Yes | S67: =IF(N67<>"Yes","",IF(COUNTBLANK(P67:R67)=3,"",IF(COUNTIF(P67:R67,"No")>0,"EXCLUDE","INCLUDE"))) -> INCLUDE | T67: =IF(S67<>"EXCLUDE","",IF(P67="No","Digital Twin mentioned only, not the subject",IF(Q67="No","No Design for Safety/Quality in full text",IF(R67="No","Methodology not codable","")))) | U67: Tier 2 - Digital Shadow (one-way physical to virtual) | V67: 0 | W67: 1 | X67: 0 | Y67: =IF(SUM(V67:X67)=0,"",IF(SUM(V67:X67)>=2,"Multi","Single")) -> Single | Z67: Both | AA67: None | AB67: Other / Mixed | AC67: Multi (two or more data types) | AD67: Single case study | AE67: 3 | AF67: Predictive analytics / decision support | AG67: DTCRAM: five-layer DT construction-risk assessment model (physical twin / data twin / twin model / data analysis / decision feedback) built via 3-round Delphi (9 experts, 15 risks incl. worker safety A1, equipment safety A2, construction quality A3) + case study (Thames Tidal Tunnel); real-time sensor data feeds simulation/risk prediction; claimed ~1% risk-probability reduction per project (A2 5%->3%, C1 3%->2%) but figures are estimates; feedback/optimisation loop described conceptually, not a demonstrated learning mechanism. [Full-text source: Endnote] | AH67: Responds to the lack of practical construction risk models: DTCRAM combines a three-round Delphi study with nine industry experts, identifying 15 construction risks and 15 countermeasures classified into 12 strategy types, with a five-layer digital twin structure (physical twin, data twin, twin model, data analysis, decision feedback) for dynamic monitoring and risk prediction, verified on the Thames Tidal Tunnel case with over 1 percent probability reduction per project. | AI67: Expert-driven and weakly operationalized: only nine Delphi experts limit objectivity, results are tied to one specific project, and the model remains at a development stage with unquantified technical and methodological challenges; future research targets higher applicability and accuracy, larger samples across project types, and artificial intelligence and big data integration. | AJ67: Unclear | AK67: The five-layer DTCRAM risk model is built from a Delphi study and a case study in which sensor-fed simulation and feedback loops are described only conceptually, so no implemented integration mechanism can be identified. | AL67: High
A68: 4036 | B68: Deng (2025) | C68: 2025 | E68: Real-time bridge disaster management: Enabling technology and applicat… | F68: Web of Science | G68: Yes | H68: Yes | I68: Yes | J68: Yes | K68: Yes | L68: =IF(COUNTBLANK(G68:K68)=5,"",IF(COUNTIF(G68:K68,"No")>0,"EXCLUDE","INCLUDE")) -> INCLUDE | M68: =IF(L68<>"EXCLUDE","",IF(G68="No","Wrong domain (non-AECO)",IF(H68="No","Digital Twin not core / buzzword",IF(I68="No","No Design for Safety/Quality/PtD",IF(J68="No","Wrong publication type",IF(K68="No","Non-English","")))))) | N68: Yes | O68: Yes | P68: Yes | Q68: Yes | R68: Yes | S68: =IF(N68<>"Yes","",IF(COUNTBLANK(P68:R68)=3,"",IF(COUNTIF(P68:R68,"No")>0,"EXCLUDE","INCLUDE"))) -> INCLUDE | T68: =IF(S68<>"EXCLUDE","",IF(P68="No","Digital Twin mentioned only, not the subject",IF(Q68="No","No Design for Safety/Quality in full text",IF(R68="No","Methodology not codable","")))) | U68: Tier 1 - Digital Model (static, no live data) | V68: 0 | W68: 0 | X68: 1 | Y68: =IF(SUM(V68:X68)=0,"",IF(SUM(V68:X68)>=2,"Multi","Single")) -> Single | Z68: Design for Safety (DfS) | AA68: None | AB68: Digital Twin platform (no machine learning) | AC68: Multi (two or more data types) | AD68: Conceptual (no test) | AE68: 3 | AF68: BIM-to-Digital-Twin architecture | AG68: Systematic review (146 articles) of bridge disaster management + proposed Real-time Bridge Disaster Management (RtBDM) framework: dynamic adaptation + digitalisation (BIM/DT integration for full-lifecycle data management and automated decision-making) + disaster cycle (pre-warning, real-time response, post-disaster recovery); addresses interoperability, delayed response, and coordination gaps. Framework only - no DT built or validated; no live data link and no learning loop. [Full-text source: Endnote] | AH68: Synthesizes 146 bridge disaster management articles to expose fragmented technology integration, delayed response and poor coordination, then proposes the RtBDM framework combining dynamic adaptation, digitalisation and a disaster-cycle component that integrates BIM and digital twin technologies with sensors, big data analytics, IoT and artificial intelligence for real-time monitoring, early warning, response and recovery across pre-disaster to post-disaster phases. | AI68: Purely conceptual: the framework is built only on literature analysis and existing tools, has not been validated in any real-world scenario, and needs ongoing updates to track technology; future research should run pilot implementations and case studies across regions, disaster types and bridge systems, and improve technology integration and data management. | AJ68: Unclear | AK68: A review-based RtBDM framework proposes BIM/DT integration with sensors and AI for real-time bridge disaster management, but no system is built or validated, so no integration mechanism is demonstrated. | AL68: High
A69: 3760 | B69: Deng (2026) | C69: 2026 | E69: Integrating LLMs and Digital Twins for Adaptive Multi-Robot Task Alloc… | F69: Scopus | G69: Yes | H69: Yes | I69: Yes | J69: Yes | K69: Yes | L69: =IF(COUNTBLANK(G69:K69)=5,"",IF(COUNTIF(G69:K69,"No")>0,"EXCLUDE","INCLUDE")) -> INCLUDE | M69: =IF(L69<>"EXCLUDE","",IF(G69="No","Wrong domain (non-AECO)",IF(H69="No","Digital Twin not core / buzzword",IF(I69="No","No Design for Safety/Quality/PtD",IF(J69="No","Wrong publication type",IF(K69="No","Non-English","")))))) | N69: Yes | O69: Yes | P69: Yes | Q69: Yes | R69: Yes | S69: =IF(N69<>"Yes","",IF(COUNTBLANK(P69:R69)=3,"",IF(COUNTIF(P69:R69,"No")>0,"EXCLUDE","INCLUDE"))) -> INCLUDE | T69: =IF(S69<>"EXCLUDE","",IF(P69="No","Digital Twin mentioned only, not the subject",IF(Q69="No","No Design for Safety/Quality in full text",IF(R69="No","Methodology not codable","")))) | U69: Tier 3 - Digital Twin (bidirectional, two-way) | V69: 0 | W69: 1 | X69: 0 | Y69: =IF(SUM(V69:X69)=0,"",IF(SUM(V69:X69)>=2,"Multi","Single")) -> Single | Z69: Design for Safety (DfS) | AA69: None | AB69: Transformer / Large Language Model (LLM) | AC69: Multi (two or more data types) | AD69: Single case study | AE69: 4 | AF69: Predictive analytics / decision support | AG69: Adaptive multi-robot task allocation framework (UTK/Amazon/TAMU): DT system enables real-time synchronization between physical operations and digital representations as user interface, creating closed-loop feedback; Integer Programming models task allocation (dependencies, heterogeneity, scheduling, replanning); LLM interprets natural-language inputs to autonomously update optimization constraints (97% accuracy in constraint/parameter extraction) without manual programming; case study demonstrates computational efficiency and LLM reasoning. Closed-loop feedback + LLM-based constraint adaptation -> Tier 3; no learning loop (LLM is inference-time, not self-improving). [Full-text source: Endnote] | AH69: Addresses static, code-bound multi-robot scheduling: a closed-loop digital twin in Unity, synchronized with ROS and Gazebo, supports integer-programming task allocation whose constraints are updated by an LLM interpreting plain-language site narratives, achieving over 97 percent constraint and parameter extraction accuracy with GPT-4.1, optimal plans within about one second and 0.08-second replanning across 1024 scenarios of 27 tasks and 15 robots. | AI69: Validated only in simulation: Gazebo idealizes robot-human collaboration and material handling, human worker actions are not modeled, and the LLM is limited to constraint extraction; extending to further construction scenarios, proactive conflict detection and pre-optimization reasoning are future work, with physical robot deployment still pending. | AJ69: Fused | AK69: An LLM interprets natural-language site narratives into integer-programming constraints that jointly determine task allocation together with the Unity DT state synchronised with ROS/Gazebo. | AL69: High
A70: 3521 | E70: Application Benefit Analysis of Digital Twin Technology in Tunnel Cons… | F70: Scopus | G70: Yes | H70: Yes | I70: Yes | J70: Yes | K70: No | L70: =IF(COUNTBLANK(G70:K70)=5,"",IF(COUNTIF(G70:K70,"No")>0,"EXCLUDE","INCLUDE")) -> EXCLUDE | M70: =IF(L70<>"EXCLUDE","",IF(G70="No","Wrong domain (non-AECO)",IF(H70="No","Digital Twin not core / buzzword",IF(I70="No","No Design for Safety/Quality/PtD",IF(J70="No","Wrong publication type",IF(K70="No","Non-English","")))))) -> Non-English | S70: =IF(N70<>"Yes","",IF(COUNTBLANK(P70:R70)=3,"",IF(COUNTIF(P70:R70,"No")>0,"EXCLUDE","INCLUDE"))) | T70: =IF(S70<>"EXCLUDE","",IF(P70="No","Digital Twin mentioned only, not the subject",IF(Q70="No","No Design for Safety/Quality in full text",IF(R70="No","Methodology not codable","")))) | Y70: =IF(SUM(V70:X70)=0,"",IF(SUM(V70:X70)>=2,"Multi","Single")) | AG70: Chinese journal (Tunnel Construction); non-English
A71: 4002 | E71: Smart building evacuation by tracking multi-camera network and explain… | F71: Web of Science | G71: Yes | H71: No | I71: Yes | J71: Yes | K71: Yes | L71: =IF(COUNTBLANK(G71:K71)=5,"",IF(COUNTIF(G71:K71,"No")>0,"EXCLUDE","INCLUDE")) -> EXCLUDE | M71: =IF(L71<>"EXCLUDE","",IF(G71="No","Wrong domain (non-AECO)",IF(H71="No","Digital Twin not core / buzzword",IF(I71="No","No Design for Safety/Quality/PtD",IF(J71="No","Wrong publication type",IF(K71="No","Non-English","")))))) -> Digital Twin not core / buzzword | S71: =IF(N71<>"Yes","",IF(COUNTBLANK(P71:R71)=3,"",IF(COUNTIF(P71:R71,"No")>0,"EXCLUDE","INCLUDE"))) | T71: =IF(S71<>"EXCLUDE","",IF(P71="No","Digital Twin mentioned only, not the subject",IF(Q71="No","No Design for Safety/Quality in full text",IF(R71="No","Methodology not codable","")))) | Y71: =IF(SUM(V71:X71)=0,"",IF(SUM(V71:X71)>=2,"Multi","Single")) | AG71: CV tracking framework; DT as end-goal only
A72: 3528 | E72: Digital twin system construction method for evaluating load carrying c… | F72: Scopus | G72: Yes | H72: Yes | I72: Yes | J72: Yes | K72: No | L72: =IF(COUNTBLANK(G72:K72)=5,"",IF(COUNTIF(G72:K72,"No")>0,"EXCLUDE","INCLUDE")) -> EXCLUDE | M72: =IF(L72<>"EXCLUDE","",IF(G72="No","Wrong domain (non-AECO)",IF(H72="No","Digital Twin not core / buzzword",IF(I72="No","No Design for Safety/Quality/PtD",IF(J72="No","Wrong publication type",IF(K72="No","Non-English","")))))) -> Non-English | S72: =IF(N72<>"Yes","",IF(COUNTBLANK(P72:R72)=3,"",IF(COUNTIF(P72:R72,"No")>0,"EXCLUDE","INCLUDE"))) | T72: =IF(S72<>"EXCLUDE","",IF(P72="No","Digital Twin mentioned only, not the subject",IF(Q72="No","No Design for Safety/Quality in full text",IF(R72="No","Methodology not codable","")))) | Y72: =IF(SUM(V72:X72)=0,"",IF(SUM(V72:X72)>=2,"Multi","Single")) | AG72: Chinese journal (CIMS); non-English full text
A73: 3736 | B73: Doukari (2026) | C73: 2026 | E73: Stakeholder-informed renovation digital twin for multi-domain monitori… | F73: Scopus | G73: Yes | H73: Yes | I73: Yes | J73: Yes | K73: Yes | L73: =IF(COUNTBLANK(G73:K73)=5,"",IF(COUNTIF(G73:K73,"No")>0,"EXCLUDE","INCLUDE")) -> INCLUDE | M73: =IF(L73<>"EXCLUDE","",IF(G73="No","Wrong domain (non-AECO)",IF(H73="No","Digital Twin not core / buzzword",IF(I73="No","No Design for Safety/Quality/PtD",IF(J73="No","Wrong publication type",IF(K73="No","Non-English","")))))) | N73: Yes | O73: Yes | P73: Yes | Q73: Yes | R73: Yes | S73: =IF(N73<>"Yes","",IF(COUNTBLANK(P73:R73)=3,"",IF(COUNTIF(P73:R73,"No")>0,"EXCLUDE","INCLUDE"))) -> INCLUDE | T73: =IF(S73<>"EXCLUDE","",IF(P73="No","Digital Twin mentioned only, not the subject",IF(Q73="No","No Design for Safety/Quality in full text",IF(R73="No","Methodology not codable","")))) | U73: Tier 2 - Digital Shadow (one-way physical to virtual) | V73: 0 | W73: 1 | X73: 0 | Y73: =IF(SUM(V73:X73)=0,"",IF(SUM(V73:X73)>=2,"Multi","Single")) -> Single | Z73: Both | AA73: None | AB73: Digital Twin platform (no machine learning) | AC73: Multi (two or more data types) | AD73: Single case study | AE73: 4 | AF73: Lifecycle / governance | AG73: Renovation Digital Twin (RDT) platform (Northumbria U, RINNO Project): pilot implementation on French demonstration site; real-time data + dashboards monitoring 13 KPIs across 5 domains (cost, schedule, quality, safety, environment); TAM evaluation (102 professionals, Attitude Toward Use RII 0.894); 73% emissions reduction achieved but economic viability challenges. One-way monitoring→dashboard→decision support; no actuation and no learning loop. [Full-text source: Endnote] | AH73: Fills the renovation-phase gap in digital twins: a stakeholder-informed Renovation Digital Twin built with Design Science Research in the RINNO project monitors 13 KPIs across cost, schedule, quality, safety and environment on the Project Sarrazins demo site in Lille, and a Technology Acceptance Model survey of 102 professionals gave attitude toward use RII 0.894 while the site achieved a 73 percent emissions reduction. | AI73: Proof-of-concept scope: a single renovation project, functional verification only, no quantified cost, schedule or safety improvements, a short evaluation period, a TAM sample biased to early-career professionals, manual data entry, and no AI or predictive analytics beyond historical KPI visualization; future work calls for multi-site validation, longitudinal studies, IoT automation, deep-learning prediction and cognitive twin capabilities. | AJ73: Co-present | AK73: Real-time data and dashboards monitor 13 KPIs across five domains (cost, schedule, quality, safety, environment) in one renovation DT platform, without a stated shared reference frame joining the domains. | AL73: Medium
A74: 3625 | E74: Digital twin-driven on-line monitoring method of metal selective laser… | F74: Scopus | G74: No | H74: Yes | I74: Yes | J74: Yes | K74: No | L74: =IF(COUNTBLANK(G74:K74)=5,"",IF(COUNTIF(G74:K74,"No")>0,"EXCLUDE","INCLUDE")) -> EXCLUDE | M74: =IF(L74<>"EXCLUDE","",IF(G74="No","Wrong domain (non-AECO)",IF(H74="No","Digital Twin not core / buzzword",IF(I74="No","No Design for Safety/Quality/PtD",IF(J74="No","Wrong publication type",IF(K74="No","Non-English","")))))) -> Wrong domain (non-AECO) | S74: =IF(N74<>"Yes","",IF(COUNTBLANK(P74:R74)=3,"",IF(COUNTIF(P74:R74,"No")>0,"EXCLUDE","INCLUDE"))) | T74: =IF(S74<>"EXCLUDE","",IF(P74="No","Digital Twin mentioned only, not the subject",IF(Q74="No","No Design for Safety/Quality in full text",IF(R74="No","Methodology not codable","")))) | Y74: =IF(SUM(V74:X74)=0,"",IF(SUM(V74:X74)>=2,"Multi","Single")) | AG74: Additive manufacturing; Chinese journal, non-English
A75: 3906 | B75: ElDin (2022) | C75: 2022 | E75: Digital Twins for Construction Assets Using BIM Standard Specification… | F75: Web of Science | G75: Yes | H75: Yes | I75: Yes | J75: Yes | K75: Yes | L75: =IF(COUNTBLANK(G75:K75)=5,"",IF(COUNTIF(G75:K75,"No")>0,"EXCLUDE","INCLUDE")) -> INCLUDE | M75: =IF(L75<>"EXCLUDE","",IF(G75="No","Wrong domain (non-AECO)",IF(H75="No","Digital Twin not core / buzzword",IF(I75="No","No Design for Safety/Quality/PtD",IF(J75="No","Wrong publication type",IF(K75="No","Non-English","")))))) | N75: Yes | O75: Yes | P75: Yes | Q75: Yes | R75: Yes | S75: =IF(N75<>"Yes","",IF(COUNTBLANK(P75:R75)=3,"",IF(COUNTIF(P75:R75,"No")>0,"EXCLUDE","INCLUDE"))) -> INCLUDE | T75: =IF(S75<>"EXCLUDE","",IF(P75="No","Digital Twin mentioned only, not the subject",IF(Q75="No","No Design for Safety/Quality in full text",IF(R75="No","Methodology not codable","")))) | U75: Unclear | V75: 1 | W75: 1 | X75: 1 | Y75: =IF(SUM(V75:X75)=0,"",IF(SUM(V75:X75)>=2,"Multi","Single")) -> Multi | Z75: Both | AA75: None | AB75: Digital Twin platform (no machine learning) | AC75: Multi (two or more data types) | AD75: Conceptual (no test) | AE75: 3 | AF75: BIM-to-Digital-Twin architecture | AG75: SLR (229 pubs) + conceptual DT development framework grounded in ISO 19650; no implementation or experiment; DfS/DfQ appear as application potentials, not demonstrated. [Full-text source: Endnote] | AH75: Diagnoses the standardization gap in AEC digital twins through a systematic review of 229 publications (2016 to 2021) from four databases, showing DTs remain application-driven and vendor-dependent, then proposes a conceptual DT development framework built on the ISO 19650 series: PIM and AIM information containers federated in a CDE, IoT and WSN monitoring, and machine learning for decisions and actuator actions. | AI75: Conceptual only, with no implementation or validation; the framework is a recommendation that still awaits application, and the authors state it must be proven through multiple case studies with diverse asset uses and complexities, recommending energy efficiency and indoor environmental quality as neglected test fields. | AJ75: Unclear | AK75: An SLR-based ISO 19650 DT development framework (PIM/AIM containers, CDE, IoT/WSN, ML) is proposed without any implementation, so no integration mechanism can be coded. | AL75: High
A76: 3921 | E76: Predictive digital monitoring of construction resources: an integrated… | F76: Web of Science | G76: Yes | H76: Yes | I76: No | J76: Yes | K76: Yes | L76: =IF(COUNTBLANK(G76:K76)=5,"",IF(COUNTIF(G76:K76,"No")>0,"EXCLUDE","INCLUDE")) -> EXCLUDE | M76: =IF(L76<>"EXCLUDE","",IF(G76="No","Wrong domain (non-AECO)",IF(H76="No","Digital Twin not core / buzzword",IF(I76="No","No Design for Safety/Quality/PtD",IF(J76="No","Wrong publication type",IF(K76="No","Non-English","")))))) -> No Design for Safety/Quality/PtD | S76: =IF(N76<>"Yes","",IF(COUNTBLANK(P76:R76)=3,"",IF(COUNTIF(P76:R76,"No")>0,"EXCLUDE","INCLUDE"))) | T76: =IF(S76<>"EXCLUDE","",IF(P76="No","Digital Twin mentioned only, not the subject",IF(Q76="No","No Design for Safety/Quality in full text",IF(R76="No","Methodology not codable","")))) | Y76: =IF(SUM(V76:X76)=0,"",IF(SUM(V76:X76)>=2,"Multi","Single")) | AG76: DTSRM for cost/time/resources; safety only as extension
A77: 4046 | B77: Ellul (2024) | C77: 2024 | E77: Exploring Data for Construction Digital Twins: Building Health and Saf… | F77: Web of Science | G77: Yes | H77: Yes | I77: Yes | J77: Yes | K77: Yes | L77: =IF(COUNTBLANK(G77:K77)=5,"",IF(COUNTIF(G77:K77,"No")>0,"EXCLUDE","INCLUDE")) -> INCLUDE | M77: =IF(L77<>"EXCLUDE","",IF(G77="No","Wrong domain (non-AECO)",IF(H77="No","Digital Twin not core / buzzword",IF(I77="No","No Design for Safety/Quality/PtD",IF(J77="No","Wrong publication type",IF(K77="No","Non-English","")))))) | N77: Yes | O77: Yes | P77: Yes | Q77: Yes | R77: Yes | S77: =IF(N77<>"Yes","",IF(COUNTBLANK(P77:R77)=3,"",IF(COUNTIF(P77:R77,"No")>0,"EXCLUDE","INCLUDE"))) -> INCLUDE | T77: =IF(S77<>"EXCLUDE","",IF(P77="No","Digital Twin mentioned only, not the subject",IF(Q77="No","No Design for Safety/Quality in full text",IF(R77="No","Methodology not codable","")))) | U77: Tier 3 - Digital Twin (bidirectional, two-way) | V77: 0 | W77: 1 | X77: 0 | Y77: =IF(SUM(V77:X77)=0,"",IF(SUM(V77:X77)>=2,"Multi","Single")) -> Single | Z77: Design for Safety (DfS) | AA77: None | AB77: Digital Twin platform (no machine learning) | AC77: Multi (two or more data types) | AD77: Cross-project (multiple real projects) | AE77: 3 | AF77: BIM-to-Digital-Twin architecture | AG77: Construction digital twin demonstrators (health & safety + progress monitoring) using Unreal Gaming Engine + CesiumJS mapping on a highway project (Skanska/UCL): location data integrates diverse sources; no-code approach for DT development; two case studies demonstrate 4D data presentation; explicitly described as human-in-the-loop DT (two-way communication with manual decision making) — virtual model changes reflect real-world changes, and humans act back on the physical site via decisions. Predictive capabilities discussed but not implemented; no learning loop. [Full-text source: Endnote] | AH77: Demonstrates location-enabled construction digital twins on a live Skanska highway project, building health and safety and progress monitoring twins in Unreal Engine 5 with CesiumJS georeferencing. The health and safety twin delivers site walk-throughs, clickable asset inspection records, color-coded hazard and risk boxes, and 1-metre danger-zone alerts around machinery built with no-code Blueprints. | AI77: The prototypes are proof of concept: only a small subset of live sensor data was explored, no analytics or prediction were incorporated, asset placement was manual with positional errors up to 1 metre, and no formal usability tests were run. Future work includes automated progress quantification, live worker tracking with wearables, analytics, data security and Datasmith scalability trials. | AJ77: Aligned | AK77: Location-enabled twins georeference diverse data sources through CesiumJS and place them in Unreal Engine scenes, linking hazard boxes and asset inspection records to site coordinates. | AL77: High
A78: 3912 | E78: Seismic Failure Mechanism Shift in RC Buildings Revealed by NDT-Suppor… | F78: Web of Science | G78: Yes | H78: No | I78: Yes | J78: Yes | K78: Yes | L78: =IF(COUNTBLANK(G78:K78)=5,"",IF(COUNTIF(G78:K78,"No")>0,"EXCLUDE","INCLUDE")) -> EXCLUDE | M78: =IF(L78<>"EXCLUDE","",IF(G78="No","Wrong domain (non-AECO)",IF(H78="No","Digital Twin not core / buzzword",IF(I78="No","No Design for Safety/Quality/PtD",IF(J78="No","Wrong publication type",IF(K78="No","Non-English","")))))) -> Digital Twin not core / buzzword | S78: =IF(N78<>"Yes","",IF(COUNTBLANK(P78:R78)=3,"",IF(COUNTIF(P78:R78,"No")>0,"EXCLUDE","INCLUDE"))) | T78: =IF(S78<>"EXCLUDE","",IF(P78="No","Digital Twin mentioned only, not the subject",IF(Q78="No","No Design for Safety/Quality in full text",IF(R78="No","Methodology not codable","")))) | Y78: =IF(SUM(V78:X78)=0,"",IF(SUM(V78:X78)>=2,"Multi","Single")) | AG78: Level-2 static twin = calibrated BIM; no live data link
A79: 4029 | B79: Fang (2023) | C79: 2023 | E79: Intervention and management of construction workers' unsafe behavior: … | F79: Web of Science | G79: Yes | H79: Yes | I79: Yes | J79: Yes | K79: Yes | L79: =IF(COUNTBLANK(G79:K79)=5,"",IF(COUNTIF(G79:K79,"No")>0,"EXCLUDE","INCLUDE")) -> INCLUDE | M79: =IF(L79<>"EXCLUDE","",IF(G79="No","Wrong domain (non-AECO)",IF(H79="No","Digital Twin not core / buzzword",IF(I79="No","No Design for Safety/Quality/PtD",IF(J79="No","Wrong publication type",IF(K79="No","Non-English","")))))) | N79: Yes | O79: Yes | P79: Yes | Q79: Yes | R79: Yes | S79: =IF(N79<>"Yes","",IF(COUNTBLANK(P79:R79)=3,"",IF(COUNTIF(P79:R79,"No")>0,"EXCLUDE","INCLUDE"))) -> INCLUDE | T79: =IF(S79<>"EXCLUDE","",IF(P79="No","Digital Twin mentioned only, not the subject",IF(Q79="No","No Design for Safety/Quality in full text",IF(R79="No","Methodology not codable","")))) | U79: Tier 1 - Digital Model (static, no live data) | V79: 0 | W79: 1 | X79: 0 | Y79: =IF(SUM(V79:X79)=0,"",IF(SUM(V79:X79)>=2,"Multi","Single")) -> Single | Z79: Design for Safety (DfS) | AA79: None | AB79: Agent-based model (ABM) | AC79: Single (one data type) | AD79: Simulation | AE79: 4 | AF79: Predictive analytics / decision support | AG79: Hybrid simulation digital twin model for construction worker unsafe-behavior intervention (Central South U): closed-loop structured model with control panel, proactive management panel, and reactive panel; simulates workers behavioral safety under different intervention strategies using dual-attitude theory and reinforcement theory; proactive management maintains behavioral safety longer than reactive management. Simulation model only - no live data link to a real site, no actuation, no learning loop. [Full-text source: Endnote] | AH79: Fills the behavioral-psychology gap in worker unsafe-behavior research by building a closed-loop hybrid simulation digital twin in AnyLogic that couples agent-based, system dynamics and discrete-event models with dual attitude theory and reinforcement learning. Calibrated with 84 valid questionnaires (Cronbach alpha 0.868), experiments with 84 worker agents show proactive management sustains safety after withdrawal while reactive management decays fast. | AI79: No live site data link; the model is a static simulation whose parameters come from a limited questionnaire sample, and its reliability and predictive capability are acknowledged as weaker than data-driven methods. Authors propose larger samples, EEG and eye-tracking for psychophysiological data, and adding agent-to-agent interactions as future work. | AJ79: Single | AK79: Only questionnaire-calibrated agent parameters (84 valid questionnaires, Cronbach alpha 0.868) feed the AnyLogic hybrid simulation; no second measured data type exists. | AL79: High
A80: 3782 | E80: A scientometric analysis of drone-based structural health monitoring a… | F80: Scopus | G80: Yes | H80: No | I80: Yes | J80: Yes | K80: Yes | L80: =IF(COUNTBLANK(G80:K80)=5,"",IF(COUNTIF(G80:K80,"No")>0,"EXCLUDE","INCLUDE")) -> EXCLUDE | M80: =IF(L80<>"EXCLUDE","",IF(G80="No","Wrong domain (non-AECO)",IF(H80="No","Digital Twin not core / buzzword",IF(I80="No","No Design for Safety/Quality/PtD",IF(J80="No","Wrong publication type",IF(K80="No","Non-English","")))))) -> Digital Twin not core / buzzword | S80: =IF(N80<>"Yes","",IF(COUNTBLANK(P80:R80)=3,"",IF(COUNTIF(P80:R80,"No")>0,"EXCLUDE","INCLUDE"))) | T80: =IF(S80<>"EXCLUDE","",IF(P80="No","Digital Twin mentioned only, not the subject",IF(Q80="No","No Design for Safety/Quality in full text",IF(R80="No","Methodology not codable","")))) | Y80: =IF(SUM(V80:X80)=0,"",IF(SUM(V80:X80)>=2,"Multi","Single")) | AG80: Scientometric review; DT only integration trend
A81: 3955 | E81: Development of a BIM and IoT-Based Smart Lighting Maintenance System P… | F81: Web of Science | G81: Yes | H81: Yes | I81: No | J81: Yes | K81: Yes | L81: =IF(COUNTBLANK(G81:K81)=5,"",IF(COUNTIF(G81:K81,"No")>0,"EXCLUDE","INCLUDE")) -> EXCLUDE | M81: =IF(L81<>"EXCLUDE","",IF(G81="No","Wrong domain (non-AECO)",IF(H81="No","Digital Twin not core / buzzword",IF(I81="No","No Design for Safety/Quality/PtD",IF(J81="No","Wrong publication type",IF(K81="No","Non-English","")))))) -> No Design for Safety/Quality/PtD | S81: =IF(N81<>"Yes","",IF(COUNTBLANK(P81:R81)=3,"",IF(COUNTIF(P81:R81,"No")>0,"EXCLUDE","INCLUDE"))) | T81: =IF(S81<>"EXCLUDE","",IF(P81="No","Digital Twin mentioned only, not the subject",IF(Q81="No","No Design for Safety/Quality in full text",IF(R81="No","Methodology not codable","")))) | Y81: =IF(SUM(V81:X81)=0,"",IF(SUM(V81:X81)>=2,"Multi","Single")) | AG81: FM reactive maintenance; safety incidental
A82: 3632 | E82: Machine learning for design and analysis of steel frame halls | F82: Scopus | G82: Yes | H82: No | I82: No | J82: Yes | K82: Yes | L82: =IF(COUNTBLANK(G82:K82)=5,"",IF(COUNTIF(G82:K82,"No")>0,"EXCLUDE","INCLUDE")) -> EXCLUDE | M82: =IF(L82<>"EXCLUDE","",IF(G82="No","Wrong domain (non-AECO)",IF(H82="No","Digital Twin not core / buzzword",IF(I82="No","No Design for Safety/Quality/PtD",IF(J82="No","Wrong publication type",IF(K82="No","Non-English","")))))) -> Digital Twin not core / buzzword | S82: =IF(N82<>"Yes","",IF(COUNTBLANK(P82:R82)=3,"",IF(COUNTIF(P82:R82,"No")>0,"EXCLUDE","INCLUDE"))) | T82: =IF(S82<>"EXCLUDE","",IF(P82="No","Digital Twin mentioned only, not the subject",IF(Q82="No","No Design for Safety/Quality in full text",IF(R82="No","Methodology not codable","")))) | Y82: =IF(SUM(V82:X82)=0,"",IF(SUM(V82:X82)>=2,"Multi","Single")) | AG82: AI design co-pilot; no DT
A83: 4048 | E83: Maschinelles Lernen beim Entwurf und der Bemessung von Stahlrahmenhall… | F83: Web of Science | G83: Yes | H83: No | I83: No | J83: Yes | K83: No | L83: =IF(COUNTBLANK(G83:K83)=5,"",IF(COUNTIF(G83:K83,"No")>0,"EXCLUDE","INCLUDE")) -> EXCLUDE | M83: =IF(L83<>"EXCLUDE","",IF(G83="No","Wrong domain (non-AECO)",IF(H83="No","Digital Twin not core / buzzword",IF(I83="No","No Design for Safety/Quality/PtD",IF(J83="No","Wrong publication type",IF(K83="No","Non-English","")))))) -> Digital Twin not core / buzzword | S83: =IF(N83<>"Yes","",IF(COUNTBLANK(P83:R83)=3,"",IF(COUNTIF(P83:R83,"No")>0,"EXCLUDE","INCLUDE"))) | T83: =IF(S83<>"EXCLUDE","",IF(P83="No","Digital Twin mentioned only, not the subject",IF(Q83="No","No Design for Safety/Quality in full text",IF(R83="No","Methodology not codable","")))) | Y83: =IF(SUM(V83:X83)=0,"",IF(SUM(V83:X83)>=2,"Multi","Single")) | AG83: German duplicate of ID 3632; non-English
A84: 3824 | E84: Preliminary architecture design for human-in-the-loop control of robot… | F84: Scopus | G84: No | H84: Yes | I84: No | J84: Yes | K84: Yes | L84: =IF(COUNTBLANK(G84:K84)=5,"",IF(COUNTIF(G84:K84,"No")>0,"EXCLUDE","INCLUDE")) -> EXCLUDE | M84: =IF(L84<>"EXCLUDE","",IF(G84="No","Wrong domain (non-AECO)",IF(H84="No","Digital Twin not core / buzzword",IF(I84="No","No Design for Safety/Quality/PtD",IF(J84="No","Wrong publication type",IF(K84="No","Non-English","")))))) -> Wrong domain (non-AECO) | S84: =IF(N84<>"Yes","",IF(COUNTBLANK(P84:R84)=3,"",IF(COUNTIF(P84:R84,"No")>0,"EXCLUDE","INCLUDE"))) | T84: =IF(S84<>"EXCLUDE","",IF(P84="No","Digital Twin mentioned only, not the subject",IF(Q84="No","No Design for Safety/Quality in full text",IF(R84="No","Methodology not codable","")))) | Y84: =IF(SUM(V84:X84)=0,"",IF(SUM(V84:X84)>=2,"Multi","Single")) | AG84: Fusion-reactor maintenance robotics; not AECO
A85: 3493 | B85: Franciosi (2024) | C85: 2024 | E85: Digital twins in bridge engineering for streamlined maintenance and en… | F85: Scopus | G85: Yes | H85: Yes | I85: Yes | J85: Yes | K85: Yes | L85: =IF(COUNTBLANK(G85:K85)=5,"",IF(COUNTIF(G85:K85,"No")>0,"EXCLUDE","INCLUDE")) -> INCLUDE | M85: =IF(L85<>"EXCLUDE","",IF(G85="No","Wrong domain (non-AECO)",IF(H85="No","Digital Twin not core / buzzword",IF(I85="No","No Design for Safety/Quality/PtD",IF(J85="No","Wrong publication type",IF(K85="No","Non-English","")))))) | N85: Yes | O85: Yes | P85: Yes | Q85: Yes | R85: Yes | S85: =IF(N85<>"Yes","",IF(COUNTBLANK(P85:R85)=3,"",IF(COUNTIF(P85:R85,"No")>0,"EXCLUDE","INCLUDE"))) -> INCLUDE | T85: =IF(S85<>"EXCLUDE","",IF(P85="No","Digital Twin mentioned only, not the subject",IF(Q85="No","No Design for Safety/Quality in full text",IF(R85="No","Methodology not codable","")))) | U85: Tier 2 - Digital Shadow (one-way physical to virtual) | V85: 0 | W85: 0 | X85: 1 | Y85: =IF(SUM(V85:X85)=0,"",IF(SUM(V85:X85)>=2,"Multi","Single")) -> Single | Z85: Design for Safety (DfS) | AA85: None | AB85: Finite Element Method / physics-based | AC85: Multi (two or more data types) | AD85: Single case study | AE85: 4 | AF85: Lifecycle / governance | AG85: Adaptable digital twin methodology for existing bridge management (HEIG-VD): integrates BIM + IFC (open interoperable formats) + ontology + FE models; laser-scanned 3D model converted to DT via IFC; enables structural analysis and what-if scenario simulations for maintenance decision-making; differential evolution algorithm for optimized FE model; case study demonstrates feasibility; cradle-to-cradle approach for end-of-life. One-way monitoring/analysis→maintenance decisions; no actuation and no learning loop (updates are manual inspection-based). [Full-text source: Endnote] | AH85: Establishes an adaptable methodology for existing-bridge digital twins addressing software obsolescence and interoperability: laser-scanned geometry (RIEGL VZ-2000i) converted to IFC 4.3 BIM and enriched from the KUBA database, then imported into SCIA Engineer for what-if corrosion scenarios on the 377.60 m Praz bridge and DE-algorithm FE updating against DIC measurements on the Grandson bridge. | AI85: Scan-to-BIM remains semi-automated and the DT provides no automatic defect detection; updates come in batch from inspections rather than a real-time link. Future work covers a method to integrate inspection and monitoring results into DTs, extension to new bridges during design, and linking DTs into networks for whole transport corridors. | AJ85: Aligned | AK85: RIEGL VZ-2000i laser-scanned geometry is converted to IFC 4.3 BIM, and the SCIA Engineer FE model is updated against DIC measurements, linking scan geometry and measurement data through the shared bridge model. | AL85: High
A86: 4032 | E86: Resilient ventilation network construction in complex underground mini… | F86: Web of Science | G86: No | H86: Yes | I86: Yes | J86: Yes | K86: Yes | L86: =IF(COUNTBLANK(G86:K86)=5,"",IF(COUNTIF(G86:K86,"No")>0,"EXCLUDE","INCLUDE")) -> EXCLUDE | M86: =IF(L86<>"EXCLUDE","",IF(G86="No","Wrong domain (non-AECO)",IF(H86="No","Digital Twin not core / buzzword",IF(I86="No","No Design for Safety/Quality/PtD",IF(J86="No","Wrong publication type",IF(K86="No","Non-English","")))))) -> Wrong domain (non-AECO) | S86: =IF(N86<>"Yes","",IF(COUNTBLANK(P86:R86)=3,"",IF(COUNTIF(P86:R86,"No")>0,"EXCLUDE","INCLUDE"))) | T86: =IF(S86<>"EXCLUDE","",IF(P86="No","Digital Twin mentioned only, not the subject",IF(Q86="No","No Design for Safety/Quality in full text",IF(R86="No","Methodology not codable","")))) | Y86: =IF(SUM(V86:X86)=0,"",IF(SUM(V86:X86)>=2,"Multi","Single")) | AG86: Mining ventilation; not AECO built environment
A87: 3775 | B87: Gao (2025) | C87: 2025 | E87: Digital twin-based vibration displacement sensing and recognition tech… | F87: Scopus | G87: Yes | H87: Yes | I87: Yes | J87: Yes | K87: Yes | L87: =IF(COUNTBLANK(G87:K87)=5,"",IF(COUNTIF(G87:K87,"No")>0,"EXCLUDE","INCLUDE")) -> INCLUDE | M87: =IF(L87<>"EXCLUDE","",IF(G87="No","Wrong domain (non-AECO)",IF(H87="No","Digital Twin not core / buzzword",IF(I87="No","No Design for Safety/Quality/PtD",IF(J87="No","Wrong publication type",IF(K87="No","Non-English","")))))) | N87: Yes | O87: Yes | P87: Yes | Q87: Yes | R87: Yes | S87: =IF(N87<>"Yes","",IF(COUNTBLANK(P87:R87)=3,"",IF(COUNTIF(P87:R87,"No")>0,"EXCLUDE","INCLUDE"))) -> INCLUDE | T87: =IF(S87<>"EXCLUDE","",IF(P87="No","Digital Twin mentioned only, not the subject",IF(Q87="No","No Design for Safety/Quality in full text",IF(R87="No","Methodology not codable","")))) | U87: Tier 2 - Digital Shadow (one-way physical to virtual) | V87: 0 | W87: 1 | X87: 0 | Y87: =IF(SUM(V87:X87)=0,"",IF(SUM(V87:X87)>=2,"Multi","Single")) -> Single | Z87: Design for Safety (DfS) | AA87: None | AB87: Other / Mixed | AC87: Single (one data type) | AD87: Simulation | AE87: 3 | AF87: Predictive analytics / decision support | AG87: DT-based construction safety-management model for large engineering structures (48 m-span steel roof): DT generates real-time structural state samples that train a PSO-optimised BP neural network for vibration displacement / stress prediction (vertical displacement PA 98.2%, cable stress PA 99.1%, EV 0.978); validated only on a numerical model under 5 simulated working conditions; monitoring-and-warning only, no actuation, offline-trained predictor, no learning loop. [Full-text source: Endnote] | AH87: Combines a digital twin construction-safety model with a PSO-optimized BP neural network for vibration displacement sensing and recognition of large structures: the twin generates real-time structural state training samples and the model reaches 98.2 percent prediction accuracy overall, 99.1 percent for tension-cable stress, with eigenvalue EV 0.978 and correct critical-component identification on a 48 m span steel roof model. | AI87: Validation is numerical, using a 48 m steel roof structural model with five working conditions rather than a monitored real project; the paper reports no live site data or actuation and no explicit limitations section. Future direction stated is only to deepen digital twin research for construction safety assessment and structural optimization design. | AJ87: Single | AK87: Only twin-generated structural-state samples (numerical 48 m steel roof under five working conditions) train the PSO-BP predictor; no live measured data exists. | AL87: High
A88: 3826 | E88: Cooperative Localization in Transportation 5.0 | F88: Scopus | G88: No | H88: No | I88: No | J88: Yes | K88: Yes | L88: =IF(COUNTBLANK(G88:K88)=5,"",IF(COUNTIF(G88:K88,"No")>0,"EXCLUDE","INCLUDE")) -> EXCLUDE | M88: =IF(L88<>"EXCLUDE","",IF(G88="No","Wrong domain (non-AECO)",IF(H88="No","Digital Twin not core / buzzword",IF(I88="No","No Design for Safety/Quality/PtD",IF(J88="No","Wrong publication type",IF(K88="No","Non-English","")))))) -> Wrong domain (non-AECO) | S88: =IF(N88<>"Yes","",IF(COUNTBLANK(P88:R88)=3,"",IF(COUNTIF(P88:R88,"No")>0,"EXCLUDE","INCLUDE"))) | T88: =IF(S88<>"EXCLUDE","",IF(P88="No","Digital Twin mentioned only, not the subject",IF(Q88="No","No Design for Safety/Quality in full text",IF(R88="No","Methodology not codable","")))) | Y88: =IF(SUM(V88:X88)=0,"",IF(SUM(V88:X88)>=2,"Multi","Single")) | AG88: Vehicle localization framework; not AECO
A89: 3876 | B89: Gao (2024) | C89: 2024 | E89: Bridge Digital Twin for Practical Bridge Operation and Maintenance by … | F89: Web of Science | G89: Yes | H89: Yes | I89: Yes | J89: Yes | K89: Yes | L89: =IF(COUNTBLANK(G89:K89)=5,"",IF(COUNTIF(G89:K89,"No")>0,"EXCLUDE","INCLUDE")) -> INCLUDE | M89: =IF(L89<>"EXCLUDE","",IF(G89="No","Wrong domain (non-AECO)",IF(H89="No","Digital Twin not core / buzzword",IF(I89="No","No Design for Safety/Quality/PtD",IF(J89="No","Wrong publication type",IF(K89="No","Non-English","")))))) | N89: Yes | O89: Yes | P89: Yes | Q89: Yes | R89: Yes | S89: =IF(N89<>"Yes","",IF(COUNTBLANK(P89:R89)=3,"",IF(COUNTIF(P89:R89,"No")>0,"EXCLUDE","INCLUDE"))) -> INCLUDE | T89: =IF(S89<>"EXCLUDE","",IF(P89="No","Digital Twin mentioned only, not the subject",IF(Q89="No","No Design for Safety/Quality in full text",IF(R89="No","Methodology not codable","")))) | U89: Tier 2 - Digital Shadow (one-way physical to virtual) | V89: 0 | W89: 0 | X89: 1 | Y89: =IF(SUM(V89:X89)=0,"",IF(SUM(V89:X89)>=2,"Multi","Single")) -> Single | Z89: Design for Safety (DfS) | AA89: None | AB89: Digital Twin platform (no machine learning) | AC89: Multi (two or more data types) | AD89: Single case study | AE89: 4 | AF89: Lifecycle / governance | AG89: Integrated bridge DT system (Cardiff U): combines WebGIS (Cesium), WebBIM (Xeokit), and graph algorithms (Neo4j) in a three-layer architecture with a common data environment (CDE); enables real-time monitoring, drone-enabled inspection, maintenance planning, traffic diversion, and logistics optimization; adaptive data structure with JSON-based bridge defect information modeling and triple-based roadmap graphs; SHM system flags structural issues and triggers alerts/traffic redirection; defects from drone inspection inform maintenance planning. One-way monitoring→analysis→decision support; no actuation and no learning loop. [Full-text source: Endnote] | AH89: Integrates WebGIS (Cesium), WebBIM (Xeokit) and graph algorithms (Neo4j) in a three-layer bridge DT with a common data environment, JSON-based defect modeling and triple-based roadmap graphs, enabling real-time monitoring, drone inspection, traffic diversion and maintenance planning; validated on the River Neath Swing Bridge with regional operation and individual maintenance case studies. | AI89: Defect information modeling relies on custom JSON files that lack extensibility, and the multi-module stack risks cross-platform compatibility issues as functionality grows. Future work targets redefining defect and damage data in IFC format, improving cross-platform interoperability and scalability for more advanced bridge DT applications. | AJ89: Aligned | AK89: WebGIS (Cesium), WebBIM (Xeokit) and Neo4j graph algorithms are integrated in a three-layer architecture with a common data environment, spatially linking GIS, BIM and defect data for the River Neath Swing Bridge. | AL89: High
A90: 3786 | E90: Virtual and Augmented Reality Use Cases for Fusion Design Engineering | F90: Scopus | G90: No | H90: No | I90: No | J90: Yes | K90: Yes | L90: =IF(COUNTBLANK(G90:K90)=5,"",IF(COUNTIF(G90:K90,"No")>0,"EXCLUDE","INCLUDE")) -> EXCLUDE | M90: =IF(L90<>"EXCLUDE","",IF(G90="No","Wrong domain (non-AECO)",IF(H90="No","Digital Twin not core / buzzword",IF(I90="No","No Design for Safety/Quality/PtD",IF(J90="No","Wrong publication type",IF(K90="No","Non-English","")))))) -> Wrong domain (non-AECO) | S90: =IF(N90<>"Yes","",IF(COUNTBLANK(P90:R90)=3,"",IF(COUNTIF(P90:R90,"No")>0,"EXCLUDE","INCLUDE"))) | T90: =IF(S90<>"EXCLUDE","",IF(P90="No","Digital Twin mentioned only, not the subject",IF(Q90="No","No Design for Safety/Quality in full text",IF(R90="No","Methodology not codable","")))) | Y90: =IF(SUM(V90:X90)=0,"",IF(SUM(V90:X90)>=2,"Multi","Single")) | AG90: Fusion-energy facility design; not AECO
A91: 3778 | E91: Digital twin for smart coal mining workface: Technological frame and c… | F91: Scopus | G91: No | H91: Yes | I91: Yes | J91: Yes | K91: No | L91: =IF(COUNTBLANK(G91:K91)=5,"",IF(COUNTIF(G91:K91,"No")>0,"EXCLUDE","INCLUDE")) -> EXCLUDE | M91: =IF(L91<>"EXCLUDE","",IF(G91="No","Wrong domain (non-AECO)",IF(H91="No","Digital Twin not core / buzzword",IF(I91="No","No Design for Safety/Quality/PtD",IF(J91="No","Wrong publication type",IF(K91="No","Non-English","")))))) -> Wrong domain (non-AECO) | S91: =IF(N91<>"Yes","",IF(COUNTBLANK(P91:R91)=3,"",IF(COUNTIF(P91:R91,"No")>0,"EXCLUDE","INCLUDE"))) | T91: =IF(S91<>"EXCLUDE","",IF(P91="No","Digital Twin mentioned only, not the subject",IF(Q91="No","No Design for Safety/Quality in full text",IF(R91="No","Methodology not codable","")))) | Y91: =IF(SUM(V91:X91)=0,"",IF(SUM(V91:X91)>=2,"Multi","Single")) | AG91: Mining; Chinese journal, non-English
A92: 3797 | E92: Construction of Autonomous Collaborative Resource Control System for E… | F92: Scopus | G92: No | H92: Yes | I92: No | J92: Yes | K92: Yes | L92: =IF(COUNTBLANK(G92:K92)=5,"",IF(COUNTIF(G92:K92,"No")>0,"EXCLUDE","INCLUDE")) -> EXCLUDE | M92: =IF(L92<>"EXCLUDE","",IF(G92="No","Wrong domain (non-AECO)",IF(H92="No","Digital Twin not core / buzzword",IF(I92="No","No Design for Safety/Quality/PtD",IF(J92="No","Wrong publication type",IF(K92="No","Non-English","")))))) -> Wrong domain (non-AECO) | S92: =IF(N92<>"Yes","",IF(COUNTBLANK(P92:R92)=3,"",IF(COUNTIF(P92:R92,"No")>0,"EXCLUDE","INCLUDE"))) | T92: =IF(S92<>"EXCLUDE","",IF(P92="No","Digital Twin mentioned only, not the subject",IF(Q92="No","No Design for Safety/Quality in full text",IF(R92="No","Methodology not codable","")))) | Y92: =IF(SUM(V92:X92)=0,"",IF(SUM(V92:X92)>=2,"Multi","Single")) | AG92: EV charging/IoV scheduling; not AECO
A93: 3979 | B93: Geng (2025) | C93: 2025 | E93: Integrating multi-source data for life-cycle risk assessment of bridge… | F93: Web of Science | G93: Yes | H93: Yes | I93: Yes | J93: Yes | K93: Yes | L93: =IF(COUNTBLANK(G93:K93)=5,"",IF(COUNTIF(G93:K93,"No")>0,"EXCLUDE","INCLUDE")) -> INCLUDE | M93: =IF(L93<>"EXCLUDE","",IF(G93="No","Wrong domain (non-AECO)",IF(H93="No","Digital Twin not core / buzzword",IF(I93="No","No Design for Safety/Quality/PtD",IF(J93="No","Wrong publication type",IF(K93="No","Non-English","")))))) | N93: Yes | O93: Yes | P93: Yes | Q93: Yes | R93: Yes | S93: =IF(N93<>"Yes","",IF(COUNTBLANK(P93:R93)=3,"",IF(COUNTIF(P93:R93,"No")>0,"EXCLUDE","INCLUDE"))) -> INCLUDE | T93: =IF(S93<>"EXCLUDE","",IF(P93="No","Digital Twin mentioned only, not the subject",IF(Q93="No","No Design for Safety/Quality in full text",IF(R93="No","Methodology not codable","")))) | U93: Tier 2 - Digital Shadow (one-way physical to virtual) | V93: 0 | W93: 0 | X93: 1 | Y93: =IF(SUM(V93:X93)=0,"",IF(SUM(V93:X93)>=2,"Multi","Single")) -> Single | Z93: Design for Safety (DfS) | AA93: Implemented | AB93: Bayesian / probabilistic | AC93: Multi (two or more data types) | AD93: Single case study | AE93: 4 | AF93: Predictive analytics / decision support | AG93: System digital twin (SDT) for life-cycle risk assessment of bridge networks: Bayesian network (BN) integrates multi-source data (NBI bridge inspections, FDOT traffic/AADT, USGS river gage) to update bridge failure risk (superstructure + scour) over time via automated Bayesian inference (indicator matrix for annual updates; network risk profile trends up as data update reduces uncertainty). Miami-Dade County case: 1,034 bridges, 6,478 nodes, 10,584 edges; 3 flexibility scenarios (new bridge, decommissioning, climate-change flood with CPT recalibration). Updating is implemented Bayesian inference — but authors state framework "has not yet been validated"; CPT refits are manual, no autonomous learning loop. [Full-text source: Endnote] | AH93: Proposes a Bayesian-network system digital twin for county-scale life-cycle risk assessment of bridge networks, fusing NBI inspection ratings, traffic monitoring and river gage data across 1,034 bridges, 1,261 traffic stations and 10 river gages in Miami-Dade County, with a 6,478-node, 10,584-edge graph capturing component, system and cross-system correlations for scenario-based risk updating. | AI93: The framework has not yet been validated with field or laboratory tests, and its large Bayesian network demands 97,484.8 MB of memory just to store conditional probability tables, limiting practical scale-up. Future work includes custom Bayesian networks to cut computation, validation through field coring and lab testing, and adding restoration and resilience modelling. | AJ93: Fused | AK93: A Bayesian network fuses NBI inspection ratings, FDOT traffic monitoring and USGS river-gage data into one 6,478-node, 10,584-edge network that updates bridge failure risk through automated Bayesian inference. | AL93: High
A94: 3962 | E94: Federation of non-destructive testing data for bridge asset management | F94: Web of Science | G94: Yes | H94: No | I94: Yes | J94: Yes | K94: Yes | L94: =IF(COUNTBLANK(G94:K94)=5,"",IF(COUNTIF(G94:K94,"No")>0,"EXCLUDE","INCLUDE")) -> EXCLUDE | M94: =IF(L94<>"EXCLUDE","",IF(G94="No","Wrong domain (non-AECO)",IF(H94="No","Digital Twin not core / buzzword",IF(I94="No","No Design for Safety/Quality/PtD",IF(J94="No","Wrong publication type",IF(K94="No","Non-English","")))))) -> Digital Twin not core / buzzword | S94: =IF(N94<>"Yes","",IF(COUNTBLANK(P94:R94)=3,"",IF(COUNTIF(P94:R94,"No")>0,"EXCLUDE","INCLUDE"))) | T94: =IF(S94<>"EXCLUDE","",IF(P94="No","Digital Twin mentioned only, not the subject",IF(Q94="No","No Design for Safety/Quality in full text",IF(R94="No","Methodology not codable","")))) | Y94: =IF(SUM(V94:X94)=0,"",IF(SUM(V94:X94)>=2,"Multi","Single")) | AG94: NDT data federation in Revit; DT as future tool
A95: 3542 | E95: Construction of damage-free digital twin of damaged aero-engine blades… | F95: Scopus | G95: No | H95: Yes | I95: No | J95: Yes | K95: Yes | L95: =IF(COUNTBLANK(G95:K95)=5,"",IF(COUNTIF(G95:K95,"No")>0,"EXCLUDE","INCLUDE")) -> EXCLUDE | M95: =IF(L95<>"EXCLUDE","",IF(G95="No","Wrong domain (non-AECO)",IF(H95="No","Digital Twin not core / buzzword",IF(I95="No","No Design for Safety/Quality/PtD",IF(J95="No","Wrong publication type",IF(K95="No","Non-English","")))))) -> Wrong domain (non-AECO) | S95: =IF(N95<>"Yes","",IF(COUNTBLANK(P95:R95)=3,"",IF(COUNTIF(P95:R95,"No")>0,"EXCLUDE","INCLUDE"))) | T95: =IF(S95<>"EXCLUDE","",IF(P95="No","Digital Twin mentioned only, not the subject",IF(Q95="No","No Design for Safety/Quality in full text",IF(R95="No","Methodology not codable","")))) | Y95: =IF(SUM(V95:X95)=0,"",IF(SUM(V95:X95)>=2,"Multi","Single")) | AG95: Aerospace remanufacturing
A96: 3580 | E96: The Conventional Construction Scenario and the Emergence of Advance Te… | F96: Scopus | G96: Yes | H96: No | I96: No | J96: Yes | K96: Yes | L96: =IF(COUNTBLANK(G96:K96)=5,"",IF(COUNTIF(G96:K96,"No")>0,"EXCLUDE","INCLUDE")) -> EXCLUDE | M96: =IF(L96<>"EXCLUDE","",IF(G96="No","Wrong domain (non-AECO)",IF(H96="No","Digital Twin not core / buzzword",IF(I96="No","No Design for Safety/Quality/PtD",IF(J96="No","Wrong publication type",IF(K96="No","Non-English","")))))) -> Digital Twin not core / buzzword | S96: =IF(N96<>"Yes","",IF(COUNTBLANK(P96:R96)=3,"",IF(COUNTIF(P96:R96,"No")>0,"EXCLUDE","INCLUDE"))) | T96: =IF(S96<>"EXCLUDE","",IF(P96="No","Digital Twin mentioned only, not the subject",IF(Q96="No","No Design for Safety/Quality in full text",IF(R96="No","Methodology not codable","")))) | Y96: =IF(SUM(V96:X96)=0,"",IF(SUM(V96:X96)>=2,"Multi","Single")) | AG96: Tech-adoption survey; DT one item in a list
A97: 3611 | E97: Digital twin driven airflow intelligent control system for the air out… | F97: Scopus | G97: No | H97: Yes | I97: Yes | J97: Yes | K97: No | L97: =IF(COUNTBLANK(G97:K97)=5,"",IF(COUNTIF(G97:K97,"No")>0,"EXCLUDE","INCLUDE")) -> EXCLUDE | M97: =IF(L97<>"EXCLUDE","",IF(G97="No","Wrong domain (non-AECO)",IF(H97="No","Digital Twin not core / buzzword",IF(I97="No","No Design for Safety/Quality/PtD",IF(J97="No","Wrong publication type",IF(K97="No","Non-English","")))))) -> Wrong domain (non-AECO) | S97: =IF(N97<>"Yes","",IF(COUNTBLANK(P97:R97)=3,"",IF(COUNTIF(P97:R97,"No")>0,"EXCLUDE","INCLUDE"))) | T97: =IF(S97<>"EXCLUDE","",IF(P97="No","Digital Twin mentioned only, not the subject",IF(Q97="No","No Design for Safety/Quality in full text",IF(R97="No","Methodology not codable","")))) | Y97: =IF(SUM(V97:X97)=0,"",IF(SUM(V97:X97)>=2,"Multi","Single")) | AG97: Mining ventilation; Chinese journal, non-English
A98: 4005 | B98: Gonzalez-Boehme (2023) | C98: 2023 | E98: Mixed Reality for Safe and Reliable Human-Robot Collaboration in Timbe… | F98: Web of Science | G98: Yes | H98: Yes | I98: Yes | J98: Yes | K98: Yes | L98: =IF(COUNTBLANK(G98:K98)=5,"",IF(COUNTIF(G98:K98,"No")>0,"EXCLUDE","INCLUDE")) -> INCLUDE | M98: =IF(L98<>"EXCLUDE","",IF(G98="No","Wrong domain (non-AECO)",IF(H98="No","Digital Twin not core / buzzword",IF(I98="No","No Design for Safety/Quality/PtD",IF(J98="No","Wrong publication type",IF(K98="No","Non-English","")))))) | N98: Yes | O98: Yes | P98: Yes | Q98: Yes | R98: Yes | S98: =IF(N98<>"Yes","",IF(COUNTBLANK(P98:R98)=3,"",IF(COUNTIF(P98:R98,"No")>0,"EXCLUDE","INCLUDE"))) -> INCLUDE | T98: =IF(S98<>"EXCLUDE","",IF(P98="No","Digital Twin mentioned only, not the subject",IF(Q98="No","No Design for Safety/Quality in full text",IF(R98="No","Methodology not codable","")))) | U98: Tier 3 - Digital Twin (bidirectional, two-way) | V98: 0 | W98: 1 | X98: 0 | Y98: =IF(SUM(V98:X98)=0,"",IF(SUM(V98:X98)>=2,"Multi","Single")) -> Single | Z98: Design for Safety (DfS) | AA98: None | AB98: Perception / Computer Vision | AC98: Multi (two or more data types) | AD98: Single case study | AE98: 4 | AF98: Design for Safety | AG98: Mixed Reality-based human-robot collaboration for timber frame construction (USM Chile): vision-based collaborative industrial robot system for wood stereotomy; carpenter lays out joinery with conventional marks, robot cuts based on visual interpretation; digital twin of robot previsualizes all motions for task validation and safety (when to enter workspace); real-time visual feedback between human and robot; 3D model of cut shape constructed from vision system data. Bidirectional human-robot collaboration with robot executing physical tasks → Tier 3; no ML learning loop (rule-based mark interpretation). [Full-text source: Endnote] | AH98: Addresses the real-time human-robot communication gap in timber frame construction: a vision-based collaborative robot interprets the layout marks drawn by a carpenter as cutting operations, and a robot digital twin shown through HoloLens 2 mixed reality previews all motions, danger zones and collision warnings so the carpenter can safely time entry to the collaborative workspace under ISO/TS 15066. | AI98: Only robot-operator collision risk is detected automatically; tracking of other workspace elements must still be added, and the system awaits calibration of assembly tools and tests with real carpenters. Future work includes defining shared human-robot spaces, optimizing auxiliary trajectories and tool orientations, and handling robot payload constraints. | AJ98: Aligned | AK98: Vision-derived geometry of the cut shape and the robot digital twin share the robot kinematic frame for MR previsualisation, while mark interpretation and motion preview remain separate processes. | AL98: High
A99: 3652 | E99: Protecting critical infrastructure against cascading effects: The PREC… | F99: Scopus | G99: No | H99: Yes | I99: No | J99: Yes | K99: Yes | L99: =IF(COUNTBLANK(G99:K99)=5,"",IF(COUNTIF(G99:K99,"No")>0,"EXCLUDE","INCLUDE")) -> EXCLUDE | M99: =IF(L99<>"EXCLUDE","",IF(G99="No","Wrong domain (non-AECO)",IF(H99="No","Digital Twin not core / buzzword",IF(I99="No","No Design for Safety/Quality/PtD",IF(J99="No","Wrong publication type",IF(K99="No","Non-English","")))))) -> Wrong domain (non-AECO) | S99: =IF(N99<>"Yes","",IF(COUNTBLANK(P99:R99)=3,"",IF(COUNTIF(P99:R99,"No")>0,"EXCLUDE","INCLUDE"))) | T99: =IF(S99<>"EXCLUDE","",IF(P99="No","Digital Twin mentioned only, not the subject",IF(Q99="No","No Design for Safety/Quality in full text",IF(R99="No","Methodology not codable","")))) | Y99: =IF(SUM(V99:X99)=0,"",IF(SUM(V99:X99)>=2,"Multi","Single")) | AG99: Cyber-physical security of CI generally; not AECO-specific
A100: 3942 | E100: Robotic devices for Structural Health Monitoring | F100: Web of Science | G100: Yes | H100: No | I100: Yes | J100: Yes | K100: Yes | L100: =IF(COUNTBLANK(G100:K100)=5,"",IF(COUNTIF(G100:K100,"No")>0,"EXCLUDE","INCLUDE")) -> EXCLUDE | M100: =IF(L100<>"EXCLUDE","",IF(G100="No","Wrong domain (non-AECO)",IF(H100="No","Digital Twin not core / buzzword",IF(I100="No","No Design for Safety/Quality/PtD",IF(J100="No","Wrong publication type",IF(K100="No","Non-English","")))))) -> Digital Twin not core / buzzword | S100: =IF(N100<>"Yes","",IF(COUNTBLANK(P100:R100)=3,"",IF(COUNTIF(P100:R100,"No")>0,"EXCLUDE","INCLUDE"))) | T100: =IF(S100<>"EXCLUDE","",IF(P100="No","Digital Twin mentioned only, not the subject",IF(Q100="No","No Design for Safety/Quality in full text",IF(R100="No","Methodology not codable","")))) | Y100: =IF(SUM(V100:X100)=0,"",IF(SUM(V100:X100)>=2,"Multi","Single")) | AG100: Robotics-for-SHM review; DT creation only attempts
...

Sheet Step1_Report
A1: STEP 1 & PRISMA - screening outcomes (auto)
A3: PRISMA stage | B3: n
A4: Records identified (in matrix) | B4: =COUNTA(Matrix!$A$2:$A$451) -> 429
A5: Records screened (Stage-1 decided) | B5: =COUNTIF(Matrix!$L$2:$L$451,"INCLUDE")+COUNTIF(Matrix!$L$2:$L$451,"EXCLUDE") -> 429
A6: Excluded at Stage-1 (title/abstract) | B6: =COUNTIF(Matrix!$L$2:$L$451,"EXCLUDE") -> 262
A7: Stage-1 INCLUDE -> sought for retrieval | B7: =COUNTIF(Matrix!$L$2:$L$451,"INCLUDE") -> 167
A8: PDF full text on hand (gateway = Yes) | B8: =COUNTIFS(Matrix!$L$2:$L$451,"INCLUDE",Matrix!$N$2:$N$451,"Yes") -> 162
A9: PDF not yet on hand (revisit later) | B9: =COUNTIFS(Matrix!$L$2:$L$451,"INCLUDE",Matrix!$N$2:$N$451,"No") -> 3
A10: Reports assessed for eligibility (full text) | B10: =COUNTIFS(Matrix!$N$2:$N$451,"Yes",Matrix!$S$2:$S$451,"INCLUDE")+COUNTIFS(Matrix!$N$2:$N$451,"Yes",Matrix!$S$2:$S$451,"EXCLUDE") -> 162
A11: Excluded at Stage-2 (full text, with reasons) | B11: =COUNTIF(Matrix!$S$2:$S$451,"EXCLUDE") -> 11
A12: STUDIES INCLUDED IN SYNTHESIS | B12: =COUNTIF(Matrix!$S$2:$S$451,"INCLUDE") -> 151
A14: Stage-1 exclusion reasons
A15: Reason | B15: n
A16: Wrong domain (non-AECO) | B16: =COUNTIF(Matrix!$M$2:$M$451,"Wrong domain (non-AECO)") -> 99
A17: Digital Twin not core / buzzword | B17: =COUNTIF(Matrix!$M$2:$M$451,"Digital Twin not core / buzzword") -> 112
A18: No Design for Safety/Quality/PtD | B18: =COUNTIF(Matrix!$M$2:$M$451,"No Design for Safety/Quality/PtD") -> 21
A19: Wrong publication type | B19: =COUNTIF(Matrix!$M$2:$M$451,"Wrong publication type") -> 0
A20: Non-English | B20: =COUNTIF(Matrix!$M$2:$M$451,"Non-English") -> 30
A21: Total Stage-1 exclusions | B21: =SUM(B16:B20) -> 262
A23: Stage-2 (full-text) exclusion reasons
A24: Reason | B24: n
A25: Digital Twin mentioned only, not the subject | B25: =COUNTIF(Matrix!$T$2:$T$451,"Digital Twin mentioned only, not the subject") -> 10
A26: No Design for Safety/Quality in full text | B26: =COUNTIF(Matrix!$T$2:$T$451,"No Design for Safety/Quality in full text") -> 1
A27: Methodology not codable | B27: =COUNTIF(Matrix!$T$2:$T$451,"Methodology not codable") -> 0
A28: Total Stage-2 exclusions | B28: =SUM(B25:B27) -> 11

Sheet PRISMA_Shapes
E14: 112
E15: 99
E16: 30
E17: 21
A58: LIVE DATA FEED — the text of every shape above is generated from these formula cells
A59: Key | B59: Text used in shape (live formula)
A60: Identified | B60: ="Records identified from databases"&CHAR(10)&"(Scopus · Web of Science)"&CHAR(10)&"n = "&TEXT(Step1_Report!$B$4,"0") -> Records identified from databases (Scopus · Web of Science) n = 429
A61: Screened | B61: ="Records screened at Stage 1"&CHAR(10)&"(title & abstract)"&CHAR(10)&"n = "&TEXT(Step1_Report!$B$5,"0") -> Records screened at Stage 1 (title & abstract) n = 429
A62: Excluded1 | B62: ="Records excluded at Stage 1 n = "&TEXT(Step1_Report!$B$6,"0")&CHAR(10)&"• "&Step1_Report!$A$17&": "&TEXT(Step1_Report!$B$17,"0")&CHAR(10)&"• "&Step1_Report!$A$16&": "&TEXT(Step1_Report!$B$16,"0")&CHAR(10)&"• "&Step1_Report!$A$20&": "&TEXT(Step1_Report!$B$20,"0")&CHAR(10)&"• "&Step1_Report!$A$18&": "&TEXT(Step1_Report!$B$18,"0")&CHAR(10)&"• "&Step1_Report!$A$19&": "&TEXT(Step1_Report!$B$19,"0") -> Records excluded at Stage 1 n = 262 • Digital Twin not core / buzzword: 112 • Wrong domain (non-AECO): 99 • Non-English: 30 • No Design for Safety/Quality/PtD: 21 • Wrong publication type: 0
A63: Sought | B63: ="Reports sought for retrieval"&CHAR(10)&"n = "&TEXT(Step1_Report!$B$7,"0") -> Reports sought for retrieval n = 167
A64: NotRetrieved | B64: ="Reports not retrieved"&CHAR(10)&"(full-text PDF not on hand)"&CHAR(10)&"n = "&TEXT(Step1_Report!$B$7-Step1_Report!$B$10,"0") -> Reports not retrieved (full-text PDF not on hand) n = 5
A65: Assessed | B65: ="Reports assessed for eligibility"&CHAR(10)&"(Stage 2 — full text)"&CHAR(10)&"n = "&TEXT(Step1_Report!$B$10,"0") -> Reports assessed for eligibility (Stage 2 — full text) n = 162
A66: Excluded2 | B66: ="Reports excluded at Stage 2 n = "&TEXT(Step1_Report!$B$11,"0")&CHAR(10)&"• "&Step1_Report!$A$25&": "&TEXT(Step1_Report!$B$25,"0")&CHAR(10)&"• "&Step1_Report!$A$26&": "&TEXT(Step1_Report!$B$26,"0")&CHAR(10)&"• "&Step1_Report!$A$27&": "&TEXT(Step1_Report!$B$27,"0") -> Reports excluded at Stage 2 n = 11 • Digital Twin mentioned only, not the subject: 10 • No Design for Safety/Quality in full text: 1 • Methodology not codable: 0
A67: Included | B67: ="STUDIES INCLUDED IN SYNTHESIS"&CHAR(10)&"n = "&TEXT(Step1_Report!$B$12,"0") -> STUDIES INCLUDED IN SYNTHESIS n = 151
A68: PanelHeader | B68: ="Characteristics of the "&TEXT(Step3_Report!$B$2,"0")&" included studies" -> Characteristics of the 151 included studies
A69: PanelTier | B69: ="Digital Twin capability tier (Gap 1)"&CHAR(10)&"• Tier 1 – Digital Model: "&TEXT(Step3_Report!$B$6,"0")&" ("&TEXT(Step3_Report!$C$6,"0.0%")&")"&CHAR(10)&"• Tier 2 – Digital Shadow: "&TEXT(Step3_Report!$B$7,"0")&" ("&TEXT(Step3_Report!$C$7,"0.0%")&")"&CHAR(10)&"• Tier 3 – Digital Twin: "&TEXT(Step3_Report!$B$8,"0")&" ("&TEXT(Step3_Report!$C$8,"0.0%")&")"&CHAR(10)&"• Tier 4 – Cognitive: "&TEXT(Step3_Report!$B$9,"0")&" ("&TEXT(Step3_Report!$C$9,"0.0%")&")"&CHAR(10)&"• Unclear: "&TEXT(Step3_Report!$B$10,"0")&" ("&TEXT(Step3_Report!$C$10,"0.0%")&")" -> Digital Twin capability tier (Gap 1) • Tier 1 – Digital Model: 31 (20.5%) • Tier 2 – Digital Shadow: 91 (60.3%) • Tier 3 – Digital Twin: 21 (13.9%) • Tier 4 – Cognitive: 0 (0.0%) • Unclear: 8 (5.3%)
A70: PanelSelf | B70: =Step3_Report!$A$12&CHAR(10)&"• None: "&TEXT(Step3_Report!$B$14,"0")&" ("&TEXT(Step3_Report!$C$14,"0.0%")&")"&CHAR(10)&"• Mentioned only: "&TEXT(Step3_Report!$B$15,"0")&" ("&TEXT(Step3_Report!$C$15,"0.0%")&")"&CHAR(10)&"• Implemented: "&TEXT(Step3_Report!$B$16,"0")&" ("&TEXT(Step3_Report!$C$16,"0.0%")&")"&CHAR(10)&"• Convergence-characterised: "&TEXT(Step3_Report!$B$17,"0")&" ("&TEXT(Step3_Report!$C$17,"0.0%")&")" -> Self-improvement / convergence (Gap 4 - core gap) • None: 133 (88.1%) • Mentioned only: 8 (5.3%) • Implemented: 10 (6.6%) • Convergence-characterised: 0 (0.0%)
A71: PanelValid | B71: ="Validation level (Gap 5)"&CHAR(10)&"• Conceptual (no test): "&TEXT(Step3_Report!$B$33,"0")&" ("&TEXT(Step3_Report!$C$33,"0.0%")&")"&CHAR(10)&"• Simulation: "&TEXT(Step3_Report!$B$34,"0")&" ("&TEXT(Step3_Report!$C$34,"0.0%")&")"&CHAR(10)&"• Single case study: "&TEXT(Step3_Report!$B$35,"0")&" ("&TEXT(Step3_Report!$C$35,"0.0%")&")"&CHAR(10)&"• Cross-project: "&TEXT(Step3_Report!$B$36,"0")&" ("&TEXT(Step3_Report!$C$36,"0.0%")&")" -> Validation level (Gap 5) • Conceptual (no test): 19 (12.6%) • Simulation: 19 (12.6%) • Single case study: 106 (70.2%) • Cross-project: 7 (4.6%)
A72: PanelPhase | B72: ="Lifecycle phase coverage (Gap 3)"&CHAR(10)&"• Design (any): "&TEXT(Step3_Report!$B$55,"0")&CHAR(10)&"• Construction (any): "&TEXT(Step3_Report!$B$56,"0")&CHAR(10)&"• Operation (any): "&TEXT(Step3_Report!$B$57,"0")&CHAR(10)&"• Single-phase: "&TEXT(Step3_Report!$B$58,"0")&CHAR(10)&"• Multi-phase (cross-phase): "&TEXT(Step3_Report!$B$59,"0") -> Lifecycle phase coverage (Gap 3) • Design (any): 5 • Construction (any): 81 • Operation (any): 72 • Single-phase: 146 • Multi-phase (cross-phase): 5
A73: Title | B73: ="PRISMA 2020 flow diagram — Digital Twins for Design for Safety & Quality in AECO" -> PRISMA 2020 flow diagram — Digital Twins for Design for Safety & Quality in AECO
A74: Footnote | B74: ="Shapes version. Shape text is generated from the live formulas in this feed block — ask to refresh the shapes after changing the Matrix. ""Not retrieved"" = "&TEXT(Step1_Report!$B$7-Step1_Report!$B$10,"0")&" ("&TEXT(Step1_Report!$B$9,"0")&" PDF pending + "&TEXT(Step1_Report!$B$7-Step1_Report!$B$10-Step1_Report!$B$9,"0")&" flagged duplicates)." -> Shapes version. Shape text is generated from the live formulas in this feed block — ask to refresh the shapes after changing the Matrix. "Not retrieved" = 5 (3 PDF pending + 2 flagged duplicates).
A75: PanelModality | B75: =Step3_Report!$A$26&CHAR(10)&"• Single (one data type): "&TEXT(Step3_Report!$B$28,"0")&" ("&TEXT(Step3_Report!$C$28,"0.0%")&")"&CHAR(10)&"• Multi (two or more data types): "&TEXT(Step3_Report!$B$29,"0")&" ("&TEXT(Step3_Report!$C$29,"0.0%")&")" -> Data modality (Gap 2) • Single (one data type): 14 (9.3%) • Multi (two or more data types): 137 (90.7%)
A76: PanelFusion | B76: =Step3_Report!$A$80&CHAR(10)&"• Single: "&TEXT(Step3_Report!$B$82,"0")&" ("&TEXT(Step3_Report!$C$82,"0.0%")&")"&CHAR(10)&"• Co-present: "&TEXT(Step3_Report!$B$83,"0")&" ("&TEXT(Step3_Report!$C$83,"0.0%")&")"&CHAR(10)&"• Aligned: "&TEXT(Step3_Report!$B$84,"0")&" ("&TEXT(Step3_Report!$C$84,"0.0%")&")"&CHAR(10)&"• Fused: "&TEXT(Step3_Report!$B$85,"0")&" ("&TEXT(Step3_Report!$C$85,"0.0%")&")"&CHAR(10)&"• Unclear: "&TEXT(Step3_Report!$B$86,"0")&" ("&TEXT(Step3_Report!$C$86,"0.0%")&")" -> Fusion depth (Gap 2b - how deeply are the data types actually integrated?) • Single: 19 (12.6%) • Co-present: 3 (2.0%) • Aligned: 39 (25.8%) • Fused: 71 (47.0%) • Unclear: 19 (12.6%)
A77: FusionHeadline | B77: =Step3_Report!$A$105 -> Even among the 71 Fused studies, 64 (90.1%) implement no self-improvement and 0 characterise convergence - deep data integration does NOT translate into adaptive capability.

Sheet Step3_Report
A1: STEP 3 - deep-read synthesis tables (auto = findings section)
A2: Total included studies | B2: =COUNTIF(Matrix!$S$2:$S$451,"INCLUDE") -> 151
A4: Digital Twin capability tier (Gap 1)
A5: Category | B5: n | C5: % of incl.
A6: Tier 1 - Digital Model (static, no live data) | B6: =COUNTIFS(Matrix!$S$2:$S$451,"INCLUDE",Matrix!$U$2:$U$451,"Tier 1 - Digital Model (static, no live data)") -> 31 | C6: =IF($B$2=0,"-",B6/$B$2) -> 0.20529801
A7: Tier 2 - Digital Shadow (one-way physical to virtual) | B7: =COUNTIFS(Matrix!$S$2:$S$451,"INCLUDE",Matrix!$U$2:$U$451,"Tier 2 - Digital Shadow (one-way physical to virtual)") -> 91 | C7: =IF($B$2=0,"-",B7/$B$2) -> 0.60264901
A8: Tier 3 - Digital Twin (bidirectional, two-way) | B8: =COUNTIFS(Matrix!$S$2:$S$451,"INCLUDE",Matrix!$U$2:$U$451,"Tier 3 - Digital Twin (bidirectional, two-way)") -> 21 | C8: =IF($B$2=0,"-",B8/$B$2) -> 0.13907285
A9: Tier 4 - Cognitive / Self-improving | B9: =COUNTIFS(Matrix!$S$2:$S$451,"INCLUDE",Matrix!$U$2:$U$451,"Tier 4 - Cognitive / Self-improving") -> 0 | C9: =IF($B$2=0,"-",B9/$B$2) -> 0
A10: Unclear | B10: =COUNTIFS(Matrix!$S$2:$S$451,"INCLUDE",Matrix!$U$2:$U$451,"Unclear") -> 8 | C10: =IF($B$2=0,"-",B10/$B$2) -> 0.052980132
A12: Self-improvement / convergence (Gap 4 - core gap)
A13: Category | B13: n | C13: % of incl.
A14: None | B14: =COUNTIFS(Matrix!$S$2:$S$451,"INCLUDE",Matrix!$AA$2:$AA$451,"None") -> 133 | C14: =IF($B$2=0,"-",B14/$B$2) -> 0.8807947
A15: Mentioned only | B15: =COUNTIFS(Matrix!$S$2:$S$451,"INCLUDE",Matrix!$AA$2:$AA$451,"Mentioned only") -> 8 | C15: =IF($B$2=0,"-",B15/$B$2) -> 0.052980132
A16: Implemented | B16: =COUNTIFS(Matrix!$S$2:$S$451,"INCLUDE",Matrix!$AA$2:$AA$451,"Implemented") -> 10 | C16: =IF($B$2=0,"-",B16/$B$2) -> 0.066225166
A17: Convergence-characterised | B17: =COUNTIFS(Matrix!$S$2:$S$451,"INCLUDE",Matrix!$AA$2:$AA$451,"Convergence-characterised") -> 0 | C17: =IF($B$2=0,"-",B17/$B$2) -> 0
A19: Design-for-X target
A20: Category | B20: n | C20: % of incl.
A21: Design for Safety (DfS) | B21: =COUNTIFS(Matrix!$S$2:$S$451,"INCLUDE",Matrix!$Z$2:$Z$451,"Design for Safety (DfS)") -> 133 | C21: =IF($B$2=0,"-",B21/$B$2) -> 0.8807947
A22: Design for Quality (DfQ) | B22: =COUNTIFS(Matrix!$S$2:$S$451,"INCLUDE",Matrix!$Z$2:$Z$451,"Design for Quality (DfQ)") -> 10 | C22: =IF($B$2=0,"-",B22/$B$2) -> 0.066225166
A23: Both | B23: =COUNTIFS(Matrix!$S$2:$S$451,"INCLUDE",Matrix!$Z$2:$Z$451,"Both") -> 8 | C23: =IF($B$2=0,"-",B23/$B$2) -> 0.052980132
A24: Other | B24: =COUNTIFS(Matrix!$S$2:$S$451,"INCLUDE",Matrix!$Z$2:$Z$451,"Other") -> 0 | C24: =IF($B$2=0,"-",B24/$B$2) -> 0
A26: Data modality (Gap 2)
A27: Category | B27: n | C27: % of incl.
A28: Single (one data type) | B28: =COUNTIFS(Matrix!$S$2:$S$451,"INCLUDE",Matrix!$AC$2:$AC$451,"Single (one data type)") -> 14 | C28: =IF($B$2=0,"-",B28/$B$2) -> 0.092715232
A29: Multi (two or more data types) | B29: =COUNTIFS(Matrix!$S$2:$S$451,"INCLUDE",Matrix!$AC$2:$AC$451,"Multi (two or more data types)") -> 137 | C29: =IF($B$2=0,"-",B29/$B$2) -> 0.90728477
A31: Validation level (Gap 5)
A32: Category | B32: n | C32: % of incl.
A33: Conceptual (no test) | B33: =COUNTIFS(Matrix!$S$2:$S$451,"INCLUDE",Matrix!$AD$2:$AD$451,"Conceptual (no test)") -> 19 | C33: =IF($B$2=0,"-",B33/$B$2) -> 0.12582781
A34: Simulation | B34: =COUNTIFS(Matrix!$S$2:$S$451,"INCLUDE",Matrix!$AD$2:$AD$451,"Simulation") -> 19 | C34: =IF($B$2=0,"-",B34/$B$2) -> 0.12582781
A35: Single case study | B35: =COUNTIFS(Matrix!$S$2:$S$451,"INCLUDE",Matrix!$AD$2:$AD$451,"Single case study") -> 106 | C35: =IF($B$2=0,"-",B35/$B$2) -> 0.70198675
A36: Cross-project (multiple real projects) | B36: =COUNTIFS(Matrix!$S$2:$S$451,"INCLUDE",Matrix!$AD$2:$AD$451,"Cross-project (multiple real projects)") -> 7 | C36: =IF($B$2=0,"-",B36/$B$2) -> 0.046357616
A38: Methodology (RQ2)
A39: Category | B39: n | C39: % of incl.
A40: Computer Vision / CNN / object-detection | B40: =COUNTIFS(Matrix!$S$2:$S$451,"INCLUDE",Matrix!$AB$2:$AB$451,"Computer Vision / CNN / object-detection") -> 3 | C40: =IF($B$2=0,"-",B40/$B$2) -> 0.01986755
A41: Graph Neural Network (GNN) | B41: =COUNTIFS(Matrix!$S$2:$S$451,"INCLUDE",Matrix!$AB$2:$AB$451,"Graph Neural Network (GNN)") -> 3 | C41: =IF($B$2=0,"-",B41/$B$2) -> 0.01986755
A42: LSTM / RNN (recurrent networks) | B42: =COUNTIFS(Matrix!$S$2:$S$451,"INCLUDE",Matrix!$AB$2:$AB$451,"LSTM / RNN (recurrent networks)") -> 2 | C42: =IF($B$2=0,"-",B42/$B$2) -> 0.013245033
A43: Transformer / Large Language Model (LLM) | B43: =COUNTIFS(Matrix!$S$2:$S$451,"INCLUDE",Matrix!$AB$2:$AB$451,"Transformer / Large Language Model (LLM)") -> 8 | C43: =IF($B$2=0,"-",B43/$B$2) -> 0.052980132
A44: Reinforcement Learning (RL) | B44: =COUNTIFS(Matrix!$S$2:$S$451,"INCLUDE",Matrix!$AB$2:$AB$451,"Reinforcement Learning (RL)") -> 2 | C44: =IF($B$2=0,"-",B44/$B$2) -> 0.013245033
A45: Bayesian / probabilistic | B45: =COUNTIFS(Matrix!$S$2:$S$451,"INCLUDE",Matrix!$AB$2:$AB$451,"Bayesian / probabilistic") -> 4 | C45: =IF($B$2=0,"-",B45/$B$2) -> 0.026490066
A46: Agent-based model (ABM) | B46: =COUNTIFS(Matrix!$S$2:$S$451,"INCLUDE",Matrix!$AB$2:$AB$451,"Agent-based model (ABM)") -> 1 | C46: =IF($B$2=0,"-",B46/$B$2) -> 0.0066225166
A47: Finite Element Method / physics-based | B47: =COUNTIFS(Matrix!$S$2:$S$451,"INCLUDE",Matrix!$AB$2:$AB$451,"Finite Element Method / physics-based") -> 15 | C47: =IF($B$2=0,"-",B47/$B$2) -> 0.099337748
A48: Ontology / semantic | B48: =COUNTIFS(Matrix!$S$2:$S$451,"INCLUDE",Matrix!$AB$2:$AB$451,"Ontology / semantic") -> 9 | C48: =IF($B$2=0,"-",B48/$B$2) -> 0.059602649
A49: Statistical / change-point | B49: =COUNTIFS(Matrix!$S$2:$S$451,"INCLUDE",Matrix!$AB$2:$AB$451,"Statistical / change-point") -> 8 | C49: =IF($B$2=0,"-",B49/$B$2) -> 0.052980132
A50: Digital Twin platform (no machine learning) | B50: =COUNTIFS(Matrix!$S$2:$S$451,"INCLUDE",Matrix!$AB$2:$AB$451,"Digital Twin platform (no machine learning)") -> 40 | C50: =IF($B$2=0,"-",B50/$B$2) -> 0.26490066
A51: Other / Mixed | B51: =COUNTIFS(Matrix!$S$2:$S$451,"INCLUDE",Matrix!$AB$2:$AB$451,"Other / Mixed") -> 35 | C51: =IF($B$2=0,"-",B51/$B$2) -> 0.23178808
A53: Lifecycle phase coverage (Gap 3)
A54: Coverage | B54: n
A55: Design (any) | B55: =COUNTIFS(Matrix!$S$2:$S$451,"INCLUDE",Matrix!$V$2:$V$451,1) -> 5
A56: Construction (any) | B56: =COUNTIFS(Matrix!$S$2:$S$451,"INCLUDE",Matrix!$W$2:$W$451,1) -> 81
A57: Operation (any) | B57: =COUNTIFS(Matrix!$S$2:$S$451,"INCLUDE",Matrix!$X$2:$X$451,1) -> 72
A58: Single-phase | B58: =COUNTIFS(Matrix!$S$2:$S$451,"INCLUDE",Matrix!$Y$2:$Y$451,"Single") -> 146
A59: Multi-phase (cross-phase) | B59: =COUNTIFS(Matrix!$S$2:$S$451,"INCLUDE",Matrix!$Y$2:$Y$451,"Multi") -> 5
A61: Gap 2 x Gap 4 cross-tab - is multimodal data converted into adaptive capability?
A62: Data modality \ Self-improvement | B62: =$A$14 -> None | C62: =$A$15 -> Mentioned only | D62: =$A$16 -> Implemented | E62: =$A$17 -> Convergence-characterised | F62: Total
A63: =$A$28 -> Single (one data type) | B63: =COUNTIFS(Matrix!$S$2:$S$451,"INCLUDE",Matrix!$AC$2:$AC$451,$A63,Matrix!$AA$2:$AA$451,B$62) -> 11 | C63: =COUNTIFS(Matrix!$S$2:$S$451,"INCLUDE",Matrix!$AC$2:$AC$451,$A63,Matrix!$AA$2:$AA$451,C$62) -> 1 | D63: =COUNTIFS(Matrix!$S$2:$S$451,"INCLUDE",Matrix!$AC$2:$AC$451,$A63,Matrix!$AA$2:$AA$451,D$62) -> 2 | E63: =COUNTIFS(Matrix!$S$2:$S$451,"INCLUDE",Matrix!$AC$2:$AC$451,$A63,Matrix!$AA$2:$AA$451,E$62) -> 0 | F63: =SUM(B63:E63) -> 14
A64: =$A$29 -> Multi (two or more data types) | B64: =COUNTIFS(Matrix!$S$2:$S$451,"INCLUDE",Matrix!$AC$2:$AC$451,$A64,Matrix!$AA$2:$AA$451,B$62) -> 122 | C64: =COUNTIFS(Matrix!$S$2:$S$451,"INCLUDE",Matrix!$AC$2:$AC$451,$A64,Matrix!$AA$2:$AA$451,C$62) -> 7 | D64: =COUNTIFS(Matrix!$S$2:$S$451,"INCLUDE",Matrix!$AC$2:$AC$451,$A64,Matrix!$AA$2:$AA$451,D$62) -> 8 | E64: =COUNTIFS(Matrix!$S$2:$S$451,"INCLUDE",Matrix!$AC$2:$AC$451,$A64,Matrix!$AA$2:$AA$451,E$62) -> 0 | F64: =SUM(B64:E64) -> 137
A65: Total | B65: =SUM(B63:B64) -> 133 | C65: =SUM(C63:C64) -> 8 | D65: =SUM(D63:D64) -> 10 | E65: =SUM(E63:E64) -> 0 | F65: =SUM(F63:F64) -> 151
A67: Same cross-tab as % of each modality row (does data richness become adaptive capability?)
A68: Data modality \ Self-improvement | B68: =B$62 -> None | C68: =C$62 -> Mentioned only | D68: =D$62 -> Implemented | E68: =E$62 -> Convergence-characterised | F68: Total
A69: =$A$63 -> Single (one data type) | B69: =IF($F63=0,"-",B63/$F63) -> 0.78571429 | C69: =IF($F63=0,"-",C63/$F63) -> 0.071428571 | D69: =IF($F63=0,"-",D63/$F63) -> 0.14285714 | E69: =IF($F63=0,"-",E63/$F63) -> 0 | F69: =IF($F63=0,"-",F63/$F63) -> 1
A70: =$A$64 -> Multi (two or more data types) | B70: =IF($F64=0,"-",B64/$F64) -> 0.89051095 | C70: =IF($F64=0,"-",C64/$F64) -> 0.051094891 | D70: =IF($F64=0,"-",D64/$F64) -> 0.058394161 | E70: =IF($F64=0,"-",E64/$F64) -> 0 | F70: =IF($F64=0,"-",F64/$F64) -> 1
A72: Cross-tab integrity check (grand total must equal total included studies)
A73: Cross-tab grand total | B73: =$F$65 -> 151
A74: Total included studies | B74: =$B$2 -> 151
A75: Reconciles? | B75: =IF($F$65=$B$2,"OK - "&TEXT($F$65,"0")&" studies fully cross-classified","MISMATCH: "&TEXT($F$65-$B$2,"+0;-0")&" - check for blank codes in Matrix AA/AC") -> OK - 151 studies fully cross-classified
A77: Headline (auto)
A78: ="Of the "&TEXT($F$64,"0")&" multimodal studies, "&TEXT($B$64,"0")&" ("&TEXT($B$64/$F$64,"0.0%")&") implement no self-improvement at all; only "&TEXT($D$64,"0")&" ("&TEXT($D$64/$F$64,"0.0%")&") implement it and "&TEXT($E$64,"0")&" characterise convergence." -> Of the 137 multimodal studies, 122 (89.1%) implement no self-improvement at all; only 8 (5.8%) implement it and 0 characterise convergence.
A80: Fusion depth (Gap 2b - how deeply are the data types actually integrated?) | E80: Fusion coding confidence
A81: Category | B81: n | C81: % of incl. | E81: Confidence | F81: n
A82: ='1_CodeLists'!$K$2 -> Single | B82: =COUNTIFS(Matrix!$S$2:$S$451,"INCLUDE",Matrix!$AJ$2:$AJ$451,$A82) -> 19 | C82: =IF($B$2=0,"-",B82/$B$2) -> 0.12582781 | E82: ='1_CodeLists'!$L$2 -> High | F82: =COUNTIFS(Matrix!$S$2:$S$451,"INCLUDE",Matrix!$AL$2:$AL$451,$E82) -> 109
A83: ='1_CodeLists'!$K$3 -> Co-present | B83: =COUNTIFS(Matrix!$S$2:$S$451,"INCLUDE",Matrix!$AJ$2:$AJ$451,$A83) -> 3 | C83: =IF($B$2=0,"-",B83/$B$2) -> 0.01986755 | E83: ='1_CodeLists'!$L$3 -> Medium | F83: =COUNTIFS(Matrix!$S$2:$S$451,"INCLUDE",Matrix!$AL$2:$AL$451,$E83) -> 42
A84: ='1_CodeLists'!$K$4 -> Aligned | B84: =COUNTIFS(Matrix!$S$2:$S$451,"INCLUDE",Matrix!$AJ$2:$AJ$451,$A84) -> 39 | C84: =IF($B$2=0,"-",B84/$B$2) -> 0.25827815 | E84: ='1_CodeLists'!$L$4 -> Low | F84: =COUNTIFS(Matrix!$S$2:$S$451,"INCLUDE",Matrix!$AL$2:$AL$451,$E84) -> 0
A85: ='1_CodeLists'!$K$5 -> Fused | B85: =COUNTIFS(Matrix!$S$2:$S$451,"INCLUDE",Matrix!$AJ$2:$AJ$451,$A85) -> 71 | C85: =IF($B$2=0,"-",B85/$B$2) -> 0.47019868 | E85: Rows flagged for review | F85: =COUNTIFS(Matrix!$S$2:$S$451,"INCLUDE",Matrix!$AM$2:$AM$451,"<>") -> 5
A86: ='1_CodeLists'!$K$6 -> Unclear | B86: =COUNTIFS(Matrix!$S$2:$S$451,"INCLUDE",Matrix!$AJ$2:$AJ$451,$A86) -> 19 | C86: =IF($B$2=0,"-",B86/$B$2) -> 0.12582781
A87: Total | B87: =SUM(B82:B86) -> 151 | C87: =IF($B$2=0,"-",B87/$B$2) -> 1
A89: Fusion depth x Gap 4 cross-tab - does deeper integration produce adaptive capability?
A90: Fusion depth \ Self-improvement | B90: =$A$14 -> None | C90: =$A$15 -> Mentioned only | D90: =$A$16 -> Implemented | E90: =$A$17 -> Convergence-characterised | F90: Total
A91: =$A$82 -> Single | B91: =COUNTIFS(Matrix!$S$2:$S$451,"INCLUDE",Matrix!$AJ$2:$AJ$451,$A91,Matrix!$AA$2:$AA$451,B$90) -> 16 | C91: =COUNTIFS(Matrix!$S$2:$S$451,"INCLUDE",Matrix!$AJ$2:$AJ$451,$A91,Matrix!$AA$2:$AA$451,C$90) -> 1 | D91: =COUNTIFS(Matrix!$S$2:$S$451,"INCLUDE",Matrix!$AJ$2:$AJ$451,$A91,Matrix!$AA$2:$AA$451,D$90) -> 2 | E91: =COUNTIFS(Matrix!$S$2:$S$451,"INCLUDE",Matrix!$AJ$2:$AJ$451,$A91,Matrix!$AA$2:$AA$451,E$90) -> 0 | F91: =SUM(B91:E91) -> 19
A92: =$A$83 -> Co-present | B92: =COUNTIFS(Matrix!$S$2:$S$451,"INCLUDE",Matrix!$AJ$2:$AJ$451,$A92,Matrix!$AA$2:$AA$451,B$90) -> 3 | C92: =COUNTIFS(Matrix!$S$2:$S$451,"INCLUDE",Matrix!$AJ$2:$AJ$451,$A92,Matrix!$AA$2:$AA$451,C$90) -> 0 | D92: =COUNTIFS(Matrix!$S$2:$S$451,"INCLUDE",Matrix!$AJ$2:$AJ$451,$A92,Matrix!$AA$2:$AA$451,D$90) -> 0 | E92: =COUNTIFS(Matrix!$S$2:$S$451,"INCLUDE",Matrix!$AJ$2:$AJ$451,$A92,Matrix!$AA$2:$AA$451,E$90) -> 0 | F92: =SUM(B92:E92) -> 3
A93: =$A$84 -> Aligned | B93: =COUNTIFS(Matrix!$S$2:$S$451,"INCLUDE",Matrix!$AJ$2:$AJ$451,$A93,Matrix!$AA$2:$AA$451,B$90) -> 35 | C93: =COUNTIFS(Matrix!$S$2:$S$451,"INCLUDE",Matrix!$AJ$2:$AJ$451,$A93,Matrix!$AA$2:$AA$451,C$90) -> 3 | D93: =COUNTIFS(Matrix!$S$2:$S$451,"INCLUDE",Matrix!$AJ$2:$AJ$451,$A93,Matrix!$AA$2:$AA$451,D$90) -> 1 | E93: =COUNTIFS(Matrix!$S$2:$S$451,"INCLUDE",Matrix!$AJ$2:$AJ$451,$A93,Matrix!$AA$2:$AA$451,E$90) -> 0 | F93: =SUM(B93:E93) -> 39
A94: =$A$85 -> Fused | B94: =COUNTIFS(Matrix!$S$2:$S$451,"INCLUDE",Matrix!$AJ$2:$AJ$451,$A94,Matrix!$AA$2:$AA$451,B$90) -> 64 | C94: =COUNTIFS(Matrix!$S$2:$S$451,"INCLUDE",Matrix!$AJ$2:$AJ$451,$A94,Matrix!$AA$2:$AA$451,C$90) -> 0 | D94: =COUNTIFS(Matrix!$S$2:$S$451,"INCLUDE",Matrix!$AJ$2:$AJ$451,$A94,Matrix!$AA$2:$AA$451,D$90) -> 7 | E94: =COUNTIFS(Matrix!$S$2:$S$451,"INCLUDE",Matrix!$AJ$2:$AJ$451,$A94,Matrix!$AA$2:$AA$451,E$90) -> 0 | F94: =SUM(B94:E94) -> 71
A95: =$A$86 -> Unclear | B95: =COUNTIFS(Matrix!$S$2:$S$451,"INCLUDE",Matrix!$AJ$2:$AJ$451,$A95,Matrix!$AA$2:$AA$451,B$90) -> 15 | C95: =COUNTIFS(Matrix!$S$2:$S$451,"INCLUDE",Matrix!$AJ$2:$AJ$451,$A95,Matrix!$AA$2:$AA$451,C$90) -> 4 | D95: =COUNTIFS(Matrix!$S$2:$S$451,"INCLUDE",Matrix!$AJ$2:$AJ$451,$A95,Matrix!$AA$2:$AA$451,D$90) -> 0 | E95: =COUNTIFS(Matrix!$S$2:$S$451,"INCLUDE",Matrix!$AJ$2:$AJ$451,$A95,Matrix!$AA$2:$AA$451,E$90) -> 0 | F95: =SUM(B95:E95) -> 19
A96: Total | B96: =SUM(B91:B95) -> 133 | C96: =SUM(C91:C95) -> 8 | D96: =SUM(D91:D95) -> 10 | E96: =SUM(E91:E95) -> 0 | F96: =SUM(F91:F95) -> 151
A98: Fusion coding integrity check
A99: Fusion cross-tab grand total | B99: =$F$96 -> 151
A100: Total included studies | B100: =$B$2 -> 151
A101: Reconciles? | B101: =IF($F$96=$B$2,"OK - "&TEXT($F$96,"0")&" studies fully fusion-coded","MISMATCH: "&TEXT($F$96-$B$2,"+0;-0")&" - check blanks in Matrix AJ") -> OK - 151 studies fully fusion-coded
A103: Headline (auto)
A104: ="Of the "&TEXT($B$29,"0")&" multimodal studies only "&TEXT($B$86+$B$85,"0")&" reach Fused or Aligned with genuine joint inference; "&TEXT($B$83,"0")&" remain merely Co-present and "&TEXT($B$86,"0")&" are Unclear. Deepest integration (Fused) = "&TEXT($B$85,"0")&" ("&TEXT($C$85,"0.0%")&" of all included)." -> Of the 137 multimodal studies only 90 reach Fused or Aligned with genuine joint inference; 3 remain merely Co-present and 19 are Unclear. Deepest integration (Fused) = 71 (47.0% of all included).
A105: ="Even among the "&TEXT($F$94,"0")&" Fused studies, "&TEXT($B$94,"0")&" ("&TEXT($B$94/$F$94,"0.0%")&") implement no self-improvement and "&TEXT($E$94,"0")&" characterise convergence - deep data integration does NOT translate into adaptive capability." -> Even among the 71 Fused studies, 64 (90.1%) implement no self-improvement and 0 characterise convergence - deep data integration does NOT translate into adaptive capability.
